Workbook

Sheet Y26年渠道汇总
B1: Items | C1: 1月 | D1: 2月 | E1: 3月 | F1: 4月 | G1: 5月 | H1: 6月 | I1: 7月 | J1: 8月 | K1: 9月 | L1: 10月 | M1: 11月 | N1: 12月 | O1: 合计 1-12月 | P1: 费比 | Q1: 备注
B2: 退后销量 | O2: =SUM(C2:N2) -> 0
B3: 自补前GMV | C3: =C5/(1-$P$11) -> 48693750 | D3: =D5/(1-$P$11) -> 39641975 | E3: =E5/(1-$P$11) -> 39696543 | F3: =F5/(1-$P$11) -> 33168148 | G3: =G5/(1-$P$11) -> 70671341 | H3: =H5/(1-$P$11) -> 62217250 | I3: =I5/(1-$P$11) -> 40116707 | J3: =J5/(1-$P$11) -> 55324024 | ... N3: =N5/(1-$P$11) -> 49275904 | O3: =SUM(C3:N3) -> 6.1363962e+08
B4: 国补自补费用 | C4: =C3*$P$11 -> 4869375 | D4: =D3*$P$11 -> 3964197.5 | E4: =E3*$P$11 -> 3969654.3 | F4: =F3*$P$11 -> 3316814.8 | G4: =G3*$P$11 -> 7067134.1 | H4: =H3*$P$11 -> 6221725 | I4: =I3*$P$11 -> 4011670.7 | J4: =J3*$P$11 -> 5532402.4 | ... N4: =N3*$P$11 -> 4927590.4 | O4: =SUM(C4:N4) -> 61363962
B5: GMV（剔除国补的费用后） | C5: 43824375 | D5: 35677778 | E5: 35726889 | F5: 29851333 | G5: 63604207 | H5: 55995525 | I5: 36105037 | J5: 49791622 | K5: 39717110 | L5: 66929205 | M5: 50704265 | N5: 44348313 | O5: =SUM(C5:N5) -> 5.5227566e+08
B6: 退货率（发货前+后） | C6: 0.2 | D6: 0.19 | E6: 0.19 | F6: 0.19 | G6: 0.18 | H6: 0.2 | I6: 0.18 | J6: 0.18 | K6: 0.18 | L6: 0.17 | M6: 0.17 | N6: 0.17 | O6: =1-O7/O5 -> 0.1825153
B7: GSV（剔除国补费用后） | C7: =C5*(1-C6) -> 35059500 | D7: =D5*(1-D6) -> 28899000 | E7: =E5*(1-E6) -> 28938780 | F7: =F5*(1-F6) -> 24179580 | G7: =G5*(1-G6) -> 52155450 | H7: =H5*(1-H6) -> 44796420 | I7: =I5*(1-I6) -> 29606130 | J7: =J5*(1-J6) -> 40829130 | ... N7: =N5*(1-N6) -> 36809100 | O7: =SUM(C7:N7) -> 451476900
C8: =C3*(1-C6) -> 38955000 | D8: =D3*(1-D6) -> 32110000 | E8: =E3*(1-E6) -> 32154200 | F8: =F3*(1-F6) -> 26866200 | G8: =G3*(1-G6) -> 57950500 | H8: =H3*(1-H6) -> 49773800 | I8: =I3*(1-I6) -> 32895700 | J8: =J3*(1-J6) -> 45365700 | ... N8: =N3*(1-N6) -> 40899000 | O8: =SUM(C8:N8) -> 501641000 | P8: =O8/O3 -> 0.8174847
B9: 零售价（去除退货后的） | O9: =SUM(C9:N9) -> 0
B10: 合同折扣及返利 (线下） | O10: =SUM(C10:N10) -> 0 | Q10: 线下填写
B11: 国补自补 （线上） | C11: =C3*$P$11 -> 4869375 | D11: =D3*$P$11 -> 3964197.5 | E11: =E3*$P$11 -> 3969654.3 | F11: =F3*$P$11 -> 3316814.8 | G11: =G3*$P$11 -> 7067134.1 | H11: =H3*$P$11 -> 6221725 | I11: =I3*$P$11 -> 4011670.7 | J11: =J3*$P$11 -> 5532402.4 | ... N11: =N3*$P$11 -> 4927590.4 | O11: =SUM(C11:N11) -> 61363962 | P11: 0.1 | Q11: 按照全年拉平10%
B12: 红包消费券等促销折扣 | O12: =SUM(C12:N12) -> 0
B13: TTL 折扣合计 | C13: =SUM(C10:C12) -> 4869375 | D13: =SUM(D10:D12) -> 3964197.5 | E13: =SUM(E10:E12) -> 3969654.3 | F13: =SUM(F10:F12) -> 3316814.8 | G13: =SUM(G10:G12) -> 7067134.1 | H13: =SUM(H10:H12) -> 6221725 | I13: =SUM(I10:I12) -> 4011670.7 | J13: =SUM(J10:J12) -> 5532402.4 | ... N13: =SUM(N10:N12) -> 4927590.4 | O13: =SUM(C13:N13) -> 61363962
B14: GSV | C14: =C7 -> 35059500 | D14: =D7 -> 28899000 | E14: =E7 -> 28938780 | F14: =F7 -> 24179580 | G14: =G7 -> 52155450 | H14: =H7 -> 44796420 | I14: =I7 -> 29606130 | J14: =J7 -> 40829130 | ... N14: =N7 -> 36809100 | O14: =SUM(C14:N14) -> 451476900
B15: 营业收入 | C15: =+C7/1.13 -> 31026106 | D15: =+D7/1.13 -> 25574336 | E15: =+E7/1.13 -> 25609540 | F15: =+F7/1.13 -> 21397858 | G15: =+G7/1.13 -> 46155265 | H15: =+H7/1.13 -> 39642850 | I15: =+I7/1.13 -> 26200115 | J15: =+J7/1.13 -> 36131973 | ... N15: =+N7/1.13 -> 32574425 | O15: =SUM(C15:N15) -> 3.9953708e+08
B17: 标准主品配件成本 | C17: =C15*(1-C22) -> 15202792 | D17: =D15*(1-D22) -> 12275681 | E17: =E15*(1-E22) -> 12036484 | F17: =F15*(1-F22) -> 9843014.9 | G17: =G15*(1-G22) -> 20769869 | H17: =H15*(1-H22) -> 17442854 | I17: =I15*(1-I22) -> 11266049 | J17: =J15*(1-J22) -> 14814109 | ... N17: =N15*(1-N22) -> 12052537 | O17: =SUM(C17:N17) -> 1.7055677e+08 | P17: =O17/O15 -> 0.42688597
B18: 产品毛利 | C18: =C15-C17 -> 15823314 | D18: =D15-D17 -> 13298655 | E18: =E15-E17 -> 13573056 | F18: =F15-F17 -> 11554844 | G18: =G15-G17 -> 25385396 | H18: =H15-H17 -> 22199996 | I18: =I15-I17 -> 14934066 | J18: =J15-J17 -> 21317864 | ... N18: =N15-N17 -> 20521888 | O18: =SUM(C18:N18) -> 2.2898031e+08 | P18: =O18/$O$15 -> 0.57311403
B19: 头程/尾程物流/仓储费用 | C19: =C15*2.5% -> 775652.65 | D19: =D15*2.5% -> 639358.41 | E19: =E15*2.5% -> 640238.5 | F19: =F15*2.5% -> 534946.46 | G19: =G15*2.5% -> 1153881.6 | H19: =H15*2.5% -> 991071.24 | I19: =I15*2.5% -> 655002.88 | J19: =J15*2.5% -> 903299.34 | ... N19: =N15*2.5% -> 814360.62 | O19: =SUM(C19:N19) -> 9988427 | P19: 0.025 | Q19: 按照全年平均2.5%
B20: 成本合计（产品+物流） | C20: =SUM(C17,C19) -> 15978445 | D20: =SUM(D17,D19) -> 12915040 | E20: =SUM(E17,E19) -> 12676722 | F20: =SUM(F17,F19) -> 10377961 | G20: =SUM(G17,G19) -> 21923751 | H20: =SUM(H17,H19) -> 18433925 | I20: =SUM(I17,I19) -> 11921052 | J20: =SUM(J17,J19) -> 15717408 | ... N20: =SUM(N17,N19) -> 12866898 | O20: =SUM(C20:N20) -> 1.805452e+08 | P20: =O20/$O$15 -> 0.45188597
B21: 净毛利 | C21: =C15-C20 -> 15047662 | D21: =D15-D20 -> 12659296 | E21: =E15-E20 -> 12932818 | F21: =F15-F20 -> 11019897 | G21: =G15-G20 -> 24231514 | H21: =H15-H20 -> 21208925 | I21: =I15-I20 -> 14279063 | J21: =J15-J20 -> 20414565 | ... N21: =N15-N20 -> 19707527 | O21: =SUM(C21:N21) -> 2.1899188e+08 | P21: =O21/$O$15 -> 0.54811403
B22: 实际产品毛利率 | C22: 0.51 | D22: 0.52 | E22: 0.53 | F22: 0.54 | G22: 0.55 | H22: 0.56 | I22: 0.57 | J22: 0.59 | K22: 0.6 | L22: 0.61 | M22: 0.62 | N22: 0.63 | O22: =O18/$O$15 -> 0.57311403
B23: 合计毛利率 | C23: =IFERROR(1-C20/C15,0) -> 0.485 | D23: =IFERROR(1-D20/D15,0) -> 0.495 | E23: =IFERROR(1-E20/E15,0) -> 0.505 | F23: =IFERROR(1-F20/F15,0) -> 0.515 | G23: =IFERROR(1-G20/G15,0) -> 0.525 | H23: =IFERROR(1-H20/H15,0) -> 0.535 | I23: =IFERROR(1-I20/I15,0) -> 0.545 | J23: =IFERROR(1-J20/J15,0) -> 0.565 | ... O23: =IFERROR(1-O20/O15,0) -> 0.54811403
B25: 品牌及内容费用 | C25: =SUM(C26:C30) -> 3723132.7 | D25: =SUM(D26:D30) -> 1022973.5 | E25: =SUM(E26:E30) -> 2560954 | F25: =SUM(F26:F30) -> 1069892.9 | G25: =SUM(G26:G30) -> 5538631.9 | H25: =SUM(H26:H30) -> 2774999.5 | I25: =SUM(I26:I30) -> 1572006.9 | J25: =SUM(J26:J30) -> 2167918.4 | ... N25: =SUM(N26:N30) -> 1302977 | O25: =SUM(C25:N25) -> 28393104 | P25: =O25/$O$15 -> 0.071065003
B26: 展会 | O26: =SUM(C26:N26) -> 0 | P26: =O26/$O$15 -> 0
B27: 品牌营销 | O27: =SUM(C27:N27) -> 0 | P27: =O27/$O$15 -> 0
B28: 内容素材制作 | O28: =SUM(C28:N28) -> 0 | P28: =O28/$O$15 -> 0
B29: 公关费用 | O29: =SUM(C29:N29) -> 0 | P29: =O29/$O$15 -> 0
B30: 达人种草、样机及加热 | C30: =C15*C35 -> 3723132.7 | D30: =D15*D35 -> 1022973.5 | E30: =E15*E35 -> 2560954 | F30: =F15*F35 -> 1069892.9 | G30: =G15*G35 -> 5538631.9 | H30: =H15*H35 -> 2774999.5 | I30: =I15*I35 -> 1572006.9 | J30: =J15*J35 -> 2167918.4 | ... N30: =N15*N35 -> 1302977 | O30: =SUM(C30:N30) -> 28393104 | P30: =O30/$O$15 -> 0.071065003
B31: 展会(费率)
B32: 品牌营销（费率）
B33: 内容素材制作（费率）
B34: 公关费用（费率）
B35: 达人种草、样机及加热（费率） | C35: 0.12 | D35: 0.04 | E35: 0.1 | F35: 0.05 | G35: 0.12 | H35: 0.07 | I35: 0.06 | J35: 0.06 | K35: 0.03 | L35: 0.08 | M35: 0.05 | N35: 0.04
B36: 效果广告 | C36: =SUM(C37:C39) -> 6825743.4 | D36: =SUM(D37:D39) -> 5626354 | E36: =SUM(E37:E39) -> 5634098.8 | F36: =SUM(F37:F39) -> 4707528.8 | G36: =SUM(G37:G39) -> 10154158 | H36: =SUM(H37:H39) -> 8721426.9 | I36: =SUM(I37:I39) -> 5764025.3 | J36: =SUM(J37:J39) -> 7949034.2 | ... N36: =SUM(N37:N39) -> 7166373.5 | O36: =SUM(C36:N36) -> 87898158 | P36: =O36/$O$15 -> 0.22
B37: 站内投放 | C37: =C$15*C40 -> 4343654.9 | D37: =D$15*D40 -> 3580407.1 | E37: =E$15*E40 -> 3585335.6 | F37: =F$15*F40 -> 2995700.2 | G37: =G$15*G40 -> 6461737.2 | H37: =H$15*H40 -> 5549998.9 | I37: =I$15*I40 -> 3668016.1 | J37: =J$15*J40 -> 5058476.3 | ... N37: =N$15*N40 -> 4560419.5 | O37: =SUM(C37:N37) -> 55935191 | P37: =O37/$O$15 -> 0.14 | Q37: 全年平均14%
B38: 千川投放 | C38: =C$15*C41 -> 1861566.4 | D38: =D$15*D41 -> 1534460.2 | E38: =E$15*E41 -> 1536572.4 | F38: =F$15*F41 -> 1283871.5 | G38: =G$15*G41 -> 2769315.9 | H38: =H$15*H41 -> 2378571 | I38: =I$15*I41 -> 1572006.9 | J38: =J$15*J41 -> 2167918.4 | ... N38: =N$15*N41 -> 1954465.5 | O38: =SUM(C38:N38) -> 23972225 | P38: =O38/$O$15 -> 0.06 | Q38: 全年平均6%
B39: 站外投放 | C39: =C$15*C42 -> 620522.12 | D39: =D$15*D42 -> 511486.73 | E39: =E$15*E42 -> 512190.8 | F39: =F$15*F42 -> 427957.17 | G39: =G$15*G42 -> 923105.31 | H39: =H$15*H42 -> 792856.99 | I39: =I$15*I42 -> 524002.3 | J39: =J$15*J42 -> 722639.47 | ... N39: =N$15*N42 -> 651488.5 | O39: =SUM(C39:N39) -> 7990741.6 | P39: =O39/$O$15 -> 0.02 | Q39: 全年平均2%
B40: 站内投放（费率） | C40: 0.14 | D40: 0.14 | E40: 0.14 | F40: 0.14 | G40: 0.14 | H40: 0.14 | I40: 0.14 | J40: 0.14 | K40: 0.14 | L40: 0.14 | M40: 0.14 | N40: 0.14 | O40: =O37/$O$15 -> 0.14
B41: 千川投放（费率） | C41: 0.06 | D41: 0.06 | E41: 0.06 | F41: 0.06 | G41: 0.06 | H41: 0.06 | I41: 0.06 | J41: 0.06 | K41: 0.06 | L41: 0.06 | M41: 0.06 | N41: 0.06 | O41: =O38/$O$15 -> 0.06
B42: 站外投放（费率） | C42: 0.02 | D42: 0.02 | E42: 0.02 | F42: 0.02 | G42: 0.02 | H42: 0.02 | I42: 0.02 | J42: 0.02 | K42: 0.02 | L42: 0.02 | M42: 0.02 | N42: 0.02 | O42: =O39/$O$15 -> 0.02
B43: 线上营销费用 | C43: =SUM(C44:C45) -> 930783.19 | D43: =SUM(D44:D45) -> 767230.09 | E43: =SUM(E44:E45) -> 768286.19 | F43: =SUM(F44:F45) -> 641935.75 | G43: =SUM(G44:G45) -> 1384658 | H43: =SUM(H44:H45) -> 1189285.5 | I43: =SUM(I44:I45) -> 786003.45 | J43: =SUM(J44:J45) -> 1083959.2 | ... N43: =SUM(N44:N45) -> 977232.74 | O43: =SUM(C43:N43) -> 11986112 | P43: =O43/$O$15 -> 0.03
B44: 直播费用 | C44: =C15*$P$44 -> 310261.06 | D44: =D15*$P$44 -> 255743.36 | E44: =E15*$P$44 -> 256095.4 | F44: =F15*$P$44 -> 213978.58 | G44: =G15*$P$44 -> 461552.65 | H44: =H15*$P$44 -> 396428.5 | I44: =I15*$P$44 -> 262001.15 | J44: =J15*$P$44 -> 361319.73 | ... N44: =N15*$P$44 -> 325744.25 | O44: =SUM(C44:N44) -> 3995370.8 | P44: 0.01 | Q44: 全年1%
B45: 赠品费用 | C45: =C15*$P$45 -> 620522.12 | D45: =D15*$P$45 -> 511486.73 | E45: =E15*$P$45 -> 512190.8 | F45: =F15*$P$45 -> 427957.17 | G45: =G15*$P$45 -> 923105.31 | H45: =H15*$P$45 -> 792856.99 | I45: =I15*$P$45 -> 524002.3 | J45: =J15*$P$45 -> 722639.47 | ... N45: =N15*$P$45 -> 651488.5 | O45: =SUM(C45:N45) -> 7990741.6 | P45: 0.02 | Q45: 全年2%
B46: 线下市场费用 | C46: =SUM(C47:C50) -> 0 | D46: =SUM(D47:D50) -> 0 | E46: =SUM(E47:E50) -> 0 | F46: =SUM(F47:F50) -> 0 | G46: =SUM(G47:G50) -> 0 | H46: =SUM(H47:H50) -> 0 | I46: =SUM(I47:I50) -> 0 | J46: =SUM(J47:J50) -> 0 | ... N46: =SUM(N47:N50) -> 0 | O46: =SUM(C46:N46) -> 0 | P46: =O46/$O$15 -> 0
B47: 线下渠道展陈、促销费用 | O47: =SUM(C47:N47) -> 0 | P47: =O47/$O$15 -> 0
B48: 租金+物业+水电 | O48: =SUM(C48:N48) -> 0 | P48: =O48/$O$15 -> 0
B49: 门店人工 | O49: =SUM(C49:N49) -> 0 | P49: =O49/$O$15 -> 0
B50: 门店展陈装修等其他 | O50: =SUM(C50:N50) -> 0 | P50: =O50/$O$15 -> 0
B51: 市场投入费用 | C51: =SUM(C25,C36,C43,C46) -> 11479659 | D51: =SUM(D25,D36,D43,D46) -> 7416557.5 | E51: =SUM(E25,E36,E43,E46) -> 8963338.9 | F51: =SUM(F25,F36,F43,F46) -> 6419357.5 | G51: =SUM(G25,G36,G43,G46) -> 17077448 | H51: =SUM(H25,H36,H43,H46) -> 12685712 | I51: =SUM(I25,I36,I43,I46) -> 8122035.7 | J51: =SUM(J25,J36,J43,J46) -> 11200912 | ... N51: =SUM(N25,N36,N43,N46) -> 9446583.2 | O51: =SUM(C51:N51) -> 1.2827737e+08 | P51: =O51/$O$15 -> 0.321065
B52: 平台佣金 | C52: =C15*$P$52 -> 1644383.6 | D52: =D15*$P$52 -> 1355439.8 | E52: =E15*$P$52 -> 1357305.6 | F52: =F15*$P$52 -> 1134086.5 | G52: =G15*$P$52 -> 2446229.1 | H52: =H15*$P$52 -> 2101071 | I52: =I15*$P$52 -> 1388606.1 | J52: =J15*$P$52 -> 1914994.6 | ... N52: =N15*$P$52 -> 1726444.5 | O52: =SUM(C52:N52) -> 21175465 | P52: 0.053 | Q52: 全年平均5.3%
B53: 平台其他费用 | C53: =C15*$P$53 -> 434365.49 | D53: =D15*$P$53 -> 358040.71 | E53: =E15*$P$53 -> 358533.56 | F53: =F15*$P$53 -> 299570.02 | G53: =G15*$P$53 -> 646173.72 | H53: =H15*$P$53 -> 554999.89 | I53: =I15*$P$53 -> 366801.61 | J53: =J15*$P$53 -> 505847.63 | ... N53: =N15*$P$53 -> 456041.95 | O53: =SUM(C53:N53) -> 5593519.1 | P53: 0.014 | Q53: 全年平均1.4%
B54: 售后费用 | C54: =C15*$P$54 -> 930783.19 | D54: =D15*$P$54 -> 767230.09 | E54: =E15*$P$54 -> 768286.19 | F54: =F15*$P$54 -> 641935.75 | G54: =G15*$P$54 -> 1384658 | H54: =H15*$P$54 -> 1189285.5 | I54: =I15*$P$54 -> 786003.45 | J54: =J15*$P$54 -> 1083959.2 | ... N54: =N15*$P$54 -> 977232.74 | O54: =SUM(C54:N54) -> 11986112 | P54: 0.03 | Q54: 全年平均3%
B55: 短信及店铺软件 | C55: =C15*$P$55 -> 31026.106 | D55: =D15*$P$55 -> 25574.336 | E55: =E15*$P$55 -> 25609.54 | F55: =F15*$P$55 -> 21397.858 | G55: =G15*$P$55 -> 46155.265 | H55: =H15*$P$55 -> 39642.85 | I55: =I15*$P$55 -> 26200.115 | J55: =J15*$P$55 -> 36131.973 | ... N55: =N15*$P$55 -> 32574.425 | O55: =SUM(C55:N55) -> 399537.08 | P55: 0.001 | Q55: 全年平均0.1%
B56: 其他运营费用（咨询调研等） | C56: 20 | G56: 20 | O56: =SUM(C56:N56) -> 40 | P56: =O56/$O$15 -> 1.0011586e-07
B57: 店铺运营费用 | C57: =SUM(C52:C56) -> 3040578.4 | D57: =SUM(D52:D56) -> 2506285 | E57: =SUM(E52:E56) -> 2509734.9 | F57: =SUM(F52:F56) -> 2096990.1 | G57: =SUM(G52:G56) -> 4523236 | H57: =SUM(H52:H56) -> 3884999.3 | I57: =SUM(I52:I56) -> 2567611.3 | J57: =SUM(J52:J56) -> 3540933.4 | ... N57: =SUM(N52:N56) -> 3192293.6 | O57: =SUM(C57:N57) -> 39154674 | P57: =O57/$O$15 -> 0.0980001
B58: A&P 合计数 | C58: =SUM(C51,C57) -> 14520238 | D58: =SUM(D51,D57) -> 9922842.5 | E58: =SUM(E51,E57) -> 11473074 | F58: =SUM(F51,F57) -> 8516347.6 | G58: =SUM(G51,G57) -> 21600684 | H58: =SUM(H51,H57) -> 16570711 | I58: =SUM(I51,I57) -> 10689647 | J58: =SUM(J51,J57) -> 14741845 | ... N58: =SUM(N51,N57) -> 12638877 | O58: =SUM(C58:N58) -> 1.6743205e+08 | P58: =O58/$O$15 -> 0.4190651
B59: 店铺利润 | C59: =C21-C58 -> 527423.81 | D59: =D21-D58 -> 2736454 | E59: =E21-E58 -> 1459743.8 | F59: =F21-F58 -> 2503549.4 | G59: =G21-G58 -> 2630830.1 | H59: =H21-H58 -> 4638213.4 | I59: =I21-I58 -> 3589415.8 | J59: =J21-J58 -> 5672719.8 | ... N59: =N21-N58 -> 7068650.2 | O59: =SUM(C59:N59) -> 51559833 | P59: =O59/$O$15 -> 0.12904893

Sheet 26年全渠道汇总
B1: Items | C1: 1月 | D1: 2月 | E1: 3月 | F1: 4月 | G1: 5月 | H1: 6月 | I1: 7月 | J1: 8月 | K1: 9月 | L1: 10月 | M1: 11月 | N1: 12月 | O1: 合计 1-12月 | P1: 费比 | Q1: 备注
B2: 退后销量 | C2: =淘系!C2+抖音!C2+PDD!C2+得物!C2+京东自营财经口径!C2+京东POP财经口径!C2+'视频号+官网+小程序'!C2+快手!C2+唯品会!C2+'线下门店-直营'!C2+'线下门店-经销'!C2+线下渠道!C2+淘系达播!C2+抖音达播!C2 -> 90463.684 | D2: =淘系!D2+抖音!D2+PDD!D2+得物!D2+京东自营财经口径!D2+京东POP财经口径!D2+'视频号+官网+小程序'!D2+快手!D2+唯品会!D2+'线下门店-直营'!D2+'线下门店-经销'!D2+线下渠道!D2+淘系达播!D2+抖音达播!D2 -> 81993.689 | E2: =淘系!E2+抖音!E2+PDD!E2+得物!E2+京东自营财经口径!E2+京东POP财经口径!E2+'视频号+官网+小程序'!E2+快手!E2+唯品会!E2+'线下门店-直营'!E2+'线下门店-经销'!E2+线下渠道!E2+淘系达播!E2+抖音达播!E2 -> 95977.292 | F2: =淘系!F2+抖音!F2+PDD!F2+得物!F2+京东自营财经口径!F2+京东POP财经口径!F2+'视频号+官网+小程序'!F2+快手!F2+唯品会!F2+'线下门店-直营'!F2+'线下门店-经销'!F2+线下渠道!F2+淘系达播!F2+抖音达播!F2 -> 80112.964 | G2: =淘系!G2+抖音!G2+PDD!G2+得物!G2+京东自营财经口径!G2+京东POP财经口径!G2+'视频号+官网+小程序'!G2+快手!G2+唯品会!G2+'线下门店-直营'!G2+'线下门店-经销'!G2+线下渠道!G2+淘系达播!G2+抖音达播!G2 -> 138286.3 | H2: =淘系!H2+抖音!H2+PDD!H2+得物!H2+京东自营财经口径!H2+京东POP财经口径!H2+'视频号+官网+小程序'!H2+快手!H2+唯品会!H2+'线下门店-直营'!H2+'线下门店-经销'!H2+线下渠道!H2+淘系达播!H2+抖音达播!H2 -> 121225.56 | I2: =淘系!I2+抖音!I2+PDD!I2+得物!I2+京东自营财经口径!I2+京东POP财经口径!I2+'视频号+官网+小程序'!I2+快手!I2+唯品会!I2+'线下门店-直营'!I2+'线下门店-经销'!I2+线下渠道!I2+淘系达播!I2+抖音达播!I2 -> 80120.129 | J2: =淘系!J2+抖音!J2+PDD!J2+得物!J2+京东自营财经口径!J2+京东POP财经口径!J2+'视频号+官网+小程序'!J2+快手!J2+唯品会!J2+'线下门店-直营'!J2+'线下门店-经销'!J2+线下渠道!J2+淘系达播!J2+抖音达播!J2 -> 99963.489 | ... N2: =淘系!N2+抖音!N2+PDD!N2+得物!N2+京东自营财经口径!N2+京东POP财经口径!N2+'视频号+官网+小程序'!N2+快手!N2+唯品会!N2+'线下门店-直营'!N2+'线下门店-经销'!N2+线下渠道!N2+淘系达播!N2+抖音达播!N2 -> 104902.51 | O2: =SUM(C2:N2) -> 1264551.1
B3: 自补前GMV | O3: =SUM(C3:N3) -> 0 | Q3: 渠道填写
B4: 自补前GSV | O4: =SUM(C4:N4) -> 0 | Q4: 渠道填写
B5: 国补自补费用 | C5: =淘系!C5+抖音!C5+PDD!C5+得物!C5+京东自营财经口径!C5+京东POP财经口径!C5+'视频号+官网+小程序'!C5+快手!C5+唯品会!C5+'线下门店-直营'!C5+'线下门店-经销'!C5+线下渠道!C5+淘系达播!C5+抖音达播!C5 -> 4607684.7 | D5: =淘系!D5+抖音!D5+PDD!D5+得物!D5+京东自营财经口径!D5+京东POP财经口径!D5+'视频号+官网+小程序'!D5+快手!D5+唯品会!D5+'线下门店-直营'!D5+'线下门店-经销'!D5+线下渠道!D5+淘系达播!D5+抖音达播!D5 -> 4599816.6 | E5: =淘系!E5+抖音!E5+PDD!E5+得物!E5+京东自营财经口径!E5+京东POP财经口径!E5+'视频号+官网+小程序'!E5+快手!E5+唯品会!E5+'线下门店-直营'!E5+'线下门店-经销'!E5+线下渠道!E5+淘系达播!E5+抖音达播!E5 -> 3914048.7 | F5: =淘系!F5+抖音!F5+PDD!F5+得物!F5+京东自营财经口径!F5+京东POP财经口径!F5+'视频号+官网+小程序'!F5+快手!F5+唯品会!F5+'线下门店-直营'!F5+'线下门店-经销'!F5+线下渠道!F5+淘系达播!F5+抖音达播!F5 -> 3349087.8 | G5: =淘系!G5+抖音!G5+PDD!G5+得物!G5+京东自营财经口径!G5+京东POP财经口径!G5+'视频号+官网+小程序'!G5+快手!G5+唯品会!G5+'线下门店-直营'!G5+'线下门店-经销'!G5+线下渠道!G5+淘系达播!G5+抖音达播!G5 -> 7313638.2 | H5: =淘系!H5+抖音!H5+PDD!H5+得物!H5+京东自营财经口径!H5+京东POP财经口径!H5+'视频号+官网+小程序'!H5+快手!H5+唯品会!H5+'线下门店-直营'!H5+'线下门店-经销'!H5+线下渠道!H5+淘系达播!H5+抖音达播!H5 -> 6508325.2 | I5: =淘系!I5+抖音!I5+PDD!I5+得物!I5+京东自营财经口径!I5+京东POP财经口径!I5+'视频号+官网+小程序'!I5+快手!I5+唯品会!I5+'线下门店-直营'!I5+'线下门店-经销'!I5+线下渠道!I5+淘系达播!I5+抖音达播!I5 -> 4346063.5 | J5: =淘系!J5+抖音!J5+PDD!J5+得物!J5+京东自营财经口径!J5+京东POP财经口径!J5+'视频号+官网+小程序'!J5+快手!J5+唯品会!J5+'线下门店-直营'!J5+'线下门店-经销'!J5+线下渠道!J5+淘系达播!J5+抖音达播!J5 -> 6197224 | ... N5: =淘系!N5+抖音!N5+PDD!N5+得物!N5+京东自营财经口径!N5+京东POP财经口径!N5+'视频号+官网+小程序'!N5+快手!N5+唯品会!N5+'线下门店-直营'!N5+'线下门店-经销'!N5+线下渠道!N5+淘系达播!N5+抖音达播!N5 -> 5803843.5 | O5: =SUM(C5:N5) -> 66408445 | Q5: 渠道填写
B6: GMV（国补后） | C6: =淘系!C6+抖音!C6+PDD!C6+得物!C6+京东自营财经口径!C6+京东POP财经口径!C6+'视频号+官网+小程序'!C6+快手!C6+唯品会!C6+'线下门店-直营'!C6++'线下门店-经销'!C6+线下渠道!C6+淘系达播!C6+抖音达播!C6 -> 38655631 | D6: =淘系!D6+抖音!D6+PDD!D6+得物!D6+京东自营财经口径!D6+京东POP财经口径!D6+'视频号+官网+小程序'!D6+快手!D6+唯品会!D6+'线下门店-直营'!D6++'线下门店-经销'!D6+线下渠道!D6+淘系达播!D6+抖音达播!D6 -> 38582248 | E6: =淘系!E6+抖音!E6+PDD!E6+得物!E6+京东自营财经口径!E6+京东POP财经口径!E6+'视频号+官网+小程序'!E6+快手!E6+唯品会!E6+'线下门店-直营'!E6++'线下门店-经销'!E6+线下渠道!E6+淘系达播!E6+抖音达播!E6 -> 32900883 | F6: =淘系!F6+抖音!F6+PDD!F6+得物!F6+京东自营财经口径!F6+京东POP财经口径!F6+'视频号+官网+小程序'!F6+快手!F6+唯品会!F6+'线下门店-直营'!F6++'线下门店-经销'!F6+线下渠道!F6+淘系达播!F6+抖音达播!F6 -> 27774427 | G6: =淘系!G6+抖音!G6+PDD!G6+得物!G6+京东自营财经口径!G6+京东POP财经口径!G6+'视频号+官网+小程序'!G6+快手!G6+唯品会!G6+'线下门店-直营'!G6++'线下门店-经销'!G6+线下渠道!G6+淘系达播!G6+抖音达播!G6 -> 60823575 | H6: =淘系!H6+抖音!H6+PDD!H6+得物!H6+京东自营财经口径!H6+京东POP财经口径!H6+'视频号+官网+小程序'!H6+快手!H6+唯品会!H6+'线下门店-直营'!H6++'线下门店-经销'!H6+线下渠道!H6+淘系达播!H6+抖音达播!H6 -> 54131266 | I6: =淘系!I6+抖音!I6+PDD!I6+得物!I6+京东自营财经口径!I6+京东POP财经口径!I6+'视频号+官网+小程序'!I6+快手!I6+唯品会!I6+'线下门店-直营'!I6++'线下门店-经销'!I6+线下渠道!I6+淘系达播!I6+抖音达播!I6 -> 37710759 | J6: =淘系!J6+抖音!J6+PDD!J6+得物!J6+京东自营财经口径!J6+京东POP财经口径!J6+'视频号+官网+小程序'!J6+快手!J6+唯品会!J6+'线下门店-直营'!J6++'线下门店-经销'!J6+线下渠道!J6+淘系达播!J6+抖音达播!J6 -> 53940593 | ... N6: =淘系!N6+抖音!N6+PDD!N6+得物!N6+京东自营财经口径!N6+京东POP财经口径!N6+'视频号+官网+小程序'!N6+快手!N6+唯品会!N6+'线下门店-直营'!N6++'线下门店-经销'!N6+线下渠道!N6+淘系达播!N6+抖音达播!N6 -> 51587222 | O6: =SUM(C6:N6) -> 5.7138404e+08 | Q6: 渠道填写
B7: 退货率（发货前+后） | C7: =1-C8/C6 -> 0.19274148 | D7: =1-D8/D6 -> 0.19111768 | E7: =1-E8/E6 -> 0.18967141 | F7: =1-F8/F6 -> 0.16821472 | G7: =1-G8/G6 -> 0.20600984 | H7: =1-H8/H6 -> 0.1885906 | I7: =1-I8/I6 -> 0.18659903 | J7: =1-J8/J6 -> 0.21274421 | ... O7: =1-O8/O6 -> 0.20097971 | Q7: 渠道填写
B8: GSV（国补后） | C8: =淘系!C8+抖音!C8+PDD!C8+得物!C8+京东自营财经口径!C8+京东POP财经口径!C8+'视频号+官网+小程序'!C8+快手!C8+唯品会!C8+'线下门店-直营'!C8++'线下门店-经销'!C8+线下渠道!C8+淘系达播!C8+抖音达播!C8 -> 31205088 | D8: =淘系!D8+抖音!D8+PDD!D8+得物!D8+京东自营财经口径!D8+京东POP财经口径!D8+'视频号+官网+小程序'!D8+快手!D8+唯品会!D8+'线下门店-直营'!D8++'线下门店-经销'!D8+线下渠道!D8+淘系达播!D8+抖音达播!D8 -> 31208498 | E8: =淘系!E8+抖音!E8+PDD!E8+得物!E8+京东自营财经口径!E8+京东POP财经口径!E8+'视频号+官网+小程序'!E8+快手!E8+唯品会!E8+'线下门店-直营'!E8++'线下门店-经销'!E8+线下渠道!E8+淘系达播!E8+抖音达播!E8 -> 26660526 | F8: =淘系!F8+抖音!F8+PDD!F8+得物!F8+京东自营财经口径!F8+京东POP财经口径!F8+'视频号+官网+小程序'!F8+快手!F8+唯品会!F8+'线下门店-直营'!F8++'线下门店-经销'!F8+线下渠道!F8+淘系达播!F8+抖音达播!F8 -> 23102360 | G8: =淘系!G8+抖音!G8+PDD!G8+得物!G8+京东自营财经口径!G8+京东POP财经口径!G8+'视频号+官网+小程序'!G8+快手!G8+唯品会!G8+'线下门店-直营'!G8++'线下门店-经销'!G8+线下渠道!G8+淘系达播!G8+抖音达播!G8 -> 48293320 | H8: =淘系!H8+抖音!H8+PDD!H8+得物!H8+京东自营财经口径!H8+京东POP财经口径!H8+'视频号+官网+小程序'!H8+快手!H8+唯品会!H8+'线下门店-直营'!H8++'线下门店-经销'!H8+线下渠道!H8+淘系达播!H8+抖音达播!H8 -> 43922618 | I8: =淘系!I8+抖音!I8+PDD!I8+得物!I8+京东自营财经口径!I8+京东POP财经口径!I8+'视频号+官网+小程序'!I8+快手!I8+唯品会!I8+'线下门店-直营'!I8++'线下门店-经销'!I8+线下渠道!I8+淘系达播!I8+抖音达播!I8 -> 30673968 | J8: =淘系!J8+抖音!J8+PDD!J8+得物!J8+京东自营财经口径!J8+京东POP财经口径!J8+'视频号+官网+小程序'!J8+快手!J8+唯品会!J8+'线下门店-直营'!J8++'线下门店-经销'!J8+线下渠道!J8+淘系达播!J8+抖音达播!J8 -> 42465045 | ... N8: =淘系!N8+抖音!N8+PDD!N8+得物!N8+京东自营财经口径!N8+京东POP财经口径!N8+'视频号+官网+小程序'!N8+快手!N8+唯品会!N8+'线下门店-直营'!N8++'线下门店-经销'!N8+线下渠道!N8+淘系达播!N8+抖音达播!N8 -> 42115074 | O8: =SUM(C8:N8) -> 4.5654745e+08 | Q8: 渠道填写
B10: 零售价（去除退货后的） | C10: =淘系!C10+抖音!C10+PDD!C10+得物!C10+京东自营财经口径!C10+京东POP财经口径!C10+'视频号+官网+小程序'!C10+快手!C10+唯品会!C10+'线下门店-直营'!C10++'线下门店-经销'!C10+线下渠道!C10+淘系达播!C10+抖音达播!C10 -> 43169030 | D10: =淘系!D10+抖音!D10+PDD!D10+得物!D10+京东自营财经口径!D10+京东POP财经口径!D10+'视频号+官网+小程序'!D10+快手!D10+唯品会!D10+'线下门店-直营'!D10++'线下门店-经销'!D10+线下渠道!D10+淘系达播!D10+抖音达播!D10 -> 41319765 | E10: =淘系!E10+抖音!E10+PDD!E10+得物!E10+京东自营财经口径!E10+京东POP财经口径!E10+'视频号+官网+小程序'!E10+快手!E10+唯品会!E10+'线下门店-直营'!E10++'线下门店-经销'!E10+线下渠道!E10+淘系达播!E10+抖音达播!E10 -> 34649173 | F10: =淘系!F10+抖音!F10+PDD!F10+得物!F10+京东自营财经口径!F10+京东POP财经口径!F10+'视频号+官网+小程序'!F10+快手!F10+唯品会!F10+'线下门店-直营'!F10++'线下门店-经销'!F10+线下渠道!F10+淘系达播!F10+抖音达播!F10 -> 30349389 | G10: =淘系!G10+抖音!G10+PDD!G10+得物!G10+京东自营财经口径!G10+京东POP财经口径!G10+'视频号+官网+小程序'!G10+快手!G10+唯品会!G10+'线下门店-直营'!G10++'线下门店-经销'!G10+线下渠道!G10+淘系达播!G10+抖音达播!G10 -> 62773132 | H10: =淘系!H10+抖音!H10+PDD!H10+得物!H10+京东自营财经口径!H10+京东POP财经口径!H10+'视频号+官网+小程序'!H10+快手!H10+唯品会!H10+'线下门店-直营'!H10++'线下门店-经销'!H10+线下渠道!H10+淘系达播!H10+抖音达播!H10 -> 57311536 | I10: =淘系!I10+抖音!I10+PDD!I10+得物!I10+京东自营财经口径!I10+京东POP财经口径!I10+'视频号+官网+小程序'!I10+快手!I10+唯品会!I10+'线下门店-直营'!I10++'线下门店-经销'!I10+线下渠道!I10+淘系达播!I10+抖音达播!I10 -> 40240744 | J10: =淘系!J10+抖音!J10+PDD!J10+得物!J10+京东自营财经口径!J10+京东POP财经口径!J10+'视频号+官网+小程序'!J10+快手!J10+唯品会!J10+'线下门店-直营'!J10++'线下门店-经销'!J10+线下渠道!J10+淘系达播!J10+抖音达播!J10 -> 55453830 | ... N10: =淘系!N10+抖音!N10+PDD!N10+得物!N10+京东自营财经口径!N10+京东POP财经口径!N10+'视频号+官网+小程序'!N10+快手!N10+唯品会!N10+'线下门店-直营'!N10++'线下门店-经销'!N10+线下渠道!N10+淘系达播!N10+抖音达播!N10 -> 55451705 | O10: =SUM(C10:N10) -> 5.9951799e+08 | Q10: 渠道第二次填写
B11: 合同折扣及返利 (线下） | C11: =淘系!C11+抖音!C11+PDD!C11+得物!C11+京东自营财经口径!C11+京东POP财经口径!C11+'视频号+官网+小程序'!C11+快手!C11+唯品会!C11+'线下门店-直营'!C11+'线下门店-经销'!C11+线下渠道!C11+淘系达播!C11+抖音达播!C11 -> 1195159.2 | D11: =淘系!D11+抖音!D11+PDD!D11+得物!D11+京东自营财经口径!D11+京东POP财经口径!D11+'视频号+官网+小程序'!D11+快手!D11+唯品会!D11+'线下门店-直营'!D11+'线下门店-经销'!D11+线下渠道!D11+淘系达播!D11+抖音达播!D11 -> 1300782.2 | E11: =淘系!E11+抖音!E11+PDD!E11+得物!E11+京东自营财经口径!E11+京东POP财经口径!E11+'视频号+官网+小程序'!E11+快手!E11+唯品会!E11+'线下门店-直营'!E11+'线下门店-经销'!E11+线下渠道!E11+淘系达播!E11+抖音达播!E11 -> 1017203.9 | F11: =淘系!F11+抖音!F11+PDD!F11+得物!F11+京东自营财经口径!F11+京东POP财经口径!F11+'视频号+官网+小程序'!F11+快手!F11+唯品会!F11+'线下门店-直营'!F11+'线下门店-经销'!F11+线下渠道!F11+淘系达播!F11+抖音达播!F11 -> 947622.99 | G11: =淘系!G11+抖音!G11+PDD!G11+得物!G11+京东自营财经口径!G11+京东POP财经口径!G11+'视频号+官网+小程序'!G11+快手!G11+唯品会!G11+'线下门店-直营'!G11+'线下门店-经销'!G11+线下渠道!G11+淘系达播!G11+抖音达播!G11 -> 1706368.4 | H11: =淘系!H11+抖音!H11+PDD!H11+得物!H11+京东自营财经口径!H11+京东POP财经口径!H11+'视频号+官网+小程序'!H11+快手!H11+唯品会!H11+'线下门店-直营'!H11+'线下门店-经销'!H11+线下渠道!H11+淘系达播!H11+抖音达播!H11 -> 1674116.6 | I11: =淘系!I11+抖音!I11+PDD!I11+得物!I11+京东自营财经口径!I11+京东POP财经口径!I11+'视频号+官网+小程序'!I11+快手!I11+唯品会!I11+'线下门店-直营'!I11+'线下门店-经销'!I11+线下渠道!I11+淘系达播!I11+抖音达播!I11 -> 1317289.2 | J11: =淘系!J11+抖音!J11+PDD!J11+得物!J11+京东自营财经口径!J11+京东POP财经口径!J11+'视频号+官网+小程序'!J11+快手!J11+唯品会!J11+'线下门店-直营'!J11+'线下门店-经销'!J11+线下渠道!J11+淘系达播!J11+抖音达播!J11 -> 1660136.2 | ... N11: =淘系!N11+抖音!N11+PDD!N11+得物!N11+京东自营财经口径!N11+京东POP财经口径!N11+'视频号+官网+小程序'!N11+快手!N11+唯品会!N11+'线下门店-直营'!N11+'线下门店-经销'!N11+线下渠道!N11+淘系达播!N11+抖音达播!N11 -> 2086010.3 | O11: =SUM(C11:N11) -> 18348907 | P11: =O11/O8 -> 0.040190581 | Q11: 线下渠道填写 | R11: =O11/$O$10 -> 0.030606099
B12: 国补自补 （线上） | C12: =淘系!C12+抖音!C12+PDD!C12+得物!C12+京东自营财经口径!C12+京东POP财经口径!C12+'视频号+官网+小程序'!C12+快手!C12+唯品会!C12+'线下门店-直营'!C12+'线下门店-经销'!C12+线下渠道!C12+淘系达播!C12+抖音达播!C12 -> 3374204.7 | D12: =淘系!D12+抖音!D12+PDD!D12+得物!D12+京东自营财经口径!D12+京东POP财经口径!D12+'视频号+官网+小程序'!D12+快手!D12+唯品会!D12+'线下门店-直营'!D12+'线下门店-经销'!D12+线下渠道!D12+淘系达播!D12+抖音达播!D12 -> 3225504 | E12: =淘系!E12+抖音!E12+PDD!E12+得物!E12+京东自营财经口径!E12+京东POP财经口径!E12+'视频号+官网+小程序'!E12+快手!E12+唯品会!E12+'线下门店-直营'!E12+'线下门店-经销'!E12+线下渠道!E12+淘系达播!E12+抖音达播!E12 -> 2793045.8 | F12: =淘系!F12+抖音!F12+PDD!F12+得物!F12+京东自营财经口径!F12+京东POP财经口径!F12+'视频号+官网+小程序'!F12+快手!F12+唯品会!F12+'线下门店-直营'!F12+'线下门店-经销'!F12+线下渠道!F12+淘系达播!F12+抖音达播!F12 -> 2421445.1 | G12: =淘系!G12+抖音!G12+PDD!G12+得物!G12+京东自营财经口径!G12+京东POP财经口径!G12+'视频号+官网+小程序'!G12+快手!G12+唯品会!G12+'线下门店-直营'!G12+'线下门店-经销'!G12+线下渠道!G12+淘系达播!G12+抖音达播!G12 -> 5483400.1 | H12: =淘系!H12+抖音!H12+PDD!H12+得物!H12+京东自营财经口径!H12+京东POP财经口径!H12+'视频号+官网+小程序'!H12+快手!H12+唯品会!H12+'线下门店-直营'!H12+'线下门店-经销'!H12+线下渠道!H12+淘系达播!H12+抖音达播!H12 -> 4885124.8 | I12: =淘系!I12+抖音!I12+PDD!I12+得物!I12+京东自营财经口径!I12+京东POP财经口径!I12+'视频号+官网+小程序'!I12+快手!I12+唯品会!I12+'线下门店-直营'!I12+'线下门店-经销'!I12+线下渠道!I12+淘系达播!I12+抖音达播!I12 -> 3103718.8 | J12: =淘系!J12+抖音!J12+PDD!J12+得物!J12+京东自营财经口径!J12+京东POP财经口径!J12+'视频号+官网+小程序'!J12+快手!J12+唯品会!J12+'线下门店-直营'!J12+'线下门店-经销'!J12+线下渠道!J12+淘系达播!J12+抖音达播!J12 -> 4576920.8 | ... N12: =淘系!N12+抖音!N12+PDD!N12+得物!N12+京东自营财经口径!N12+京东POP财经口径!N12+'视频号+官网+小程序'!N12+快手!N12+唯品会!N12+'线下门店-直营'!N12+'线下门店-经销'!N12+线下渠道!N12+淘系达播!N12+抖音达播!N12 -> 4234950.4 | O12: =SUM(C12:N12) -> 48800085 | P12: =O12/O8 -> 0.1068894 | Q12: 渠道填写 | R12: =O12/$O$10 -> 0.081398866
B13: 红包消费券等促销折扣 | C13: =淘系!C13+抖音!C13+PDD!C13+得物!C13+京东自营财经口径!C13+京东POP财经口径!C13+'视频号+官网+小程序'!C13+快手!C13+唯品会!C13+'线下门店-直营'!C13+'线下门店-经销'!C13+线下渠道!C13+淘系达播!C13+抖音达播!C13 -> 7394578.7 | D13: =淘系!D13+抖音!D13+PDD!D13+得物!D13+京东自营财经口径!D13+京东POP财经口径!D13+'视频号+官网+小程序'!D13+快手!D13+唯品会!D13+'线下门店-直营'!D13+'线下门店-经销'!D13+线下渠道!D13+淘系达播!D13+抖音达播!D13 -> 5584980.1 | E13: =淘系!E13+抖音!E13+PDD!E13+得物!E13+京东自营财经口径!E13+京东POP财经口径!E13+'视频号+官网+小程序'!E13+快手!E13+唯品会!E13+'线下门店-直营'!E13+'线下门店-经销'!E13+线下渠道!E13+淘系达播!E13+抖音达播!E13 -> 4178396.9 | F13: =淘系!F13+抖音!F13+PDD!F13+得物!F13+京东自营财经口径!F13+京东POP财经口径!F13+'视频号+官网+小程序'!F13+快手!F13+唯品会!F13+'线下门店-直营'!F13+'线下门店-经销'!F13+线下渠道!F13+淘系达播!F13+抖音达播!F13 -> 3877961.3 | G13: =淘系!G13+抖音!G13+PDD!G13+得物!G13+京东自营财经口径!G13+京东POP财经口径!G13+'视频号+官网+小程序'!G13+快手!G13+唯品会!G13+'线下门店-直营'!G13+'线下门店-经销'!G13+线下渠道!G13+淘系达播!G13+抖音达播!G13 -> 7290043.5 | H13: =淘系!H13+抖音!H13+PDD!H13+得物!H13+京东自营财经口径!H13+京东POP财经口径!H13+'视频号+官网+小程序'!H13+快手!H13+唯品会!H13+'线下门店-直营'!H13+'线下门店-经销'!H13+线下渠道!H13+淘系达播!H13+抖音达播!H13 -> 6829676.2 | I13: =淘系!I13+抖音!I13+PDD!I13+得物!I13+京东自营财经口径!I13+京东POP财经口径!I13+'视频号+官网+小程序'!I13+快手!I13+唯品会!I13+'线下门店-直营'!I13+'线下门店-经销'!I13+线下渠道!I13+淘系达播!I13+抖音达播!I13 -> 5145768 | J13: =淘系!J13+抖音!J13+PDD!J13+得物!J13+京东自营财经口径!J13+京东POP财经口径!J13+'视频号+官网+小程序'!J13+快手!J13+唯品会!J13+'线下门店-直营'!J13+'线下门店-经销'!J13+线下渠道!J13+淘系达播!J13+抖音达播!J13 -> 6751727.9 | ... N13: =淘系!N13+抖音!N13+PDD!N13+得物!N13+京东自营财经口径!N13+京东POP财经口径!N13+'视频号+官网+小程序'!N13+快手!N13+唯品会!N13+'线下门店-直营'!N13+'线下门店-经销'!N13+线下渠道!N13+淘系达播!N13+抖音达播!N13 -> 7015669.9 | O13: =SUM(C13:N13) -> 75821557 | P13: =O13/O8 -> 0.16607596 | Q13: 渠道填写 | R13: =O13/$O$10 -> 0.12647086
B14: TTL 折扣合计 | C14: =SUM(C11:C13) -> 11963943 | D14: =SUM(D11:D13) -> 10111266 | E14: =SUM(E11:E13) -> 7988646.6 | F14: =SUM(F11:F13) -> 7247029.4 | G14: =SUM(G11:G13) -> 14479812 | H14: =SUM(H11:H13) -> 13388918 | I14: =SUM(I11:I13) -> 9566775.9 | J14: =SUM(J11:J13) -> 12988785 | ... N14: =SUM(N11:N13) -> 13336631 | O14: =SUM(C14:N14) -> 1.4297055e+08 | P14: =O14/O8 -> 0.31315595 | R14: =O14/$O$10 -> 0.23847583
B15: GSV | C15: =C8 -> 31205088 | D15: =D8 -> 31208498 | E15: =E8 -> 26660526 | F15: =F8 -> 23102360 | G15: =G8 -> 48293320 | H15: =H8 -> 43922618 | I15: =I8 -> 30673968 | J15: =J8 -> 42465045 | ... N15: =N8 -> 42115074 | O15: =SUM(C15:N15) -> 4.5654745e+08
B16: 营业收入 | C16: =+C8/1.13 -> 27615122 | D16: =+D8/1.13 -> 27618140 | E16: =+E8/1.13 -> 23593386 | F16: =+F8/1.13 -> 20444566 | G16: =+G8/1.13 -> 42737451 | H16: =+H8/1.13 -> 38869573 | I16: =+I8/1.13 -> 27145104 | J16: =+J8/1.13 -> 37579685 | ... N16: =+N8/1.13 -> 37269977 | O16: =SUM(C16:N16) -> 4.0402429e+08 | T16: =O16-淘系!O16-淘系达播!O16-抖音!O16-抖音达播!O16-快手!O16-京东POP财经口径!O16-京东自营财经口径!O16-PDD!O16-得物!O16-'视频号+官网+小程序'!O16-唯品会!O16-'线下门店-直营'!O16-'线下门店-经销'!O16-线下渠道!O16 -> 0
C17: =C14/C15 -> 0.38339718 | T17: =O17-淘系!O17-淘系达播!O17-抖音!O17-抖音达播!O17-快手!O17-京东POP财经口径!O17-京东自营财经口径!O17-PDD!O17-得物!O17-'视频号+官网+小程序'!O17-唯品会!O17-'线下门店-直营'!O17-'线下门店-经销'!O17-线下渠道!O17 -> 0
B18: 标准主品配件成本 | C18: =淘系!C18+抖音!C18+PDD!C18+得物!C18+京东自营财经口径!C18+京东POP财经口径!C18+'视频号+官网+小程序'!C18+快手!C18+唯品会!C18+'线下门店-直营'!C18+'线下门店-经销'!C18+线下渠道!C18+淘系达播!C18+抖音达播!C18 -> 13519375 | D18: =淘系!D18+抖音!D18+PDD!D18+得物!D18+京东自营财经口径!D18+京东POP财经口径!D18+'视频号+官网+小程序'!D18+快手!D18+唯品会!D18+'线下门店-直营'!D18+'线下门店-经销'!D18+线下渠道!D18+淘系达播!D18+抖音达播!D18 -> 13428662 | E18: =淘系!E18+抖音!E18+PDD!E18+得物!E18+京东自营财经口径!E18+京东POP财经口径!E18+'视频号+官网+小程序'!E18+快手!E18+唯品会!E18+'线下门店-直营'!E18+'线下门店-经销'!E18+线下渠道!E18+淘系达播!E18+抖音达播!E18 -> 11966213 | F18: =淘系!F18+抖音!F18+PDD!F18+得物!F18+京东自营财经口径!F18+京东POP财经口径!F18+'视频号+官网+小程序'!F18+快手!F18+唯品会!F18+'线下门店-直营'!F18+'线下门店-经销'!F18+线下渠道!F18+淘系达播!F18+抖音达播!F18 -> 10347617 | G18: =淘系!G18+抖音!G18+PDD!G18+得物!G18+京东自营财经口径!G18+京东POP财经口径!G18+'视频号+官网+小程序'!G18+快手!G18+唯品会!G18+'线下门店-直营'!G18+'线下门店-经销'!G18+线下渠道!G18+淘系达播!G18+抖音达播!G18 -> 19576713 | H18: =淘系!H18+抖音!H18+PDD!H18+得物!H18+京东自营财经口径!H18+京东POP财经口径!H18+'视频号+官网+小程序'!H18+快手!H18+唯品会!H18+'线下门店-直营'!H18+'线下门店-经销'!H18+线下渠道!H18+淘系达播!H18+抖音达播!H18 -> 17979627 | I18: =淘系!I18+抖音!I18+PDD!I18+得物!I18+京东自营财经口径!I18+京东POP财经口径!I18+'视频号+官网+小程序'!I18+快手!I18+唯品会!I18+'线下门店-直营'!I18+'线下门店-经销'!I18+线下渠道!I18+淘系达播!I18+抖音达播!I18 -> 11695231 | J18: =淘系!J18+抖音!J18+PDD!J18+得物!J18+京东自营财经口径!J18+京东POP财经口径!J18+'视频号+官网+小程序'!J18+快手!J18+唯品会!J18+'线下门店-直营'!J18+'线下门店-经销'!J18+线下渠道!J18+淘系达播!J18+抖音达播!J18 -> 16035701 | ... N18: =淘系!N18+抖音!N18+PDD!N18+得物!N18+京东自营财经口径!N18+京东POP财经口径!N18+'视频号+官网+小程序'!N18+快手!N18+唯品会!N18+'线下门店-直营'!N18+'线下门店-经销'!N18+线下渠道!N18+淘系达播!N18+抖音达播!N18 -> 14738372 | O18: =SUM(C18:N18) -> 1.7888455e+08 | P18: =O18/O16 -> 0.44275693 | R18: Y25 Bi 成本54% | T18: =O18-淘系!O18-淘系达播!O18-抖音!O18-抖音达播!O18-快手!O18-京东POP财经口径!O18-京东自营财经口径!O18-PDD!O18-得物!O18-'视频号+官网+小程序'!O18-唯品会!O18-'线下门店-直营'!O18-'线下门店-经销'!O18-线下渠道!O18 -> 0
B19: 产品毛利 | C19: =C16-C18 -> 14095747 | D19: =D16-D18 -> 14189478 | E19: =E16-E18 -> 11627173 | F19: =F16-F18 -> 10096949 | G19: =G16-G18 -> 23160738 | H19: =H16-H18 -> 20889947 | I19: =I16-I18 -> 15449874 | J19: =J16-J18 -> 21543984 | ... N19: =N16-N18 -> 22531606 | O19: =SUM(C19:N19) -> 2.2513973e+08 | P19: =O19/$O$16 -> 0.55724307 | R19: =O16*0.12 -> 48482915 | T19: =O19-淘系!O19-淘系达播!O19-抖音!O19-抖音达播!O19-快手!O19-京东POP财经口径!O19-京东自营财经口径!O19-PDD!O19-得物!O19-'视频号+官网+小程序'!O19-唯品会!O19-'线下门店-直营'!O19-'线下门店-经销'!O19-线下渠道!O19 -> 0
B20: 头程/尾程物流/仓储费用 | C20: =C16*2.5% -> 690378.04 | D20: =D16*2.5% -> 690453.5 | E20: =E16*2.5% -> 589834.65 | F20: =F16*2.5% -> 511114.15 | G20: =G16*2.5% -> 1068436.3 | H20: =H16*2.5% -> 971739.34 | I20: =I16*2.5% -> 678627.61 | J20: =J16*2.5% -> 939492.14 | ... N20: =N16*2.5% -> 931749.43 | O20: =SUM(C20:N20) -> 10100607 | P20: 0.025 | T20: =O20-淘系!O20-淘系达播!O20-抖音!O20-抖音达播!O20-快手!O20-京东POP财经口径!O20-京东自营财经口径!O20-PDD!O20-得物!O20-'视频号+官网+小程序'!O20-唯品会!O20-'线下门店-直营'!O20-'线下门店-经销'!O20-线下渠道!O20 -> 40154.706
B21: 成本合计（产品+物流） | C21: =SUM(C18,C20) -> 14209753 | D21: =SUM(D18,D20) -> 14119115 | E21: =SUM(E18,E20) -> 12556047 | F21: =SUM(F18,F20) -> 10858731 | G21: =SUM(G18,G20) -> 20645149 | H21: =SUM(H18,H20) -> 18951366 | I21: =SUM(I18,I20) -> 12373858 | J21: =SUM(J18,J20) -> 16975194 | ... N21: =SUM(N18,N20) -> 15670121 | O21: =SUM(C21:N21) -> 1.8898516e+08 | P21: =O21/$O$16 -> 0.46775693 | T21: =O21-淘系!O21-淘系达播!O21-抖音!O21-抖音达播!O21-快手!O21-京东POP财经口径!O21-京东自营财经口径!O21-PDD!O21-得物!O21-'视频号+官网+小程序'!O21-唯品会!O21-'线下门店-直营'!O21-'线下门店-经销'!O21-线下渠道!O21 -> 40154.706
B22: 净毛利 | C22: =C16-C21 -> 13405369 | D22: =D16-D21 -> 13499025 | E22: =E16-E21 -> 11037339 | F22: =F16-F21 -> 9585835.3 | G22: =G16-G21 -> 22092302 | H22: =H16-H21 -> 19918207 | I22: =I16-I21 -> 14771246 | J22: =J16-J21 -> 20604492 | ... N22: =N16-N21 -> 21599856 | O22: =SUM(C22:N22) -> 2.1503913e+08 | P22: =O22/$O$16 -> 0.53224307 | T22: =O22-淘系!O22-淘系达播!O22-抖音!O22-抖音达播!O22-快手!O22-京东POP财经口径!O22-京东自营财经口径!O22-PDD!O22-得物!O22-'视频号+官网+小程序'!O22-唯品会!O22-'线下门店-直营'!O22-'线下门店-经销'!O22-线下渠道!O22 -> -40154.706
B23: 实际产品毛利率 | C23: =C19/C16 -> 0.5104358 | D23: =D19/D16 -> 0.51377386 | E23: =E19/E16 -> 0.49281495 | F23: =F19/F16 -> 0.49386958 | G23: =G19/G16 -> 0.54193073 | H23: =H19/H16 -> 0.537437 | I23: =I19/I16 -> 0.56915876 | J23: =J19/J16 -> 0.57328804 | ... O23: =O19/O16 -> 0.55724307 | R23: top down 毛利53% | T23: =O23-淘系!O23-淘系达播!O23-抖音!O23-抖音达播!O23-快手!O23-京东POP财经口径!O23-京东自营财经口径!O23-PDD!O23-得物!O23-'视频号+官网+小程序'!O23-唯品会!O23-'线下门店-直营'!O23-'线下门店-经销'!O23-线下渠道!O23 -> -7.2810622
B24: 合计毛利率 | C24: =IFERROR(1-C21/C16,0) -> 0.4854358 | D24: =IFERROR(1-D21/D16,0) -> 0.48877386 | E24: =IFERROR(1-E21/E16,0) -> 0.46781495 | F24: =IFERROR(1-F21/F16,0) -> 0.46886958 | G24: =IFERROR(1-G21/G16,0) -> 0.51693073 | H24: =IFERROR(1-H21/H16,0) -> 0.512437 | I24: =IFERROR(1-I21/I16,0) -> 0.54415876 | J24: =IFERROR(1-J21/J16,0) -> 0.54828804 | ... O24: =IFERROR(1-O21/O16,0) -> 0.53224307 | T24: =O24-淘系!O24-淘系达播!O24-抖音!O24-抖音达播!O24-快手!O24-京东POP财经口径!O24-京东自营财经口径!O24-PDD!O24-得物!O24-'视频号+官网+小程序'!O24-唯品会!O24-'线下门店-直营'!O24-'线下门店-经销'!O24-线下渠道!O24 -> -6.9890622
T25: =O25-淘系!O25-淘系达播!O25-抖音!O25-抖音达播!O25-快手!O25-京东POP财经口径!O25-京东自营财经口径!O25-PDD!O25-得物!O25-'视频号+官网+小程序'!O25-唯品会!O25-'线下门店-直营'!O25-'线下门店-经销'!O25-线下渠道!O25 -> 0
B26: 品牌及内容费用 | C26: =SUM(C27:C31) -> 751638.84 | D26: =SUM(D27:D31) -> 2209499.7 | E26: =SUM(E27:E31) -> 3628334.4 | F26: =SUM(F27:F31) -> 2088171 | G26: =SUM(G27:G31) -> 8100807.4 | H26: =SUM(H27:H31) -> 4791643.2 | I26: =SUM(I27:I31) -> 1089143.2 | J26: =SUM(J27:J31) -> 1639717.7 | ... N26: =SUM(N27:N31) -> 1241819.8 | O26: =SUM(C26:N26) -> 32991134 | P26: =O26/$O$16 -> 0.081656313 | T26: =O26-淘系!O26-淘系达播!O26-抖音!O26-抖音达播!O26-快手!O26-京东POP财经口径!O26-京东自营财经口径!O26-PDD!O26-得物!O26-'视频号+官网+小程序'!O26-唯品会!O26-'线下门店-直营'!O26-'线下门店-经销'!O26-线下渠道!O26 -> 0
B27: 展会 | C27: =淘系!C27+抖音!C27+PDD!C27+得物!C27+京东自营财经口径!C27+京东POP财经口径!C27+'视频号+官网+小程序'!C27+快手!C27+唯品会!C27+'线下门店-直营'!C27+'线下门店-经销'!C27+线下渠道!C27+淘系达播!C27+抖音达播!C27 -> 0 | D27: =淘系!D27+抖音!D27+PDD!D27+得物!D27+京东自营财经口径!D27+京东POP财经口径!D27+'视频号+官网+小程序'!D27+快手!D27+唯品会!D27+'线下门店-直营'!D27+'线下门店-经销'!D27+线下渠道!D27+淘系达播!D27+抖音达播!D27 -> 0 | E27: =淘系!E27+抖音!E27+PDD!E27+得物!E27+京东自营财经口径!E27+京东POP财经口径!E27+'视频号+官网+小程序'!E27+快手!E27+唯品会!E27+'线下门店-直营'!E27+'线下门店-经销'!E27+线下渠道!E27+淘系达播!E27+抖音达播!E27 -> 64814.267 | F27: =淘系!F27+抖音!F27+PDD!F27+得物!F27+京东自营财经口径!F27+京东POP财经口径!F27+'视频号+官网+小程序'!F27+快手!F27+唯品会!F27+'线下门店-直营'!F27+'线下门店-经销'!F27+线下渠道!F27+淘系达播!F27+抖音达播!F27 -> 54155.074 | G27: =淘系!G27+抖音!G27+PDD!G27+得物!G27+京东自营财经口径!G27+京东POP财经口径!G27+'视频号+官网+小程序'!G27+快手!G27+唯品会!G27+'线下门店-直营'!G27+'线下门店-经销'!G27+线下渠道!G27+淘系达播!G27+抖音达播!G27 -> 115388.16 | H27: =淘系!H27+抖音!H27+PDD!H27+得物!H27+京东自营财经口径!H27+京东POP财经口径!H27+'视频号+官网+小程序'!H27+快手!H27+唯品会!H27+'线下门店-直营'!H27+'线下门店-经销'!H27+线下渠道!H27+淘系达播!H27+抖音达播!H27 -> 101584.8 | I27: =淘系!I27+抖音!I27+PDD!I27+得物!I27+京东自营财经口径!I27+京东POP财经口径!I27+'视频号+官网+小程序'!I27+快手!I27+唯品会!I27+'线下门店-直营'!I27+'线下门店-经销'!I27+线下渠道!I27+淘系达播!I27+抖音达播!I27 -> 65500.288 | J27: =淘系!J27+抖音!J27+PDD!J27+得物!J27+京东自营财经口径!J27+京东POP财经口径!J27+'视频号+官网+小程序'!J27+快手!J27+唯品会!J27+'线下门店-直营'!J27+'线下门店-经销'!J27+线下渠道!J27+淘系达播!J27+抖音达播!J27 -> 90329.934 | ... N27: =淘系!N27+抖音!N27+PDD!N27+得物!N27+京东自营财经口径!N27+京东POP财经口径!N27+'视频号+官网+小程序'!N27+快手!N27+唯品会!N27+'线下门店-直营'!N27+'线下门店-经销'!N27+线下渠道!N27+淘系达播!N27+抖音达播!N27 -> 0 | O27: =SUM(C27:N27) -> 777231.54 | P27: =O27/$O$16 -> 0.0019237248 | T27: =O27-淘系!O27-淘系达播!O27-抖音!O27-抖音达播!O27-快手!O27-京东POP财经口径!O27-京东自营财经口径!O27-PDD!O27-得物!O27-'视频号+官网+小程序'!O27-唯品会!O27-'线下门店-直营'!O27-'线下门店-经销'!O27-线下渠道!O27 -> -1.6007107e-10
B28: 品牌营销 | C28: =淘系!C28+抖音!C28+PDD!C28+得物!C28+京东自营财经口径!C28+京东POP财经口径!C28+'视频号+官网+小程序'!C28+快手!C28+唯品会!C28+'线下门店-直营'!C28+'线下门店-经销'!C28+线下渠道!C28+淘系达播!C28+抖音达播!C28 -> 209195 | D28: =淘系!D28+抖音!D28+PDD!D28+得物!D28+京东自营财经口径!D28+京东POP财经口径!D28+'视频号+官网+小程序'!D28+快手!D28+唯品会!D28+'线下门店-直营'!D28+'线下门店-经销'!D28+线下渠道!D28+淘系达播!D28+抖音达播!D28 -> 209195 | E28: =淘系!E28+抖音!E28+PDD!E28+得物!E28+京东自营财经口径!E28+京东POP财经口径!E28+'视频号+官网+小程序'!E28+快手!E28+唯品会!E28+'线下门店-直营'!E28+'线下门店-经销'!E28+线下渠道!E28+淘系达播!E28+抖音达播!E28 -> 209195 | F28: =淘系!F28+抖音!F28+PDD!F28+得物!F28+京东自营财经口径!F28+京东POP财经口径!F28+'视频号+官网+小程序'!F28+快手!F28+唯品会!F28+'线下门店-直营'!F28+'线下门店-经销'!F28+线下渠道!F28+淘系达播!F28+抖音达播!F28 -> 274181.09 | G28: =淘系!G28+抖音!G28+PDD!G28+得物!G28+京东自营财经口径!G28+京东POP财经口径!G28+'视频号+官网+小程序'!G28+快手!G28+唯品会!G28+'线下门店-直营'!G28+'线下门店-经销'!G28+线下渠道!G28+淘系达播!G28+抖音达播!G28 -> 901523.98 | H28: =淘系!H28+抖音!H28+PDD!H28+得物!H28+京东自营财经口径!H28+京东POP财经口径!H28+'视频号+官网+小程序'!H28+快手!H28+唯品会!H28+'线下门店-直营'!H28+'线下门店-经销'!H28+线下渠道!H28+淘系达播!H28+抖音达播!H28 -> 534266.37 | I28: =淘系!I28+抖音!I28+PDD!I28+得物!I28+京东自营财经口径!I28+京东POP财经口径!I28+'视频号+官网+小程序'!I28+快手!I28+唯品会!I28+'线下门店-直营'!I28+'线下门店-经销'!I28+线下渠道!I28+淘系达播!I28+抖音达播!I28 -> 209195 | J28: =淘系!J28+抖音!J28+PDD!J28+得物!J28+京东自营财经口径!J28+京东POP财经口径!J28+'视频号+官网+小程序'!J28+快手!J28+唯品会!J28+'线下门店-直营'!J28+'线下门店-经销'!J28+线下渠道!J28+淘系达播!J28+抖音达播!J28 -> 317590.92 | ... N28: =淘系!N28+抖音!N28+PDD!N28+得物!N28+京东自营财经口径!N28+京东POP财经口径!N28+'视频号+官网+小程序'!N28+快手!N28+唯品会!N28+'线下门店-直营'!N28+'线下门店-经销'!N28+线下渠道!N28+淘系达播!N28+抖音达播!N28 -> 209195 | O28: =SUM(C28:N28) -> 4187779.5 | P28: =O28/$O$16 -> 0.010365168 | T28: =O28-淘系!O28-淘系达播!O28-抖音!O28-抖音达播!O28-快手!O28-京东POP财经口径!O28-京东自营财经口径!O28-PDD!O28-得物!O28-'视频号+官网+小程序'!O28-唯品会!O28-'线下门店-直营'!O28-'线下门店-经销'!O28-线下渠道!O28 -> 5.5297278e-10
B29: 内容素材制作 | C29: =淘系!C29+抖音!C29+PDD!C29+得物!C29+京东自营财经口径!C29+京东POP财经口径!C29+'视频号+官网+小程序'!C29+快手!C29+唯品会!C29+'线下门店-直营'!C29+'线下门店-经销'!C29+线下渠道!C29+淘系达播!C29+抖音达播!C29 -> 31801.759 | D29: =淘系!D29+抖音!D29+PDD!D29+得物!D29+京东自营财经口径!D29+京东POP财经口径!D29+'视频号+官网+小程序'!D29+快手!D29+唯品会!D29+'线下门店-直营'!D29+'线下门店-经销'!D29+线下渠道!D29+淘系达播!D29+抖音达播!D29 -> 25890.069 | E29: =淘系!E29+抖音!E29+PDD!E29+得物!E29+京东自营财经口径!E29+京东POP财经口径!E29+'视频号+官网+小程序'!E29+快手!E29+唯品会!E29+'线下门店-直营'!E29+'线下门店-经销'!E29+线下渠道!E29+淘系达播!E29+抖音达播!E29 -> 25925.707 | F29: =淘系!F29+抖音!F29+PDD!F29+得物!F29+京东自营财经口径!F29+京东POP财经口径!F29+'视频号+官网+小程序'!F29+快手!F29+唯品会!F29+'线下门店-直营'!F29+'线下门店-经销'!F29+线下渠道!F29+淘系达播!F29+抖音达播!F29 -> 108310.15 | G29: =淘系!G29+抖音!G29+PDD!G29+得物!G29+京东自营财经口径!G29+京东POP财经口径!G29+'视频号+官网+小程序'!G29+快手!G29+唯品会!G29+'线下门店-直营'!G29+'线下门店-经销'!G29+线下渠道!G29+淘系达播!G29+抖音达播!G29 -> 692328.98 | H29: =淘系!H29+抖音!H29+PDD!H29+得物!H29+京东自营财经口径!H29+京东POP财经口径!H29+'视频号+官网+小程序'!H29+快手!H29+唯品会!H29+'线下门店-直营'!H29+'线下门店-经销'!H29+线下渠道!H29+淘系达播!H29+抖音达播!H29 -> 446973.13 | I29: =淘系!I29+抖音!I29+PDD!I29+得物!I29+京东自营财经口径!I29+京东POP财经口径!I29+'视频号+官网+小程序'!I29+快手!I29+唯品会!I29+'线下门店-直营'!I29+'线下门店-经销'!I29+线下渠道!I29+淘系达播!I29+抖音达播!I29 -> 0 | J29: =淘系!J29+抖音!J29+PDD!J29+得物!J29+京东自营财经口径!J29+京东POP财经口径!J29+'视频号+官网+小程序'!J29+快手!J29+唯品会!J29+'线下门店-直营'!J29+'线下门店-经销'!J29+线下渠道!J29+淘系达播!J29+抖音达播!J29 -> 108395.92 | ... N29: =淘系!N29+抖音!N29+PDD!N29+得物!N29+京东自营财经口径!N29+京东POP财经口径!N29+'视频号+官网+小程序'!N29+快手!N29+唯品会!N29+'线下门店-直营'!N29+'线下门店-经销'!N29+线下渠道!N29+淘系达播!N29+抖音达播!N29 -> 32181.962 | O29: =SUM(C29:N29) -> 2129189.5 | P29: =O29/$O$16 -> 0.0052699542 | T29: =O29-淘系!O29-淘系达播!O29-抖音!O29-抖音达播!O29-快手!O29-京东POP财经口径!O29-京东自营财经口径!O29-PDD!O29-得物!O29-'视频号+官网+小程序'!O29-唯品会!O29-'线下门店-直营'!O29-'线下门店-经销'!O29-线下渠道!O29 -> 0
B30: 公关费用 | C30: =淘系!C30+抖音!C30+PDD!C30+得物!C30+京东自营财经口径!C30+京东POP财经口径!C30+'视频号+官网+小程序'!C30+快手!C30+唯品会!C30+'线下门店-直营'!C30+'线下门店-经销'!C30+线下渠道!C30+淘系达播!C30+抖音达播!C30 -> 31801.759 | D30: =淘系!D30+抖音!D30+PDD!D30+得物!D30+京东自营财经口径!D30+京东POP财经口径!D30+'视频号+官网+小程序'!D30+快手!D30+唯品会!D30+'线下门店-直营'!D30+'线下门店-经销'!D30+线下渠道!D30+淘系达播!D30+抖音达播!D30 -> 25890.069 | E30: =淘系!E30+抖音!E30+PDD!E30+得物!E30+京东自营财经口径!E30+京东POP财经口径!E30+'视频号+官网+小程序'!E30+快手!E30+唯品会!E30+'线下门店-直营'!E30+'线下门店-经销'!E30+线下渠道!E30+淘系达播!E30+抖音达播!E30 -> 207405.66 | F30: =淘系!F30+抖音!F30+PDD!F30+得物!F30+京东自营财经口径!F30+京东POP财经口径!F30+'视频号+官网+小程序'!F30+快手!F30+唯品会!F30+'线下门店-直营'!F30+'线下门店-经销'!F30+线下渠道!F30+淘系达播!F30+抖音达播!F30 -> 21662.029 | G30: =淘系!G30+抖音!G30+PDD!G30+得物!G30+京东自营财经口径!G30+京东POP财经口径!G30+'视频号+官网+小程序'!G30+快手!G30+唯品会!G30+'线下门店-直营'!G30+'线下门店-经销'!G30+线下渠道!G30+淘系达播!G30+抖音达播!G30 -> 138465.8 | H30: =淘系!H30+抖音!H30+PDD!H30+得物!H30+京东自营财经口径!H30+京东POP财经口径!H30+'视频号+官网+小程序'!H30+快手!H30+唯品会!H30+'线下门店-直营'!H30+'线下门店-经销'!H30+线下渠道!H30+淘系达播!H30+抖音达播!H30 -> 40633.921 | I30: =淘系!I30+抖音!I30+PDD!I30+得物!I30+京东自营财经口径!I30+京东POP财经口径!I30+'视频号+官网+小程序'!I30+快手!I30+唯品会!I30+'线下门店-直营'!I30+'线下门店-经销'!I30+线下渠道!I30+淘系达播!I30+抖音达播!I30 -> 26200.115 | J30: =淘系!J30+抖音!J30+PDD!J30+得物!J30+京东自营财经口径!J30+京东POP财经口径!J30+'视频号+官网+小程序'!J30+快手!J30+唯品会!J30+'线下门店-直营'!J30+'线下门店-经销'!J30+线下渠道!J30+淘系达播!J30+抖音达播!J30 -> 36131.973 | ... N30: =淘系!N30+抖音!N30+PDD!N30+得物!N30+京东自营财经口径!N30+京东POP财经口径!N30+'视频号+官网+小程序'!N30+快手!N30+唯品会!N30+'线下门店-直营'!N30+'线下门店-经销'!N30+线下渠道!N30+淘系达播!N30+抖音达播!N30 -> 32181.962 | O30: =SUM(C30:N30) -> 759919.23 | P30: =O30/$O$16 -> 0.0018808751 | T30: =O30-淘系!O30-淘系达播!O30-抖音!O30-抖音达播!O30-快手!O30-京东POP财经口径!O30-京东自营财经口径!O30-PDD!O30-得物!O30-'视频号+官网+小程序'!O30-唯品会!O30-'线下门店-直营'!O30-'线下门店-经销'!O30-线下渠道!O30 -> 0
B31: 达人种草、样机及加热 | C31: =淘系!C31+抖音!C31+PDD!C31+得物!C31+京东自营财经口径!C31+京东POP财经口径!C31+'视频号+官网+小程序'!C31+快手!C31+唯品会!C31+'线下门店-直营'!C31+'线下门店-经销'!C31+线下渠道!C31+淘系达播!C31+抖音达播!C31 -> 478840.32 | D31: =淘系!D31+抖音!D31+PDD!D31+得物!D31+京东自营财经口径!D31+京东POP财经口径!D31+'视频号+官网+小程序'!D31+快手!D31+唯品会!D31+'线下门店-直营'!D31+'线下门店-经销'!D31+线下渠道!D31+淘系达播!D31+抖音达播!D31 -> 1948524.6 | E31: =淘系!E31+抖音!E31+PDD!E31+得物!E31+京东自营财经口径!E31+京东POP财经口径!E31+'视频号+官网+小程序'!E31+快手!E31+唯品会!E31+'线下门店-直营'!E31+'线下门店-经销'!E31+线下渠道!E31+淘系达播!E31+抖音达播!E31 -> 3120993.8 | F31: =淘系!F31+抖音!F31+PDD!F31+得物!F31+京东自营财经口径!F31+京东POP财经口径!F31+'视频号+官网+小程序'!F31+快手!F31+唯品会!F31+'线下门店-直营'!F31+'线下门店-经销'!F31+线下渠道!F31+淘系达播!F31+抖音达播!F31 -> 1629862.7 | G31: =淘系!G31+抖音!G31+PDD!G31+得物!G31+京东自营财经口径!G31+京东POP财经口径!G31+'视频号+官网+小程序'!G31+快手!G31+唯品会!G31+'线下门店-直营'!G31+'线下门店-经销'!G31+线下渠道!G31+淘系达播!G31+抖音达播!G31 -> 6253100.5 | H31: =淘系!H31+抖音!H31+PDD!H31+得物!H31+京东自营财经口径!H31+京东POP财经口径!H31+'视频号+官网+小程序'!H31+快手!H31+唯品会!H31+'线下门店-直营'!H31+'线下门店-经销'!H31+线下渠道!H31+淘系达播!H31+抖音达播!H31 -> 3668185 | I31: =淘系!I31+抖音!I31+PDD!I31+得物!I31+京东自营财经口径!I31+京东POP财经口径!I31+'视频号+官网+小程序'!I31+快手!I31+唯品会!I31+'线下门店-直营'!I31+'线下门店-经销'!I31+线下渠道!I31+淘系达播!I31+抖音达播!I31 -> 788247.76 | J31: =淘系!J31+抖音!J31+PDD!J31+得物!J31+京东自营财经口径!J31+京东POP财经口径!J31+'视频号+官网+小程序'!J31+快手!J31+唯品会!J31+'线下门店-直营'!J31+'线下门店-经销'!J31+线下渠道!J31+淘系达播!J31+抖音达播!J31 -> 1087268.9 | ... N31: =淘系!N31+抖音!N31+PDD!N31+得物!N31+京东自营财经口径!N31+京东POP财经口径!N31+'视频号+官网+小程序'!N31+快手!N31+唯品会!N31+'线下门店-直营'!N31+'线下门店-经销'!N31+线下渠道!N31+淘系达播!N31+抖音达播!N31 -> 968260.91 | O31: =SUM(C31:N31) -> 25137014 | P31: =O31/$O$16 -> 0.062216591 | T31: =O31-淘系!O31-淘系达播!O31-抖音!O31-抖音达播!O31-快手!O31-京东POP财经口径!O31-京东自营财经口径!O31-PDD!O31-得物!O31-'视频号+官网+小程序'!O31-唯品会!O31-'线下门店-直营'!O31-'线下门店-经销'!O31-线下渠道!O31 -> 0
B32: 展会(费率) | T32: =O32-淘系!O32-淘系达播!O32-抖音!O32-抖音达播!O32-快手!O32-京东POP财经口径!O32-京东自营财经口径!O32-PDD!O32-得物!O32-'视频号+官网+小程序'!O32-唯品会!O32-'线下门店-直营'!O32-'线下门店-经销'!O32-线下渠道!O32 -> 0
B33: 品牌营销（费率） | T33: =O33-淘系!O33-淘系达播!O33-抖音!O33-抖音达播!O33-快手!O33-京东POP财经口径!O33-京东自营财经口径!O33-PDD!O33-得物!O33-'视频号+官网+小程序'!O33-唯品会!O33-'线下门店-直营'!O33-'线下门店-经销'!O33-线下渠道!O33 -> 0
B34: 内容素材制作（费率） | T34: =O34-淘系!O34-淘系达播!O34-抖音!O34-抖音达播!O34-快手!O34-京东POP财经口径!O34-京东自营财经口径!O34-PDD!O34-得物!O34-'视频号+官网+小程序'!O34-唯品会!O34-'线下门店-直营'!O34-'线下门店-经销'!O34-线下渠道!O34 -> 0
B35: 公关费用（费率） | T35: =O35-淘系!O35-淘系达播!O35-抖音!O35-抖音达播!O35-快手!O35-京东POP财经口径!O35-京东自营财经口径!O35-PDD!O35-得物!O35-'视频号+官网+小程序'!O35-唯品会!O35-'线下门店-直营'!O35-'线下门店-经销'!O35-线下渠道!O35 -> 0
B36: 达人种草、样机及加热（费率） | T36: =O36-淘系!O36-淘系达播!O36-抖音!O36-抖音达播!O36-快手!O36-京东POP财经口径!O36-京东自营财经口径!O36-PDD!O36-得物!O36-'视频号+官网+小程序'!O36-唯品会!O36-'线下门店-直营'!O36-'线下门店-经销'!O36-线下渠道!O36 -> 0
B37: 效果广告 | C37: =SUM(C38:C40) -> 5289161.1 | D37: =SUM(D38:D40) -> 6011795.3 | E37: =SUM(E38:E40) -> 4469411.7 | F37: =SUM(F38:F40) -> 3799706.2 | G37: =SUM(G38:G40) -> 9797097.2 | H37: =SUM(H38:H40) -> 8746823 | I37: =SUM(I38:I40) -> 4912801.7 | J37: =SUM(J38:J40) -> 8629549.9 | ... N37: =SUM(N38:N40) -> 6666059 | O37: =SUM(C37:N37) -> 82824979 | P37: =O37/$O$16 -> 0.205 | R37: =O16*20.5% -> 82824979 | T37: =O37-淘系!O37-淘系达播!O37-抖音!O37-抖音达播!O37-快手!O37-京东POP财经口径!O37-京东自营财经口径!O37-PDD!O37-得物!O37-'视频号+官网+小程序'!O37-唯品会!O37-'线下门店-直营'!O37-'线下门店-经销'!O37-线下渠道!O37 -> -2.3283064e-10
B38: 站内投放 | C38: =淘系!C38+抖音!C38+PDD!C38+得物!C38+京东自营财经口径!C38+京东POP财经口径!C38+'视频号+官网+小程序'!C38+快手!C38+唯品会!C38+'线下门店-直营'!C38+'线下门店-经销'!C38+线下渠道!C38+淘系达播!C38+抖音达播!C38 -> 2292019.8 | D38: =淘系!D38+抖音!D38+PDD!D38+得物!D38+京东自营财经口径!D38+京东POP财经口径!D38+'视频号+官网+小程序'!D38+快手!D38+唯品会!D38+'线下门店-直营'!D38+'线下门店-经销'!D38+线下渠道!D38+淘系达播!D38+抖音达播!D38 -> 2749177.4 | E38: =淘系!E38+抖音!E38+PDD!E38+得物!E38+京东自营财经口径!E38+京东POP财经口径!E38+'视频号+官网+小程序'!E38+快手!E38+唯品会!E38+'线下门店-直营'!E38+'线下门店-经销'!E38+线下渠道!E38+淘系达播!E38+抖音达播!E38 -> 2219902.6 | F38: =淘系!F38+抖音!F38+PDD!F38+得物!F38+京东自营财经口径!F38+京东POP财经口径!F38+'视频号+官网+小程序'!F38+快手!F38+唯品会!F38+'线下门店-直营'!F38+'线下门店-经销'!F38+线下渠道!F38+淘系达播!F38+抖音达播!F38 -> 1900622 | G38: =淘系!G38+抖音!G38+PDD!G38+得物!G38+京东自营财经口径!G38+京东POP财经口径!G38+'视频号+官网+小程序'!G38+快手!G38+唯品会!G38+'线下门店-直营'!G38+'线下门店-经销'!G38+线下渠道!G38+淘系达播!G38+抖音达播!G38 -> 4748153.5 | H38: =淘系!H38+抖音!H38+PDD!H38+得物!H38+京东自营财经口径!H38+京东POP财经口径!H38+'视频号+官网+小程序'!H38+快手!H38+唯品会!H38+'线下门店-直营'!H38+'线下门店-经销'!H38+线下渠道!H38+淘系达播!H38+抖音达播!H38 -> 4563874.8 | I38: =淘系!I38+抖音!I38+PDD!I38+得物!I38+京东自营财经口径!I38+京东POP财经口径!I38+'视频号+官网+小程序'!I38+快手!I38+唯品会!I38+'线下门店-直营'!I38+'线下门店-经销'!I38+线下渠道!I38+淘系达播!I38+抖音达播!I38 -> 2576178.9 | J38: =淘系!J38+抖音!J38+PDD!J38+得物!J38+京东自营财经口径!J38+京东POP财经口径!J38+'视频号+官网+小程序'!J38+快手!J38+唯品会!J38+'线下门店-直营'!J38+'线下门店-经销'!J38+线下渠道!J38+淘系达播!J38+抖音达播!J38 -> 4648298.8 | ... N38: =淘系!N38+抖音!N38+PDD!N38+得物!N38+京东自营财经口径!N38+京东POP财经口径!N38+'视频号+官网+小程序'!N38+快手!N38+唯品会!N38+'线下门店-直营'!N38+'线下门店-经销'!N38+线下渠道!N38+淘系达播!N38+抖音达播!N38 -> 3186379.6 | O38: =SUM(C38:N38) -> 41931094 | P38: =O38/$O$16 -> 0.1037836 | Q38: 投放填写 | R38: =O37-R37 -> -0.04135856 | T38: =O38-淘系!O38-淘系达播!O38-抖音!O38-抖音达播!O38-快手!O38-京东POP财经口径!O38-京东自营财经口径!O38-PDD!O38-得物!O38-'视频号+官网+小程序'!O38-唯品会!O38-'线下门店-直营'!O38-'线下门店-经销'!O38-线下渠道!O38 -> -1.3271347e-08
B39: 千川投放 | C39: =淘系!C39+抖音!C39+PDD!C39+得物!C39+京东自营财经口径!C39+京东POP财经口径!C39+'视频号+官网+小程序'!C39+快手!C39+唯品会!C39+'线下门店-直营'!C39+'线下门店-经销'!C39+线下渠道!C39+淘系达播!C39+抖音达播!C39 -> 2298503 | D39: =淘系!D39+抖音!D39+PDD!D39+得物!D39+京东自营财经口径!D39+京东POP财经口径!D39+'视频号+官网+小程序'!D39+快手!D39+唯品会!D39+'线下门店-直营'!D39+'线下门店-经销'!D39+线下渠道!D39+淘系达播!D39+抖音达播!D39 -> 2468200.8 | E39: =淘系!E39+抖音!E39+PDD!E39+得物!E39+京东自营财经口径!E39+京东POP财经口径!E39+'视频号+官网+小程序'!E39+快手!E39+唯品会!E39+'线下门店-直营'!E39+'线下门店-经销'!E39+线下渠道!E39+淘系达播!E39+抖音达播!E39 -> 1582066.6 | F39: =淘系!F39+抖音!F39+PDD!F39+得物!F39+京东自营财经口径!F39+京东POP财经口径!F39+'视频号+官网+小程序'!F39+快手!F39+唯品会!F39+'线下门店-直营'!F39+'线下门店-经销'!F39+线下渠道!F39+淘系达播!F39+抖音达播!F39 -> 1336204.9 | G39: =淘系!G39+抖音!G39+PDD!G39+得物!G39+京东自营财经口径!G39+京东POP财经口径!G39+'视频号+官网+小程序'!G39+快手!G39+唯品会!G39+'线下门店-直营'!G39+'线下门店-经销'!G39+线下渠道!G39+淘系达播!G39+抖音达播!G39 -> 3070752.4 | H39: =淘系!H39+抖音!H39+PDD!H39+得物!H39+京东自营财经口径!H39+京东POP财经口径!H39+'视频号+官网+小程序'!H39+快手!H39+唯品会!H39+'线下门店-直营'!H39+'线下门店-经销'!H39+线下渠道!H39+淘系达播!H39+抖音达播!H39 -> 2791593.1 | I39: =淘系!I39+抖音!I39+PDD!I39+得物!I39+京东自营财经口径!I39+京东POP财经口径!I39+'视频号+官网+小程序'!I39+快手!I39+唯品会!I39+'线下门店-直营'!I39+'线下门店-经销'!I39+线下渠道!I39+淘系达播!I39+抖音达播!I39 -> 1603445.8 | J39: =淘系!J39+抖音!J39+PDD!J39+得物!J39+京东自营财经口径!J39+京东POP财经口径!J39+'视频号+官网+小程序'!J39+快手!J39+唯品会!J39+'线下门店-直营'!J39+'线下门店-经销'!J39+线下渠道!J39+淘系达播!J39+抖音达播!J39 -> 2583206.5 | ... N39: =淘系!N39+抖音!N39+PDD!N39+得物!N39+京东自营财经口径!N39+京东POP财经口径!N39+'视频号+官网+小程序'!N39+快手!N39+唯品会!N39+'线下门店-直营'!N39+'线下门店-经销'!N39+线下渠道!N39+淘系达播!N39+抖音达播!N39 -> 2571042.5 | O39: =SUM(C39:N39) -> 27750461 | P39: =O39/$O$16 -> 0.06868513 | Q39: 投放填写 | R39: =淘系!O31+抖音!O31+京东自营财经口径!O31 -> 20683454 | T39: =O39-淘系!O39-淘系达播!O39-抖音!O39-抖音达播!O39-快手!O39-京东POP财经口径!O39-京东自营财经口径!O39-PDD!O39-得物!O39-'视频号+官网+小程序'!O39-唯品会!O39-'线下门店-直营'!O39-'线下门店-经销'!O39-线下渠道!O39 -> 0
B40: 站外投放 | C40: =淘系!C40+抖音!C40+PDD!C40+得物!C40+京东自营财经口径!C40+京东POP财经口径!C40+'视频号+官网+小程序'!C40+快手!C40+唯品会!C40+'线下门店-直营'!C40+'线下门店-经销'!C40+线下渠道!C40+淘系达播!C40+抖音达播!C40 -> 698638.3 | D40: =淘系!D40+抖音!D40+PDD!D40+得物!D40+京东自营财经口径!D40+京东POP财经口径!D40+'视频号+官网+小程序'!D40+快手!D40+唯品会!D40+'线下门店-直营'!D40+'线下门店-经销'!D40+线下渠道!D40+淘系达播!D40+抖音达播!D40 -> 794417.05 | E40: =淘系!E40+抖音!E40+PDD!E40+得物!E40+京东自营财经口径!E40+京东POP财经口径!E40+'视频号+官网+小程序'!E40+快手!E40+唯品会!E40+'线下门店-直营'!E40+'线下门店-经销'!E40+线下渠道!E40+淘系达播!E40+抖音达播!E40 -> 667442.57 | F40: =淘系!F40+抖音!F40+PDD!F40+得物!F40+京东自营财经口径!F40+京东POP财经口径!F40+'视频号+官网+小程序'!F40+快手!F40+唯品会!F40+'线下门店-直营'!F40+'线下门店-经销'!F40+线下渠道!F40+淘系达播!F40+抖音达播!F40 -> 562879.37 | G40: =淘系!G40+抖音!G40+PDD!G40+得物!G40+京东自营财经口径!G40+京东POP财经口径!G40+'视频号+官网+小程序'!G40+快手!G40+唯品会!G40+'线下门店-直营'!G40+'线下门店-经销'!G40+线下渠道!G40+淘系达播!G40+抖音达播!G40 -> 1978191.3 | H40: =淘系!H40+抖音!H40+PDD!H40+得物!H40+京东自营财经口径!H40+京东POP财经口径!H40+'视频号+官网+小程序'!H40+快手!H40+唯品会!H40+'线下门店-直营'!H40+'线下门店-经销'!H40+线下渠道!H40+淘系达播!H40+抖音达播!H40 -> 1391355.1 | I40: =淘系!I40+抖音!I40+PDD!I40+得物!I40+京东自营财经口径!I40+京东POP财经口径!I40+'视频号+官网+小程序'!I40+快手!I40+唯品会!I40+'线下门店-直营'!I40+'线下门店-经销'!I40+线下渠道!I40+淘系达播!I40+抖音达播!I40 -> 733176.96 | J40: =淘系!J40+抖音!J40+PDD!J40+得物!J40+京东自营财经口径!J40+京东POP财经口径!J40+'视频号+官网+小程序'!J40+快手!J40+唯品会!J40+'线下门店-直营'!J40+'线下门店-经销'!J40+线下渠道!J40+淘系达播!J40+抖音达播!J40 -> 1398044.6 | ... N40: =淘系!N40+抖音!N40+PDD!N40+得物!N40+京东自营财经口径!N40+京东POP财经口径!N40+'视频号+官网+小程序'!N40+快手!N40+唯品会!N40+'线下门店-直营'!N40+'线下门店-经销'!N40+线下渠道!N40+淘系达播!N40+抖音达播!N40 -> 908636.98 | O40: =SUM(C40:N40) -> 13143425 | P40: =O40/$O$16 -> 0.032531273 | Q40: 投放填写 | R40: =淘系!O31 -> 9080973.7 | S40: =R40/$R$39 -> 0.43904531 | T40: =O40-淘系!O40-淘系达播!O40-抖音!O40-抖音达播!O40-快手!O40-京东POP财经口径!O40-京东自营财经口径!O40-PDD!O40-得物!O40-'视频号+官网+小程序'!O40-唯品会!O40-'线下门店-直营'!O40-'线下门店-经销'!O40-线下渠道!O40 -> 0
B41: 站内投放（费率） | C41: =C38/C$16 -> 0.08299872 | D41: =D38/D$16 -> 0.099542454 | E41: =E38/E$16 -> 0.094090036 | F41: =F38/F$16 -> 0.092964652 | G41: =G38/G$16 -> 0.11110053 | H41: =H38/H$16 -> 0.1174151 | I41: =I38/I$16 -> 0.094903997 | J41: =J38/J$16 -> 0.1236918 | ... N41: =N38/N$16 -> 0.085494541 | O41: =O38/$O$16 -> 0.1037836 | Q41: 投放填写 | S41: =R41/$R$39 -> 0 | T41: =O41-淘系!O41-淘系达播!O41-抖音!O41-抖音达播!O41-快手!O41-京东POP财经口径!O41-京东自营财经口径!O41-PDD!O41-得物!O41-'视频号+官网+小程序'!O41-唯品会!O41-'线下门店-直营'!O41-'线下门店-经销'!O41-线下渠道!O41 -> -0.99470872
B42: 千川投放（费率） | C42: =C39/C$16 -> 0.083233492 | D42: =D39/D$16 -> 0.089368827 | E42: =E39/E$16 -> 0.067055511 | F42: =F39/F$16 -> 0.065357458 | G42: =G39/G$16 -> 0.071851556 | H42: =H39/H$16 -> 0.071819493 | I42: =I39/I$16 -> 0.05906943 | J42: =J39/J$16 -> 0.06873944 | ... N42: =N39/N$16 -> 0.068984278 | O42: =O39/$O$16 -> 0.06868513 | Q42: 投放填写 | S42: =R42/$R$39 -> 0 | T42: =O42-淘系!O42-淘系达播!O42-抖音!O42-抖音达播!O42-快手!O42-京东POP财经口径!O42-京东自营财经口径!O42-PDD!O42-得物!O42-'视频号+官网+小程序'!O42-唯品会!O42-'线下门店-直营'!O42-'线下门店-经销'!O42-线下渠道!O42 -> -0.29602075
B43: 站外投放（费率） | C43: =C40/C$16 -> 0.025299121 | D43: =D40/D$16 -> 0.028764321 | E43: =E40/E$16 -> 0.028289393 | F43: =F40/F$16 -> 0.027531979 | G43: =G40/G$16 -> 0.046287068 | H43: =H40/H$16 -> 0.035795481 | I43: =I40/I$16 -> 0.027009546 | J43: =J40/J$16 -> 0.037202136 | ... N43: =N40/N$16 -> 0.024379864 | O43: =O40/$O$16 -> 0.032531273 | Q43: 投放填写 | S43: =R43/$R$39 -> 0 | T43: =O43-淘系!O43-淘系达播!O43-抖音!O43-抖音达播!O43-快手!O43-京东POP财经口径!O43-京东自营财经口径!O43-PDD!O43-得物!O43-'视频号+官网+小程序'!O43-唯品会!O43-'线下门店-直营'!O43-'线下门店-经销'!O43-线下渠道!O43 -> -0.09050279
B44: 线上营销费用 | C44: =SUM(C45:C46) -> 873457.07 | D44: =SUM(D45:D46) -> 891315.7 | E44: =SUM(E45:E46) -> 784090.16 | F44: =SUM(F45:F46) -> 610146.64 | G44: =SUM(G45:G46) -> 1521937.3 | H44: =SUM(H45:H46) -> 1188479.9 | I44: =SUM(I45:I46) -> 779366.81 | J44: =SUM(J45:J46) -> 1264018.6 | ... N44: =SUM(N45:N46) -> 1089471.6 | O44: =SUM(C44:N44) -> 13187609 | P44: =O44/$O$16 -> 0.032640634 | R44: =抖音!O31 -> 5348171.2 | S44: =R44/$R$39 -> 0.25857244 | T44: =O44-淘系!O44-淘系达播!O44-抖音!O44-抖音达播!O44-快手!O44-京东POP财经口径!O44-京东自营财经口径!O44-PDD!O44-得物!O44-'视频号+官网+小程序'!O44-唯品会!O44-'线下门店-直营'!O44-'线下门店-经销'!O44-线下渠道!O44 -> -1.2805685e-09
B45: 直播费用 | C45: =淘系!C45+抖音!C45+PDD!C45+得物!C45+京东自营财经口径!C45+京东POP财经口径!C45+'视频号+官网+小程序'!C45+快手!C45+唯品会!C45+'线下门店-直营'!C45+'线下门店-经销'!C45+线下渠道!C45+淘系达播!C45+抖音达播!C45 -> 162529.49 | D45: =淘系!D45+抖音!D45+PDD!D45+得物!D45+京东自营财经口径!D45+京东POP财经口径!D45+'视频号+官网+小程序'!D45+快手!D45+唯品会!D45+'线下门店-直营'!D45+'线下门店-经销'!D45+线下渠道!D45+淘系达播!D45+抖音达播!D45 -> 155166.99 | E45: =淘系!E45+抖音!E45+PDD!E45+得物!E45+京东自营财经口径!E45+京东POP财经口径!E45+'视频号+官网+小程序'!E45+快手!E45+唯品会!E45+'线下门店-直营'!E45+'线下门店-经销'!E45+线下渠道!E45+淘系达播!E45+抖音达播!E45 -> 194579.22 | F45: =淘系!F45+抖音!F45+PDD!F45+得物!F45+京东自营财经口径!F45+京东POP财经口径!F45+'视频号+官网+小程序'!F45+快手!F45+唯品会!F45+'线下门店-直营'!F45+'线下门店-经销'!F45+线下渠道!F45+淘系达播!F45+抖音达播!F45 -> 106561.31 | G45: =淘系!G45+抖音!G45+PDD!G45+得物!G45+京东自营财经口径!G45+京东POP财经口径!G45+'视频号+官网+小程序'!G45+快手!G45+唯品会!G45+'线下门店-直营'!G45+'线下门店-经销'!G45+线下渠道!G45+淘系达播!G45+抖音达播!G45 -> 442337.33 | H45: =淘系!H45+抖音!H45+PDD!H45+得物!H45+京东自营财经口径!H45+京东POP财经口径!H45+'视频号+官网+小程序'!H45+快手!H45+唯品会!H45+'线下门店-直营'!H45+'线下门店-经销'!H45+线下渠道!H45+淘系达播!H45+抖音达播!H45 -> 242039.41 | I45: =淘系!I45+抖音!I45+PDD!I45+得物!I45+京东自营财经口径!I45+京东POP财经口径!I45+'视频号+官网+小程序'!I45+快手!I45+唯品会!I45+'线下门店-直营'!I45+'线下门店-经销'!I45+线下渠道!I45+淘系达播!I45+抖音达播!I45 -> 126179.03 | J45: =淘系!J45+抖音!J45+PDD!J45+得物!J45+京东自营财经口径!J45+京东POP财经口径!J45+'视频号+官网+小程序'!J45+快手!J45+唯品会!J45+'线下门店-直营'!J45+'线下门店-经销'!J45+线下渠道!J45+淘系达播!J45+抖音达播!J45 -> 326056.34 | ... N45: =淘系!N45+抖音!N45+PDD!N45+得物!N45+京东自营财经口径!N45+京东POP财经口径!N45+'视频号+官网+小程序'!N45+快手!N45+唯品会!N45+'线下门店-直营'!N45+'线下门店-经销'!N45+线下渠道!N45+淘系达播!N45+抖音达播!N45 -> 174825.03 | O45: =SUM(C45:N45) -> 3171238.9 | P45: =O45/$O$16 -> 0.0078491293 | Q45: 达人填写 | R45: =京东自营财经口径!O31 -> 6254309.5 | S45: =R45/$R$39 -> 0.30238225 | T45: =O45-淘系!O45-淘系达播!O45-抖音!O45-抖音达播!O45-快手!O45-京东POP财经口径!O45-京东自营财经口径!O45-PDD!O45-得物!O45-'视频号+官网+小程序'!O45-唯品会!O45-'线下门店-直营'!O45-'线下门店-经销'!O45-线下渠道!O45 -> -5.3842086e-10
B46: 赠品费用 | C46: =淘系!C46+抖音!C46+PDD!C46+得物!C46+京东自营财经口径!C46+京东POP财经口径!C46+'视频号+官网+小程序'!C46+快手!C46+唯品会!C46+'线下门店-直营'!C46+'线下门店-经销'!C46+线下渠道!C46+淘系达播!C46+抖音达播!C46 -> 710927.58 | D46: =淘系!D46+抖音!D46+PDD!D46+得物!D46+京东自营财经口径!D46+京东POP财经口径!D46+'视频号+官网+小程序'!D46+快手!D46+唯品会!D46+'线下门店-直营'!D46+'线下门店-经销'!D46+线下渠道!D46+淘系达播!D46+抖音达播!D46 -> 736148.72 | E46: =淘系!E46+抖音!E46+PDD!E46+得物!E46+京东自营财经口径!E46+京东POP财经口径!E46+'视频号+官网+小程序'!E46+快手!E46+唯品会!E46+'线下门店-直营'!E46+'线下门店-经销'!E46+线下渠道!E46+淘系达播!E46+抖音达播!E46 -> 589510.94 | F46: =淘系!F46+抖音!F46+PDD!F46+得物!F46+京东自营财经口径!F46+京东POP财经口径!F46+'视频号+官网+小程序'!F46+快手!F46+唯品会!F46+'线下门店-直营'!F46+'线下门店-经销'!F46+线下渠道!F46+淘系达播!F46+抖音达播!F46 -> 503585.33 | G46: =淘系!G46+抖音!G46+PDD!G46+得物!G46+京东自营财经口径!G46+京东POP财经口径!G46+'视频号+官网+小程序'!G46+快手!G46+唯品会!G46+'线下门店-直营'!G46+'线下门店-经销'!G46+线下渠道!G46+淘系达播!G46+抖音达播!G46 -> 1079600 | H46: =淘系!H46+抖音!H46+PDD!H46+得物!H46+京东自营财经口径!H46+京东POP财经口径!H46+'视频号+官网+小程序'!H46+快手!H46+唯品会!H46+'线下门店-直营'!H46+'线下门店-经销'!H46+线下渠道!H46+淘系达播!H46+抖音达播!H46 -> 946440.5 | I46: =淘系!I46+抖音!I46+PDD!I46+得物!I46+京东自营财经口径!I46+京东POP财经口径!I46+'视频号+官网+小程序'!I46+快手!I46+唯品会!I46+'线下门店-直营'!I46+'线下门店-经销'!I46+线下渠道!I46+淘系达播!I46+抖音达播!I46 -> 653187.78 | J46: =淘系!J46+抖音!J46+PDD!J46+得物!J46+京东自营财经口径!J46+京东POP财经口径!J46+'视频号+官网+小程序'!J46+快手!J46+唯品会!J46+'线下门店-直营'!J46+'线下门店-经销'!J46+线下渠道!J46+淘系达播!J46+抖音达播!J46 -> 937962.25 | ... N46: =淘系!N46+抖音!N46+PDD!N46+得物!N46+京东自营财经口径!N46+京东POP财经口径!N46+'视频号+官网+小程序'!N46+快手!N46+唯品会!N46+'线下门店-直营'!N46+'线下门店-经销'!N46+线下渠道!N46+淘系达播!N46+抖音达播!N46 -> 914646.58 | O46: =SUM(C46:N46) -> 10016370 | P46: =O46/$O$16 -> 0.024791504 | Q46: 渠道填写 | T46: =O46-淘系!O46-淘系达播!O46-抖音!O46-抖音达播!O46-快手!O46-京东POP财经口径!O46-京东自营财经口径!O46-PDD!O46-得物!O46-'视频号+官网+小程序'!O46-唯品会!O46-'线下门店-直营'!O46-'线下门店-经销'!O46-线下渠道!O46 -> -18223.07
B47: 直播费用（费率） | C47: =C45/C$16 -> 0.005885525 | D47: =D45/D$16 -> 0.0056182997 | E47: =E45/E$16 -> 0.0082471934 | F47: =F45/F$16 -> 0.0052122069 | G47: =G45/G$16 -> 0.01035011 | H47: =H45/H$16 -> 0.0062269634 | I47: =I45/I$16 -> 0.0046483161 | J47: =J45/J$16 -> 0.0086763989 | ... O47: =O45/O$16 -> 0.0078491293
B48: 赠品费用（费率） | C48: =C46/C$16 -> 0.025744141 | D48: =D46/D$16 -> 0.026654536 | E48: =E46/E$16 -> 0.02498628 | F48: =F46/F$16 -> 0.024631745 | G48: =G46/G$16 -> 0.025261216 | H48: =H46/H$16 -> 0.024349135 | I48: =I46/I$16 -> 0.024062821 | J48: =J46/J$16 -> 0.024959289 | ... O48: =O46/O$16 -> 0.024791504
B49: 线下市场费用 | C49: =SUM(C50:C53) -> 657080.28 | D49: =SUM(D50:D53) -> 636510.42 | E49: =SUM(E50:E53) -> 641266.51 | F49: =SUM(F50:F53) -> 662889.29 | G49: =SUM(G50:G53) -> 717270.27 | H49: =SUM(H50:H53) -> 966198.14 | I49: =SUM(I50:I53) -> 933219.49 | J49: =SUM(J50:J53) -> 963447.11 | ... N49: =SUM(N50:N53) -> 1542325.9 | O49: =SUM(C49:N49) -> 11366424 | P49: =O49/$O$16 -> 0.028133022 | R49: =$R$38*S40+R40 -> 9080973.6 | T49: =O49-淘系!O47-淘系达播!O47-抖音!O47-抖音达播!O47-快手!O47-京东POP财经口径!O47-京东自营财经口径!O47-PDD!O47-得物!O47-'视频号+官网+小程序'!O47-唯品会!O47-'线下门店-直营'!O47-'线下门店-经销'!O47-线下渠道!O47 -> 0
B50: 线下渠道展陈、促销费用 | C50: =淘系!C48+抖音!C48+PDD!C48+得物!C48+京东自营财经口径!C48+京东POP财经口径!C48+'视频号+官网+小程序'!C48+快手!C48+唯品会!C48+'线下门店-直营'!C48+'线下门店-经销'!C48+线下渠道!C48+淘系达播!C48+抖音达播!C48 -> 273499.09 | D50: =淘系!D48+抖音!D48+PDD!D48+得物!D48+京东自营财经口径!D48+京东POP财经口径!D48+'视频号+官网+小程序'!D48+快手!D48+唯品会!D48+'线下门店-直营'!D48+'线下门店-经销'!D48+线下渠道!D48+淘系达播!D48+抖音达播!D48 -> 282312.63 | E50: =淘系!E48+抖音!E48+PDD!E48+得物!E48+京东自营财经口径!E48+京东POP财经口径!E48+'视频号+官网+小程序'!E48+快手!E48+唯品会!E48+'线下门店-直营'!E48+'线下门店-经销'!E48+线下渠道!E48+淘系达播!E48+抖音达播!E48 -> 248013.19 | F50: =淘系!F48+抖音!F48+PDD!F48+得物!F48+京东自营财经口径!F48+京东POP财经口径!F48+'视频号+官网+小程序'!F48+快手!F48+唯品会!F48+'线下门店-直营'!F48+'线下门店-经销'!F48+线下渠道!F48+淘系达播!F48+抖音达播!F48 -> 271172.87 | G50: =淘系!G48+抖音!G48+PDD!G48+得物!G48+京东自营财经口径!G48+京东POP财经口径!G48+'视频号+官网+小程序'!G48+快手!G48+唯品会!G48+'线下门店-直营'!G48+'线下门店-经销'!G48+线下渠道!G48+淘系达播!G48+抖音达播!G48 -> 411814.03 | H50: =淘系!H48+抖音!H48+PDD!H48+得物!H48+京东自营财经口径!H48+京东POP财经口径!H48+'视频号+官网+小程序'!H48+快手!H48+唯品会!H48+'线下门店-直营'!H48+'线下门店-经销'!H48+线下渠道!H48+淘系达播!H48+抖音达播!H48 -> 560242.14 | I50: =淘系!I48+抖音!I48+PDD!I48+得物!I48+京东自营财经口径!I48+京东POP财经口径!I48+'视频号+官网+小程序'!I48+快手!I48+唯品会!I48+'线下门店-直营'!I48+'线下门店-经销'!I48+线下渠道!I48+淘系达播!I48+抖音达播!I48 -> 548529.71 | J50: =淘系!J48+抖音!J48+PDD!J48+得物!J48+京东自营财经口径!J48+京东POP财经口径!J48+'视频号+官网+小程序'!J48+快手!J48+唯品会!J48+'线下门店-直营'!J48+'线下门店-经销'!J48+线下渠道!J48+淘系达播!J48+抖音达播!J48 -> 616741.81 | ... N50: =淘系!N48+抖音!N48+PDD!N48+得物!N48+京东自营财经口径!N48+京东POP财经口径!N48+'视频号+官网+小程序'!N48+快手!N48+唯品会!N48+'线下门店-直营'!N48+'线下门店-经销'!N48+线下渠道!N48+淘系达播!N48+抖音达播!N48 -> 1012182.7 | O50: =SUM(C50:N50) -> 6581385.2 | P50: =O50/$O$16 -> 0.016289578 | Q50: 线下门店 | R50: =R38*S44+R44 -> 5348171.2 | T50: =O50-淘系!O48-淘系达播!O48-抖音!O48-抖音达播!O48-快手!O48-京东POP财经口径!O48-京东自营财经口径!O48-PDD!O48-得物!O48-'视频号+官网+小程序'!O48-唯品会!O48-'线下门店-直营'!O48-'线下门店-经销'!O48-线下渠道!O48 -> 0
B51: 租金+物业+水电 | C51: =淘系!C49+抖音!C49+PDD!C49+得物!C49+京东自营财经口径!C49+京东POP财经口径!C49+'视频号+官网+小程序'!C49+快手!C49+唯品会!C49+'线下门店-直营'!C49+'线下门店-经销'!C49+线下渠道!C49+淘系达播!C49+抖音达播!C49 -> 151958.47 | D51: =淘系!D49+抖音!D49+PDD!D49+得物!D49+京东自营财经口径!D49+京东POP财经口径!D49+'视频号+官网+小程序'!D49+快手!D49+唯品会!D49+'线下门店-直营'!D49+'线下门店-经销'!D49+线下渠道!D49+淘系达播!D49+抖音达播!D49 -> 132683.54 | E51: =淘系!E49+抖音!E49+PDD!E49+得物!E49+京东自营财经口径!E49+京东POP财经口径!E49+'视频号+官网+小程序'!E49+快手!E49+唯品会!E49+'线下门店-直营'!E49+'线下门店-经销'!E49+线下渠道!E49+淘系达播!E49+抖音达播!E49 -> 144087.64 | F51: =淘系!F49+抖音!F49+PDD!F49+得物!F49+京东自营财经口径!F49+京东POP财经口径!F49+'视频号+官网+小程序'!F49+快手!F49+唯品会!F49+'线下门店-直营'!F49+'线下门店-经销'!F49+线下渠道!F49+淘系达播!F49+抖音达播!F49 -> 135605.02 | G51: =淘系!G49+抖音!G49+PDD!G49+得物!G49+京东自营财经口径!G49+京东POP财经口径!G49+'视频号+官网+小程序'!G49+快手!G49+唯品会!G49+'线下门店-直营'!G49+'线下门店-经销'!G49+线下渠道!G49+淘系达播!G49+抖音达播!G49 -> 102872.77 | H51: =淘系!H49+抖音!H49+PDD!H49+得物!H49+京东自营财经口径!H49+京东POP财经口径!H49+'视频号+官网+小程序'!H49+快手!H49+唯品会!H49+'线下门店-直营'!H49+'线下门店-经销'!H49+线下渠道!H49+淘系达播!H49+抖音达播!H49 -> 143943.35 | I51: =淘系!I49+抖音!I49+PDD!I49+得物!I49+京东自营财经口径!I49+京东POP财经口径!I49+'视频号+官网+小程序'!I49+快手!I49+唯品会!I49+'线下门店-直营'!I49+'线下门店-经销'!I49+线下渠道!I49+淘系达播!I49+抖音达播!I49 -> 131789.64 | J51: =淘系!J49+抖音!J49+PDD!J49+得物!J49+京东自营财经口径!J49+京东POP财经口径!J49+'视频号+官网+小程序'!J49+快手!J49+唯品会!J49+'线下门店-直营'!J49+'线下门店-经销'!J49+线下渠道!J49+淘系达播!J49+抖音达播!J49 -> 112127.73 | ... N51: =淘系!N49+抖音!N49+PDD!N49+得物!N49+京东自营财经口径!N49+京东POP财经口径!N49+'视频号+官网+小程序'!N49+快手!N49+唯品会!N49+'线下门店-直营'!N49+'线下门店-经销'!N49+线下渠道!N49+淘系达播!N49+抖音达播!N49 -> 139684.73 | O51: =SUM(C51:N51) -> 1566703.2 | P51: =O51/$O$16 -> 0.0038777451 | Q51: 线下门店 | R51: =R38*S45+R45 -> 6254309.4 | T51: =O51-淘系!O49-淘系达播!O49-抖音!O49-抖音达播!O49-快手!O49-京东POP财经口径!O49-京东自营财经口径!O49-PDD!O49-得物!O49-'视频号+官网+小程序'!O49-唯品会!O49-'线下门店-直营'!O49-'线下门店-经销'!O49-线下渠道!O49 -> 0
B52: 门店人工 | C52: =淘系!C50+抖音!C50+PDD!C50+得物!C50+京东自营财经口径!C50+京东POP财经口径!C50+'视频号+官网+小程序'!C50+快手!C50+唯品会!C50+'线下门店-直营'!C50+'线下门店-经销'!C50+线下渠道!C50+淘系达播!C50+抖音达播!C50 -> 112000 | D52: =淘系!D50+抖音!D50+PDD!D50+得物!D50+京东自营财经口径!D50+京东POP财经口径!D50+'视频号+官网+小程序'!D50+快手!D50+唯品会!D50+'线下门店-直营'!D50+'线下门店-经销'!D50+线下渠道!D50+淘系达播!D50+抖音达播!D50 -> 120000 | E52: =淘系!E50+抖音!E50+PDD!E50+得物!E50+京东自营财经口径!E50+京东POP财经口径!E50+'视频号+官网+小程序'!E50+快手!E50+唯品会!E50+'线下门店-直营'!E50+'线下门店-经销'!E50+线下渠道!E50+淘系达播!E50+抖音达播!E50 -> 132000 | F52: =淘系!F50+抖音!F50+PDD!F50+得物!F50+京东自营财经口径!F50+京东POP财经口径!F50+'视频号+官网+小程序'!F50+快手!F50+唯品会!F50+'线下门店-直营'!F50+'线下门店-经销'!F50+线下渠道!F50+淘系达播!F50+抖音达播!F50 -> 145000 | G52: =淘系!G50+抖音!G50+PDD!G50+得物!G50+京东自营财经口径!G50+京东POP财经口径!G50+'视频号+官网+小程序'!G50+快手!G50+唯品会!G50+'线下门店-直营'!G50+'线下门店-经销'!G50+线下渠道!G50+淘系达播!G50+抖音达播!G50 -> 110000 | H52: =淘系!H50+抖音!H50+PDD!H50+得物!H50+京东自营财经口径!H50+京东POP财经口径!H50+'视频号+官网+小程序'!H50+快手!H50+唯品会!H50+'线下门店-直营'!H50+'线下门店-经销'!H50+线下渠道!H50+淘系达播!H50+抖音达播!H50 -> 135000 | I52: =淘系!I50+抖音!I50+PDD!I50+得物!I50+京东自营财经口径!I50+京东POP财经口径!I50+'视频号+官网+小程序'!I50+快手!I50+唯品会!I50+'线下门店-直营'!I50+'线下门店-经销'!I50+线下渠道!I50+淘系达播!I50+抖音达播!I50 -> 120000 | J52: =淘系!J50+抖音!J50+PDD!J50+得物!J50+京东自营财经口径!J50+京东POP财经口径!J50+'视频号+官网+小程序'!J50+快手!J50+唯品会!J50+'线下门店-直营'!J50+'线下门店-经销'!J50+线下渠道!J50+淘系达播!J50+抖音达播!J50 -> 110000 | ... N52: =淘系!N50+抖音!N50+PDD!N50+得物!N50+京东自营财经口径!N50+京东POP财经口径!N50+'视频号+官网+小程序'!N50+快手!N50+唯品会!N50+'线下门店-直营'!N50+'线下门店-经销'!N50+线下渠道!N50+淘系达播!N50+抖音达播!N50 -> 145000 | O52: =SUM(C52:N52) -> 1509000 | P52: =O52/$O$16 -> 0.003734924 | Q52: 线下门店 | T52: =O52-淘系!O50-淘系达播!O50-抖音!O50-抖音达播!O50-快手!O50-京东POP财经口径!O50-京东自营财经口径!O50-PDD!O50-得物!O50-'视频号+官网+小程序'!O50-唯品会!O50-'线下门店-直营'!O50-'线下门店-经销'!O50-线下渠道!O50 -> 0
B53: 门店展陈装修等其他 | C53: =淘系!C51+抖音!C51+PDD!C51+得物!C51+京东自营财经口径!C51+京东POP财经口径!C51+'视频号+官网+小程序'!C51+快手!C51+唯品会!C51+'线下门店-直营'!C51+'线下门店-经销'!C51+线下渠道!C51+淘系达播!C51+抖音达播!C51 -> 119622.72 | D53: =淘系!D51+抖音!D51+PDD!D51+得物!D51+京东自营财经口径!D51+京东POP财经口径!D51+'视频号+官网+小程序'!D51+快手!D51+唯品会!D51+'线下门店-直营'!D51+'线下门店-经销'!D51+线下渠道!D51+淘系达播!D51+抖音达播!D51 -> 101514.26 | E53: =淘系!E51+抖音!E51+PDD!E51+得物!E51+京东自营财经口径!E51+京东POP财经口径!E51+'视频号+官网+小程序'!E51+快手!E51+唯品会!E51+'线下门店-直营'!E51+'线下门店-经销'!E51+线下渠道!E51+淘系达播!E51+抖音达播!E51 -> 117165.68 | F53: =淘系!F51+抖音!F51+PDD!F51+得物!F51+京东自营财经口径!F51+京东POP财经口径!F51+'视频号+官网+小程序'!F51+快手!F51+唯品会!F51+'线下门店-直营'!F51+'线下门店-经销'!F51+线下渠道!F51+淘系达播!F51+抖音达播!F51 -> 111111.4 | G53: =淘系!G51+抖音!G51+PDD!G51+得物!G51+京东自营财经口径!G51+京东POP财经口径!G51+'视频号+官网+小程序'!G51+快手!G51+唯品会!G51+'线下门店-直营'!G51+'线下门店-经销'!G51+线下渠道!G51+淘系达播!G51+抖音达播!G51 -> 92583.465 | H53: =淘系!H51+抖音!H51+PDD!H51+得物!H51+京东自营财经口径!H51+京东POP财经口径!H51+'视频号+官网+小程序'!H51+快手!H51+唯品会!H51+'线下门店-直营'!H51+'线下门店-经销'!H51+线下渠道!H51+淘系达播!H51+抖音达播!H51 -> 127012.66 | I53: =淘系!I51+抖音!I51+PDD!I51+得物!I51+京东自营财经口径!I51+京东POP财经口径!I51+'视频号+官网+小程序'!I51+快手!I51+唯品会!I51+'线下门店-直营'!I51+'线下门店-经销'!I51+线下渠道!I51+淘系达播!I51+抖音达播!I51 -> 132900.14 | J53: =淘系!J51+抖音!J51+PDD!J51+得物!J51+京东自营财经口径!J51+京东POP财经口径!J51+'视频号+官网+小程序'!J51+快手!J51+唯品会!J51+'线下门店-直营'!J51+'线下门店-经销'!J51+线下渠道!J51+淘系达播!J51+抖音达播!J51 -> 124577.57 | ... N53: =淘系!N51+抖音!N51+PDD!N51+得物!N51+京东自营财经口径!N51+京东POP财经口径!N51+'视频号+官网+小程序'!N51+快手!N51+唯品会!N51+'线下门店-直营'!N51+'线下门店-经销'!N51+线下渠道!N51+淘系达播!N51+抖音达播!N51 -> 245458.49 | O53: =SUM(C53:N53) -> 1709335.7 | P53: =O53/$O$16 -> 0.0042307746 | Q53: 线下门店 | T53: =O53-淘系!O51-淘系达播!O51-抖音!O51-抖音达播!O51-快手!O51-京东POP财经口径!O51-京东自营财经口径!O51-PDD!O51-得物!O51-'视频号+官网+小程序'!O51-唯品会!O51-'线下门店-直营'!O51-'线下门店-经销'!O51-线下渠道!O51 -> 0
B54: 市场投入费用 | C54: =SUM(C26,C37,C44,C49) -> 7571337.2 | D54: =SUM(D26,D37,D44,D49) -> 9749121.1 | E54: =SUM(E26,E37,E44,E49) -> 9523102.8 | F54: =SUM(F26,F37,F44,F49) -> 7160913.2 | G54: =SUM(G26,G37,G44,G49) -> 20137112 | H54: =SUM(H26,H37,H44,H49) -> 15693144 | I54: =SUM(I26,I37,I44,I49) -> 7714531.2 | J54: =SUM(J26,J37,J44,J49) -> 12496733 | ... N54: =SUM(N26,N37,N44,N49) -> 10539676 | O54: =SUM(C54:N54) -> 1.4037015e+08 | P54: =O54/$O$16 -> 0.34742997 | T54: =O54-淘系!O52-淘系达播!O52-抖音!O52-抖音达播!O52-快手!O52-京东POP财经口径!O52-京东自营财经口径!O52-PDD!O52-得物!O52-'视频号+官网+小程序'!O52-唯品会!O52-'线下门店-直营'!O52-'线下门店-经销'!O52-线下渠道!O52 -> -1.0244548e-08
B55: 平台佣金 | C55: =淘系!C53+抖音!C53+PDD!C53+得物!C53+京东自营财经口径!C53+京东POP财经口径!C53+'视频号+官网+小程序'!C53+快手!C53+唯品会!C53+'线下门店-直营'!C53+'线下门店-经销'!C53+线下渠道!C53+淘系达播!C53+抖音达播!C53 -> 545556.88 | D55: =淘系!D53+抖音!D53+PDD!D53+得物!D53+京东自营财经口径!D53+京东POP财经口径!D53+'视频号+官网+小程序'!D53+快手!D53+唯品会!D53+'线下门店-直营'!D53+'线下门店-经销'!D53+线下渠道!D53+淘系达播!D53+抖音达播!D53 -> 530099.86 | E55: =淘系!E53+抖音!E53+PDD!E53+得物!E53+京东自营财经口径!E53+京东POP财经口径!E53+'视频号+官网+小程序'!E53+快手!E53+唯品会!E53+'线下门店-直营'!E53+'线下门店-经销'!E53+线下渠道!E53+淘系达播!E53+抖音达播!E53 -> 459150.76 | F55: =淘系!F53+抖音!F53+PDD!F53+得物!F53+京东自营财经口径!F53+京东POP财经口径!F53+'视频号+官网+小程序'!F53+快手!F53+唯品会!F53+'线下门店-直营'!F53+'线下门店-经销'!F53+线下渠道!F53+淘系达播!F53+抖音达播!F53 -> 386682.7 | G55: =淘系!G53+抖音!G53+PDD!G53+得物!G53+京东自营财经口径!G53+京东POP财经口径!G53+'视频号+官网+小程序'!G53+快手!G53+唯品会!G53+'线下门店-直营'!G53+'线下门店-经销'!G53+线下渠道!G53+淘系达播!G53+抖音达播!G53 -> 881670.41 | H55: =淘系!H53+抖音!H53+PDD!H53+得物!H53+京东自营财经口径!H53+京东POP财经口径!H53+'视频号+官网+小程序'!H53+快手!H53+唯品会!H53+'线下门店-直营'!H53+'线下门店-经销'!H53+线下渠道!H53+淘系达播!H53+抖音达播!H53 -> 775856.22 | I55: =淘系!I53+抖音!I53+PDD!I53+得物!I53+京东自营财经口径!I53+京东POP财经口径!I53+'视频号+官网+小程序'!I53+快手!I53+唯品会!I53+'线下门店-直营'!I53+'线下门店-经销'!I53+线下渠道!I53+淘系达播!I53+抖音达播!I53 -> 507479.6 | J55: =淘系!J53+抖音!J53+PDD!J53+得物!J53+京东自营财经口径!J53+京东POP财经口径!J53+'视频号+官网+小程序'!J53+快手!J53+唯品会!J53+'线下门店-直营'!J53+'线下门店-经销'!J53+线下渠道!J53+淘系达播!J53+抖音达播!J53 -> 754147.41 | ... N55: =淘系!N53+抖音!N53+PDD!N53+得物!N53+京东自营财经口径!N53+京东POP财经口径!N53+'视频号+官网+小程序'!N53+快手!N53+唯品会!N53+'线下门店-直营'!N53+'线下门店-经销'!N53+线下渠道!N53+淘系达播!N53+抖音达播!N53 -> 670023.88 | O55: =SUM(C55:N55) -> 7876233.7 | P55: =O55/$O$16 -> 0.019494456 | T55: =O55-淘系!O53-淘系达播!O53-抖音!O53-抖音达播!O53-快手!O53-京东POP财经口径!O53-京东自营财经口径!O53-PDD!O53-得物!O53-'视频号+官网+小程序'!O53-唯品会!O53-'线下门店-直营'!O53-'线下门店-经销'!O53-线下渠道!O53 -> -1.1350494e-09
B56: 平台其他费用 | C56: =淘系!C54+抖音!C54+PDD!C54+得物!C54+京东自营财经口径!C54+京东POP财经口径!C54+'视频号+官网+小程序'!C54+快手!C54+唯品会!C54+'线下门店-直营'!C54+'线下门店-经销'!C54+线下渠道!C54+淘系达播!C54+抖音达播!C54 -> 361150.6 | D56: =淘系!D54+抖音!D54+PDD!D54+得物!D54+京东自营财经口径!D54+京东POP财经口径!D54+'视频号+官网+小程序'!D54+快手!D54+唯品会!D54+'线下门店-直营'!D54+'线下门店-经销'!D54+线下渠道!D54+淘系达播!D54+抖音达播!D54 -> 365217.22 | E56: =淘系!E54+抖音!E54+PDD!E54+得物!E54+京东自营财经口径!E54+京东POP财经口径!E54+'视频号+官网+小程序'!E54+快手!E54+唯品会!E54+'线下门店-直营'!E54+'线下门店-经销'!E54+线下渠道!E54+淘系达播!E54+抖音达播!E54 -> 305035.61 | F56: =淘系!F54+抖音!F54+PDD!F54+得物!F54+京东自营财经口径!F54+京东POP财经口径!F54+'视频号+官网+小程序'!F54+快手!F54+唯品会!F54+'线下门店-直营'!F54+'线下门店-经销'!F54+线下渠道!F54+淘系达播!F54+抖音达播!F54 -> 260450.25 | G56: =淘系!G54+抖音!G54+PDD!G54+得物!G54+京东自营财经口径!G54+京东POP财经口径!G54+'视频号+官网+小程序'!G54+快手!G54+唯品会!G54+'线下门店-直营'!G54+'线下门店-经销'!G54+线下渠道!G54+淘系达播!G54+抖音达播!G54 -> 464064.91 | H56: =淘系!H54+抖音!H54+PDD!H54+得物!H54+京东自营财经口径!H54+京东POP财经口径!H54+'视频号+官网+小程序'!H54+快手!H54+唯品会!H54+'线下门店-直营'!H54+'线下门店-经销'!H54+线下渠道!H54+淘系达播!H54+抖音达播!H54 -> 412716.56 | I56: =淘系!I54+抖音!I54+PDD!I54+得物!I54+京东自营财经口径!I54+京东POP财经口径!I54+'视频号+官网+小程序'!I54+快手!I54+唯品会!I54+'线下门店-直营'!I54+'线下门店-经销'!I54+线下渠道!I54+淘系达播!I54+抖音达播!I54 -> 339608.74 | J56: =淘系!J54+抖音!J54+PDD!J54+得物!J54+京东自营财经口径!J54+京东POP财经口径!J54+'视频号+官网+小程序'!J54+快手!J54+唯品会!J54+'线下门店-直营'!J54+'线下门店-经销'!J54+线下渠道!J54+淘系达播!J54+抖音达播!J54 -> 483451.94 | ... N56: =淘系!N54+抖音!N54+PDD!N54+得物!N54+京东自营财经口径!N54+京东POP财经口径!N54+'视频号+官网+小程序'!N54+快手!N54+唯品会!N54+'线下门店-直营'!N54+'线下门店-经销'!N54+线下渠道!N54+淘系达播!N54+抖音达播!N54 -> 456461.73 | O56: =SUM(C56:N56) -> 4784268.3 | P56: =O56/$O$16 -> 0.011841536 | T56: =O56-淘系!O54-淘系达播!O54-抖音!O54-抖音达播!O54-快手!O54-京东POP财经口径!O54-京东自营财经口径!O54-PDD!O54-得物!O54-'视频号+官网+小程序'!O54-唯品会!O54-'线下门店-直营'!O54-'线下门店-经销'!O54-线下渠道!O54 -> 3.7471182e-10
B57: 售后费用 | C57: =淘系!C55+抖音!C55+PDD!C55+得物!C55+京东自营财经口径!C55+京东POP财经口径!C55+'视频号+官网+小程序'!C55+快手!C55+唯品会!C55+'线下门店-直营'!C55+'线下门店-经销'!C55+线下渠道!C55+淘系达播!C55+抖音达播!C55 -> 2113042 | D57: =淘系!D55+抖音!D55+PDD!D55+得物!D55+京东自营财经口径!D55+京东POP财经口径!D55+'视频号+官网+小程序'!D55+快手!D55+唯品会!D55+'线下门店-直营'!D55+'线下门店-经销'!D55+线下渠道!D55+淘系达播!D55+抖音达播!D55 -> 1381742 | E57: =淘系!E55+抖音!E55+PDD!E55+得物!E55+京东自营财经口径!E55+京东POP财经口径!E55+'视频号+官网+小程序'!E55+快手!E55+唯品会!E55+'线下门店-直营'!E55+'线下门店-经销'!E55+线下渠道!E55+淘系达播!E55+抖音达播!E55 -> 1077748 | F57: =淘系!F55+抖音!F55+PDD!F55+得物!F55+京东自营财经口径!F55+京东POP财经口径!F55+'视频号+官网+小程序'!F55+快手!F55+唯品会!F55+'线下门店-直营'!F55+'线下门店-经销'!F55+线下渠道!F55+淘系达播!F55+抖音达播!F55 -> 1658593 | G57: =淘系!G55+抖音!G55+PDD!G55+得物!G55+京东自营财经口径!G55+京东POP财经口径!G55+'视频号+官网+小程序'!G55+快手!G55+唯品会!G55+'线下门店-直营'!G55+'线下门店-经销'!G55+线下渠道!G55+淘系达播!G55+抖音达播!G55 -> 1424395 | H57: =淘系!H55+抖音!H55+PDD!H55+得物!H55+京东自营财经口径!H55+京东POP财经口径!H55+'视频号+官网+小程序'!H55+快手!H55+唯品会!H55+'线下门店-直营'!H55+'线下门店-经销'!H55+线下渠道!H55+淘系达播!H55+抖音达播!H55 -> 997887 | I57: =淘系!I55+抖音!I55+PDD!I55+得物!I55+京东自营财经口径!I55+京东POP财经口径!I55+'视频号+官网+小程序'!I55+快手!I55+唯品会!I55+'线下门店-直营'!I55+'线下门店-经销'!I55+线下渠道!I55+淘系达播!I55+抖音达播!I55 -> 1390333 | J57: =淘系!J55+抖音!J55+PDD!J55+得物!J55+京东自营财经口径!J55+京东POP财经口径!J55+'视频号+官网+小程序'!J55+快手!J55+唯品会!J55+'线下门店-直营'!J55+'线下门店-经销'!J55+线下渠道!J55+淘系达播!J55+抖音达播!J55 -> 1075635 | ... N57: =淘系!N55+抖音!N55+PDD!N55+得物!N55+京东自营财经口径!N55+京东POP财经口径!N55+'视频号+官网+小程序'!N55+快手!N55+唯品会!N55+'线下门店-直营'!N55+'线下门店-经销'!N55+线下渠道!N55+淘系达播!N55+抖音达播!N55 -> 999777 | O57: =SUM(C57:N57) -> 15795916 | P57: =O57/$O$16 -> 0.039096452 | T57: =O57-淘系!O55-淘系达播!O55-抖音!O55-抖音达播!O55-快手!O55-京东POP财经口径!O55-京东自营财经口径!O55-PDD!O55-得物!O55-'视频号+官网+小程序'!O55-唯品会!O55-'线下门店-直营'!O55-'线下门店-经销'!O55-线下渠道!O55 -> 1066677.1
B58: 短信及店铺软件 | C58: =淘系!C56+抖音!C56+PDD!C56+得物!C56+京东自营财经口径!C56+京东POP财经口径!C56+'视频号+官网+小程序'!C56+快手!C56+唯品会!C56+'线下门店-直营'!C56+'线下门店-经销'!C56+线下渠道!C56+淘系达播!C56+抖音达播!C56 -> 46067.116 | D58: =淘系!D56+抖音!D56+PDD!D56+得物!D56+京东自营财经口径!D56+京东POP财经口径!D56+'视频号+官网+小程序'!D56+快手!D56+唯品会!D56+'线下门店-直营'!D56+'线下门店-经销'!D56+线下渠道!D56+淘系达播!D56+抖音达播!D56 -> 49007.405 | E58: =淘系!E56+抖音!E56+PDD!E56+得物!E56+京东自营财经口径!E56+京东POP财经口径!E56+'视频号+官网+小程序'!E56+快手!E56+唯品会!E56+'线下门店-直营'!E56+'线下门店-经销'!E56+线下渠道!E56+淘系达播!E56+抖音达播!E56 -> 36750.794 | F58: =淘系!F56+抖音!F56+PDD!F56+得物!F56+京东自营财经口径!F56+京东POP财经口径!F56+'视频号+官网+小程序'!F56+快手!F56+唯品会!F56+'线下门店-直营'!F56+'线下门店-经销'!F56+线下渠道!F56+淘系达播!F56+抖音达播!F56 -> 31207.446 | G58: =淘系!G56+抖音!G56+PDD!G56+得物!G56+京东自营财经口径!G56+京东POP财经口径!G56+'视频号+官网+小程序'!G56+快手!G56+唯品会!G56+'线下门店-直营'!G56+'线下门店-经销'!G56+线下渠道!G56+淘系达播!G56+抖音达播!G56 -> 67320.837 | H58: =淘系!H56+抖音!H56+PDD!H56+得物!H56+京东自营财经口径!H56+京东POP财经口径!H56+'视频号+官网+小程序'!H56+快手!H56+唯品会!H56+'线下门店-直营'!H56+'线下门店-经销'!H56+线下渠道!H56+淘系达播!H56+抖音达播!H56 -> 59261.026 | I58: =淘系!I56+抖音!I56+PDD!I56+得物!I56+京东自营财经口径!I56+京东POP财经口径!I56+'视频号+官网+小程序'!I56+快手!I56+唯品会!I56+'线下门店-直营'!I56+'线下门店-经销'!I56+线下渠道!I56+淘系达播!I56+抖音达播!I56 -> 39012.507 | J58: =淘系!J56+抖音!J56+PDD!J56+得物!J56+京东自营财经口径!J56+京东POP财经口径!J56+'视频号+官网+小程序'!J56+快手!J56+唯品会!J56+'线下门店-直营'!J56+'线下门店-经销'!J56+线下渠道!J56+淘系达播!J56+抖音达播!J56 -> 57007.786 | ... N58: =淘系!N56+抖音!N56+PDD!N56+得物!N56+京东自营财经口径!N56+京东POP财经口径!N56+'视频号+官网+小程序'!N56+快手!N56+唯品会!N56+'线下门店-直营'!N56+'线下门店-经销'!N56+线下渠道!N56+淘系达播!N56+抖音达播!N56 -> 55104.643 | O58: =SUM(C58:N58) -> 614606.61 | P58: =O58/$O$16 -> 0.001521212 | T58: =O58-淘系!O56-淘系达播!O56-抖音!O56-抖音达播!O56-快手!O56-京东POP财经口径!O56-京东自营财经口径!O56-PDD!O56-得物!O56-'视频号+官网+小程序'!O56-唯品会!O56-'线下门店-直营'!O56-'线下门店-经销'!O56-线下渠道!O56 -> 6.9348971e-11
B59: 其他运营费用（咨询调研等） | C59: =淘系!C57+抖音!C57+PDD!C57+得物!C57+京东自营财经口径!C57+京东POP财经口径!C57+'视频号+官网+小程序'!C57+快手!C57+唯品会!C57+'线下门店-直营'!C57+'线下门店-经销'!C57+线下渠道!C57+淘系达播!C57+抖音达播!C57 -> 250000 | D59: =淘系!D57+抖音!D57+PDD!D57+得物!D57+京东自营财经口径!D57+京东POP财经口径!D57+'视频号+官网+小程序'!D57+快手!D57+唯品会!D57+'线下门店-直营'!D57+'线下门店-经销'!D57+线下渠道!D57+淘系达播!D57+抖音达播!D57 -> 0 | E59: =淘系!E57+抖音!E57+PDD!E57+得物!E57+京东自营财经口径!E57+京东POP财经口径!E57+'视频号+官网+小程序'!E57+快手!E57+唯品会!E57+'线下门店-直营'!E57+'线下门店-经销'!E57+线下渠道!E57+淘系达播!E57+抖音达播!E57 -> 0 | F59: =淘系!F57+抖音!F57+PDD!F57+得物!F57+京东自营财经口径!F57+京东POP财经口径!F57+'视频号+官网+小程序'!F57+快手!F57+唯品会!F57+'线下门店-直营'!F57+'线下门店-经销'!F57+线下渠道!F57+淘系达播!F57+抖音达播!F57 -> 0 | G59: =淘系!G57+抖音!G57+PDD!G57+得物!G57+京东自营财经口径!G57+京东POP财经口径!G57+'视频号+官网+小程序'!G57+快手!G57+唯品会!G57+'线下门店-直营'!G57+'线下门店-经销'!G57+线下渠道!G57+淘系达播!G57+抖音达播!G57 -> 100000 | H59: =淘系!H57+抖音!H57+PDD!H57+得物!H57+京东自营财经口径!H57+京东POP财经口径!H57+'视频号+官网+小程序'!H57+快手!H57+唯品会!H57+'线下门店-直营'!H57+'线下门店-经销'!H57+线下渠道!H57+淘系达播!H57+抖音达播!H57 -> 0 | I59: =淘系!I57+抖音!I57+PDD!I57+得物!I57+京东自营财经口径!I57+京东POP财经口径!I57+'视频号+官网+小程序'!I57+快手!I57+唯品会!I57+'线下门店-直营'!I57+'线下门店-经销'!I57+线下渠道!I57+淘系达播!I57+抖音达播!I57 -> 0 | J59: =淘系!J57+抖音!J57+PDD!J57+得物!J57+京东自营财经口径!J57+京东POP财经口径!J57+'视频号+官网+小程序'!J57+快手!J57+唯品会!J57+'线下门店-直营'!J57+'线下门店-经销'!J57+线下渠道!J57+淘系达播!J57+抖音达播!J57 -> 0 | ... N59: =淘系!N57+抖音!N57+PDD!N57+得物!N57+京东自营财经口径!N57+京东POP财经口径!N57+'视频号+官网+小程序'!N57+快手!N57+唯品会!N57+'线下门店-直营'!N57+'线下门店-经销'!N57+线下渠道!N57+淘系达播!N57+抖音达播!N57 -> 300000 | O59: =SUM(C59:N59) -> 750000 | P59: =O59/$O$16 -> 0.001856324 | Q59: 新品需求调研，产品上市反馈 | T59: =O59-淘系!O57-淘系达播!O57-抖音!O57-抖音达播!O57-快手!O57-京东POP财经口径!O57-京东自营财经口径!O57-PDD!O57-得物!O57-'视频号+官网+小程序'!O57-唯品会!O57-'线下门店-直营'!O57-'线下门店-经销'!O57-线下渠道!O57 -> 0
B60: 店铺运营费用 | C60: =SUM(C55:C59) -> 3315816.6 | D60: =SUM(D55:D59) -> 2326066.5 | E60: =SUM(E55:E59) -> 1878685.2 | F60: =SUM(F55:F59) -> 2336933.4 | G60: =SUM(G55:G59) -> 2937451.2 | H60: =SUM(H55:H59) -> 2245720.8 | I60: =SUM(I55:I59) -> 2276433.9 | J60: =SUM(J55:J59) -> 2370242.1 | ... N60: =SUM(N55:N59) -> 2481367.3 | O60: =SUM(C60:N60) -> 29821025 | P60: =O60/$O$16 -> 0.07380998 | T60: =O60-淘系!O58-淘系达播!O58-抖音!O58-抖音达播!O58-快手!O58-京东POP财经口径!O58-京东自营财经口径!O58-PDD!O58-得物!O58-'视频号+官网+小程序'!O58-唯品会!O58-'线下门店-直营'!O58-'线下门店-经销'!O58-线下渠道!O58 -> -4.6566129e-09
B61: A&P 合计数 | C61: =SUM(C54,C60) -> 10887154 | D61: =SUM(D54,D60) -> 12075188 | E61: =SUM(E54,E60) -> 11401788 | F61: =SUM(F54,F60) -> 9497846.6 | G61: =SUM(G54,G60) -> 23074563 | H61: =SUM(H54,H60) -> 17938865 | I61: =SUM(I54,I60) -> 9990965 | J61: =SUM(J54,J60) -> 14866975 | ... N61: =SUM(N54,N60) -> 13021044 | O61: =SUM(C61:N61) -> 1.7019117e+08 | P61: =O61/$O$16 -> 0.42123995 | T61: =O61-淘系!O59-淘系达播!O59-抖音!O59-抖音达播!O59-快手!O59-京东POP财经口径!O59-京东自营财经口径!O59-PDD!O59-得物!O59-'视频号+官网+小程序'!O59-唯品会!O59-'线下门店-直营'!O59-'线下门店-经销'!O59-线下渠道!O59 -> 0
B62: 店铺利润 | C62: =C22-C61 -> 2518214.8 | D62: =D22-D61 -> 1423837.3 | E62: =E22-E61 -> -364449.22 | F62: =F22-F61 -> 87988.686 | G62: =G22-G61 -> -982261.36 | H62: =H22-H61 -> 1979342.4 | I62: =I22-I61 -> 4780281.2 | J62: =J22-J61 -> 5737516.6 | ... N62: =N22-N61 -> 8578812.4 | O62: =SUM(C62:N62) -> 44847957 | P62: =O62/$O$16 -> 0.11100312 | Q62: 1700万成本差 | T62: =O62-淘系!O60-淘系达播!O60-抖音!O60-抖音达播!O60-快手!O60-京东POP财经口径!O60-京东自营财经口径!O60-PDD!O60-得物!O60-'视频号+官网+小程序'!O60-唯品会!O60-'线下门店-直营'!O60-'线下门店-经销'!O60-线下渠道!O60 -> -40154.706
C63: =C62/C16 -> 0.091189706 | D63: =D62/D16 -> 0.051554425 | E63: =E62/E16 -> -0.015447093 | F63: =F62/F16 -> 0.0043037688 | G63: =G62/G16 -> -0.022983621 | H63: =H62/H16 -> 0.050922669 | I63: =I62/I16 -> 0.17610104 | J63: =J62/J16 -> 0.15267601 | ... O63: =O62/O16 -> 0.11100312
B65: BU 可控运营费用 | C65: =C66+C67 -> 4000000 | D65: =D66+D67 -> 4000000 | E65: =E66+E67 -> 3800000 | F65: =F66+F67 -> 3800000 | G65: =G66+G67 -> 3800000 | H65: =H66+H67 -> 2800000 | I65: =I66+I67 -> 2300000 | J65: =J66+J67 -> 2300000 | ... N65: =N66+N67 -> 2300000 | O65: =SUM(C65:N65) -> 36000000 | P65: =O65/$O$16 -> 0.089103554
B66: 销售管理费用 | C66: 500000 | D66: 500000 | E66: 500000 | F66: 500000 | G66: 500000 | H66: 500000 | I66: 500000 | J66: 500000 | K66: 500000 | L66: 500000 | M66: 500000 | N66: 500000 | O66: =SUM(C66:N66) -> 6000000 | P66: =O66/$O$16 -> 0.014850592
B67: 研发费用 | C67: 3500000 | D67: 3500000 | E67: 3300000 | F67: 3300000 | G67: 3300000 | H67: 2300000 | I67: 1800000 | J67: 1800000 | K67: 1800000 | L67: 1800000 | M67: 1800000 | N67: 1800000 | O67: =SUM(C67:N67) -> 30000000 | P67: =O67/$O$16 -> 0.074252962
B68: BU可控利润 | C68: =C62-C65 -> -1481785.2 | D68: =D62-D65 -> -2576162.7 | E68: =E62-E65 -> -4164449.2 | F68: =F62-F65 -> -3712011.3 | G68: =G62-G65 -> -4782261.4 | H68: =H62-H65 -> -820657.56 | I68: =I62-I65 -> 2480281.2 | J68: =J62-J65 -> 3437516.6 | ... N68: =N62-N65 -> 6278812.4 | O68: =SUM(C68:N68) -> 8847956.7 | P68: =O68/$O$16 -> 0.021899566
B70: BU贡献费用 | C70: 2800000 | D70: 2800000 | E70: 2800000 | F70: 2800000 | G70: 2800000 | H70: 2800000 | I70: 2800000 | J70: 2800000 | K70: 2800000 | L70: 2800000 | M70: 2800000 | N70: 2800000 | O70: =SUM(C70:N70) -> 33600000 | P70: =O70/$O$16 -> 0.083163317
B71: BU贡献利润 | C71: =C68-C70 -> -4281785.2 | D71: =D68-D70 -> -5376162.7 | E71: =E68-E70 -> -6964449.2 | F71: =F68-F70 -> -6512011.3 | G71: =G68-G70 -> -7582261.4 | H71: =H68-H70 -> -3620657.6 | I71: =I68-I70 -> -319718.77 | J71: =J68-J70 -> 637516.57 | ... N71: =N68-N70 -> 3478812.4 | O71: =SUM(C71:N71) -> -24752043 | P71: =O71/$O$16 -> -0.061263751
B73: 集团分摊费用 | C73: 1200000 | D73: 1200000 | E73: 1200000 | F73: 1200000 | G73: 1200000 | H73: 1200000 | I73: 1200000 | J73: 1200000 | K73: 1200000 | L73: 1200000 | M73: 1200000 | N73: 1200000 | O73: =SUM(C73:N73) -> 14400000 | P73: =O73/$O$16 -> 0.035641422
B75: 净利润 | C75: =C71-C73 -> -5481785.2 | D75: =D71-D73 -> -6576162.7 | E75: =E71-E73 -> -8164449.2 | F75: =F71-F73 -> -7712011.3 | G75: =G71-G73 -> -8782261.4 | H75: =H71-H73 -> -4820657.6 | I75: =I71-I73 -> -1519718.8 | J75: =J71-J73 -> -562483.43 | ... N75: =N71-N73 -> 2278812.4 | O75: =SUM(C75:N75) -> -39152043 | P75: =O75/$O$16 -> -0.096905172
B76: 净利润率 | C76: =C75/C16 -> -0.19850665 | D76: =D75/D16 -> -0.23811027 | E76: =E75/E16 -> -0.34604822 | F76: =F75/F16 -> -0.3772157 | G76: =G75/G16 -> -0.20549333 | H76: =H75/H16 -> -0.12402137 | I76: =I75/I16 -> -0.055985003 | J76: =J75/J16 -> -0.014967752 | ... N76: =N75/N16 -> 0.061143381
B78: 汇总 | C78: 去国补GMV | D78: 营业收入 | E78: 利润 | F78: 利润率
B79: 2026年全年 | C79: =O6 -> 5.7138404e+08 | D79: =O16 -> 4.0402429e+08 | E79: =O75 -> -39152043 | F79: =E79/D79 -> -0.096905172
B80: 26年H1 | C80: =SUM(C6:H6) -> 2.5286803e+08 | D80: =SUM(C16:H16) -> 1.8087824e+08 | E80: =SUM(C75:H75) -> -41537327 | F80: =E80/D80 -> -0.22964248
B81: 26年H2 | C81: =SUM(I6:N6) -> 3.1851601e+08 | D81: =SUM(I16:N16) -> 2.2314605e+08 | E81: =SUM(I75:N75) -> 2385284 | F81: =E81/D81 -> 0.01068934
C84: =C16-C18-C20-C26-C37-C44-C49-C60-C62 -> 0 | D84: =D16-D18-D20-D26-D37-D44-D49-D60-D62 -> -2.3283064e-09 | E84: =E16-E18-E20-E26-E37-E44-E49-E60-E62 -> 9.3132257e-10 | F84: =F16-F18-F20-F26-F37-F44-F49-F60-F62 -> 9.3132257e-10 | G84: =G16-G18-G20-G26-G37-G44-G49-G60-G62 -> 0 | H84: =H16-H18-H20-H26-H37-H44-H49-H60-H62 -> 0 | I84: =I16-I18-I20-I26-I37-I44-I49-I60-I62 -> 0 | J84: =J16-J18-J20-J26-J37-J44-J49-J60-J62 -> 0 | ... O84: =O16-O18-O20-O26-O37-O44-O49-O60-O62 -> 0
C85: =C10-C11-C12-C13-C15 -> -0.037740458 | D85: =D10-D11-D12-D13-D15 -> -0.02612561 | E85: =E10-E11-E12-E13-E15 -> 0.042607348 | F85: =F10-F11-F12-F13-F15 -> 0.03011547 | G85: =G10-G11-G12-G13-G15 -> -0.032073148 | H85: =H10-H11-H12-H13-H15 -> -0.027719341 | I85: =I10-I11-I12-I13-I15 -> 0.03220759 | J85: =J10-J11-J12-J13-J15 -> 0.04233516 | ... O85: =O10-O11-O12-O13-O15 -> 0.019280195
C86: =C62-淘系!C60-淘系达播!C60-抖音!C60-抖音达播!C60-快手!C60-京东POP财经口径!C60-京东自营财经口径!C60-PDD!C60-得物!C60-'视频号+官网+小程序'!C60-唯品会!C60-'线下门店-直营'!C60-'线下门店-经销'!C60-线下渠道!C60 -> -3212.3773 | D86: =D62-淘系!D60-淘系达播!D60-抖音!D60-抖音达播!D60-快手!D60-京东POP财经口径!D60-京东自营财经口径!D60-PDD!D60-得物!D60-'视频号+官网+小程序'!D60-唯品会!D60-'线下门店-直营'!D60-'线下门店-经销'!D60-线下渠道!D60 -> -3425.3841 | E86: =E62-淘系!E60-淘系达播!E60-抖音!E60-抖音达播!E60-快手!E60-京东POP财经口径!E60-京东自营财经口径!E60-PDD!E60-得物!E60-'视频号+官网+小程序'!E60-唯品会!E60-'线下门店-直营'!E60-'线下门店-经销'!E60-线下渠道!E60 -> -2786.3615 | F86: =F62-淘系!F60-淘系达播!F60-抖音!F60-抖音达播!F60-快手!F60-京东POP财经口径!F60-京东自营财经口径!F60-PDD!F60-得物!F60-'视频号+官网+小程序'!F60-唯品会!F60-'线下门店-直营'!F60-'线下门店-经销'!F60-线下渠道!F60 -> -2573.3548 | G86: =G62-淘系!G60-淘系达播!G60-抖音!G60-抖音达播!G60-快手!G60-京东POP财经口径!G60-京东自营财经口径!G60-PDD!G60-得物!G60-'视频号+官网+小程序'!G60-唯品会!G60-'线下门店-直营'!G60-'线下门店-经销'!G60-线下渠道!G60 -> -3474.3181 | H86: =H62-淘系!H60-淘系达播!H60-抖音!H60-抖音达播!H60-快手!H60-京东POP财经口径!H60-京东自营财经口径!H60-PDD!H60-得物!H60-'视频号+官网+小程序'!H60-唯品会!H60-'线下门店-直营'!H60-'线下门店-经销'!H60-线下渠道!H60 -> -3449.8511 | I86: =I62-淘系!I60-淘系达播!I60-抖音!I60-抖音达播!I60-快手!I60-京东POP财经口径!I60-京东自营财经口径!I60-PDD!I60-得物!I60-'视频号+官网+小程序'!I60-唯品会!I60-'线下门店-直营'!I60-'线下门店-经销'!I60-线下渠道!I60 -> -2597.8217 | J86: =J62-淘系!J60-淘系达播!J60-抖音!J60-抖音达播!J60-快手!J60-京东POP财经口径!J60-京东自营财经口径!J60-PDD!J60-得物!J60-'视频号+官网+小程序'!J60-唯品会!J60-'线下门店-直营'!J60-'线下门店-经销'!J60-线下渠道!J60 -> -4556.6231 | ... O86: =O62-淘系!O60-淘系达播!O60-抖音!O60-抖音达播!O60-快手!O60-京东POP财经口径!O60-京东自营财经口径!O60-PDD!O60-得物!O60-'视频号+官网+小程序'!O60-唯品会!O60-'线下门店-直营'!O60-'线下门店-经销'!O60-线下渠道!O60 -> -40154.706
B94: 品牌及内容费用 | C94: 590816.11 | D94: 1555478.6 | E94: 2581397.2 | F94: 1541409.8 | G94: 6001680.8 | H94: 3561493.5 | I94: 824897.7 | J94: 1275088.2 | K94: 1059422.3 | L94: 3244701 | M94: 1405008 | N94: 917198.16 | O94: 24558591 | P94: 0.06159487
B95: 展会 | C95: 0 | D95: 0 | E95: 64814.267 | F95: 54155.074 | G95: 115388.16 | H95: 101584.8 | I95: 65500.288 | J95: 90329.934 | K95: 72053.164 | L95: 121420.24 | M95: 91985.614 | N95: 0 | O95: 777231.54 | P95: 0.0019493576
B96: 品牌营销 | C96: 209195 | D96: 209195 | E96: 209195 | F96: 274181.09 | G96: 901523.98 | H96: 534266.37 | I96: 209195 | J96: 317590.92 | K96: 439765.12 | L96: 354899.29 | M96: 319577.74 | N96: 209195 | O96: 4187779.5 | P96: 0.010503279
B97: 内容素材制作 | C97: 31801.759 | D97: 25890.069 | E97: 25925.707 | F97: 108310.15 | G97: 692328.98 | H97: 446973.13 | I97: 0 | J97: 108395.92 | K97: 230570.12 | L97: 242840.48 | M97: 183971.23 | N97: 32181.962 | O97: 2129189.5 | P97: 0.005340174
B98: 公关费用 | C98: 31801.759 | D98: 25890.069 | E98: 207405.66 | F98: 21662.029 | G98: 138465.8 | H98: 40633.921 | I98: 26200.115 | J98: 36131.973 | K98: 28821.265 | L98: 97136.191 | M98: 73588.491 | N98: 32181.962 | O98: 759919.23 | P98: 0.0019059369
B99: 达人种草、样机及加热 | C99: 318017.59 | D99: 1294503.4 | E99: 2074056.6 | F99: 1083101.5 | G99: 4153973.9 | H99: 2438035.2 | I99: 524002.3 | J99: 722639.47 | K99: 288212.65 | L99: 2428404.8 | M99: 735884.91 | N99: 643639.24 | O99: 16704472 | P99: 0.041896123

Sheet 26年全渠道汇总（副本计算）
B1: Items | C1: 1月 | E1: 2月 | F1: 3月 | G1: 4月 | H1: 5月 | I1: 6月 | J1: 7月 | K1: 8月 | L1: 9月 | M1: 10月 | N1: 11月 | O1: 12月 | P1: 合计 1-12月 | Q1: 费比 | R1: 备注
B2: 退后销量 | C2: =淘系!C2+抖音!C2+PDD!C2+得物!C2+京东自营财经口径!C2+京东POP财经口径!C2+'视频号+官网+小程序'!C2+快手!C2+唯品会!C2+'线下门店-直营'!C2+'线下门店-经销'!C2+线下渠道!C2+淘系达播!C2+抖音达播!C2 -> 90463.684 | E2: =淘系!D2+抖音!D2+PDD!D2+得物!D2+京东自营财经口径!D2+京东POP财经口径!D2+'视频号+官网+小程序'!D2+快手!D2+唯品会!D2+'线下门店-直营'!D2+'线下门店-经销'!D2+线下渠道!D2+淘系达播!D2+抖音达播!D2 -> 81993.689 | F2: =淘系!E2+抖音!E2+PDD!E2+得物!E2+京东自营财经口径!E2+京东POP财经口径!E2+'视频号+官网+小程序'!E2+快手!E2+唯品会!E2+'线下门店-直营'!E2+'线下门店-经销'!E2+线下渠道!E2+淘系达播!E2+抖音达播!E2 -> 95977.292 | G2: =淘系!F2+抖音!F2+PDD!F2+得物!F2+京东自营财经口径!F2+京东POP财经口径!F2+'视频号+官网+小程序'!F2+快手!F2+唯品会!F2+'线下门店-直营'!F2+'线下门店-经销'!F2+线下渠道!F2+淘系达播!F2+抖音达播!F2 -> 80112.964 | H2: =淘系!G2+抖音!G2+PDD!G2+得物!G2+京东自营财经口径!G2+京东POP财经口径!G2+'视频号+官网+小程序'!G2+快手!G2+唯品会!G2+'线下门店-直营'!G2+'线下门店-经销'!G2+线下渠道!G2+淘系达播!G2+抖音达播!G2 -> 138286.3 | I2: =淘系!H2+抖音!H2+PDD!H2+得物!H2+京东自营财经口径!H2+京东POP财经口径!H2+'视频号+官网+小程序'!H2+快手!H2+唯品会!H2+'线下门店-直营'!H2+'线下门店-经销'!H2+线下渠道!H2+淘系达播!H2+抖音达播!H2 -> 121225.56 | J2: =淘系!I2+抖音!I2+PDD!I2+得物!I2+京东自营财经口径!I2+京东POP财经口径!I2+'视频号+官网+小程序'!I2+快手!I2+唯品会!I2+'线下门店-直营'!I2+'线下门店-经销'!I2+线下渠道!I2+淘系达播!I2+抖音达播!I2 -> 80120.129 | K2: =淘系!J2+抖音!J2+PDD!J2+得物!J2+京东自营财经口径!J2+京东POP财经口径!J2+'视频号+官网+小程序'!J2+快手!J2+唯品会!J2+'线下门店-直营'!J2+'线下门店-经销'!J2+线下渠道!J2+淘系达播!J2+抖音达播!J2 -> 99963.489 | L2: =淘系!K2+抖音!K2+PDD!K2+得物!K2+京东自营财经口径!K2+京东POP财经口径!K2+'视频号+官网+小程序'!K2+快手!K2+唯品会!K2+'线下门店-直营'!K2+'线下门店-经销'!K2+线下渠道!K2+淘系达播!K2+抖音达播!K2 -> 109614.03 | ... O2: =淘系!N2+抖音!N2+PDD!N2+得物!N2+京东自营财经口径!N2+京东POP财经口径!N2+'视频号+官网+小程序'!N2+快手!N2+唯品会!N2+'线下门店-直营'!N2+'线下门店-经销'!N2+线下渠道!N2+淘系达播!N2+抖音达播!N2 -> 104902.51 | P2: =SUM(C2:O2) -> 1264551.1
B3: 自补前GMV | P3: =SUM(C3:O3) -> 0 | R3: 渠道填写
B4: 自补前GSV | P4: =SUM(C4:O4) -> 0 | R4: 渠道填写
B5: 国补自补费用 | C5: =淘系!C5+抖音!C5+PDD!C5+得物!C5+京东自营财经口径!C5+京东POP财经口径!C5+'视频号+官网+小程序'!C5+快手!C5+唯品会!C5+'线下门店-直营'!C5+'线下门店-经销'!C5+线下渠道!C5+淘系达播!C5+抖音达播!C5 -> 4607684.7 | E5: =淘系!D5+抖音!D5+PDD!D5+得物!D5+京东自营财经口径!D5+京东POP财经口径!D5+'视频号+官网+小程序'!D5+快手!D5+唯品会!D5+'线下门店-直营'!D5+'线下门店-经销'!D5+线下渠道!D5+淘系达播!D5+抖音达播!D5 -> 4599816.6 | F5: =淘系!E5+抖音!E5+PDD!E5+得物!E5+京东自营财经口径!E5+京东POP财经口径!E5+'视频号+官网+小程序'!E5+快手!E5+唯品会!E5+'线下门店-直营'!E5+'线下门店-经销'!E5+线下渠道!E5+淘系达播!E5+抖音达播!E5 -> 3914048.7 | G5: =淘系!F5+抖音!F5+PDD!F5+得物!F5+京东自营财经口径!F5+京东POP财经口径!F5+'视频号+官网+小程序'!F5+快手!F5+唯品会!F5+'线下门店-直营'!F5+'线下门店-经销'!F5+线下渠道!F5+淘系达播!F5+抖音达播!F5 -> 3349087.8 | H5: =淘系!G5+抖音!G5+PDD!G5+得物!G5+京东自营财经口径!G5+京东POP财经口径!G5+'视频号+官网+小程序'!G5+快手!G5+唯品会!G5+'线下门店-直营'!G5+'线下门店-经销'!G5+线下渠道!G5+淘系达播!G5+抖音达播!G5 -> 7313638.2 | I5: =淘系!H5+抖音!H5+PDD!H5+得物!H5+京东自营财经口径!H5+京东POP财经口径!H5+'视频号+官网+小程序'!H5+快手!H5+唯品会!H5+'线下门店-直营'!H5+'线下门店-经销'!H5+线下渠道!H5+淘系达播!H5+抖音达播!H5 -> 6508325.2 | J5: =淘系!I5+抖音!I5+PDD!I5+得物!I5+京东自营财经口径!I5+京东POP财经口径!I5+'视频号+官网+小程序'!I5+快手!I5+唯品会!I5+'线下门店-直营'!I5+'线下门店-经销'!I5+线下渠道!I5+淘系达播!I5+抖音达播!I5 -> 4346063.5 | K5: =淘系!J5+抖音!J5+PDD!J5+得物!J5+京东自营财经口径!J5+京东POP财经口径!J5+'视频号+官网+小程序'!J5+快手!J5+唯品会!J5+'线下门店-直营'!J5+'线下门店-经销'!J5+线下渠道!J5+淘系达播!J5+抖音达播!J5 -> 6197224 | L5: =淘系!K5+抖音!K5+PDD!K5+得物!K5+京东自营财经口径!K5+京东POP财经口径!K5+'视频号+官网+小程序'!K5+快手!K5+唯品会!K5+'线下门店-直营'!K5+'线下门店-经销'!K5+线下渠道!K5+淘系达播!K5+抖音达播!K5 -> 4425098.7 | ... O5: =淘系!N5+抖音!N5+PDD!N5+得物!N5+京东自营财经口径!N5+京东POP财经口径!N5+'视频号+官网+小程序'!N5+快手!N5+唯品会!N5+'线下门店-直营'!N5+'线下门店-经销'!N5+线下渠道!N5+淘系达播!N5+抖音达播!N5 -> 5803843.5 | P5: =SUM(C5:O5) -> 66408445 | R5: 渠道填写
B6: GMV（国补后） | C6: =淘系!C6+抖音!C6+PDD!C6+得物!C6+京东自营财经口径!C6+京东POP财经口径!C6+'视频号+官网+小程序'!C6+快手!C6+唯品会!C6+'线下门店-直营'!C6++'线下门店-经销'!C6+线下渠道!C6+淘系达播!C6+抖音达播!C6 -> 38655631 | E6: =淘系!D6+抖音!D6+PDD!D6+得物!D6+京东自营财经口径!D6+京东POP财经口径!D6+'视频号+官网+小程序'!D6+快手!D6+唯品会!D6+'线下门店-直营'!D6++'线下门店-经销'!D6+线下渠道!D6+淘系达播!D6+抖音达播!D6 -> 38582248 | F6: =淘系!E6+抖音!E6+PDD!E6+得物!E6+京东自营财经口径!E6+京东POP财经口径!E6+'视频号+官网+小程序'!E6+快手!E6+唯品会!E6+'线下门店-直营'!E6++'线下门店-经销'!E6+线下渠道!E6+淘系达播!E6+抖音达播!E6 -> 32900883 | G6: =淘系!F6+抖音!F6+PDD!F6+得物!F6+京东自营财经口径!F6+京东POP财经口径!F6+'视频号+官网+小程序'!F6+快手!F6+唯品会!F6+'线下门店-直营'!F6++'线下门店-经销'!F6+线下渠道!F6+淘系达播!F6+抖音达播!F6 -> 27774427 | H6: =淘系!G6+抖音!G6+PDD!G6+得物!G6+京东自营财经口径!G6+京东POP财经口径!G6+'视频号+官网+小程序'!G6+快手!G6+唯品会!G6+'线下门店-直营'!G6++'线下门店-经销'!G6+线下渠道!G6+淘系达播!G6+抖音达播!G6 -> 60823575 | I6: =淘系!H6+抖音!H6+PDD!H6+得物!H6+京东自营财经口径!H6+京东POP财经口径!H6+'视频号+官网+小程序'!H6+快手!H6+唯品会!H6+'线下门店-直营'!H6++'线下门店-经销'!H6+线下渠道!H6+淘系达播!H6+抖音达播!H6 -> 54131266 | J6: =淘系!I6+抖音!I6+PDD!I6+得物!I6+京东自营财经口径!I6+京东POP财经口径!I6+'视频号+官网+小程序'!I6+快手!I6+唯品会!I6+'线下门店-直营'!I6++'线下门店-经销'!I6+线下渠道!I6+淘系达播!I6+抖音达播!I6 -> 37710759 | K6: =淘系!J6+抖音!J6+PDD!J6+得物!J6+京东自营财经口径!J6+京东POP财经口径!J6+'视频号+官网+小程序'!J6+快手!J6+唯品会!J6+'线下门店-直营'!J6++'线下门店-经销'!J6+线下渠道!J6+淘系达播!J6+抖音达播!J6 -> 53940593 | L6: =淘系!K6+抖音!K6+PDD!K6+得物!K6+京东自营财经口径!K6+京东POP财经口径!K6+'视频号+官网+小程序'!K6+快手!K6+唯品会!K6+'线下门店-直营'!K6++'线下门店-经销'!K6+线下渠道!K6+淘系达播!K6+抖音达播!K6 -> 40234860 | ... O6: =淘系!N6+抖音!N6+PDD!N6+得物!N6+京东自营财经口径!N6+京东POP财经口径!N6+'视频号+官网+小程序'!N6+快手!N6+唯品会!N6+'线下门店-直营'!N6++'线下门店-经销'!N6+线下渠道!N6+淘系达播!N6+抖音达播!N6 -> 51587222 | P6: =SUM(C6:O6) -> 5.7138404e+08 | R6: 渠道填写
B7: 退货率（发货前+后） | C7: =1-C8/C6 -> 0.19274148 | E7: =1-E8/E6 -> 0.19111768 | F7: =1-F8/F6 -> 0.18967141 | G7: =1-G8/G6 -> 0.16821472 | H7: =1-H8/H6 -> 0.20600984 | I7: =1-I8/I6 -> 0.1885906 | J7: =1-J8/J6 -> 0.18659903 | K7: =1-K8/K6 -> 0.21274421 | L7: =1-L8/L6 -> 0.22807461 | ... P7: =1-P8/P6 -> 0.20097971 | R7: 渠道填写
B8: GSV（国补后） | C8: =淘系!C8+抖音!C8+PDD!C8+得物!C8+京东自营财经口径!C8+京东POP财经口径!C8+'视频号+官网+小程序'!C8+快手!C8+唯品会!C8+'线下门店-直营'!C8++'线下门店-经销'!C8+线下渠道!C8+淘系达播!C8+抖音达播!C8 -> 31205088 | E8: =淘系!D8+抖音!D8+PDD!D8+得物!D8+京东自营财经口径!D8+京东POP财经口径!D8+'视频号+官网+小程序'!D8+快手!D8+唯品会!D8+'线下门店-直营'!D8++'线下门店-经销'!D8+线下渠道!D8+淘系达播!D8+抖音达播!D8 -> 31208498 | F8: =淘系!E8+抖音!E8+PDD!E8+得物!E8+京东自营财经口径!E8+京东POP财经口径!E8+'视频号+官网+小程序'!E8+快手!E8+唯品会!E8+'线下门店-直营'!E8++'线下门店-经销'!E8+线下渠道!E8+淘系达播!E8+抖音达播!E8 -> 26660526 | G8: =淘系!F8+抖音!F8+PDD!F8+得物!F8+京东自营财经口径!F8+京东POP财经口径!F8+'视频号+官网+小程序'!F8+快手!F8+唯品会!F8+'线下门店-直营'!F8++'线下门店-经销'!F8+线下渠道!F8+淘系达播!F8+抖音达播!F8 -> 23102360 | H8: =淘系!G8+抖音!G8+PDD!G8+得物!G8+京东自营财经口径!G8+京东POP财经口径!G8+'视频号+官网+小程序'!G8+快手!G8+唯品会!G8+'线下门店-直营'!G8++'线下门店-经销'!G8+线下渠道!G8+淘系达播!G8+抖音达播!G8 -> 48293320 | I8: =淘系!H8+抖音!H8+PDD!H8+得物!H8+京东自营财经口径!H8+京东POP财经口径!H8+'视频号+官网+小程序'!H8+快手!H8+唯品会!H8+'线下门店-直营'!H8++'线下门店-经销'!H8+线下渠道!H8+淘系达播!H8+抖音达播!H8 -> 43922618 | J8: =淘系!I8+抖音!I8+PDD!I8+得物!I8+京东自营财经口径!I8+京东POP财经口径!I8+'视频号+官网+小程序'!I8+快手!I8+唯品会!I8+'线下门店-直营'!I8++'线下门店-经销'!I8+线下渠道!I8+淘系达播!I8+抖音达播!I8 -> 30673968 | K8: =淘系!J8+抖音!J8+PDD!J8+得物!J8+京东自营财经口径!J8+京东POP财经口径!J8+'视频号+官网+小程序'!J8+快手!J8+唯品会!J8+'线下门店-直营'!J8++'线下门店-经销'!J8+线下渠道!J8+淘系达播!J8+抖音达播!J8 -> 42465045 | L8: =淘系!K8+抖音!K8+PDD!K8+得物!K8+京东自营财经口径!K8+京东POP财经口径!K8+'视频号+官网+小程序'!K8+快手!K8+唯品会!K8+'线下门店-直营'!K8++'线下门店-经销'!K8+线下渠道!K8+淘系达播!K8+抖音达播!K8 -> 31058310 | ... O8: =淘系!N8+抖音!N8+PDD!N8+得物!N8+京东自营财经口径!N8+京东POP财经口径!N8+'视频号+官网+小程序'!N8+快手!N8+唯品会!N8+'线下门店-直营'!N8++'线下门店-经销'!N8+线下渠道!N8+淘系达播!N8+抖音达播!N8 -> 42115074 | P8: =SUM(C8:O8) -> 4.5654745e+08 | R8: 渠道填写
B10: 零售价（去除退货后的） | C10: =淘系!C10+抖音!C10+PDD!C10+得物!C10+京东自营财经口径!C10+京东POP财经口径!C10+'视频号+官网+小程序'!C10+快手!C10+唯品会!C10+'线下门店-直营'!C10++'线下门店-经销'!C10+线下渠道!C10+淘系达播!C10+抖音达播!C10 -> 43169030 | E10: =淘系!D10+抖音!D10+PDD!D10+得物!D10+京东自营财经口径!D10+京东POP财经口径!D10+'视频号+官网+小程序'!D10+快手!D10+唯品会!D10+'线下门店-直营'!D10++'线下门店-经销'!D10+线下渠道!D10+淘系达播!D10+抖音达播!D10 -> 41319765 | F10: =淘系!E10+抖音!E10+PDD!E10+得物!E10+京东自营财经口径!E10+京东POP财经口径!E10+'视频号+官网+小程序'!E10+快手!E10+唯品会!E10+'线下门店-直营'!E10++'线下门店-经销'!E10+线下渠道!E10+淘系达播!E10+抖音达播!E10 -> 34649173 | G10: =淘系!F10+抖音!F10+PDD!F10+得物!F10+京东自营财经口径!F10+京东POP财经口径!F10+'视频号+官网+小程序'!F10+快手!F10+唯品会!F10+'线下门店-直营'!F10++'线下门店-经销'!F10+线下渠道!F10+淘系达播!F10+抖音达播!F10 -> 30349389 | H10: =淘系!G10+抖音!G10+PDD!G10+得物!G10+京东自营财经口径!G10+京东POP财经口径!G10+'视频号+官网+小程序'!G10+快手!G10+唯品会!G10+'线下门店-直营'!G10++'线下门店-经销'!G10+线下渠道!G10+淘系达播!G10+抖音达播!G10 -> 62773132 | I10: =淘系!H10+抖音!H10+PDD!H10+得物!H10+京东自营财经口径!H10+京东POP财经口径!H10+'视频号+官网+小程序'!H10+快手!H10+唯品会!H10+'线下门店-直营'!H10++'线下门店-经销'!H10+线下渠道!H10+淘系达播!H10+抖音达播!H10 -> 57311536 | J10: =淘系!I10+抖音!I10+PDD!I10+得物!I10+京东自营财经口径!I10+京东POP财经口径!I10+'视频号+官网+小程序'!I10+快手!I10+唯品会!I10+'线下门店-直营'!I10++'线下门店-经销'!I10+线下渠道!I10+淘系达播!I10+抖音达播!I10 -> 40240744 | K10: =淘系!J10+抖音!J10+PDD!J10+得物!J10+京东自营财经口径!J10+京东POP财经口径!J10+'视频号+官网+小程序'!J10+快手!J10+唯品会!J10+'线下门店-直营'!J10++'线下门店-经销'!J10+线下渠道!J10+淘系达播!J10+抖音达播!J10 -> 55453830 | L10: =淘系!K10+抖音!K10+PDD!K10+得物!K10+京东自营财经口径!K10+京东POP财经口径!K10+'视频号+官网+小程序'!K10+快手!K10+唯品会!K10+'线下门店-直营'!K10++'线下门店-经销'!K10+线下渠道!K10+淘系达播!K10+抖音达播!K10 -> 40718429 | ... O10: =淘系!N10+抖音!N10+PDD!N10+得物!N10+京东自营财经口径!N10+京东POP财经口径!N10+'视频号+官网+小程序'!N10+快手!N10+唯品会!N10+'线下门店-直营'!N10++'线下门店-经销'!N10+线下渠道!N10+淘系达播!N10+抖音达播!N10 -> 55451705 | P10: =SUM(C10:O10) -> 5.9951799e+08 | R10: 渠道第二次填写
B11: 合同折扣及返利 (线下） | C11: =淘系!C11+抖音!C11+PDD!C11+得物!C11+京东自营财经口径!C11+京东POP财经口径!C11+'视频号+官网+小程序'!C11+快手!C11+唯品会!C11+'线下门店-直营'!C11+'线下门店-经销'!C11+线下渠道!C11+淘系达播!C11+抖音达播!C11 -> 1195159.2 | E11: =淘系!D11+抖音!D11+PDD!D11+得物!D11+京东自营财经口径!D11+京东POP财经口径!D11+'视频号+官网+小程序'!D11+快手!D11+唯品会!D11+'线下门店-直营'!D11+'线下门店-经销'!D11+线下渠道!D11+淘系达播!D11+抖音达播!D11 -> 1300782.2 | F11: =淘系!E11+抖音!E11+PDD!E11+得物!E11+京东自营财经口径!E11+京东POP财经口径!E11+'视频号+官网+小程序'!E11+快手!E11+唯品会!E11+'线下门店-直营'!E11+'线下门店-经销'!E11+线下渠道!E11+淘系达播!E11+抖音达播!E11 -> 1017203.9 | G11: =淘系!F11+抖音!F11+PDD!F11+得物!F11+京东自营财经口径!F11+京东POP财经口径!F11+'视频号+官网+小程序'!F11+快手!F11+唯品会!F11+'线下门店-直营'!F11+'线下门店-经销'!F11+线下渠道!F11+淘系达播!F11+抖音达播!F11 -> 947622.99 | H11: =淘系!G11+抖音!G11+PDD!G11+得物!G11+京东自营财经口径!G11+京东POP财经口径!G11+'视频号+官网+小程序'!G11+快手!G11+唯品会!G11+'线下门店-直营'!G11+'线下门店-经销'!G11+线下渠道!G11+淘系达播!G11+抖音达播!G11 -> 1706368.4 | I11: =淘系!H11+抖音!H11+PDD!H11+得物!H11+京东自营财经口径!H11+京东POP财经口径!H11+'视频号+官网+小程序'!H11+快手!H11+唯品会!H11+'线下门店-直营'!H11+'线下门店-经销'!H11+线下渠道!H11+淘系达播!H11+抖音达播!H11 -> 1674116.6 | J11: =淘系!I11+抖音!I11+PDD!I11+得物!I11+京东自营财经口径!I11+京东POP财经口径!I11+'视频号+官网+小程序'!I11+快手!I11+唯品会!I11+'线下门店-直营'!I11+'线下门店-经销'!I11+线下渠道!I11+淘系达播!I11+抖音达播!I11 -> 1317289.2 | K11: =淘系!J11+抖音!J11+PDD!J11+得物!J11+京东自营财经口径!J11+京东POP财经口径!J11+'视频号+官网+小程序'!J11+快手!J11+唯品会!J11+'线下门店-直营'!J11+'线下门店-经销'!J11+线下渠道!J11+淘系达播!J11+抖音达播!J11 -> 1660136.2 | L11: =淘系!K11+抖音!K11+PDD!K11+得物!K11+京东自营财经口径!K11+京东POP财经口径!K11+'视频号+官网+小程序'!K11+快手!K11+唯品会!K11+'线下门店-直营'!K11+'线下门店-经销'!K11+线下渠道!K11+淘系达播!K11+抖音达播!K11 -> 1299971.8 | ... O11: =淘系!N11+抖音!N11+PDD!N11+得物!N11+京东自营财经口径!N11+京东POP财经口径!N11+'视频号+官网+小程序'!N11+快手!N11+唯品会!N11+'线下门店-直营'!N11+'线下门店-经销'!N11+线下渠道!N11+淘系达播!N11+抖音达播!N11 -> 2086010.3 | P11: =SUM(C11:O11) -> 18348907 | Q11: =P11/P8 -> 0.040190581 | R11: 线下渠道填写 | S11: =P11/$P$10 -> 0.030606099
B12: 国补自补 （线上） | C12: =淘系!C12+抖音!C12+PDD!C12+得物!C12+京东自营财经口径!C12+京东POP财经口径!C12+'视频号+官网+小程序'!C12+快手!C12+唯品会!C12+'线下门店-直营'!C12+'线下门店-经销'!C12+线下渠道!C12+淘系达播!C12+抖音达播!C12 -> 3374204.7 | E12: =淘系!D12+抖音!D12+PDD!D12+得物!D12+京东自营财经口径!D12+京东POP财经口径!D12+'视频号+官网+小程序'!D12+快手!D12+唯品会!D12+'线下门店-直营'!D12+'线下门店-经销'!D12+线下渠道!D12+淘系达播!D12+抖音达播!D12 -> 3225504 | F12: =淘系!E12+抖音!E12+PDD!E12+得物!E12+京东自营财经口径!E12+京东POP财经口径!E12+'视频号+官网+小程序'!E12+快手!E12+唯品会!E12+'线下门店-直营'!E12+'线下门店-经销'!E12+线下渠道!E12+淘系达播!E12+抖音达播!E12 -> 2793045.8 | G12: =淘系!F12+抖音!F12+PDD!F12+得物!F12+京东自营财经口径!F12+京东POP财经口径!F12+'视频号+官网+小程序'!F12+快手!F12+唯品会!F12+'线下门店-直营'!F12+'线下门店-经销'!F12+线下渠道!F12+淘系达播!F12+抖音达播!F12 -> 2421445.1 | H12: =淘系!G12+抖音!G12+PDD!G12+得物!G12+京东自营财经口径!G12+京东POP财经口径!G12+'视频号+官网+小程序'!G12+快手!G12+唯品会!G12+'线下门店-直营'!G12+'线下门店-经销'!G12+线下渠道!G12+淘系达播!G12+抖音达播!G12 -> 5483400.1 | I12: =淘系!H12+抖音!H12+PDD!H12+得物!H12+京东自营财经口径!H12+京东POP财经口径!H12+'视频号+官网+小程序'!H12+快手!H12+唯品会!H12+'线下门店-直营'!H12+'线下门店-经销'!H12+线下渠道!H12+淘系达播!H12+抖音达播!H12 -> 4885124.8 | J12: =淘系!I12+抖音!I12+PDD!I12+得物!I12+京东自营财经口径!I12+京东POP财经口径!I12+'视频号+官网+小程序'!I12+快手!I12+唯品会!I12+'线下门店-直营'!I12+'线下门店-经销'!I12+线下渠道!I12+淘系达播!I12+抖音达播!I12 -> 3103718.8 | K12: =淘系!J12+抖音!J12+PDD!J12+得物!J12+京东自营财经口径!J12+京东POP财经口径!J12+'视频号+官网+小程序'!J12+快手!J12+唯品会!J12+'线下门店-直营'!J12+'线下门店-经销'!J12+线下渠道!J12+淘系达播!J12+抖音达播!J12 -> 4576920.8 | L12: =淘系!K12+抖音!K12+PDD!K12+得物!K12+京东自营财经口径!K12+京东POP财经口径!K12+'视频号+官网+小程序'!K12+快手!K12+唯品会!K12+'线下门店-直营'!K12+'线下门店-经销'!K12+线下渠道!K12+淘系达播!K12+抖音达播!K12 -> 3197466.3 | ... O12: =淘系!N12+抖音!N12+PDD!N12+得物!N12+京东自营财经口径!N12+京东POP财经口径!N12+'视频号+官网+小程序'!N12+快手!N12+唯品会!N12+'线下门店-直营'!N12+'线下门店-经销'!N12+线下渠道!N12+淘系达播!N12+抖音达播!N12 -> 4234950.4 | P12: =SUM(C12:O12) -> 48800085 | Q12: =P12/P8 -> 0.1068894 | R12: 渠道填写 | S12: =P12/$P$10 -> 0.081398866
B13: 红包消费券等促销折扣 | C13: =淘系!C13+抖音!C13+PDD!C13+得物!C13+京东自营财经口径!C13+京东POP财经口径!C13+'视频号+官网+小程序'!C13+快手!C13+唯品会!C13+'线下门店-直营'!C13+'线下门店-经销'!C13+线下渠道!C13+淘系达播!C13+抖音达播!C13 -> 7394578.7 | E13: =淘系!D13+抖音!D13+PDD!D13+得物!D13+京东自营财经口径!D13+京东POP财经口径!D13+'视频号+官网+小程序'!D13+快手!D13+唯品会!D13+'线下门店-直营'!D13+'线下门店-经销'!D13+线下渠道!D13+淘系达播!D13+抖音达播!D13 -> 5584980.1 | F13: =淘系!E13+抖音!E13+PDD!E13+得物!E13+京东自营财经口径!E13+京东POP财经口径!E13+'视频号+官网+小程序'!E13+快手!E13+唯品会!E13+'线下门店-直营'!E13+'线下门店-经销'!E13+线下渠道!E13+淘系达播!E13+抖音达播!E13 -> 4178396.9 | G13: =淘系!F13+抖音!F13+PDD!F13+得物!F13+京东自营财经口径!F13+京东POP财经口径!F13+'视频号+官网+小程序'!F13+快手!F13+唯品会!F13+'线下门店-直营'!F13+'线下门店-经销'!F13+线下渠道!F13+淘系达播!F13+抖音达播!F13 -> 3877961.3 | H13: =淘系!G13+抖音!G13+PDD!G13+得物!G13+京东自营财经口径!G13+京东POP财经口径!G13+'视频号+官网+小程序'!G13+快手!G13+唯品会!G13+'线下门店-直营'!G13+'线下门店-经销'!G13+线下渠道!G13+淘系达播!G13+抖音达播!G13 -> 7290043.5 | I13: =淘系!H13+抖音!H13+PDD!H13+得物!H13+京东自营财经口径!H13+京东POP财经口径!H13+'视频号+官网+小程序'!H13+快手!H13+唯品会!H13+'线下门店-直营'!H13+'线下门店-经销'!H13+线下渠道!H13+淘系达播!H13+抖音达播!H13 -> 6829676.2 | J13: =淘系!I13+抖音!I13+PDD!I13+得物!I13+京东自营财经口径!I13+京东POP财经口径!I13+'视频号+官网+小程序'!I13+快手!I13+唯品会!I13+'线下门店-直营'!I13+'线下门店-经销'!I13+线下渠道!I13+淘系达播!I13+抖音达播!I13 -> 5145768 | K13: =淘系!J13+抖音!J13+PDD!J13+得物!J13+京东自营财经口径!J13+京东POP财经口径!J13+'视频号+官网+小程序'!J13+快手!J13+唯品会!J13+'线下门店-直营'!J13+'线下门店-经销'!J13+线下渠道!J13+淘系达播!J13+抖音达播!J13 -> 6751727.9 | L13: =淘系!K13+抖音!K13+PDD!K13+得物!K13+京东自营财经口径!K13+京东POP财经口径!K13+'视频号+官网+小程序'!K13+快手!K13+唯品会!K13+'线下门店-直营'!K13+'线下门店-经销'!K13+线下渠道!K13+淘系达播!K13+抖音达播!K13 -> 5162680.5 | ... O13: =淘系!N13+抖音!N13+PDD!N13+得物!N13+京东自营财经口径!N13+京东POP财经口径!N13+'视频号+官网+小程序'!N13+快手!N13+唯品会!N13+'线下门店-直营'!N13+'线下门店-经销'!N13+线下渠道!N13+淘系达播!N13+抖音达播!N13 -> 7015669.9 | P13: =SUM(C13:O13) -> 75821557 | Q13: =P13/P8 -> 0.16607596 | R13: 渠道填写 | S13: =P13/$P$10 -> 0.12647086
B14: TTL 折扣合计 | C14: =SUM(C11:C13) -> 11963943 | E14: =SUM(E11:E13) -> 10111266 | F14: =SUM(F11:F13) -> 7988646.6 | G14: =SUM(G11:G13) -> 7247029.4 | H14: =SUM(H11:H13) -> 14479812 | I14: =SUM(I11:I13) -> 13388918 | J14: =SUM(J11:J13) -> 9566775.9 | K14: =SUM(K11:K13) -> 12988785 | L14: =SUM(L11:L13) -> 9660118.5 | ... O14: =SUM(O11:O13) -> 13336631 | P14: =SUM(C14:O14) -> 1.4297055e+08 | Q14: =P14/P8 -> 0.31315595 | S14: =P14/$P$10 -> 0.23847583
B15: GSV | C15: =C8 -> 31205088 | E15: =E8 -> 31208498 | F15: =F8 -> 26660526 | G15: =G8 -> 23102360 | H15: =H8 -> 48293320 | I15: =I8 -> 43922618 | J15: =J8 -> 30673968 | K15: =K8 -> 42465045 | L15: =L8 -> 31058310 | ... O15: =O8 -> 42115074 | P15: =SUM(C15:O15) -> 4.5654745e+08
B16: 营业收入 | C16: =+C8/1.13 -> 27615122 | E16: =+E8/1.13 -> 27618140 | F16: =+F8/1.13 -> 23593386 | G16: =+G8/1.13 -> 20444566 | H16: =+H8/1.13 -> 42737451 | I16: =+I8/1.13 -> 38869573 | J16: =+J8/1.13 -> 27145104 | K16: =+K8/1.13 -> 37579685 | L16: =+L8/1.13 -> 27485230 | ... O16: =+O8/1.13 -> 37269977 | P16: =SUM(C16:O16) -> 4.0402429e+08 | U16: =P16-淘系!O16-淘系达播!O16-抖音!O16-抖音达播!O16-快手!O16-京东POP财经口径!O16-京东自营财经口径!O16-PDD!O16-得物!O16-'视频号+官网+小程序'!O16-唯品会!O16-'线下门店-直营'!O16-'线下门店-经销'!O16-线下渠道!O16 -> 0
C17: =C14/C15 -> 0.38339718 | U17: =P17-淘系!O17-淘系达播!O17-抖音!O17-抖音达播!O17-快手!O17-京东POP财经口径!O17-京东自营财经口径!O17-PDD!O17-得物!O17-'视频号+官网+小程序'!O17-唯品会!O17-'线下门店-直营'!O17-'线下门店-经销'!O17-线下渠道!O17 -> 0
B18: 标准主品配件成本 | C18: =淘系!C18+抖音!C18+PDD!C18+得物!C18+京东自营财经口径!C18+京东POP财经口径!C18+'视频号+官网+小程序'!C18+快手!C18+唯品会!C18+'线下门店-直营'!C18+'线下门店-经销'!C18+线下渠道!C18+淘系达播!C18+抖音达播!C18 -> 13519375 | E18: =淘系!D18+抖音!D18+PDD!D18+得物!D18+京东自营财经口径!D18+京东POP财经口径!D18+'视频号+官网+小程序'!D18+快手!D18+唯品会!D18+'线下门店-直营'!D18+'线下门店-经销'!D18+线下渠道!D18+淘系达播!D18+抖音达播!D18 -> 13428662 | F18: =淘系!E18+抖音!E18+PDD!E18+得物!E18+京东自营财经口径!E18+京东POP财经口径!E18+'视频号+官网+小程序'!E18+快手!E18+唯品会!E18+'线下门店-直营'!E18+'线下门店-经销'!E18+线下渠道!E18+淘系达播!E18+抖音达播!E18 -> 11966213 | G18: =淘系!F18+抖音!F18+PDD!F18+得物!F18+京东自营财经口径!F18+京东POP财经口径!F18+'视频号+官网+小程序'!F18+快手!F18+唯品会!F18+'线下门店-直营'!F18+'线下门店-经销'!F18+线下渠道!F18+淘系达播!F18+抖音达播!F18 -> 10347617 | H18: =淘系!G18+抖音!G18+PDD!G18+得物!G18+京东自营财经口径!G18+京东POP财经口径!G18+'视频号+官网+小程序'!G18+快手!G18+唯品会!G18+'线下门店-直营'!G18+'线下门店-经销'!G18+线下渠道!G18+淘系达播!G18+抖音达播!G18 -> 19576713 | I18: =淘系!H18+抖音!H18+PDD!H18+得物!H18+京东自营财经口径!H18+京东POP财经口径!H18+'视频号+官网+小程序'!H18+快手!H18+唯品会!H18+'线下门店-直营'!H18+'线下门店-经销'!H18+线下渠道!H18+淘系达播!H18+抖音达播!H18 -> 17979627 | J18: =淘系!I18+抖音!I18+PDD!I18+得物!I18+京东自营财经口径!I18+京东POP财经口径!I18+'视频号+官网+小程序'!I18+快手!I18+唯品会!I18+'线下门店-直营'!I18+'线下门店-经销'!I18+线下渠道!I18+淘系达播!I18+抖音达播!I18 -> 11695231 | K18: =淘系!J18+抖音!J18+PDD!J18+得物!J18+京东自营财经口径!J18+京东POP财经口径!J18+'视频号+官网+小程序'!J18+快手!J18+唯品会!J18+'线下门店-直营'!J18+'线下门店-经销'!J18+线下渠道!J18+淘系达播!J18+抖音达播!J18 -> 16035701 | L18: =淘系!K18+抖音!K18+PDD!K18+得物!K18+京东自营财经口径!K18+京东POP财经口径!K18+'视频号+官网+小程序'!K18+快手!K18+唯品会!K18+'线下门店-直营'!K18+'线下门店-经销'!K18+线下渠道!K18+淘系达播!K18+抖音达播!K18 -> 11502651 | ... O18: =淘系!N18+抖音!N18+PDD!N18+得物!N18+京东自营财经口径!N18+京东POP财经口径!N18+'视频号+官网+小程序'!N18+快手!N18+唯品会!N18+'线下门店-直营'!N18+'线下门店-经销'!N18+线下渠道!N18+淘系达播!N18+抖音达播!N18 -> 14738372 | P18: =SUM(C18:O18) -> 1.7888455e+08 | Q18: =P18/P16 -> 0.44275693 | S18: Y25 Bi 成本54% | U18: =P18-淘系!O18-淘系达播!O18-抖音!O18-抖音达播!O18-快手!O18-京东POP财经口径!O18-京东自营财经口径!O18-PDD!O18-得物!O18-'视频号+官网+小程序'!O18-唯品会!O18-'线下门店-直营'!O18-'线下门店-经销'!O18-线下渠道!O18 -> 0
B19: 产品毛利 | C19: =C16-C18 -> 14095747 | E19: =E16-E18 -> 14189478 | F19: =F16-F18 -> 11627173 | G19: =G16-G18 -> 10096949 | H19: =H16-H18 -> 23160738 | I19: =I16-I18 -> 20889947 | J19: =J16-J18 -> 15449874 | K19: =K16-K18 -> 21543984 | L19: =L16-L18 -> 15982579 | ... O19: =O16-O18 -> 22531606 | P19: =SUM(C19:O19) -> 2.2513973e+08 | Q19: =P19/$P$16 -> 0.55724307 | S19: =P16*0.12 -> 48482915 | U19: =P19-淘系!O19-淘系达播!O19-抖音!O19-抖音达播!O19-快手!O19-京东POP财经口径!O19-京东自营财经口径!O19-PDD!O19-得物!O19-'视频号+官网+小程序'!O19-唯品会!O19-'线下门店-直营'!O19-'线下门店-经销'!O19-线下渠道!O19 -> 0
B20: 头程/尾程物流/仓储费用 | C20: =C16*2.5% -> 690378.04 | E20: =E16*2.5% -> 690453.5 | F20: =F16*2.5% -> 589834.65 | G20: =G16*2.5% -> 511114.15 | H20: =H16*2.5% -> 1068436.3 | I20: =I16*2.5% -> 971739.34 | J20: =J16*2.5% -> 678627.61 | K20: =K16*2.5% -> 939492.14 | L20: =L16*2.5% -> 687130.75 | ... O20: =O16*2.5% -> 931749.43 | P20: =SUM(C20:O20) -> 10100607 | Q20: 0.025 | U20: =P20-淘系!O20-淘系达播!O20-抖音!O20-抖音达播!O20-快手!O20-京东POP财经口径!O20-京东自营财经口径!O20-PDD!O20-得物!O20-'视频号+官网+小程序'!O20-唯品会!O20-'线下门店-直营'!O20-'线下门店-经销'!O20-线下渠道!O20 -> 40154.706
B21: 成本合计（产品+物流） | C21: =SUM(C18,C20) -> 14209753 | E21: =SUM(E18,E20) -> 14119115 | F21: =SUM(F18,F20) -> 12556047 | G21: =SUM(G18,G20) -> 10858731 | H21: =SUM(H18,H20) -> 20645149 | I21: =SUM(I18,I20) -> 18951366 | J21: =SUM(J18,J20) -> 12373858 | K21: =SUM(K18,K20) -> 16975194 | L21: =SUM(L18,L20) -> 12189781 | ... O21: =SUM(O18,O20) -> 15670121 | P21: =SUM(C21:O21) -> 1.8898516e+08 | Q21: =P21/$P$16 -> 0.46775693 | U21: =P21-淘系!O21-淘系达播!O21-抖音!O21-抖音达播!O21-快手!O21-京东POP财经口径!O21-京东自营财经口径!O21-PDD!O21-得物!O21-'视频号+官网+小程序'!O21-唯品会!O21-'线下门店-直营'!O21-'线下门店-经销'!O21-线下渠道!O21 -> 40154.706
B22: 净毛利 | C22: =C16-C21 -> 13405369 | E22: =E16-E21 -> 13499025 | F22: =F16-F21 -> 11037339 | G22: =G16-G21 -> 9585835.3 | H22: =H16-H21 -> 22092302 | I22: =I16-I21 -> 19918207 | J22: =J16-J21 -> 14771246 | K22: =K16-K21 -> 20604492 | L22: =L16-L21 -> 15295449 | ... O22: =O16-O21 -> 21599856 | P22: =SUM(C22:O22) -> 2.1503913e+08 | Q22: =P22/$P$16 -> 0.53224307 | U22: =P22-淘系!O22-淘系达播!O22-抖音!O22-抖音达播!O22-快手!O22-京东POP财经口径!O22-京东自营财经口径!O22-PDD!O22-得物!O22-'视频号+官网+小程序'!O22-唯品会!O22-'线下门店-直营'!O22-'线下门店-经销'!O22-线下渠道!O22 -> -40154.706
B23: 实际产品毛利率 | C23: =C19/C16 -> 0.5104358 | E23: =E19/E16 -> 0.51377386 | F23: =F19/F16 -> 0.49281495 | G23: =G19/G16 -> 0.49386958 | H23: =H19/H16 -> 0.54193073 | I23: =I19/I16 -> 0.537437 | J23: =J19/J16 -> 0.56915876 | K23: =K19/K16 -> 0.57328804 | L23: =L19/L16 -> 0.58149702 | ... P23: =P19/P16 -> 0.55724307 | S23: top down 毛利53% | U23: =P23-淘系!O23-淘系达播!O23-抖音!O23-抖音达播!O23-快手!O23-京东POP财经口径!O23-京东自营财经口径!O23-PDD!O23-得物!O23-'视频号+官网+小程序'!O23-唯品会!O23-'线下门店-直营'!O23-'线下门店-经销'!O23-线下渠道!O23 -> -7.2810622
B24: 合计毛利率 | C24: =IFERROR(1-C21/C16,0) -> 0.4854358 | E24: =IFERROR(1-E21/E16,0) -> 0.48877386 | F24: =IFERROR(1-F21/F16,0) -> 0.46781495 | G24: =IFERROR(1-G21/G16,0) -> 0.46886958 | H24: =IFERROR(1-H21/H16,0) -> 0.51693073 | I24: =IFERROR(1-I21/I16,0) -> 0.512437 | J24: =IFERROR(1-J21/J16,0) -> 0.54415876 | K24: =IFERROR(1-K21/K16,0) -> 0.54828804 | L24: =IFERROR(1-L21/L16,0) -> 0.55649702 | ... P24: =IFERROR(1-P21/P16,0) -> 0.53224307 | U24: =P24-淘系!O24-淘系达播!O24-抖音!O24-抖音达播!O24-快手!O24-京东POP财经口径!O24-京东自营财经口径!O24-PDD!O24-得物!O24-'视频号+官网+小程序'!O24-唯品会!O24-'线下门店-直营'!O24-'线下门店-经销'!O24-线下渠道!O24 -> -6.9890622
U25: =P25-淘系!O25-淘系达播!O25-抖音!O25-抖音达播!O25-快手!O25-京东POP财经口径!O25-京东自营财经口径!O25-PDD!O25-得物!O25-'视频号+官网+小程序'!O25-唯品会!O25-'线下门店-直营'!O25-'线下门店-经销'!O25-线下渠道!O25 -> 0
B26: 品牌及内容费用 | C26: =SUM(C27:C31) -> 751638.84 | D26: =C26/C$16 -> 0.027218379 | E26: =SUM(E27:E31) -> 2209499.7 | F26: =SUM(F27:F31) -> 3628334.4 | G26: =SUM(G27:G31) -> 2088171 | H26: =SUM(H27:H31) -> 8100807.4 | I26: =SUM(I27:I31) -> 4791643.2 | J26: =SUM(J27:J31) -> 1089143.2 | K26: =SUM(K27:K31) -> 1639717.7 | L26: =SUM(L27:L31) -> 1204886 | ... O26: =SUM(O27:O31) -> 1241819.8 | P26: =SUM(C26:O26) -> 32991134 | Q26: =P26/$P$16 -> 0.081656313 | U26: =P26-淘系!O26-淘系达播!O26-抖音!O26-抖音达播!O26-快手!O26-京东POP财经口径!O26-京东自营财经口径!O26-PDD!O26-得物!O26-'视频号+官网+小程序'!O26-唯品会!O26-'线下门店-直营'!O26-'线下门店-经销'!O26-线下渠道!O26 -> 0.027218378
B27: 展会 | C27: =淘系!C27+抖音!C27+PDD!C27+得物!C27+京东自营财经口径!C27+京东POP财经口径!C27+'视频号+官网+小程序'!C27+快手!C27+唯品会!C27+'线下门店-直营'!C27+'线下门店-经销'!C27+线下渠道!C27+淘系达播!C27+抖音达播!C27 -> 0 | E27: =淘系!D27+抖音!D27+PDD!D27+得物!D27+京东自营财经口径!D27+京东POP财经口径!D27+'视频号+官网+小程序'!D27+快手!D27+唯品会!D27+'线下门店-直营'!D27+'线下门店-经销'!D27+线下渠道!D27+淘系达播!D27+抖音达播!D27 -> 0 | F27: =淘系!E27+抖音!E27+PDD!E27+得物!E27+京东自营财经口径!E27+京东POP财经口径!E27+'视频号+官网+小程序'!E27+快手!E27+唯品会!E27+'线下门店-直营'!E27+'线下门店-经销'!E27+线下渠道!E27+淘系达播!E27+抖音达播!E27 -> 64814.267 | G27: =淘系!F27+抖音!F27+PDD!F27+得物!F27+京东自营财经口径!F27+京东POP财经口径!F27+'视频号+官网+小程序'!F27+快手!F27+唯品会!F27+'线下门店-直营'!F27+'线下门店-经销'!F27+线下渠道!F27+淘系达播!F27+抖音达播!F27 -> 54155.074 | H27: =淘系!G27+抖音!G27+PDD!G27+得物!G27+京东自营财经口径!G27+京东POP财经口径!G27+'视频号+官网+小程序'!G27+快手!G27+唯品会!G27+'线下门店-直营'!G27+'线下门店-经销'!G27+线下渠道!G27+淘系达播!G27+抖音达播!G27 -> 115388.16 | I27: =淘系!H27+抖音!H27+PDD!H27+得物!H27+京东自营财经口径!H27+京东POP财经口径!H27+'视频号+官网+小程序'!H27+快手!H27+唯品会!H27+'线下门店-直营'!H27+'线下门店-经销'!H27+线下渠道!H27+淘系达播!H27+抖音达播!H27 -> 101584.8 | J27: =淘系!I27+抖音!I27+PDD!I27+得物!I27+京东自营财经口径!I27+京东POP财经口径!I27+'视频号+官网+小程序'!I27+快手!I27+唯品会!I27+'线下门店-直营'!I27+'线下门店-经销'!I27+线下渠道!I27+淘系达播!I27+抖音达播!I27 -> 65500.288 | K27: =淘系!J27+抖音!J27+PDD!J27+得物!J27+京东自营财经口径!J27+京东POP财经口径!J27+'视频号+官网+小程序'!J27+快手!J27+唯品会!J27+'线下门店-直营'!J27+'线下门店-经销'!J27+线下渠道!J27+淘系达播!J27+抖音达播!J27 -> 90329.934 | L27: =淘系!K27+抖音!K27+PDD!K27+得物!K27+京东自营财经口径!K27+京东POP财经口径!K27+'视频号+官网+小程序'!K27+快手!K27+唯品会!K27+'线下门店-直营'!K27+'线下门店-经销'!K27+线下渠道!K27+淘系达播!K27+抖音达播!K27 -> 72053.164 | ... O27: =淘系!N27+抖音!N27+PDD!N27+得物!N27+京东自营财经口径!N27+京东POP财经口径!N27+'视频号+官网+小程序'!N27+快手!N27+唯品会!N27+'线下门店-直营'!N27+'线下门店-经销'!N27+线下渠道!N27+淘系达播!N27+抖音达播!N27 -> 0 | P27: =SUM(C27:O27) -> 777231.54 | Q27: =P27/$P$16 -> 0.0019237248 | U27: =P27-淘系!O27-淘系达播!O27-抖音!O27-抖音达播!O27-快手!O27-京东POP财经口径!O27-京东自营财经口径!O27-PDD!O27-得物!O27-'视频号+官网+小程序'!O27-唯品会!O27-'线下门店-直营'!O27-'线下门店-经销'!O27-线下渠道!O27 -> -1.6007107e-10
B28: 品牌营销 | C28: =淘系!C28+抖音!C28+PDD!C28+得物!C28+京东自营财经口径!C28+京东POP财经口径!C28+'视频号+官网+小程序'!C28+快手!C28+唯品会!C28+'线下门店-直营'!C28+'线下门店-经销'!C28+线下渠道!C28+淘系达播!C28+抖音达播!C28 -> 209195 | E28: =淘系!D28+抖音!D28+PDD!D28+得物!D28+京东自营财经口径!D28+京东POP财经口径!D28+'视频号+官网+小程序'!D28+快手!D28+唯品会!D28+'线下门店-直营'!D28+'线下门店-经销'!D28+线下渠道!D28+淘系达播!D28+抖音达播!D28 -> 209195 | F28: =淘系!E28+抖音!E28+PDD!E28+得物!E28+京东自营财经口径!E28+京东POP财经口径!E28+'视频号+官网+小程序'!E28+快手!E28+唯品会!E28+'线下门店-直营'!E28+'线下门店-经销'!E28+线下渠道!E28+淘系达播!E28+抖音达播!E28 -> 209195 | G28: =淘系!F28+抖音!F28+PDD!F28+得物!F28+京东自营财经口径!F28+京东POP财经口径!F28+'视频号+官网+小程序'!F28+快手!F28+唯品会!F28+'线下门店-直营'!F28+'线下门店-经销'!F28+线下渠道!F28+淘系达播!F28+抖音达播!F28 -> 274181.09 | H28: =淘系!G28+抖音!G28+PDD!G28+得物!G28+京东自营财经口径!G28+京东POP财经口径!G28+'视频号+官网+小程序'!G28+快手!G28+唯品会!G28+'线下门店-直营'!G28+'线下门店-经销'!G28+线下渠道!G28+淘系达播!G28+抖音达播!G28 -> 901523.98 | I28: =淘系!H28+抖音!H28+PDD!H28+得物!H28+京东自营财经口径!H28+京东POP财经口径!H28+'视频号+官网+小程序'!H28+快手!H28+唯品会!H28+'线下门店-直营'!H28+'线下门店-经销'!H28+线下渠道!H28+淘系达播!H28+抖音达播!H28 -> 534266.37 | J28: =淘系!I28+抖音!I28+PDD!I28+得物!I28+京东自营财经口径!I28+京东POP财经口径!I28+'视频号+官网+小程序'!I28+快手!I28+唯品会!I28+'线下门店-直营'!I28+'线下门店-经销'!I28+线下渠道!I28+淘系达播!I28+抖音达播!I28 -> 209195 | K28: =淘系!J28+抖音!J28+PDD!J28+得物!J28+京东自营财经口径!J28+京东POP财经口径!J28+'视频号+官网+小程序'!J28+快手!J28+唯品会!J28+'线下门店-直营'!J28+'线下门店-经销'!J28+线下渠道!J28+淘系达播!J28+抖音达播!J28 -> 317590.92 | L28: =淘系!K28+抖音!K28+PDD!K28+得物!K28+京东自营财经口径!K28+京东POP财经口径!K28+'视频号+官网+小程序'!K28+快手!K28+唯品会!K28+'线下门店-直营'!K28+'线下门店-经销'!K28+线下渠道!K28+淘系达播!K28+抖音达播!K28 -> 439765.12 | ... O28: =淘系!N28+抖音!N28+PDD!N28+得物!N28+京东自营财经口径!N28+京东POP财经口径!N28+'视频号+官网+小程序'!N28+快手!N28+唯品会!N28+'线下门店-直营'!N28+'线下门店-经销'!N28+线下渠道!N28+淘系达播!N28+抖音达播!N28 -> 209195 | P28: =SUM(C28:O28) -> 4187779.5 | Q28: =P28/$P$16 -> 0.010365168 | U28: =P28-淘系!O28-淘系达播!O28-抖音!O28-抖音达播!O28-快手!O28-京东POP财经口径!O28-京东自营财经口径!O28-PDD!O28-得物!O28-'视频号+官网+小程序'!O28-唯品会!O28-'线下门店-直营'!O28-'线下门店-经销'!O28-线下渠道!O28 -> 5.5297278e-10
B29: 内容素材制作 | C29: =淘系!C29+抖音!C29+PDD!C29+得物!C29+京东自营财经口径!C29+京东POP财经口径!C29+'视频号+官网+小程序'!C29+快手!C29+唯品会!C29+'线下门店-直营'!C29+'线下门店-经销'!C29+线下渠道!C29+淘系达播!C29+抖音达播!C29 -> 31801.759 | E29: =淘系!D29+抖音!D29+PDD!D29+得物!D29+京东自营财经口径!D29+京东POP财经口径!D29+'视频号+官网+小程序'!D29+快手!D29+唯品会!D29+'线下门店-直营'!D29+'线下门店-经销'!D29+线下渠道!D29+淘系达播!D29+抖音达播!D29 -> 25890.069 | F29: =淘系!E29+抖音!E29+PDD!E29+得物!E29+京东自营财经口径!E29+京东POP财经口径!E29+'视频号+官网+小程序'!E29+快手!E29+唯品会!E29+'线下门店-直营'!E29+'线下门店-经销'!E29+线下渠道!E29+淘系达播!E29+抖音达播!E29 -> 25925.707 | G29: =淘系!F29+抖音!F29+PDD!F29+得物!F29+京东自营财经口径!F29+京东POP财经口径!F29+'视频号+官网+小程序'!F29+快手!F29+唯品会!F29+'线下门店-直营'!F29+'线下门店-经销'!F29+线下渠道!F29+淘系达播!F29+抖音达播!F29 -> 108310.15 | H29: =淘系!G29+抖音!G29+PDD!G29+得物!G29+京东自营财经口径!G29+京东POP财经口径!G29+'视频号+官网+小程序'!G29+快手!G29+唯品会!G29+'线下门店-直营'!G29+'线下门店-经销'!G29+线下渠道!G29+淘系达播!G29+抖音达播!G29 -> 692328.98 | I29: =淘系!H29+抖音!H29+PDD!H29+得物!H29+京东自营财经口径!H29+京东POP财经口径!H29+'视频号+官网+小程序'!H29+快手!H29+唯品会!H29+'线下门店-直营'!H29+'线下门店-经销'!H29+线下渠道!H29+淘系达播!H29+抖音达播!H29 -> 446973.13 | J29: =淘系!I29+抖音!I29+PDD!I29+得物!I29+京东自营财经口径!I29+京东POP财经口径!I29+'视频号+官网+小程序'!I29+快手!I29+唯品会!I29+'线下门店-直营'!I29+'线下门店-经销'!I29+线下渠道!I29+淘系达播!I29+抖音达播!I29 -> 0 | K29: =淘系!J29+抖音!J29+PDD!J29+得物!J29+京东自营财经口径!J29+京东POP财经口径!J29+'视频号+官网+小程序'!J29+快手!J29+唯品会!J29+'线下门店-直营'!J29+'线下门店-经销'!J29+线下渠道!J29+淘系达播!J29+抖音达播!J29 -> 108395.92 | L29: =淘系!K29+抖音!K29+PDD!K29+得物!K29+京东自营财经口径!K29+京东POP财经口径!K29+'视频号+官网+小程序'!K29+快手!K29+唯品会!K29+'线下门店-直营'!K29+'线下门店-经销'!K29+线下渠道!K29+淘系达播!K29+抖音达播!K29 -> 230570.12 | ... O29: =淘系!N29+抖音!N29+PDD!N29+得物!N29+京东自营财经口径!N29+京东POP财经口径!N29+'视频号+官网+小程序'!N29+快手!N29+唯品会!N29+'线下门店-直营'!N29+'线下门店-经销'!N29+线下渠道!N29+淘系达播!N29+抖音达播!N29 -> 32181.962 | P29: =SUM(C29:O29) -> 2129189.5 | Q29: =P29/$P$16 -> 0.0052699542 | U29: =P29-淘系!O29-淘系达播!O29-抖音!O29-抖音达播!O29-快手!O29-京东POP财经口径!O29-京东自营财经口径!O29-PDD!O29-得物!O29-'视频号+官网+小程序'!O29-唯品会!O29-'线下门店-直营'!O29-'线下门店-经销'!O29-线下渠道!O29 -> 0
B30: 公关费用 | C30: =淘系!C30+抖音!C30+PDD!C30+得物!C30+京东自营财经口径!C30+京东POP财经口径!C30+'视频号+官网+小程序'!C30+快手!C30+唯品会!C30+'线下门店-直营'!C30+'线下门店-经销'!C30+线下渠道!C30+淘系达播!C30+抖音达播!C30 -> 31801.759 | E30: =淘系!D30+抖音!D30+PDD!D30+得物!D30+京东自营财经口径!D30+京东POP财经口径!D30+'视频号+官网+小程序'!D30+快手!D30+唯品会!D30+'线下门店-直营'!D30+'线下门店-经销'!D30+线下渠道!D30+淘系达播!D30+抖音达播!D30 -> 25890.069 | F30: =淘系!E30+抖音!E30+PDD!E30+得物!E30+京东自营财经口径!E30+京东POP财经口径!E30+'视频号+官网+小程序'!E30+快手!E30+唯品会!E30+'线下门店-直营'!E30+'线下门店-经销'!E30+线下渠道!E30+淘系达播!E30+抖音达播!E30 -> 207405.66 | G30: =淘系!F30+抖音!F30+PDD!F30+得物!F30+京东自营财经口径!F30+京东POP财经口径!F30+'视频号+官网+小程序'!F30+快手!F30+唯品会!F30+'线下门店-直营'!F30+'线下门店-经销'!F30+线下渠道!F30+淘系达播!F30+抖音达播!F30 -> 21662.029 | H30: =淘系!G30+抖音!G30+PDD!G30+得物!G30+京东自营财经口径!G30+京东POP财经口径!G30+'视频号+官网+小程序'!G30+快手!G30+唯品会!G30+'线下门店-直营'!G30+'线下门店-经销'!G30+线下渠道!G30+淘系达播!G30+抖音达播!G30 -> 138465.8 | I30: =淘系!H30+抖音!H30+PDD!H30+得物!H30+京东自营财经口径!H30+京东POP财经口径!H30+'视频号+官网+小程序'!H30+快手!H30+唯品会!H30+'线下门店-直营'!H30+'线下门店-经销'!H30+线下渠道!H30+淘系达播!H30+抖音达播!H30 -> 40633.921 | J30: =淘系!I30+抖音!I30+PDD!I30+得物!I30+京东自营财经口径!I30+京东POP财经口径!I30+'视频号+官网+小程序'!I30+快手!I30+唯品会!I30+'线下门店-直营'!I30+'线下门店-经销'!I30+线下渠道!I30+淘系达播!I30+抖音达播!I30 -> 26200.115 | K30: =淘系!J30+抖音!J30+PDD!J30+得物!J30+京东自营财经口径!J30+京东POP财经口径!J30+'视频号+官网+小程序'!J30+快手!J30+唯品会!J30+'线下门店-直营'!J30+'线下门店-经销'!J30+线下渠道!J30+淘系达播!J30+抖音达播!J30 -> 36131.973 | L30: =淘系!K30+抖音!K30+PDD!K30+得物!K30+京东自营财经口径!K30+京东POP财经口径!K30+'视频号+官网+小程序'!K30+快手!K30+唯品会!K30+'线下门店-直营'!K30+'线下门店-经销'!K30+线下渠道!K30+淘系达播!K30+抖音达播!K30 -> 28821.265 | ... O30: =淘系!N30+抖音!N30+PDD!N30+得物!N30+京东自营财经口径!N30+京东POP财经口径!N30+'视频号+官网+小程序'!N30+快手!N30+唯品会!N30+'线下门店-直营'!N30+'线下门店-经销'!N30+线下渠道!N30+淘系达播!N30+抖音达播!N30 -> 32181.962 | P30: =SUM(C30:O30) -> 759919.23 | Q30: =P30/$P$16 -> 0.0018808751 | U30: =P30-淘系!O30-淘系达播!O30-抖音!O30-抖音达播!O30-快手!O30-京东POP财经口径!O30-京东自营财经口径!O30-PDD!O30-得物!O30-'视频号+官网+小程序'!O30-唯品会!O30-'线下门店-直营'!O30-'线下门店-经销'!O30-线下渠道!O30 -> 0
B31: 达人种草、样机及加热 | C31: =淘系!C31+抖音!C31+PDD!C31+得物!C31+京东自营财经口径!C31+京东POP财经口径!C31+'视频号+官网+小程序'!C31+快手!C31+唯品会!C31+'线下门店-直营'!C31+'线下门店-经销'!C31+线下渠道!C31+淘系达播!C31+抖音达播!C31 -> 478840.32 | E31: =淘系!D31+抖音!D31+PDD!D31+得物!D31+京东自营财经口径!D31+京东POP财经口径!D31+'视频号+官网+小程序'!D31+快手!D31+唯品会!D31+'线下门店-直营'!D31+'线下门店-经销'!D31+线下渠道!D31+淘系达播!D31+抖音达播!D31 -> 1948524.6 | F31: =淘系!E31+抖音!E31+PDD!E31+得物!E31+京东自营财经口径!E31+京东POP财经口径!E31+'视频号+官网+小程序'!E31+快手!E31+唯品会!E31+'线下门店-直营'!E31+'线下门店-经销'!E31+线下渠道!E31+淘系达播!E31+抖音达播!E31 -> 3120993.8 | G31: =淘系!F31+抖音!F31+PDD!F31+得物!F31+京东自营财经口径!F31+京东POP财经口径!F31+'视频号+官网+小程序'!F31+快手!F31+唯品会!F31+'线下门店-直营'!F31+'线下门店-经销'!F31+线下渠道!F31+淘系达播!F31+抖音达播!F31 -> 1629862.7 | H31: =淘系!G31+抖音!G31+PDD!G31+得物!G31+京东自营财经口径!G31+京东POP财经口径!G31+'视频号+官网+小程序'!G31+快手!G31+唯品会!G31+'线下门店-直营'!G31+'线下门店-经销'!G31+线下渠道!G31+淘系达播!G31+抖音达播!G31 -> 6253100.5 | I31: =淘系!H31+抖音!H31+PDD!H31+得物!H31+京东自营财经口径!H31+京东POP财经口径!H31+'视频号+官网+小程序'!H31+快手!H31+唯品会!H31+'线下门店-直营'!H31+'线下门店-经销'!H31+线下渠道!H31+淘系达播!H31+抖音达播!H31 -> 3668185 | J31: =淘系!I31+抖音!I31+PDD!I31+得物!I31+京东自营财经口径!I31+京东POP财经口径!I31+'视频号+官网+小程序'!I31+快手!I31+唯品会!I31+'线下门店-直营'!I31+'线下门店-经销'!I31+线下渠道!I31+淘系达播!I31+抖音达播!I31 -> 788247.76 | K31: =淘系!J31+抖音!J31+PDD!J31+得物!J31+京东自营财经口径!J31+京东POP财经口径!J31+'视频号+官网+小程序'!J31+快手!J31+唯品会!J31+'线下门店-直营'!J31+'线下门店-经销'!J31+线下渠道!J31+淘系达播!J31+抖音达播!J31 -> 1087268.9 | L31: =淘系!K31+抖音!K31+PDD!K31+得物!K31+京东自营财经口径!K31+京东POP财经口径!K31+'视频号+官网+小程序'!K31+快手!K31+唯品会!K31+'线下门店-直营'!K31+'线下门店-经销'!K31+线下渠道!K31+淘系达播!K31+抖音达播!K31 -> 433676.37 | ... O31: =淘系!N31+抖音!N31+PDD!N31+得物!N31+京东自营财经口径!N31+京东POP财经口径!N31+'视频号+官网+小程序'!N31+快手!N31+唯品会!N31+'线下门店-直营'!N31+'线下门店-经销'!N31+线下渠道!N31+淘系达播!N31+抖音达播!N31 -> 968260.91 | P31: =SUM(C31:O31) -> 25137014 | Q31: =P31/$P$16 -> 0.062216591 | U31: =P31-淘系!O31-淘系达播!O31-抖音!O31-抖音达播!O31-快手!O31-京东POP财经口径!O31-京东自营财经口径!O31-PDD!O31-得物!O31-'视频号+官网+小程序'!O31-唯品会!O31-'线下门店-直营'!O31-'线下门店-经销'!O31-线下渠道!O31 -> 0
B32: 展会(费率) | U32: =P32-淘系!O32-淘系达播!O32-抖音!O32-抖音达播!O32-快手!O32-京东POP财经口径!O32-京东自营财经口径!O32-PDD!O32-得物!O32-'视频号+官网+小程序'!O32-唯品会!O32-'线下门店-直营'!O32-'线下门店-经销'!O32-线下渠道!O32 -> 0
B33: 品牌营销（费率） | U33: =P33-淘系!O33-淘系达播!O33-抖音!O33-抖音达播!O33-快手!O33-京东POP财经口径!O33-京东自营财经口径!O33-PDD!O33-得物!O33-'视频号+官网+小程序'!O33-唯品会!O33-'线下门店-直营'!O33-'线下门店-经销'!O33-线下渠道!O33 -> 0
B34: 内容素材制作（费率） | U34: =P34-淘系!O34-淘系达播!O34-抖音!O34-抖音达播!O34-快手!O34-京东POP财经口径!O34-京东自营财经口径!O34-PDD!O34-得物!O34-'视频号+官网+小程序'!O34-唯品会!O34-'线下门店-直营'!O34-'线下门店-经销'!O34-线下渠道!O34 -> 0
B35: 公关费用（费率） | U35: =P35-淘系!O35-淘系达播!O35-抖音!O35-抖音达播!O35-快手!O35-京东POP财经口径!O35-京东自营财经口径!O35-PDD!O35-得物!O35-'视频号+官网+小程序'!O35-唯品会!O35-'线下门店-直营'!O35-'线下门店-经销'!O35-线下渠道!O35 -> 0
B36: 达人种草、样机及加热（费率） | U36: =P36-淘系!O36-淘系达播!O36-抖音!O36-抖音达播!O36-快手!O36-京东POP财经口径!O36-京东自营财经口径!O36-PDD!O36-得物!O36-'视频号+官网+小程序'!O36-唯品会!O36-'线下门店-直营'!O36-'线下门店-经销'!O36-线下渠道!O36 -> 0
B37: 效果广告 | C37: =SUM(C38:C40) -> 5289161.1 | D37: =C37/C$16 -> 0.19153133 | E37: =SUM(E38:E40) -> 6011795.3 | F37: =SUM(F38:F40) -> 4469411.7 | G37: =SUM(G38:G40) -> 3799706.2 | H37: =SUM(H38:H40) -> 9797097.2 | I37: =SUM(I38:I40) -> 8746823 | J37: =SUM(J38:J40) -> 4912801.7 | K37: =SUM(K38:K40) -> 8629549.9 | L37: =SUM(L38:L40) -> 5128807.9 | ... O37: =SUM(O38:O40) -> 6666059 | P37: =SUM(C37:O37) -> 82824979 | Q37: =P37/$P$16 -> 0.205 | S37: =P16*20.5% -> 82824979 | U37: =P37-淘系!O37-淘系达播!O37-抖音!O37-抖音达播!O37-快手!O37-京东POP财经口径!O37-京东自营财经口径!O37-PDD!O37-得物!O37-'视频号+官网+小程序'!O37-唯品会!O37-'线下门店-直营'!O37-'线下门店-经销'!O37-线下渠道!O37 -> 0.19153133
B38: 站内投放 | C38: =淘系!C38+抖音!C38+PDD!C38+得物!C38+京东自营财经口径!C38+京东POP财经口径!C38+'视频号+官网+小程序'!C38+快手!C38+唯品会!C38+'线下门店-直营'!C38+'线下门店-经销'!C38+线下渠道!C38+淘系达播!C38+抖音达播!C38 -> 2292019.8 | E38: =淘系!D38+抖音!D38+PDD!D38+得物!D38+京东自营财经口径!D38+京东POP财经口径!D38+'视频号+官网+小程序'!D38+快手!D38+唯品会!D38+'线下门店-直营'!D38+'线下门店-经销'!D38+线下渠道!D38+淘系达播!D38+抖音达播!D38 -> 2749177.4 | F38: =淘系!E38+抖音!E38+PDD!E38+得物!E38+京东自营财经口径!E38+京东POP财经口径!E38+'视频号+官网+小程序'!E38+快手!E38+唯品会!E38+'线下门店-直营'!E38+'线下门店-经销'!E38+线下渠道!E38+淘系达播!E38+抖音达播!E38 -> 2219902.6 | G38: =淘系!F38+抖音!F38+PDD!F38+得物!F38+京东自营财经口径!F38+京东POP财经口径!F38+'视频号+官网+小程序'!F38+快手!F38+唯品会!F38+'线下门店-直营'!F38+'线下门店-经销'!F38+线下渠道!F38+淘系达播!F38+抖音达播!F38 -> 1900622 | H38: =淘系!G38+抖音!G38+PDD!G38+得物!G38+京东自营财经口径!G38+京东POP财经口径!G38+'视频号+官网+小程序'!G38+快手!G38+唯品会!G38+'线下门店-直营'!G38+'线下门店-经销'!G38+线下渠道!G38+淘系达播!G38+抖音达播!G38 -> 4748153.5 | I38: =淘系!H38+抖音!H38+PDD!H38+得物!H38+京东自营财经口径!H38+京东POP财经口径!H38+'视频号+官网+小程序'!H38+快手!H38+唯品会!H38+'线下门店-直营'!H38+'线下门店-经销'!H38+线下渠道!H38+淘系达播!H38+抖音达播!H38 -> 4563874.8 | J38: =淘系!I38+抖音!I38+PDD!I38+得物!I38+京东自营财经口径!I38+京东POP财经口径!I38+'视频号+官网+小程序'!I38+快手!I38+唯品会!I38+'线下门店-直营'!I38+'线下门店-经销'!I38+线下渠道!I38+淘系达播!I38+抖音达播!I38 -> 2576178.9 | K38: =淘系!J38+抖音!J38+PDD!J38+得物!J38+京东自营财经口径!J38+京东POP财经口径!J38+'视频号+官网+小程序'!J38+快手!J38+唯品会!J38+'线下门店-直营'!J38+'线下门店-经销'!J38+线下渠道!J38+淘系达播!J38+抖音达播!J38 -> 4648298.8 | L38: =淘系!K38+抖音!K38+PDD!K38+得物!K38+京东自营财经口径!K38+京东POP财经口径!K38+'视频号+官网+小程序'!K38+快手!K38+唯品会!K38+'线下门店-直营'!K38+'线下门店-经销'!K38+线下渠道!K38+淘系达播!K38+抖音达播!K38 -> 2731039.4 | ... O38: =淘系!N38+抖音!N38+PDD!N38+得物!N38+京东自营财经口径!N38+京东POP财经口径!N38+'视频号+官网+小程序'!N38+快手!N38+唯品会!N38+'线下门店-直营'!N38+'线下门店-经销'!N38+线下渠道!N38+淘系达播!N38+抖音达播!N38 -> 3186379.6 | P38: =SUM(C38:O38) -> 41931094 | Q38: =P38/$P$16 -> 0.1037836 | R38: 投放填写 | S38: =P37-S37 -> 0.15017277 | U38: =P38-淘系!O38-淘系达播!O38-抖音!O38-抖音达播!O38-快手!O38-京东POP财经口径!O38-京东自营财经口径!O38-PDD!O38-得物!O38-'视频号+官网+小程序'!O38-唯品会!O38-'线下门店-直营'!O38-'线下门店-经销'!O38-线下渠道!O38 -> -1.3271347e-08
B39: 千川投放 | C39: =淘系!C39+抖音!C39+PDD!C39+得物!C39+京东自营财经口径!C39+京东POP财经口径!C39+'视频号+官网+小程序'!C39+快手!C39+唯品会!C39+'线下门店-直营'!C39+'线下门店-经销'!C39+线下渠道!C39+淘系达播!C39+抖音达播!C39 -> 2298503 | E39: =淘系!D39+抖音!D39+PDD!D39+得物!D39+京东自营财经口径!D39+京东POP财经口径!D39+'视频号+官网+小程序'!D39+快手!D39+唯品会!D39+'线下门店-直营'!D39+'线下门店-经销'!D39+线下渠道!D39+淘系达播!D39+抖音达播!D39 -> 2468200.8 | F39: =淘系!E39+抖音!E39+PDD!E39+得物!E39+京东自营财经口径!E39+京东POP财经口径!E39+'视频号+官网+小程序'!E39+快手!E39+唯品会!E39+'线下门店-直营'!E39+'线下门店-经销'!E39+线下渠道!E39+淘系达播!E39+抖音达播!E39 -> 1582066.6 | G39: =淘系!F39+抖音!F39+PDD!F39+得物!F39+京东自营财经口径!F39+京东POP财经口径!F39+'视频号+官网+小程序'!F39+快手!F39+唯品会!F39+'线下门店-直营'!F39+'线下门店-经销'!F39+线下渠道!F39+淘系达播!F39+抖音达播!F39 -> 1336204.9 | H39: =淘系!G39+抖音!G39+PDD!G39+得物!G39+京东自营财经口径!G39+京东POP财经口径!G39+'视频号+官网+小程序'!G39+快手!G39+唯品会!G39+'线下门店-直营'!G39+'线下门店-经销'!G39+线下渠道!G39+淘系达播!G39+抖音达播!G39 -> 3070752.4 | I39: =淘系!H39+抖音!H39+PDD!H39+得物!H39+京东自营财经口径!H39+京东POP财经口径!H39+'视频号+官网+小程序'!H39+快手!H39+唯品会!H39+'线下门店-直营'!H39+'线下门店-经销'!H39+线下渠道!H39+淘系达播!H39+抖音达播!H39 -> 2791593.1 | J39: =淘系!I39+抖音!I39+PDD!I39+得物!I39+京东自营财经口径!I39+京东POP财经口径!I39+'视频号+官网+小程序'!I39+快手!I39+唯品会!I39+'线下门店-直营'!I39+'线下门店-经销'!I39+线下渠道!I39+淘系达播!I39+抖音达播!I39 -> 1603445.8 | K39: =淘系!J39+抖音!J39+PDD!J39+得物!J39+京东自营财经口径!J39+京东POP财经口径!J39+'视频号+官网+小程序'!J39+快手!J39+唯品会!J39+'线下门店-直营'!J39+'线下门店-经销'!J39+线下渠道!J39+淘系达播!J39+抖音达播!J39 -> 2583206.5 | L39: =淘系!K39+抖音!K39+PDD!K39+得物!K39+京东自营财经口径!K39+京东POP财经口径!K39+'视频号+官网+小程序'!K39+快手!K39+唯品会!K39+'线下门店-直营'!K39+'线下门店-经销'!K39+线下渠道!K39+淘系达播!K39+抖音达播!K39 -> 1594158.2 | ... O39: =淘系!N39+抖音!N39+PDD!N39+得物!N39+京东自营财经口径!N39+京东POP财经口径!N39+'视频号+官网+小程序'!N39+快手!N39+唯品会!N39+'线下门店-直营'!N39+'线下门店-经销'!N39+线下渠道!N39+淘系达播!N39+抖音达播!N39 -> 2571042.5 | P39: =SUM(C39:O39) -> 27750461 | Q39: =P39/$P$16 -> 0.06868513 | R39: 投放填写 | S39: =淘系!O31+抖音!O31+京东自营财经口径!O31 -> 20683454 | U39: =P39-淘系!O39-淘系达播!O39-抖音!O39-抖音达播!O39-快手!O39-京东POP财经口径!O39-京东自营财经口径!O39-PDD!O39-得物!O39-'视频号+官网+小程序'!O39-唯品会!O39-'线下门店-直营'!O39-'线下门店-经销'!O39-线下渠道!O39 -> 0
B40: 站外投放 | C40: =淘系!C40+抖音!C40+PDD!C40+得物!C40+京东自营财经口径!C40+京东POP财经口径!C40+'视频号+官网+小程序'!C40+快手!C40+唯品会!C40+'线下门店-直营'!C40+'线下门店-经销'!C40+线下渠道!C40+淘系达播!C40+抖音达播!C40 -> 698638.3 | E40: =淘系!D40+抖音!D40+PDD!D40+得物!D40+京东自营财经口径!D40+京东POP财经口径!D40+'视频号+官网+小程序'!D40+快手!D40+唯品会!D40+'线下门店-直营'!D40+'线下门店-经销'!D40+线下渠道!D40+淘系达播!D40+抖音达播!D40 -> 794417.05 | F40: =淘系!E40+抖音!E40+PDD!E40+得物!E40+京东自营财经口径!E40+京东POP财经口径!E40+'视频号+官网+小程序'!E40+快手!E40+唯品会!E40+'线下门店-直营'!E40+'线下门店-经销'!E40+线下渠道!E40+淘系达播!E40+抖音达播!E40 -> 667442.57 | G40: =淘系!F40+抖音!F40+PDD!F40+得物!F40+京东自营财经口径!F40+京东POP财经口径!F40+'视频号+官网+小程序'!F40+快手!F40+唯品会!F40+'线下门店-直营'!F40+'线下门店-经销'!F40+线下渠道!F40+淘系达播!F40+抖音达播!F40 -> 562879.37 | H40: =淘系!G40+抖音!G40+PDD!G40+得物!G40+京东自营财经口径!G40+京东POP财经口径!G40+'视频号+官网+小程序'!G40+快手!G40+唯品会!G40+'线下门店-直营'!G40+'线下门店-经销'!G40+线下渠道!G40+淘系达播!G40+抖音达播!G40 -> 1978191.3 | I40: =淘系!H40+抖音!H40+PDD!H40+得物!H40+京东自营财经口径!H40+京东POP财经口径!H40+'视频号+官网+小程序'!H40+快手!H40+唯品会!H40+'线下门店-直营'!H40+'线下门店-经销'!H40+线下渠道!H40+淘系达播!H40+抖音达播!H40 -> 1391355.1 | J40: =淘系!I40+抖音!I40+PDD!I40+得物!I40+京东自营财经口径!I40+京东POP财经口径!I40+'视频号+官网+小程序'!I40+快手!I40+唯品会!I40+'线下门店-直营'!I40+'线下门店-经销'!I40+线下渠道!I40+淘系达播!I40+抖音达播!I40 -> 733176.96 | K40: =淘系!J40+抖音!J40+PDD!J40+得物!J40+京东自营财经口径!J40+京东POP财经口径!J40+'视频号+官网+小程序'!J40+快手!J40+唯品会!J40+'线下门店-直营'!J40+'线下门店-经销'!J40+线下渠道!J40+淘系达播!J40+抖音达播!J40 -> 1398044.6 | L40: =淘系!K40+抖音!K40+PDD!K40+得物!K40+京东自营财经口径!K40+京东POP财经口径!K40+'视频号+官网+小程序'!K40+快手!K40+唯品会!K40+'线下门店-直营'!K40+'线下门店-经销'!K40+线下渠道!K40+淘系达播!K40+抖音达播!K40 -> 803610.32 | ... O40: =淘系!N40+抖音!N40+PDD!N40+得物!N40+京东自营财经口径!N40+京东POP财经口径!N40+'视频号+官网+小程序'!N40+快手!N40+唯品会!N40+'线下门店-直营'!N40+'线下门店-经销'!N40+线下渠道!N40+淘系达播!N40+抖音达播!N40 -> 908636.98 | P40: =SUM(C40:O40) -> 13143425 | Q40: =P40/$P$16 -> 0.032531273 | R40: 投放填写 | S40: =淘系!O31 -> 9080973.7 | T40: =S40/$S$39 -> 0.43904531 | U40: =P40-淘系!O40-淘系达播!O40-抖音!O40-抖音达播!O40-快手!O40-京东POP财经口径!O40-京东自营财经口径!O40-PDD!O40-得物!O40-'视频号+官网+小程序'!O40-唯品会!O40-'线下门店-直营'!O40-'线下门店-经销'!O40-线下渠道!O40 -> 0
B41: 站内投放（费率） | C41: =C38/C$16 -> 0.08299872 | E41: =E38/E$16 -> 0.099542454 | F41: =F38/F$16 -> 0.094090036 | G41: =G38/G$16 -> 0.092964652 | H41: =H38/H$16 -> 0.11110053 | I41: =I38/I$16 -> 0.1174151 | J41: =J38/J$16 -> 0.094903997 | K41: =K38/K$16 -> 0.1236918 | L41: =L38/L$16 -> 0.09936389 | ... O41: =O38/O$16 -> 0.085494541 | P41: =P38/$P$16 -> 0.1037836 | R41: 投放填写 | T41: =S41/$S$39 -> 0 | U41: =P41-淘系!O41-淘系达播!O41-抖音!O41-抖音达播!O41-快手!O41-京东POP财经口径!O41-京东自营财经口径!O41-PDD!O41-得物!O41-'视频号+官网+小程序'!O41-唯品会!O41-'线下门店-直营'!O41-'线下门店-经销'!O41-线下渠道!O41 -> -0.99470872
B42: 千川投放（费率） | C42: =C39/C$16 -> 0.083233492 | E42: =E39/E$16 -> 0.089368827 | F42: =F39/F$16 -> 0.067055511 | G42: =G39/G$16 -> 0.065357458 | H42: =H39/H$16 -> 0.071851556 | I42: =I39/I$16 -> 0.071819493 | J42: =J39/J$16 -> 0.05906943 | K42: =K39/K$16 -> 0.06873944 | L42: =L39/L$16 -> 0.058000539 | ... O42: =O39/O$16 -> 0.068984278 | P42: =P39/$P$16 -> 0.06868513 | R42: 投放填写 | T42: =S42/$S$39 -> 0 | U42: =P42-淘系!O42-淘系达播!O42-抖音!O42-抖音达播!O42-快手!O42-京东POP财经口径!O42-京东自营财经口径!O42-PDD!O42-得物!O42-'视频号+官网+小程序'!O42-唯品会!O42-'线下门店-直营'!O42-'线下门店-经销'!O42-线下渠道!O42 -> -0.29602075
B43: 站外投放（费率） | C43: =C40/C$16 -> 0.025299121 | E43: =E40/E$16 -> 0.028764321 | F43: =F40/F$16 -> 0.028289393 | G43: =G40/G$16 -> 0.027531979 | H43: =H40/H$16 -> 0.046287068 | I43: =I40/I$16 -> 0.035795481 | J43: =J40/J$16 -> 0.027009546 | K43: =K40/K$16 -> 0.037202136 | L43: =L40/L$16 -> 0.029237897 | ... O43: =O40/O$16 -> 0.024379864 | P43: =P40/$P$16 -> 0.032531273 | R43: 投放填写 | T43: =S43/$S$39 -> 0 | U43: =P43-淘系!O43-淘系达播!O43-抖音!O43-抖音达播!O43-快手!O43-京东POP财经口径!O43-京东自营财经口径!O43-PDD!O43-得物!O43-'视频号+官网+小程序'!O43-唯品会!O43-'线下门店-直营'!O43-'线下门店-经销'!O43-线下渠道!O43 -> -0.09050279
B44: 线上营销费用 | C44: =SUM(C45:C46) -> 873457.07 | D44: =C44/C$16 -> 0.031629666 | E44: =SUM(E45:E46) -> 891315.7 | F44: =SUM(F45:F46) -> 784090.16 | G44: =SUM(G45:G46) -> 610146.64 | H44: =SUM(H45:H46) -> 1521937.3 | I44: =SUM(I45:I46) -> 1188479.9 | J44: =SUM(J45:J46) -> 779366.81 | K44: =SUM(K45:K46) -> 1264018.6 | L44: =SUM(L45:L46) -> 822841.28 | ... O44: =SUM(O45:O46) -> 1089471.6 | P44: =SUM(C44:O44) -> 13187609 | Q44: =P44/$P$16 -> 0.032640634 | S44: =抖音!O31 -> 5348171.2 | T44: =S44/$S$39 -> 0.25857244 | U44: =P44-淘系!O44-淘系达播!O44-抖音!O44-抖音达播!O44-快手!O44-京东POP财经口径!O44-京东自营财经口径!O44-PDD!O44-得物!O44-'视频号+官网+小程序'!O44-唯品会!O44-'线下门店-直营'!O44-'线下门店-经销'!O44-线下渠道!O44 -> 0.031629665
B45: 直播费用 | C45: =淘系!C45+抖音!C45+PDD!C45+得物!C45+京东自营财经口径!C45+京东POP财经口径!C45+'视频号+官网+小程序'!C45+快手!C45+唯品会!C45+'线下门店-直营'!C45+'线下门店-经销'!C45+线下渠道!C45+淘系达播!C45+抖音达播!C45 -> 162529.49 | E45: =淘系!D45+抖音!D45+PDD!D45+得物!D45+京东自营财经口径!D45+京东POP财经口径!D45+'视频号+官网+小程序'!D45+快手!D45+唯品会!D45+'线下门店-直营'!D45+'线下门店-经销'!D45+线下渠道!D45+淘系达播!D45+抖音达播!D45 -> 155166.99 | F45: =淘系!E45+抖音!E45+PDD!E45+得物!E45+京东自营财经口径!E45+京东POP财经口径!E45+'视频号+官网+小程序'!E45+快手!E45+唯品会!E45+'线下门店-直营'!E45+'线下门店-经销'!E45+线下渠道!E45+淘系达播!E45+抖音达播!E45 -> 194579.22 | G45: =淘系!F45+抖音!F45+PDD!F45+得物!F45+京东自营财经口径!F45+京东POP财经口径!F45+'视频号+官网+小程序'!F45+快手!F45+唯品会!F45+'线下门店-直营'!F45+'线下门店-经销'!F45+线下渠道!F45+淘系达播!F45+抖音达播!F45 -> 106561.31 | H45: =淘系!G45+抖音!G45+PDD!G45+得物!G45+京东自营财经口径!G45+京东POP财经口径!G45+'视频号+官网+小程序'!G45+快手!G45+唯品会!G45+'线下门店-直营'!G45+'线下门店-经销'!G45+线下渠道!G45+淘系达播!G45+抖音达播!G45 -> 442337.33 | I45: =淘系!H45+抖音!H45+PDD!H45+得物!H45+京东自营财经口径!H45+京东POP财经口径!H45+'视频号+官网+小程序'!H45+快手!H45+唯品会!H45+'线下门店-直营'!H45+'线下门店-经销'!H45+线下渠道!H45+淘系达播!H45+抖音达播!H45 -> 242039.41 | J45: =淘系!I45+抖音!I45+PDD!I45+得物!I45+京东自营财经口径!I45+京东POP财经口径!I45+'视频号+官网+小程序'!I45+快手!I45+唯品会!I45+'线下门店-直营'!I45+'线下门店-经销'!I45+线下渠道!I45+淘系达播!I45+抖音达播!I45 -> 126179.03 | K45: =淘系!J45+抖音!J45+PDD!J45+得物!J45+京东自营财经口径!J45+京东POP财经口径!J45+'视频号+官网+小程序'!J45+快手!J45+唯品会!J45+'线下门店-直营'!J45+'线下门店-经销'!J45+线下渠道!J45+淘系达播!J45+抖音达播!J45 -> 326056.34 | L45: =淘系!K45+抖音!K45+PDD!K45+得物!K45+京东自营财经口径!K45+京东POP财经口径!K45+'视频号+官网+小程序'!K45+快手!K45+唯品会!K45+'线下门店-直营'!K45+'线下门店-经销'!K45+线下渠道!K45+淘系达播!K45+抖音达播!K45 -> 160579.68 | ... O45: =淘系!N45+抖音!N45+PDD!N45+得物!N45+京东自营财经口径!N45+京东POP财经口径!N45+'视频号+官网+小程序'!N45+快手!N45+唯品会!N45+'线下门店-直营'!N45+'线下门店-经销'!N45+线下渠道!N45+淘系达播!N45+抖音达播!N45 -> 174825.03 | P45: =SUM(C45:O45) -> 3171238.9 | Q45: =P45/$P$16 -> 0.0078491293 | R45: 达人填写 | S45: =京东自营财经口径!O31 -> 6254309.5 | T45: =S45/$S$39 -> 0.30238225 | U45: =P45-淘系!O45-淘系达播!O45-抖音!O45-抖音达播!O45-快手!O45-京东POP财经口径!O45-京东自营财经口径!O45-PDD!O45-得物!O45-'视频号+官网+小程序'!O45-唯品会!O45-'线下门店-直营'!O45-'线下门店-经销'!O45-线下渠道!O45 -> -5.3842086e-10
B46: 赠品费用 | C46: =淘系!C46+抖音!C46+PDD!C46+得物!C46+京东自营财经口径!C46+京东POP财经口径!C46+'视频号+官网+小程序'!C46+快手!C46+唯品会!C46+'线下门店-直营'!C46+'线下门店-经销'!C46+线下渠道!C46+淘系达播!C46+抖音达播!C46 -> 710927.58 | E46: =淘系!D46+抖音!D46+PDD!D46+得物!D46+京东自营财经口径!D46+京东POP财经口径!D46+'视频号+官网+小程序'!D46+快手!D46+唯品会!D46+'线下门店-直营'!D46+'线下门店-经销'!D46+线下渠道!D46+淘系达播!D46+抖音达播!D46 -> 736148.72 | F46: =淘系!E46+抖音!E46+PDD!E46+得物!E46+京东自营财经口径!E46+京东POP财经口径!E46+'视频号+官网+小程序'!E46+快手!E46+唯品会!E46+'线下门店-直营'!E46+'线下门店-经销'!E46+线下渠道!E46+淘系达播!E46+抖音达播!E46 -> 589510.94 | G46: =淘系!F46+抖音!F46+PDD!F46+得物!F46+京东自营财经口径!F46+京东POP财经口径!F46+'视频号+官网+小程序'!F46+快手!F46+唯品会!F46+'线下门店-直营'!F46+'线下门店-经销'!F46+线下渠道!F46+淘系达播!F46+抖音达播!F46 -> 503585.33 | H46: =淘系!G46+抖音!G46+PDD!G46+得物!G46+京东自营财经口径!G46+京东POP财经口径!G46+'视频号+官网+小程序'!G46+快手!G46+唯品会!G46+'线下门店-直营'!G46+'线下门店-经销'!G46+线下渠道!G46+淘系达播!G46+抖音达播!G46 -> 1079600 | I46: =淘系!H46+抖音!H46+PDD!H46+得物!H46+京东自营财经口径!H46+京东POP财经口径!H46+'视频号+官网+小程序'!H46+快手!H46+唯品会!H46+'线下门店-直营'!H46+'线下门店-经销'!H46+线下渠道!H46+淘系达播!H46+抖音达播!H46 -> 946440.5 | J46: =淘系!I46+抖音!I46+PDD!I46+得物!I46+京东自营财经口径!I46+京东POP财经口径!I46+'视频号+官网+小程序'!I46+快手!I46+唯品会!I46+'线下门店-直营'!I46+'线下门店-经销'!I46+线下渠道!I46+淘系达播!I46+抖音达播!I46 -> 653187.78 | K46: =淘系!J46+抖音!J46+PDD!J46+得物!J46+京东自营财经口径!J46+京东POP财经口径!J46+'视频号+官网+小程序'!J46+快手!J46+唯品会!J46+'线下门店-直营'!J46+'线下门店-经销'!J46+线下渠道!J46+淘系达播!J46+抖音达播!J46 -> 937962.25 | L46: =淘系!K46+抖音!K46+PDD!K46+得物!K46+京东自营财经口径!K46+京东POP财经口径!K46+'视频号+官网+小程序'!K46+快手!K46+唯品会!K46+'线下门店-直营'!K46+'线下门店-经销'!K46+线下渠道!K46+淘系达播!K46+抖音达播!K46 -> 662261.6 | ... O46: =淘系!N46+抖音!N46+PDD!N46+得物!N46+京东自营财经口径!N46+京东POP财经口径!N46+'视频号+官网+小程序'!N46+快手!N46+唯品会!N46+'线下门店-直营'!N46+'线下门店-经销'!N46+线下渠道!N46+淘系达播!N46+抖音达播!N46 -> 914646.58 | P46: =SUM(C46:O46) -> 10016370 | Q46: =P46/$P$16 -> 0.024791504 | R46: 渠道填写 | U46: =P46-淘系!O46-淘系达播!O46-抖音!O46-抖音达播!O46-快手!O46-京东POP财经口径!O46-京东自营财经口径!O46-PDD!O46-得物!O46-'视频号+官网+小程序'!O46-唯品会!O46-'线下门店-直营'!O46-'线下门店-经销'!O46-线下渠道!O46 -> -18223.07
B47: 直播费用（费率） | C47: =C45/C$16 -> 0.005885525 | E47: =E45/E$16 -> 0.0056182997 | F47: =F45/F$16 -> 0.0082471934 | G47: =G45/G$16 -> 0.0052122069 | H47: =H45/H$16 -> 0.01035011 | I47: =I45/I$16 -> 0.0062269634 | J47: =J45/J$16 -> 0.0046483161 | K47: =K45/K$16 -> 0.0086763989 | L47: =L45/L$16 -> 0.0058423989 | ... P47: =P45/P$16 -> 0.0078491293
B48: 赠品费用（费率） | C48: =C46/C$16 -> 0.025744141 | E48: =E46/E$16 -> 0.026654536 | F48: =F46/F$16 -> 0.02498628 | G48: =G46/G$16 -> 0.024631745 | H48: =H46/H$16 -> 0.025261216 | I48: =I46/I$16 -> 0.024349135 | J48: =J46/J$16 -> 0.024062821 | K48: =K46/K$16 -> 0.024959289 | L48: =L46/L$16 -> 0.024095181 | ... P48: =P46/P$16 -> 0.024791504
B49: 线下市场费用 | C49: =SUM(C50:C53) -> 657080.28 | D49: =C49/C$16 -> 0.02379422 | E49: =SUM(E50:E53) -> 636510.42 | F49: =SUM(F50:F53) -> 641266.51 | G49: =SUM(G50:G53) -> 662889.29 | H49: =SUM(H50:H53) -> 717270.27 | I49: =SUM(I50:I53) -> 966198.14 | J49: =SUM(J50:J53) -> 933219.49 | K49: =SUM(K50:K53) -> 963447.11 | L49: =SUM(L50:L53) -> 881708.22 | ... O49: =SUM(O50:O53) -> 1542325.9 | P49: =SUM(C49:O49) -> 11366424 | Q49: =P49/$P$16 -> 0.028133022 | S49: =$S$38*T40+S40 -> 9080973.7 | U49: =P49-淘系!O47-淘系达播!O47-抖音!O47-抖音达播!O47-快手!O47-京东POP财经口径!O47-京东自营财经口径!O47-PDD!O47-得物!O47-'视频号+官网+小程序'!O47-唯品会!O47-'线下门店-直营'!O47-'线下门店-经销'!O47-线下渠道!O47 -> 0.023794219
B50: 线下渠道展陈、促销费用 | C50: =淘系!C48+抖音!C48+PDD!C48+得物!C48+京东自营财经口径!C48+京东POP财经口径!C48+'视频号+官网+小程序'!C48+快手!C48+唯品会!C48+'线下门店-直营'!C48+'线下门店-经销'!C48+线下渠道!C48+淘系达播!C48+抖音达播!C48 -> 273499.09 | E50: =淘系!D48+抖音!D48+PDD!D48+得物!D48+京东自营财经口径!D48+京东POP财经口径!D48+'视频号+官网+小程序'!D48+快手!D48+唯品会!D48+'线下门店-直营'!D48+'线下门店-经销'!D48+线下渠道!D48+淘系达播!D48+抖音达播!D48 -> 282312.63 | F50: =淘系!E48+抖音!E48+PDD!E48+得物!E48+京东自营财经口径!E48+京东POP财经口径!E48+'视频号+官网+小程序'!E48+快手!E48+唯品会!E48+'线下门店-直营'!E48+'线下门店-经销'!E48+线下渠道!E48+淘系达播!E48+抖音达播!E48 -> 248013.19 | G50: =淘系!F48+抖音!F48+PDD!F48+得物!F48+京东自营财经口径!F48+京东POP财经口径!F48+'视频号+官网+小程序'!F48+快手!F48+唯品会!F48+'线下门店-直营'!F48+'线下门店-经销'!F48+线下渠道!F48+淘系达播!F48+抖音达播!F48 -> 271172.87 | H50: =淘系!G48+抖音!G48+PDD!G48+得物!G48+京东自营财经口径!G48+京东POP财经口径!G48+'视频号+官网+小程序'!G48+快手!G48+唯品会!G48+'线下门店-直营'!G48+'线下门店-经销'!G48+线下渠道!G48+淘系达播!G48+抖音达播!G48 -> 411814.03 | I50: =淘系!H48+抖音!H48+PDD!H48+得物!H48+京东自营财经口径!H48+京东POP财经口径!H48+'视频号+官网+小程序'!H48+快手!H48+唯品会!H48+'线下门店-直营'!H48+'线下门店-经销'!H48+线下渠道!H48+淘系达播!H48+抖音达播!H48 -> 560242.14 | J50: =淘系!I48+抖音!I48+PDD!I48+得物!I48+京东自营财经口径!I48+京东POP财经口径!I48+'视频号+官网+小程序'!I48+快手!I48+唯品会!I48+'线下门店-直营'!I48+'线下门店-经销'!I48+线下渠道!I48+淘系达播!I48+抖音达播!I48 -> 548529.71 | K50: =淘系!J48+抖音!J48+PDD!J48+得物!J48+京东自营财经口径!J48+京东POP财经口径!J48+'视频号+官网+小程序'!J48+快手!J48+唯品会!J48+'线下门店-直营'!J48+'线下门店-经销'!J48+线下渠道!J48+淘系达播!J48+抖音达播!J48 -> 616741.81 | L50: =淘系!K48+抖音!K48+PDD!K48+得物!K48+京东自营财经口径!K48+京东POP财经口径!K48+'视频号+官网+小程序'!K48+快手!K48+唯品会!K48+'线下门店-直营'!K48+'线下门店-经销'!K48+线下渠道!K48+淘系达播!K48+抖音达播!K48 -> 540262.26 | ... O50: =淘系!N48+抖音!N48+PDD!N48+得物!N48+京东自营财经口径!N48+京东POP财经口径!N48+'视频号+官网+小程序'!N48+快手!N48+唯品会!N48+'线下门店-直营'!N48+'线下门店-经销'!N48+线下渠道!N48+淘系达播!N48+抖音达播!N48 -> 1012182.7 | P50: =SUM(C50:O50) -> 6581385.2 | Q50: =P50/$P$16 -> 0.016289578 | R50: 线下门店 | S50: =S38*T44+S44 -> 5348171.2 | U50: =P50-淘系!O48-淘系达播!O48-抖音!O48-抖音达播!O48-快手!O48-京东POP财经口径!O48-京东自营财经口径!O48-PDD!O48-得物!O48-'视频号+官网+小程序'!O48-唯品会!O48-'线下门店-直营'!O48-'线下门店-经销'!O48-线下渠道!O48 -> 0
B51: 租金+物业+水电 | C51: =淘系!C49+抖音!C49+PDD!C49+得物!C49+京东自营财经口径!C49+京东POP财经口径!C49+'视频号+官网+小程序'!C49+快手!C49+唯品会!C49+'线下门店-直营'!C49+'线下门店-经销'!C49+线下渠道!C49+淘系达播!C49+抖音达播!C49 -> 151958.47 | E51: =淘系!D49+抖音!D49+PDD!D49+得物!D49+京东自营财经口径!D49+京东POP财经口径!D49+'视频号+官网+小程序'!D49+快手!D49+唯品会!D49+'线下门店-直营'!D49+'线下门店-经销'!D49+线下渠道!D49+淘系达播!D49+抖音达播!D49 -> 132683.54 | F51: =淘系!E49+抖音!E49+PDD!E49+得物!E49+京东自营财经口径!E49+京东POP财经口径!E49+'视频号+官网+小程序'!E49+快手!E49+唯品会!E49+'线下门店-直营'!E49+'线下门店-经销'!E49+线下渠道!E49+淘系达播!E49+抖音达播!E49 -> 144087.64 | G51: =淘系!F49+抖音!F49+PDD!F49+得物!F49+京东自营财经口径!F49+京东POP财经口径!F49+'视频号+官网+小程序'!F49+快手!F49+唯品会!F49+'线下门店-直营'!F49+'线下门店-经销'!F49+线下渠道!F49+淘系达播!F49+抖音达播!F49 -> 135605.02 | H51: =淘系!G49+抖音!G49+PDD!G49+得物!G49+京东自营财经口径!G49+京东POP财经口径!G49+'视频号+官网+小程序'!G49+快手!G49+唯品会!G49+'线下门店-直营'!G49+'线下门店-经销'!G49+线下渠道!G49+淘系达播!G49+抖音达播!G49 -> 102872.77 | I51: =淘系!H49+抖音!H49+PDD!H49+得物!H49+京东自营财经口径!H49+京东POP财经口径!H49+'视频号+官网+小程序'!H49+快手!H49+唯品会!H49+'线下门店-直营'!H49+'线下门店-经销'!H49+线下渠道!H49+淘系达播!H49+抖音达播!H49 -> 143943.35 | J51: =淘系!I49+抖音!I49+PDD!I49+得物!I49+京东自营财经口径!I49+京东POP财经口径!I49+'视频号+官网+小程序'!I49+快手!I49+唯品会!I49+'线下门店-直营'!I49+'线下门店-经销'!I49+线下渠道!I49+淘系达播!I49+抖音达播!I49 -> 131789.64 | K51: =淘系!J49+抖音!J49+PDD!J49+得物!J49+京东自营财经口径!J49+京东POP财经口径!J49+'视频号+官网+小程序'!J49+快手!J49+唯品会!J49+'线下门店-直营'!J49+'线下门店-经销'!J49+线下渠道!J49+淘系达播!J49+抖音达播!J49 -> 112127.73 | L51: =淘系!K49+抖音!K49+PDD!K49+得物!K49+京东自营财经口径!K49+京东POP财经口径!K49+'视频号+官网+小程序'!K49+快手!K49+唯品会!K49+'线下门店-直营'!K49+'线下门店-经销'!K49+线下渠道!K49+淘系达播!K49+抖音达播!K49 -> 107031.01 | ... O51: =淘系!N49+抖音!N49+PDD!N49+得物!N49+京东自营财经口径!N49+京东POP财经口径!N49+'视频号+官网+小程序'!N49+快手!N49+唯品会!N49+'线下门店-直营'!N49+'线下门店-经销'!N49+线下渠道!N49+淘系达播!N49+抖音达播!N49 -> 139684.73 | P51: =SUM(C51:O51) -> 1566703.2 | Q51: =P51/$P$16 -> 0.0038777451 | R51: 线下门店 | S51: =S38*T45+S45 -> 6254309.5 | U51: =P51-淘系!O49-淘系达播!O49-抖音!O49-抖音达播!O49-快手!O49-京东POP财经口径!O49-京东自营财经口径!O49-PDD!O49-得物!O49-'视频号+官网+小程序'!O49-唯品会!O49-'线下门店-直营'!O49-'线下门店-经销'!O49-线下渠道!O49 -> 0
B52: 门店人工 | C52: =淘系!C50+抖音!C50+PDD!C50+得物!C50+京东自营财经口径!C50+京东POP财经口径!C50+'视频号+官网+小程序'!C50+快手!C50+唯品会!C50+'线下门店-直营'!C50+'线下门店-经销'!C50+线下渠道!C50+淘系达播!C50+抖音达播!C50 -> 112000 | E52: =淘系!D50+抖音!D50+PDD!D50+得物!D50+京东自营财经口径!D50+京东POP财经口径!D50+'视频号+官网+小程序'!D50+快手!D50+唯品会!D50+'线下门店-直营'!D50+'线下门店-经销'!D50+线下渠道!D50+淘系达播!D50+抖音达播!D50 -> 120000 | F52: =淘系!E50+抖音!E50+PDD!E50+得物!E50+京东自营财经口径!E50+京东POP财经口径!E50+'视频号+官网+小程序'!E50+快手!E50+唯品会!E50+'线下门店-直营'!E50+'线下门店-经销'!E50+线下渠道!E50+淘系达播!E50+抖音达播!E50 -> 132000 | G52: =淘系!F50+抖音!F50+PDD!F50+得物!F50+京东自营财经口径!F50+京东POP财经口径!F50+'视频号+官网+小程序'!F50+快手!F50+唯品会!F50+'线下门店-直营'!F50+'线下门店-经销'!F50+线下渠道!F50+淘系达播!F50+抖音达播!F50 -> 145000 | H52: =淘系!G50+抖音!G50+PDD!G50+得物!G50+京东自营财经口径!G50+京东POP财经口径!G50+'视频号+官网+小程序'!G50+快手!G50+唯品会!G50+'线下门店-直营'!G50+'线下门店-经销'!G50+线下渠道!G50+淘系达播!G50+抖音达播!G50 -> 110000 | I52: =淘系!H50+抖音!H50+PDD!H50+得物!H50+京东自营财经口径!H50+京东POP财经口径!H50+'视频号+官网+小程序'!H50+快手!H50+唯品会!H50+'线下门店-直营'!H50+'线下门店-经销'!H50+线下渠道!H50+淘系达播!H50+抖音达播!H50 -> 135000 | J52: =淘系!I50+抖音!I50+PDD!I50+得物!I50+京东自营财经口径!I50+京东POP财经口径!I50+'视频号+官网+小程序'!I50+快手!I50+唯品会!I50+'线下门店-直营'!I50+'线下门店-经销'!I50+线下渠道!I50+淘系达播!I50+抖音达播!I50 -> 120000 | K52: =淘系!J50+抖音!J50+PDD!J50+得物!J50+京东自营财经口径!J50+京东POP财经口径!J50+'视频号+官网+小程序'!J50+快手!J50+唯品会!J50+'线下门店-直营'!J50+'线下门店-经销'!J50+线下渠道!J50+淘系达播!J50+抖音达播!J50 -> 110000 | L52: =淘系!K50+抖音!K50+PDD!K50+得物!K50+京东自营财经口径!K50+京东POP财经口径!K50+'视频号+官网+小程序'!K50+快手!K50+唯品会!K50+'线下门店-直营'!K50+'线下门店-经销'!K50+线下渠道!K50+淘系达播!K50+抖音达播!K50 -> 105000 | ... O52: =淘系!N50+抖音!N50+PDD!N50+得物!N50+京东自营财经口径!N50+京东POP财经口径!N50+'视频号+官网+小程序'!N50+快手!N50+唯品会!N50+'线下门店-直营'!N50+'线下门店-经销'!N50+线下渠道!N50+淘系达播!N50+抖音达播!N50 -> 145000 | P52: =SUM(C52:O52) -> 1509000 | Q52: =P52/$P$16 -> 0.003734924 | R52: 线下门店 | U52: =P52-淘系!O50-淘系达播!O50-抖音!O50-抖音达播!O50-快手!O50-京东POP财经口径!O50-京东自营财经口径!O50-PDD!O50-得物!O50-'视频号+官网+小程序'!O50-唯品会!O50-'线下门店-直营'!O50-'线下门店-经销'!O50-线下渠道!O50 -> 0
B53: 门店展陈装修等其他 | C53: =淘系!C51+抖音!C51+PDD!C51+得物!C51+京东自营财经口径!C51+京东POP财经口径!C51+'视频号+官网+小程序'!C51+快手!C51+唯品会!C51+'线下门店-直营'!C51+'线下门店-经销'!C51+线下渠道!C51+淘系达播!C51+抖音达播!C51 -> 119622.72 | E53: =淘系!D51+抖音!D51+PDD!D51+得物!D51+京东自营财经口径!D51+京东POP财经口径!D51+'视频号+官网+小程序'!D51+快手!D51+唯品会!D51+'线下门店-直营'!D51+'线下门店-经销'!D51+线下渠道!D51+淘系达播!D51+抖音达播!D51 -> 101514.26 | F53: =淘系!E51+抖音!E51+PDD!E51+得物!E51+京东自营财经口径!E51+京东POP财经口径!E51+'视频号+官网+小程序'!E51+快手!E51+唯品会!E51+'线下门店-直营'!E51+'线下门店-经销'!E51+线下渠道!E51+淘系达播!E51+抖音达播!E51 -> 117165.68 | G53: =淘系!F51+抖音!F51+PDD!F51+得物!F51+京东自营财经口径!F51+京东POP财经口径!F51+'视频号+官网+小程序'!F51+快手!F51+唯品会!F51+'线下门店-直营'!F51+'线下门店-经销'!F51+线下渠道!F51+淘系达播!F51+抖音达播!F51 -> 111111.4 | H53: =淘系!G51+抖音!G51+PDD!G51+得物!G51+京东自营财经口径!G51+京东POP财经口径!G51+'视频号+官网+小程序'!G51+快手!G51+唯品会!G51+'线下门店-直营'!G51+'线下门店-经销'!G51+线下渠道!G51+淘系达播!G51+抖音达播!G51 -> 92583.465 | I53: =淘系!H51+抖音!H51+PDD!H51+得物!H51+京东自营财经口径!H51+京东POP财经口径!H51+'视频号+官网+小程序'!H51+快手!H51+唯品会!H51+'线下门店-直营'!H51+'线下门店-经销'!H51+线下渠道!H51+淘系达播!H51+抖音达播!H51 -> 127012.66 | J53: =淘系!I51+抖音!I51+PDD!I51+得物!I51+京东自营财经口径!I51+京东POP财经口径!I51+'视频号+官网+小程序'!I51+快手!I51+唯品会!I51+'线下门店-直营'!I51+'线下门店-经销'!I51+线下渠道!I51+淘系达播!I51+抖音达播!I51 -> 132900.14 | K53: =淘系!J51+抖音!J51+PDD!J51+得物!J51+京东自营财经口径!J51+京东POP财经口径!J51+'视频号+官网+小程序'!J51+快手!J51+唯品会!J51+'线下门店-直营'!J51+'线下门店-经销'!J51+线下渠道!J51+淘系达播!J51+抖音达播!J51 -> 124577.57 | L53: =淘系!K51+抖音!K51+PDD!K51+得物!K51+京东自营财经口径!K51+京东POP财经口径!K51+'视频号+官网+小程序'!K51+快手!K51+唯品会!K51+'线下门店-直营'!K51+'线下门店-经销'!K51+线下渠道!K51+淘系达播!K51+抖音达播!K51 -> 129414.95 | ... O53: =淘系!N51+抖音!N51+PDD!N51+得物!N51+京东自营财经口径!N51+京东POP财经口径!N51+'视频号+官网+小程序'!N51+快手!N51+唯品会!N51+'线下门店-直营'!N51+'线下门店-经销'!N51+线下渠道!N51+淘系达播!N51+抖音达播!N51 -> 245458.49 | P53: =SUM(C53:O53) -> 1709335.7 | Q53: =P53/$P$16 -> 0.0042307746 | R53: 线下门店 | U53: =P53-淘系!O51-淘系达播!O51-抖音!O51-抖音达播!O51-快手!O51-京东POP财经口径!O51-京东自营财经口径!O51-PDD!O51-得物!O51-'视频号+官网+小程序'!O51-唯品会!O51-'线下门店-直营'!O51-'线下门店-经销'!O51-线下渠道!O51 -> 0
B54: 市场投入费用 | C54: =SUM(C26,C37,C44,C49) -> 7571337.2 | D54: =C54/C$16 -> 0.2741736 | E54: =SUM(E26,E37,E44,E49) -> 9749121.1 | F54: =SUM(F26,F37,F44,F49) -> 9523102.8 | G54: =SUM(G26,G37,G44,G49) -> 7160913.2 | H54: =SUM(H26,H37,H44,H49) -> 20137112 | I54: =SUM(I26,I37,I44,I49) -> 15693144 | J54: =SUM(J26,J37,J44,J49) -> 7714531.2 | K54: =SUM(K26,K37,K44,K49) -> 12496733 | L54: =SUM(L26,L37,L44,L49) -> 8038243.4 | ... O54: =SUM(O26,O37,O44,O49) -> 10539676 | P54: =SUM(C54:O54) -> 1.4037015e+08 | Q54: =P54/$P$16 -> 0.34742997 | U54: =P54-淘系!O52-淘系达播!O52-抖音!O52-抖音达播!O52-快手!O52-京东POP财经口径!O52-京东自营财经口径!O52-PDD!O52-得物!O52-'视频号+官网+小程序'!O52-唯品会!O52-'线下门店-直营'!O52-'线下门店-经销'!O52-线下渠道!O52 -> 0.27417361
B55: 平台佣金 | C55: =淘系!C53+抖音!C53+PDD!C53+得物!C53+京东自营财经口径!C53+京东POP财经口径!C53+'视频号+官网+小程序'!C53+快手!C53+唯品会!C53+'线下门店-直营'!C53+'线下门店-经销'!C53+线下渠道!C53+淘系达播!C53+抖音达播!C53 -> 545556.88 | E55: =淘系!D53+抖音!D53+PDD!D53+得物!D53+京东自营财经口径!D53+京东POP财经口径!D53+'视频号+官网+小程序'!D53+快手!D53+唯品会!D53+'线下门店-直营'!D53+'线下门店-经销'!D53+线下渠道!D53+淘系达播!D53+抖音达播!D53 -> 530099.86 | F55: =淘系!E53+抖音!E53+PDD!E53+得物!E53+京东自营财经口径!E53+京东POP财经口径!E53+'视频号+官网+小程序'!E53+快手!E53+唯品会!E53+'线下门店-直营'!E53+'线下门店-经销'!E53+线下渠道!E53+淘系达播!E53+抖音达播!E53 -> 459150.76 | G55: =淘系!F53+抖音!F53+PDD!F53+得物!F53+京东自营财经口径!F53+京东POP财经口径!F53+'视频号+官网+小程序'!F53+快手!F53+唯品会!F53+'线下门店-直营'!F53+'线下门店-经销'!F53+线下渠道!F53+淘系达播!F53+抖音达播!F53 -> 386682.7 | H55: =淘系!G53+抖音!G53+PDD!G53+得物!G53+京东自营财经口径!G53+京东POP财经口径!G53+'视频号+官网+小程序'!G53+快手!G53+唯品会!G53+'线下门店-直营'!G53+'线下门店-经销'!G53+线下渠道!G53+淘系达播!G53+抖音达播!G53 -> 881670.41 | I55: =淘系!H53+抖音!H53+PDD!H53+得物!H53+京东自营财经口径!H53+京东POP财经口径!H53+'视频号+官网+小程序'!H53+快手!H53+唯品会!H53+'线下门店-直营'!H53+'线下门店-经销'!H53+线下渠道!H53+淘系达播!H53+抖音达播!H53 -> 775856.22 | J55: =淘系!I53+抖音!I53+PDD!I53+得物!I53+京东自营财经口径!I53+京东POP财经口径!I53+'视频号+官网+小程序'!I53+快手!I53+唯品会!I53+'线下门店-直营'!I53+'线下门店-经销'!I53+线下渠道!I53+淘系达播!I53+抖音达播!I53 -> 507479.6 | K55: =淘系!J53+抖音!J53+PDD!J53+得物!J53+京东自营财经口径!J53+京东POP财经口径!J53+'视频号+官网+小程序'!J53+快手!J53+唯品会!J53+'线下门店-直营'!J53+'线下门店-经销'!J53+线下渠道!J53+淘系达播!J53+抖音达播!J53 -> 754147.41 | L55: =淘系!K53+抖音!K53+PDD!K53+得物!K53+京东自营财经口径!K53+京东POP财经口径!K53+'视频号+官网+小程序'!K53+快手!K53+唯品会!K53+'线下门店-直营'!K53+'线下门店-经销'!K53+线下渠道!K53+淘系达播!K53+抖音达播!K53 -> 523741.74 | ... O55: =淘系!N53+抖音!N53+PDD!N53+得物!N53+京东自营财经口径!N53+京东POP财经口径!N53+'视频号+官网+小程序'!N53+快手!N53+唯品会!N53+'线下门店-直营'!N53+'线下门店-经销'!N53+线下渠道!N53+淘系达播!N53+抖音达播!N53 -> 670023.88 | P55: =SUM(C55:O55) -> 7876233.7 | Q55: =P55/$P$16 -> 0.019494456 | U55: =P55-淘系!O53-淘系达播!O53-抖音!O53-抖音达播!O53-快手!O53-京东POP财经口径!O53-京东自营财经口径!O53-PDD!O53-得物!O53-'视频号+官网+小程序'!O53-唯品会!O53-'线下门店-直营'!O53-'线下门店-经销'!O53-线下渠道!O53 -> -1.1350494e-09
B56: 平台其他费用 | C56: =淘系!C54+抖音!C54+PDD!C54+得物!C54+京东自营财经口径!C54+京东POP财经口径!C54+'视频号+官网+小程序'!C54+快手!C54+唯品会!C54+'线下门店-直营'!C54+'线下门店-经销'!C54+线下渠道!C54+淘系达播!C54+抖音达播!C54 -> 361150.6 | E56: =淘系!D54+抖音!D54+PDD!D54+得物!D54+京东自营财经口径!D54+京东POP财经口径!D54+'视频号+官网+小程序'!D54+快手!D54+唯品会!D54+'线下门店-直营'!D54+'线下门店-经销'!D54+线下渠道!D54+淘系达播!D54+抖音达播!D54 -> 365217.22 | F56: =淘系!E54+抖音!E54+PDD!E54+得物!E54+京东自营财经口径!E54+京东POP财经口径!E54+'视频号+官网+小程序'!E54+快手!E54+唯品会!E54+'线下门店-直营'!E54+'线下门店-经销'!E54+线下渠道!E54+淘系达播!E54+抖音达播!E54 -> 305035.61 | G56: =淘系!F54+抖音!F54+PDD!F54+得物!F54+京东自营财经口径!F54+京东POP财经口径!F54+'视频号+官网+小程序'!F54+快手!F54+唯品会!F54+'线下门店-直营'!F54+'线下门店-经销'!F54+线下渠道!F54+淘系达播!F54+抖音达播!F54 -> 260450.25 | H56: =淘系!G54+抖音!G54+PDD!G54+得物!G54+京东自营财经口径!G54+京东POP财经口径!G54+'视频号+官网+小程序'!G54+快手!G54+唯品会!G54+'线下门店-直营'!G54+'线下门店-经销'!G54+线下渠道!G54+淘系达播!G54+抖音达播!G54 -> 464064.91 | I56: =淘系!H54+抖音!H54+PDD!H54+得物!H54+京东自营财经口径!H54+京东POP财经口径!H54+'视频号+官网+小程序'!H54+快手!H54+唯品会!H54+'线下门店-直营'!H54+'线下门店-经销'!H54+线下渠道!H54+淘系达播!H54+抖音达播!H54 -> 412716.56 | J56: =淘系!I54+抖音!I54+PDD!I54+得物!I54+京东自营财经口径!I54+京东POP财经口径!I54+'视频号+官网+小程序'!I54+快手!I54+唯品会!I54+'线下门店-直营'!I54+'线下门店-经销'!I54+线下渠道!I54+淘系达播!I54+抖音达播!I54 -> 339608.74 | K56: =淘系!J54+抖音!J54+PDD!J54+得物!J54+京东自营财经口径!J54+京东POP财经口径!J54+'视频号+官网+小程序'!J54+快手!J54+唯品会!J54+'线下门店-直营'!J54+'线下门店-经销'!J54+线下渠道!J54+淘系达播!J54+抖音达播!J54 -> 483451.94 | L56: =淘系!K54+抖音!K54+PDD!K54+得物!K54+京东自营财经口径!K54+京东POP财经口径!K54+'视频号+官网+小程序'!K54+快手!K54+唯品会!K54+'线下门店-直营'!K54+'线下门店-经销'!K54+线下渠道!K54+淘系达播!K54+抖音达播!K54 -> 345370.35 | ... O56: =淘系!N54+抖音!N54+PDD!N54+得物!N54+京东自营财经口径!N54+京东POP财经口径!N54+'视频号+官网+小程序'!N54+快手!N54+唯品会!N54+'线下门店-直营'!N54+'线下门店-经销'!N54+线下渠道!N54+淘系达播!N54+抖音达播!N54 -> 456461.73 | P56: =SUM(C56:O56) -> 4784268.3 | Q56: =P56/$P$16 -> 0.011841536 | U56: =P56-淘系!O54-淘系达播!O54-抖音!O54-抖音达播!O54-快手!O54-京东POP财经口径!O54-京东自营财经口径!O54-PDD!O54-得物!O54-'视频号+官网+小程序'!O54-唯品会!O54-'线下门店-直营'!O54-'线下门店-经销'!O54-线下渠道!O54 -> 3.7471182e-10
B57: 售后费用 | C57: =淘系!C55+抖音!C55+PDD!C55+得物!C55+京东自营财经口径!C55+京东POP财经口径!C55+'视频号+官网+小程序'!C55+快手!C55+唯品会!C55+'线下门店-直营'!C55+'线下门店-经销'!C55+线下渠道!C55+淘系达播!C55+抖音达播!C55 -> 2113042 | E57: =淘系!D55+抖音!D55+PDD!D55+得物!D55+京东自营财经口径!D55+京东POP财经口径!D55+'视频号+官网+小程序'!D55+快手!D55+唯品会!D55+'线下门店-直营'!D55+'线下门店-经销'!D55+线下渠道!D55+淘系达播!D55+抖音达播!D55 -> 1381742 | F57: =淘系!E55+抖音!E55+PDD!E55+得物!E55+京东自营财经口径!E55+京东POP财经口径!E55+'视频号+官网+小程序'!E55+快手!E55+唯品会!E55+'线下门店-直营'!E55+'线下门店-经销'!E55+线下渠道!E55+淘系达播!E55+抖音达播!E55 -> 1077748 | G57: =淘系!F55+抖音!F55+PDD!F55+得物!F55+京东自营财经口径!F55+京东POP财经口径!F55+'视频号+官网+小程序'!F55+快手!F55+唯品会!F55+'线下门店-直营'!F55+'线下门店-经销'!F55+线下渠道!F55+淘系达播!F55+抖音达播!F55 -> 1658593 | H57: =淘系!G55+抖音!G55+PDD!G55+得物!G55+京东自营财经口径!G55+京东POP财经口径!G55+'视频号+官网+小程序'!G55+快手!G55+唯品会!G55+'线下门店-直营'!G55+'线下门店-经销'!G55+线下渠道!G55+淘系达播!G55+抖音达播!G55 -> 1424395 | I57: =淘系!H55+抖音!H55+PDD!H55+得物!H55+京东自营财经口径!H55+京东POP财经口径!H55+'视频号+官网+小程序'!H55+快手!H55+唯品会!H55+'线下门店-直营'!H55+'线下门店-经销'!H55+线下渠道!H55+淘系达播!H55+抖音达播!H55 -> 997887 | J57: =淘系!I55+抖音!I55+PDD!I55+得物!I55+京东自营财经口径!I55+京东POP财经口径!I55+'视频号+官网+小程序'!I55+快手!I55+唯品会!I55+'线下门店-直营'!I55+'线下门店-经销'!I55+线下渠道!I55+淘系达播!I55+抖音达播!I55 -> 1390333 | K57: =淘系!J55+抖音!J55+PDD!J55+得物!J55+京东自营财经口径!J55+京东POP财经口径!J55+'视频号+官网+小程序'!J55+快手!J55+唯品会!J55+'线下门店-直营'!J55+'线下门店-经销'!J55+线下渠道!J55+淘系达播!J55+抖音达播!J55 -> 1075635 | L57: =淘系!K55+抖音!K55+PDD!K55+得物!K55+京东自营财经口径!K55+京东POP财经口径!K55+'视频号+官网+小程序'!K55+快手!K55+唯品会!K55+'线下门店-直营'!K55+'线下门店-经销'!K55+线下渠道!K55+淘系达播!K55+抖音达播!K55 -> 1482157 | ... O57: =淘系!N55+抖音!N55+PDD!N55+得物!N55+京东自营财经口径!N55+京东POP财经口径!N55+'视频号+官网+小程序'!N55+快手!N55+唯品会!N55+'线下门店-直营'!N55+'线下门店-经销'!N55+线下渠道!N55+淘系达播!N55+抖音达播!N55 -> 999777 | P57: =SUM(C57:O57) -> 15795916 | Q57: =P57/$P$16 -> 0.039096452 | U57: =P57-淘系!O55-淘系达播!O55-抖音!O55-抖音达播!O55-快手!O55-京东POP财经口径!O55-京东自营财经口径!O55-PDD!O55-得物!O55-'视频号+官网+小程序'!O55-唯品会!O55-'线下门店-直营'!O55-'线下门店-经销'!O55-线下渠道!O55 -> 1066677.1
B58: 短信及店铺软件 | C58: =淘系!C56+抖音!C56+PDD!C56+得物!C56+京东自营财经口径!C56+京东POP财经口径!C56+'视频号+官网+小程序'!C56+快手!C56+唯品会!C56+'线下门店-直营'!C56+'线下门店-经销'!C56+线下渠道!C56+淘系达播!C56+抖音达播!C56 -> 46067.116 | E58: =淘系!D56+抖音!D56+PDD!D56+得物!D56+京东自营财经口径!D56+京东POP财经口径!D56+'视频号+官网+小程序'!D56+快手!D56+唯品会!D56+'线下门店-直营'!D56+'线下门店-经销'!D56+线下渠道!D56+淘系达播!D56+抖音达播!D56 -> 49007.405 | F58: =淘系!E56+抖音!E56+PDD!E56+得物!E56+京东自营财经口径!E56+京东POP财经口径!E56+'视频号+官网+小程序'!E56+快手!E56+唯品会!E56+'线下门店-直营'!E56+'线下门店-经销'!E56+线下渠道!E56+淘系达播!E56+抖音达播!E56 -> 36750.794 | G58: =淘系!F56+抖音!F56+PDD!F56+得物!F56+京东自营财经口径!F56+京东POP财经口径!F56+'视频号+官网+小程序'!F56+快手!F56+唯品会!F56+'线下门店-直营'!F56+'线下门店-经销'!F56+线下渠道!F56+淘系达播!F56+抖音达播!F56 -> 31207.446 | H58: =淘系!G56+抖音!G56+PDD!G56+得物!G56+京东自营财经口径!G56+京东POP财经口径!G56+'视频号+官网+小程序'!G56+快手!G56+唯品会!G56+'线下门店-直营'!G56+'线下门店-经销'!G56+线下渠道!G56+淘系达播!G56+抖音达播!G56 -> 67320.837 | I58: =淘系!H56+抖音!H56+PDD!H56+得物!H56+京东自营财经口径!H56+京东POP财经口径!H56+'视频号+官网+小程序'!H56+快手!H56+唯品会!H56+'线下门店-直营'!H56+'线下门店-经销'!H56+线下渠道!H56+淘系达播!H56+抖音达播!H56 -> 59261.026 | J58: =淘系!I56+抖音!I56+PDD!I56+得物!I56+京东自营财经口径!I56+京东POP财经口径!I56+'视频号+官网+小程序'!I56+快手!I56+唯品会!I56+'线下门店-直营'!I56+'线下门店-经销'!I56+线下渠道!I56+淘系达播!I56+抖音达播!I56 -> 39012.507 | K58: =淘系!J56+抖音!J56+PDD!J56+得物!J56+京东自营财经口径!J56+京东POP财经口径!J56+'视频号+官网+小程序'!J56+快手!J56+唯品会!J56+'线下门店-直营'!J56+'线下门店-经销'!J56+线下渠道!J56+淘系达播!J56+抖音达播!J56 -> 57007.786 | L58: =淘系!K56+抖音!K56+PDD!K56+得物!K56+京东自营财经口径!K56+京东POP财经口径!K56+'视频号+官网+小程序'!K56+快手!K56+唯品会!K56+'线下门店-直营'!K56+'线下门店-经销'!K56+线下渠道!K56+淘系达播!K56+抖音达播!K56 -> 39423.565 | ... O58: =淘系!N56+抖音!N56+PDD!N56+得物!N56+京东自营财经口径!N56+京东POP财经口径!N56+'视频号+官网+小程序'!N56+快手!N56+唯品会!N56+'线下门店-直营'!N56+'线下门店-经销'!N56+线下渠道!N56+淘系达播!N56+抖音达播!N56 -> 55104.643 | P58: =SUM(C58:O58) -> 614606.61 | Q58: =P58/$P$16 -> 0.001521212 | U58: =P58-淘系!O56-淘系达播!O56-抖音!O56-抖音达播!O56-快手!O56-京东POP财经口径!O56-京东自营财经口径!O56-PDD!O56-得物!O56-'视频号+官网+小程序'!O56-唯品会!O56-'线下门店-直营'!O56-'线下门店-经销'!O56-线下渠道!O56 -> 6.9348971e-11
B59: 其他运营费用（咨询调研等） | C59: =淘系!C57+抖音!C57+PDD!C57+得物!C57+京东自营财经口径!C57+京东POP财经口径!C57+'视频号+官网+小程序'!C57+快手!C57+唯品会!C57+'线下门店-直营'!C57+'线下门店-经销'!C57+线下渠道!C57+淘系达播!C57+抖音达播!C57 -> 250000 | E59: =淘系!D57+抖音!D57+PDD!D57+得物!D57+京东自营财经口径!D57+京东POP财经口径!D57+'视频号+官网+小程序'!D57+快手!D57+唯品会!D57+'线下门店-直营'!D57+'线下门店-经销'!D57+线下渠道!D57+淘系达播!D57+抖音达播!D57 -> 0 | F59: =淘系!E57+抖音!E57+PDD!E57+得物!E57+京东自营财经口径!E57+京东POP财经口径!E57+'视频号+官网+小程序'!E57+快手!E57+唯品会!E57+'线下门店-直营'!E57+'线下门店-经销'!E57+线下渠道!E57+淘系达播!E57+抖音达播!E57 -> 0 | G59: =淘系!F57+抖音!F57+PDD!F57+得物!F57+京东自营财经口径!F57+京东POP财经口径!F57+'视频号+官网+小程序'!F57+快手!F57+唯品会!F57+'线下门店-直营'!F57+'线下门店-经销'!F57+线下渠道!F57+淘系达播!F57+抖音达播!F57 -> 0 | H59: =淘系!G57+抖音!G57+PDD!G57+得物!G57+京东自营财经口径!G57+京东POP财经口径!G57+'视频号+官网+小程序'!G57+快手!G57+唯品会!G57+'线下门店-直营'!G57+'线下门店-经销'!G57+线下渠道!G57+淘系达播!G57+抖音达播!G57 -> 100000 | I59: =淘系!H57+抖音!H57+PDD!H57+得物!H57+京东自营财经口径!H57+京东POP财经口径!H57+'视频号+官网+小程序'!H57+快手!H57+唯品会!H57+'线下门店-直营'!H57+'线下门店-经销'!H57+线下渠道!H57+淘系达播!H57+抖音达播!H57 -> 0 | J59: =淘系!I57+抖音!I57+PDD!I57+得物!I57+京东自营财经口径!I57+京东POP财经口径!I57+'视频号+官网+小程序'!I57+快手!I57+唯品会!I57+'线下门店-直营'!I57+'线下门店-经销'!I57+线下渠道!I57+淘系达播!I57+抖音达播!I57 -> 0 | K59: =淘系!J57+抖音!J57+PDD!J57+得物!J57+京东自营财经口径!J57+京东POP财经口径!J57+'视频号+官网+小程序'!J57+快手!J57+唯品会!J57+'线下门店-直营'!J57+'线下门店-经销'!J57+线下渠道!J57+淘系达播!J57+抖音达播!J57 -> 0 | L59: =淘系!K57+抖音!K57+PDD!K57+得物!K57+京东自营财经口径!K57+京东POP财经口径!K57+'视频号+官网+小程序'!K57+快手!K57+唯品会!K57+'线下门店-直营'!K57+'线下门店-经销'!K57+线下渠道!K57+淘系达播!K57+抖音达播!K57 -> 0 | ... O59: =淘系!N57+抖音!N57+PDD!N57+得物!N57+京东自营财经口径!N57+京东POP财经口径!N57+'视频号+官网+小程序'!N57+快手!N57+唯品会!N57+'线下门店-直营'!N57+'线下门店-经销'!N57+线下渠道!N57+淘系达播!N57+抖音达播!N57 -> 300000 | P59: =SUM(C59:O59) -> 750000 | Q59: =P59/$P$16 -> 0.001856324 | R59: 新品需求调研，产品上市反馈 | U59: =P59-淘系!O57-淘系达播!O57-抖音!O57-抖音达播!O57-快手!O57-京东POP财经口径!O57-京东自营财经口径!O57-PDD!O57-得物!O57-'视频号+官网+小程序'!O57-唯品会!O57-'线下门店-直营'!O57-'线下门店-经销'!O57-线下渠道!O57 -> 0
B60: 店铺运营费用 | C60: =SUM(C55:C59) -> 3315816.6 | D60: =C60/C$16 -> 0.1200725 | E60: =SUM(E55:E59) -> 2326066.5 | F60: =SUM(F55:F59) -> 1878685.2 | G60: =SUM(G55:G59) -> 2336933.4 | H60: =SUM(H55:H59) -> 2937451.2 | I60: =SUM(I55:I59) -> 2245720.8 | J60: =SUM(J55:J59) -> 2276433.9 | K60: =SUM(K55:K59) -> 2370242.1 | L60: =SUM(L55:L59) -> 2390692.6 | ... O60: =SUM(O55:O59) -> 2481367.3 | P60: =SUM(C60:O60) -> 29821025 | Q60: =P60/$P$16 -> 0.07380998 | U60: =P60-淘系!O58-淘系达播!O58-抖音!O58-抖音达播!O58-快手!O58-京东POP财经口径!O58-京东自营财经口径!O58-PDD!O58-得物!O58-'视频号+官网+小程序'!O58-唯品会!O58-'线下门店-直营'!O58-'线下门店-经销'!O58-线下渠道!O58 -> 0.12007249
B61: A&P 合计数 | C61: =SUM(C54,C60) -> 10887154 | E61: =SUM(E54,E60) -> 12075188 | F61: =SUM(F54,F60) -> 11401788 | G61: =SUM(G54,G60) -> 9497846.6 | H61: =SUM(H54,H60) -> 23074563 | I61: =SUM(I54,I60) -> 17938865 | J61: =SUM(J54,J60) -> 9990965 | K61: =SUM(K54,K60) -> 14866975 | L61: =SUM(L54,L60) -> 10428936 | ... O61: =SUM(O54,O60) -> 13021044 | P61: =SUM(C61:O61) -> 1.7019117e+08 | Q61: =P61/$P$16 -> 0.42123995 | U61: =P61-淘系!O59-淘系达播!O59-抖音!O59-抖音达播!O59-快手!O59-京东POP财经口径!O59-京东自营财经口径!O59-PDD!O59-得物!O59-'视频号+官网+小程序'!O59-唯品会!O59-'线下门店-直营'!O59-'线下门店-经销'!O59-线下渠道!O59 -> 0
B62: 店铺利润 | C62: =C22-C61 -> 2518214.8 | E62: =E22-E61 -> 1423837.3 | F62: =F22-F61 -> -364449.22 | G62: =G22-G61 -> 87988.686 | H62: =H22-H61 -> -982261.36 | I62: =I22-I61 -> 1979342.4 | J62: =J22-J61 -> 4780281.2 | K62: =K22-K61 -> 5737516.6 | L62: =L22-L61 -> 4866512.6 | ... O62: =O22-O61 -> 8578812.4 | P62: =SUM(C62:O62) -> 44847957 | Q62: =P62/$P$16 -> 0.11100312 | R62: 1700万成本差 | U62: =P62-淘系!O60-淘系达播!O60-抖音!O60-抖音达播!O60-快手!O60-京东POP财经口径!O60-京东自营财经口径!O60-PDD!O60-得物!O60-'视频号+官网+小程序'!O60-唯品会!O60-'线下门店-直营'!O60-'线下门店-经销'!O60-线下渠道!O60 -> -40154.706
C63: =C62/C16 -> 0.091189706 | E63: =E62/E16 -> 0.051554425 | F63: =F62/F16 -> -0.015447093 | G63: =G62/G16 -> 0.0043037688 | H63: =H62/H16 -> -0.022983621 | I63: =I62/I16 -> 0.050922669 | J63: =J62/J16 -> 0.17610104 | K63: =K62/K16 -> 0.15267601 | L63: =L62/L16 -> 0.17705919 | ... P63: =P62/P16 -> 0.11100312
B65: BU 可控运营费用 | C65: =C66+C67 -> 4000000 | E65: =E66+E67 -> 4000000 | F65: =F66+F67 -> 3800000 | G65: =G66+G67 -> 3800000 | H65: =H66+H67 -> 3800000 | I65: =I66+I67 -> 2800000 | J65: =J66+J67 -> 2300000 | K65: =K66+K67 -> 2300000 | L65: =L66+L67 -> 2300000 | ... O65: =O66+O67 -> 2300000 | P65: =SUM(C65:O65) -> 36000000 | Q65: =P65/$P$16 -> 0.089103554
B66: 销售管理费用 | C66: 500000 | E66: 500000 | F66: 500000 | G66: 500000 | H66: 500000 | I66: 500000 | J66: 500000 | K66: 500000 | L66: 500000 | M66: 500000 | N66: 500000 | O66: 500000 | P66: =SUM(C66:O66) -> 6000000 | Q66: =P66/$P$16 -> 0.014850592
B67: 研发费用 | C67: 3500000 | E67: 3500000 | F67: 3300000 | G67: 3300000 | H67: 3300000 | I67: 2300000 | J67: 1800000 | K67: 1800000 | L67: 1800000 | M67: 1800000 | N67: 1800000 | O67: 1800000 | P67: =SUM(C67:O67) -> 30000000 | Q67: =P67/$P$16 -> 0.074252962
B68: BU可控利润 | C68: =C62-C65 -> -1481785.2 | E68: =E62-E65 -> -2576162.7 | F68: =F62-F65 -> -4164449.2 | G68: =G62-G65 -> -3712011.3 | H68: =H62-H65 -> -4782261.4 | I68: =I62-I65 -> -820657.56 | J68: =J62-J65 -> 2480281.2 | K68: =K62-K65 -> 3437516.6 | L68: =L62-L65 -> 2566512.6 | ... O68: =O62-O65 -> 6278812.4 | P68: =SUM(C68:O68) -> 8847956.7 | Q68: =P68/$P$16 -> 0.021899566
B70: BU贡献费用 | C70: 2800000 | E70: 2800000 | F70: 2800000 | G70: 2800000 | H70: 2800000 | I70: 2800000 | J70: 2800000 | K70: 2800000 | L70: 2800000 | M70: 2800000 | N70: 2800000 | O70: 2800000 | P70: =SUM(C70:O70) -> 33600000 | Q70: =P70/$P$16 -> 0.083163317
B71: BU贡献利润 | C71: =C68-C70 -> -4281785.2 | E71: =E68-E70 -> -5376162.7 | F71: =F68-F70 -> -6964449.2 | G71: =G68-G70 -> -6512011.3 | H71: =H68-H70 -> -7582261.4 | I71: =I68-I70 -> -3620657.6 | J71: =J68-J70 -> -319718.77 | K71: =K68-K70 -> 637516.57 | L71: =L68-L70 -> -233487.4 | ... O71: =O68-O70 -> 3478812.4 | P71: =SUM(C71:O71) -> -24752043 | Q71: =P71/$P$16 -> -0.061263751
B73: 集团分摊费用 | C73: 1200000 | E73: 1200000 | F73: 1200000 | G73: 1200000 | H73: 1200000 | I73: 1200000 | J73: 1200000 | K73: 1200000 | L73: 1200000 | M73: 1200000 | N73: 1200000 | O73: 1200000 | P73: =SUM(C73:O73) -> 14400000 | Q73: =P73/$P$16 -> 0.035641422
B75: 净利润 | C75: =C71-C73 -> -5481785.2 | E75: =E71-E73 -> -6576162.7 | F75: =F71-F73 -> -8164449.2 | G75: =G71-G73 -> -7712011.3 | H75: =H71-H73 -> -8782261.4 | I75: =I71-I73 -> -4820657.6 | J75: =J71-J73 -> -1519718.8 | K75: =K71-K73 -> -562483.43 | L75: =L71-L73 -> -1433487.4 | ... O75: =O71-O73 -> 2278812.4 | P75: =SUM(C75:O75) -> -39152043 | Q75: =P75/$P$16 -> -0.096905172
B76: 净利润率 | C76: =C75/C16 -> -0.19850665 | E76: =E75/E16 -> -0.23811027 | F76: =F75/F16 -> -0.34604822 | G76: =G75/G16 -> -0.3772157 | H76: =H75/H16 -> -0.20549333 | I76: =I75/I16 -> -0.12402137 | J76: =J75/J16 -> -0.055985003 | K76: =K75/K16 -> -0.014967752 | L76: =L75/L16 -> -0.052154826 | ... O76: =O75/O16 -> 0.061143381
B78: 汇总 | C78: 去国补GMV | E78: 营业收入 | F78: 利润 | G78: 利润率
B79: 2026年全年 | C79: =P6 -> 5.7138404e+08 | E79: =P16 -> 4.0402429e+08 | F79: =P75 -> -39152043 | G79: =F79/E79 -> -0.096905172
B80: 26年H1 | C80: =SUM(C6:I6) -> 2.5286803e+08 | E80: =SUM(C16:I16) -> 1.8087824e+08 | F80: =SUM(C75:I75) -> -41537327 | G80: =F80/E80 -> -0.22964248
B81: 26年H2 | C81: =SUM(J6:O6) -> 3.1851601e+08 | E81: =SUM(J16:O16) -> 2.2314605e+08 | F81: =SUM(J75:O75) -> 2385284 | G81: =F81/E81 -> 0.01068934
C84: =C16-C18-C20-C26-C37-C44-C49-C60-C62 -> 0 | E84: =E16-E18-E20-E26-E37-E44-E49-E60-E62 -> -2.3283064e-09 | F84: =F16-F18-F20-F26-F37-F44-F49-F60-F62 -> 9.3132257e-10 | G84: =G16-G18-G20-G26-G37-G44-G49-G60-G62 -> 9.3132257e-10 | H84: =H16-H18-H20-H26-H37-H44-H49-H60-H62 -> 0 | I84: =I16-I18-I20-I26-I37-I44-I49-I60-I62 -> 0 | J84: =J16-J18-J20-J26-J37-J44-J49-J60-J62 -> 0 | K84: =K16-K18-K20-K26-K37-K44-K49-K60-K62 -> 0 | L84: =L16-L18-L20-L26-L37-L44-L49-L60-L62 -> 0 | ... P84: =P16-P18-P20-P26-P37-P44-P49-P60-P62 -> -0.39424611
C85: =C10-C11-C12-C13-C15 -> -0.037740458 | E85: =E10-E11-E12-E13-E15 -> -0.02612561 | F85: =F10-F11-F12-F13-F15 -> 0.042607348 | G85: =G10-G11-G12-G13-G15 -> 0.03011547 | H85: =H10-H11-H12-H13-H15 -> -0.032073148 | I85: =I10-I11-I12-I13-I15 -> -0.027719341 | J85: =J10-J11-J12-J13-J15 -> 0.03220759 | K85: =K10-K11-K12-K13-K15 -> 0.04233516 | L85: =L10-L11-L12-L13-L15 -> 0.039410491 | ... P85: =P10-P11-P12-P13-P15 -> 0.019280195
C86: =C62-淘系!C60-淘系达播!C60-抖音!C60-抖音达播!C60-快手!C60-京东POP财经口径!C60-京东自营财经口径!C60-PDD!C60-得物!C60-'视频号+官网+小程序'!C60-唯品会!C60-'线下门店-直营'!C60-'线下门店-经销'!C60-线下渠道!C60 -> -3212.3773 | E86: =E62-淘系!D60-淘系达播!D60-抖音!D60-抖音达播!D60-快手!D60-京东POP财经口径!D60-京东自营财经口径!D60-PDD!D60-得物!D60-'视频号+官网+小程序'!D60-唯品会!D60-'线下门店-直营'!D60-'线下门店-经销'!D60-线下渠道!D60 -> -3425.3841 | F86: =F62-淘系!E60-淘系达播!E60-抖音!E60-抖音达播!E60-快手!E60-京东POP财经口径!E60-京东自营财经口径!E60-PDD!E60-得物!E60-'视频号+官网+小程序'!E60-唯品会!E60-'线下门店-直营'!E60-'线下门店-经销'!E60-线下渠道!E60 -> -2786.3615 | G86: =G62-淘系!F60-淘系达播!F60-抖音!F60-抖音达播!F60-快手!F60-京东POP财经口径!F60-京东自营财经口径!F60-PDD!F60-得物!F60-'视频号+官网+小程序'!F60-唯品会!F60-'线下门店-直营'!F60-'线下门店-经销'!F60-线下渠道!F60 -> -2573.3548 | H86: =H62-淘系!G60-淘系达播!G60-抖音!G60-抖音达播!G60-快手!G60-京东POP财经口径!G60-京东自营财经口径!G60-PDD!G60-得物!G60-'视频号+官网+小程序'!G60-唯品会!G60-'线下门店-直营'!G60-'线下门店-经销'!G60-线下渠道!G60 -> -3474.3181 | I86: =I62-淘系!H60-淘系达播!H60-抖音!H60-抖音达播!H60-快手!H60-京东POP财经口径!H60-京东自营财经口径!H60-PDD!H60-得物!H60-'视频号+官网+小程序'!H60-唯品会!H60-'线下门店-直营'!H60-'线下门店-经销'!H60-线下渠道!H60 -> -3449.8511 | J86: =J62-淘系!I60-淘系达播!I60-抖音!I60-抖音达播!I60-快手!I60-京东POP财经口径!I60-京东自营财经口径!I60-PDD!I60-得物!I60-'视频号+官网+小程序'!I60-唯品会!I60-'线下门店-直营'!I60-'线下门店-经销'!I60-线下渠道!I60 -> -2597.8217 | K86: =K62-淘系!J60-淘系达播!J60-抖音!J60-抖音达播!J60-快手!J60-京东POP财经口径!J60-京东自营财经口径!J60-PDD!J60-得物!J60-'视频号+官网+小程序'!J60-唯品会!J60-'线下门店-直营'!J60-'线下门店-经销'!J60-线下渠道!J60 -> -4556.6231 | L86: =L62-淘系!K60-淘系达播!K60-抖音!K60-抖音达播!K60-快手!K60-京东POP财经口径!K60-京东自营财经口径!K60-PDD!K60-得物!K60-'视频号+官网+小程序'!K60-唯品会!K60-'线下门店-直营'!K60-'线下门店-经销'!K60-线下渠道!K60 -> -2786.3615 | ... P86: =P62-淘系!O60-淘系达播!O60-抖音!O60-抖音达播!O60-快手!O60-京东POP财经口径!O60-京东自营财经口径!O60-PDD!O60-得物!O60-'视频号+官网+小程序'!O60-唯品会!O60-'线下门店-直营'!O60-'线下门店-经销'!O60-线下渠道!O60 -> -40154.706
B94: 品牌及内容费用 | C94: 590816.11 | E94: 1555478.6 | F94: 2581397.2 | G94: 1541409.8 | H94: 6001680.8 | I94: 3561493.5 | J94: 824897.7 | K94: 1275088.2 | L94: 1059422.3 | M94: 3244701 | N94: 1405008 | O94: 917198.16 | P94: 24558591 | Q94: 0.06159487
B95: 展会 | C95: 0 | E95: 0 | F95: 64814.267 | G95: 54155.074 | H95: 115388.16 | I95: 101584.8 | J95: 65500.288 | K95: 90329.934 | L95: 72053.164 | M95: 121420.24 | N95: 91985.614 | O95: 0 | P95: 777231.54 | Q95: 0.0019493576
B96: 品牌营销 | C96: 209195 | E96: 209195 | F96: 209195 | G96: 274181.09 | H96: 901523.98 | I96: 534266.37 | J96: 209195 | K96: 317590.92 | L96: 439765.12 | M96: 354899.29 | N96: 319577.74 | O96: 209195 | P96: 4187779.5 | Q96: 0.010503279
B97: 内容素材制作 | C97: 31801.759 | E97: 25890.069 | F97: 25925.707 | G97: 108310.15 | H97: 692328.98 | I97: 446973.13 | J97: 0 | K97: 108395.92 | L97: 230570.12 | M97: 242840.48 | N97: 183971.23 | O97: 32181.962 | P97: 2129189.5 | Q97: 0.005340174
B98: 公关费用 | C98: 31801.759 | E98: 25890.069 | F98: 207405.66 | G98: 21662.029 | H98: 138465.8 | I98: 40633.921 | J98: 26200.115 | K98: 36131.973 | L98: 28821.265 | M98: 97136.191 | N98: 73588.491 | O98: 32181.962 | P98: 759919.23 | Q98: 0.0019059369
B99: 达人种草、样机及加热 | C99: 318017.59 | E99: 1294503.4 | F99: 2074056.6 | G99: 1083101.5 | H99: 4153973.9 | I99: 2438035.2 | J99: 524002.3 | K99: 722639.47 | L99: 288212.65 | M99: 2428404.8 | N99: 735884.91 | O99: 643639.24 | P99: 16704472 | Q99: 0.041896123

Sheet 26年全渠道汇总（仅电商）
B1: Items | C1: 1月 | D1: 2月 | E1: 3月 | F1: 4月 | G1: 5月 | H1: 6月 | I1: 7月 | J1: 8月 | K1: 9月 | L1: 10月 | M1: 11月 | N1: 12月 | O1: 合计 1-12月 | P1: 费比 | Q1: 备注
B2: 退后销量 | C2: =淘系!C2+抖音!C2+PDD!C2+得物!C2+京东自营财经口径!C2+京东POP财经口径!C2+'视频号+官网+小程序'!C2+快手!C2+唯品会!C2+'线下门店-直营'!C2+'线下门店-经销'!C2+线下渠道!C2+淘系达播!C2+抖音达播!C2 -> 90463.684 | D2: =淘系!D2+抖音!D2+PDD!D2+得物!D2+京东自营财经口径!D2+京东POP财经口径!D2+'视频号+官网+小程序'!D2+快手!D2+唯品会!D2+'线下门店-直营'!D2+'线下门店-经销'!D2+线下渠道!D2+淘系达播!D2+抖音达播!D2 -> 81993.689 | E2: =淘系!E2+抖音!E2+PDD!E2+得物!E2+京东自营财经口径!E2+京东POP财经口径!E2+'视频号+官网+小程序'!E2+快手!E2+唯品会!E2+'线下门店-直营'!E2+'线下门店-经销'!E2+线下渠道!E2+淘系达播!E2+抖音达播!E2 -> 95977.292 | F2: =淘系!F2+抖音!F2+PDD!F2+得物!F2+京东自营财经口径!F2+京东POP财经口径!F2+'视频号+官网+小程序'!F2+快手!F2+唯品会!F2+'线下门店-直营'!F2+'线下门店-经销'!F2+线下渠道!F2+淘系达播!F2+抖音达播!F2 -> 80112.964 | G2: =淘系!G2+抖音!G2+PDD!G2+得物!G2+京东自营财经口径!G2+京东POP财经口径!G2+'视频号+官网+小程序'!G2+快手!G2+唯品会!G2+'线下门店-直营'!G2+'线下门店-经销'!G2+线下渠道!G2+淘系达播!G2+抖音达播!G2 -> 138286.3 | H2: =淘系!H2+抖音!H2+PDD!H2+得物!H2+京东自营财经口径!H2+京东POP财经口径!H2+'视频号+官网+小程序'!H2+快手!H2+唯品会!H2+'线下门店-直营'!H2+'线下门店-经销'!H2+线下渠道!H2+淘系达播!H2+抖音达播!H2 -> 121225.56 | I2: =淘系!I2+抖音!I2+PDD!I2+得物!I2+京东自营财经口径!I2+京东POP财经口径!I2+'视频号+官网+小程序'!I2+快手!I2+唯品会!I2+'线下门店-直营'!I2+'线下门店-经销'!I2+线下渠道!I2+淘系达播!I2+抖音达播!I2 -> 80120.129 | J2: =淘系!J2+抖音!J2+PDD!J2+得物!J2+京东自营财经口径!J2+京东POP财经口径!J2+'视频号+官网+小程序'!J2+快手!J2+唯品会!J2+'线下门店-直营'!J2+'线下门店-经销'!J2+线下渠道!J2+淘系达播!J2+抖音达播!J2 -> 99963.489 | ... N2: =淘系!N2+抖音!N2+PDD!N2+得物!N2+京东自营财经口径!N2+京东POP财经口径!N2+'视频号+官网+小程序'!N2+快手!N2+唯品会!N2+'线下门店-直营'!N2+'线下门店-经销'!N2+线下渠道!N2+淘系达播!N2+抖音达播!N2 -> 104902.51 | O2: =SUM(C2:N2) -> 1264551.1
B3: 自补前GMV | O3: =SUM(C3:N3) -> 0 | Q3: 渠道填写
B4: 自补前GSV | C4: =淘系!C4+抖音!C4+PDD!C4+得物!C4+京东自营业务口径!C4+京东POP财经口径!C4+'视频号+官网+小程序'!C4+快手!C4+唯品会!C4+淘系达播!C4+抖音达播!C4 -> 31045758 | D4: =淘系!D4+抖音!D4+PDD!D4+得物!D4+京东自营业务口径!D4+京东POP财经口径!D4+'视频号+官网+小程序'!D4+快手!D4+唯品会!D4+淘系达播!D4+抖音达播!D4 -> 30744830 | E4: =淘系!E4+抖音!E4+PDD!E4+得物!E4+京东自营业务口径!E4+京东POP财经口径!E4+'视频号+官网+小程序'!E4+快手!E4+唯品会!E4+淘系达播!E4+抖音达播!E4 -> 26254224 | F4: =淘系!F4+抖音!F4+PDD!F4+得物!F4+京东自营业务口径!F4+京东POP财经口径!F4+'视频号+官网+小程序'!F4+快手!F4+唯品会!F4+淘系达播!F4+抖音达播!F4 -> 22440838 | G4: =淘系!G4+抖音!G4+PDD!G4+得物!G4+京东自营业务口径!G4+京东POP财经口径!G4+'视频号+官网+小程序'!G4+快手!G4+唯品会!G4+淘系达播!G4+抖音达播!G4 -> 48936202 | H4: =淘系!H4+抖音!H4+PDD!H4+得物!H4+京东自营业务口径!H4+京东POP财经口径!H4+'视频号+官网+小程序'!H4+快手!H4+唯品会!H4+淘系达播!H4+抖音达播!H4 -> 43615568 | I4: =淘系!I4+抖音!I4+PDD!I4+得物!I4+京东自营业务口径!I4+京东POP财经口径!I4+'视频号+官网+小程序'!I4+快手!I4+唯品会!I4+淘系达播!I4+抖音达播!I4 -> 29434852 | J4: =淘系!J4+抖音!J4+PDD!J4+得物!J4+京东自营业务口径!J4+京东POP财经口径!J4+'视频号+官网+小程序'!J4+快手!J4+唯品会!J4+淘系达播!J4+抖音达播!J4 -> 41843411 | ... O4: =淘系!O4+抖音!O4+PDD!O4+得物!O4+京东自营业务口径!O4+京东POP财经口径!O4+'视频号+官网+小程序'!O4+快手!O4+唯品会!O4+淘系达播!O4+抖音达播!O4 -> 4.4686817e+08 | Q4: 渠道填写
B5: 国补自补费用 | C5: =淘系!C5+抖音!C5+PDD!C5+得物!C5+京东自营财经口径!C5+京东POP财经口径!C5+'视频号+官网+小程序'!C5+快手!C5+唯品会!C5+'线下门店-直营'!C5+'线下门店-经销'!C5+线下渠道!C5+淘系达播!C5+抖音达播!C5 -> 4607684.7 | D5: =淘系!D5+抖音!D5+PDD!D5+得物!D5+京东自营财经口径!D5+京东POP财经口径!D5+'视频号+官网+小程序'!D5+快手!D5+唯品会!D5+'线下门店-直营'!D5+'线下门店-经销'!D5+线下渠道!D5+淘系达播!D5+抖音达播!D5 -> 4599816.6 | E5: =淘系!E5+抖音!E5+PDD!E5+得物!E5+京东自营财经口径!E5+京东POP财经口径!E5+'视频号+官网+小程序'!E5+快手!E5+唯品会!E5+'线下门店-直营'!E5+'线下门店-经销'!E5+线下渠道!E5+淘系达播!E5+抖音达播!E5 -> 3914048.7 | F5: =淘系!F5+抖音!F5+PDD!F5+得物!F5+京东自营财经口径!F5+京东POP财经口径!F5+'视频号+官网+小程序'!F5+快手!F5+唯品会!F5+'线下门店-直营'!F5+'线下门店-经销'!F5+线下渠道!F5+淘系达播!F5+抖音达播!F5 -> 3349087.8 | G5: =淘系!G5+抖音!G5+PDD!G5+得物!G5+京东自营财经口径!G5+京东POP财经口径!G5+'视频号+官网+小程序'!G5+快手!G5+唯品会!G5+'线下门店-直营'!G5+'线下门店-经销'!G5+线下渠道!G5+淘系达播!G5+抖音达播!G5 -> 7313638.2 | H5: =淘系!H5+抖音!H5+PDD!H5+得物!H5+京东自营财经口径!H5+京东POP财经口径!H5+'视频号+官网+小程序'!H5+快手!H5+唯品会!H5+'线下门店-直营'!H5+'线下门店-经销'!H5+线下渠道!H5+淘系达播!H5+抖音达播!H5 -> 6508325.2 | I5: =淘系!I5+抖音!I5+PDD!I5+得物!I5+京东自营财经口径!I5+京东POP财经口径!I5+'视频号+官网+小程序'!I5+快手!I5+唯品会!I5+'线下门店-直营'!I5+'线下门店-经销'!I5+线下渠道!I5+淘系达播!I5+抖音达播!I5 -> 4346063.5 | J5: =淘系!J5+抖音!J5+PDD!J5+得物!J5+京东自营财经口径!J5+京东POP财经口径!J5+'视频号+官网+小程序'!J5+快手!J5+唯品会!J5+'线下门店-直营'!J5+'线下门店-经销'!J5+线下渠道!J5+淘系达播!J5+抖音达播!J5 -> 6197224 | ... N5: =淘系!N5+抖音!N5+PDD!N5+得物!N5+京东自营财经口径!N5+京东POP财经口径!N5+'视频号+官网+小程序'!N5+快手!N5+唯品会!N5+'线下门店-直营'!N5+'线下门店-经销'!N5+线下渠道!N5+淘系达播!N5+抖音达播!N5 -> 5803843.5 | O5: =SUM(C5:N5) -> 66408445 | Q5: 渠道填写
B6: GMV（国补后） | C6: =淘系!C6+抖音!C6+PDD!C6+得物!C6+京东自营业务口径!C6+京东POP财经口径!C6+'视频号+官网+小程序'!C6+快手!C6+唯品会!C6+淘系达播!C6+抖音达播!C6 -> 34463089 | D6: =淘系!D6+抖音!D6+PDD!D6+得物!D6+京东自营业务口径!D6+京东POP财经口径!D6+'视频号+官网+小程序'!D6+快手!D6+唯品会!D6+淘系达播!D6+抖音达播!D6 -> 34521878 | E6: =淘系!E6+抖音!E6+PDD!E6+得物!E6+京东自营业务口径!E6+京东POP财经口径!E6+'视频号+官网+小程序'!E6+快手!E6+唯品会!E6+淘系达播!E6+抖音达播!E6 -> 29343709 | F6: =淘系!F6+抖音!F6+PDD!F6+得物!F6+京东自营业务口径!F6+京东POP财经口径!F6+'视频号+官网+小程序'!F6+快手!F6+唯品会!F6+淘系达播!F6+抖音达播!F6 -> 24438729 | G6: =淘系!G6+抖音!G6+PDD!G6+得物!G6+京东自营业务口径!G6+京东POP财经口径!G6+'视频号+官网+小程序'!G6+快手!G6+唯品会!G6+淘系达播!G6+抖音达播!G6 -> 55492644 | H6: =淘系!H6+抖音!H6+PDD!H6+得物!H6+京东自营业务口径!H6+京东POP财经口径!H6+'视频号+官网+小程序'!H6+快手!H6+唯品会!H6+淘系达播!H6+抖音达播!H6 -> 48501779 | I6: =淘系!I6+抖音!I6+PDD!I6+得物!I6+京东自营业务口径!I6+京东POP财经口径!I6+'视频号+官网+小程序'!I6+快手!I6+唯品会!I6+淘系达播!I6+抖音达播!I6 -> 32978711 | J6: =淘系!J6+抖音!J6+PDD!J6+得物!J6+京东自营业务口径!J6+京东POP财经口径!J6+'视频号+官网+小程序'!J6+快手!J6+唯品会!J6+淘系达播!J6+抖音达播!J6 -> 48250646 | ... O6: =淘系!O6+抖音!O6+PDD!O6+得物!O6+京东自营业务口径!O6+京东POP财经口径!O6+'视频号+官网+小程序'!O6+快手!O6+唯品会!O6+淘系达播!O6+抖音达播!O6 -> 5.0744921e+08 | Q6: 渠道填写
B7: 退货率（发货前+后） | C7: =1-C8/C6 -> 0.22778642 | D7: =1-D8/D6 -> 0.22747924 | E7: =1-E8/E6 -> 0.22493211 | F7: =1-F8/F6 -> 0.20396502 | G7: =1-G8/G6 -> 0.23707973 | H7: =1-H8/H6 -> 0.22155611 | I7: =1-I8/I6 -> 0.22512312 | J7: =1-J8/J6 -> 0.2486286 | ... O7: =1-O8/O6 -> 0.23746136 | Q7: 渠道填写
B8: GSV（国补后） | C8: =淘系!C8+抖音!C8+PDD!C8+得物!C8+京东自营业务口径!C8+京东POP财经口径!C8+'视频号+官网+小程序'!C8+快手!C8+唯品会!C8+淘系达播!C8+抖音达播!C8 -> 26612866 | D8: =淘系!D8+抖音!D8+PDD!D8+得物!D8+京东自营业务口径!D8+京东POP财经口径!D8+'视频号+官网+小程序'!D8+快手!D8+唯品会!D8+淘系达播!D8+抖音达播!D8 -> 26668868 | E8: =淘系!E8+抖音!E8+PDD!E8+得物!E8+京东自营业务口径!E8+京东POP财经口径!E8+'视频号+官网+小程序'!E8+快手!E8+唯品会!E8+淘系达播!E8+抖音达播!E8 -> 22743367 | F8: =淘系!F8+抖音!F8+PDD!F8+得物!F8+京东自营业务口径!F8+京东POP财经口径!F8+'视频号+官网+小程序'!F8+快手!F8+唯品会!F8+淘系达播!F8+抖音达播!F8 -> 19454083 | G8: =淘系!G8+抖音!G8+PDD!G8+得物!G8+京东自营业务口径!G8+京东POP财经口径!G8+'视频号+官网+小程序'!G8+快手!G8+唯品会!G8+淘系达播!G8+抖音达播!G8 -> 42336463 | H8: =淘系!H8+抖音!H8+PDD!H8+得物!H8+京东自营业务口径!H8+京东POP财经口径!H8+'视频号+官网+小程序'!H8+快手!H8+唯品会!H8+淘系达播!H8+抖音达播!H8 -> 37755914 | I8: =淘系!I8+抖音!I8+PDD!I8+得物!I8+京东自营业务口径!I8+京东POP财经口径!I8+'视频号+官网+小程序'!I8+快手!I8+唯品会!I8+淘系达播!I8+抖音达播!I8 -> 25554441 | J8: =淘系!J8+抖音!J8+PDD!J8+得物!J8+京东自营业务口径!J8+京东POP财经口径!J8+'视频号+官网+小程序'!J8+快手!J8+唯品会!J8+淘系达播!J8+抖音达播!J8 -> 36254156 | ... O8: =淘系!O8+抖音!O8+PDD!O8+得物!O8+京东自营业务口径!O8+京东POP财经口径!O8+'视频号+官网+小程序'!O8+快手!O8+唯品会!O8+淘系达播!O8+抖音达播!O8 -> 3.8694963e+08 | Q8: 渠道填写
B10: 零售价（去除退货后的） | C10: =淘系!C10+抖音!C10+PDD!C10+得物!C10+京东自营财经口径!C10+京东POP财经口径!C10+'视频号+官网+小程序'!C10+快手!C10+唯品会!C10+'线下门店-直营'!C10++'线下门店-经销'!C10+线下渠道!C10+淘系达播!C10+抖音达播!C10 -> 43169030 | D10: =淘系!D10+抖音!D10+PDD!D10+得物!D10+京东自营财经口径!D10+京东POP财经口径!D10+'视频号+官网+小程序'!D10+快手!D10+唯品会!D10+'线下门店-直营'!D10++'线下门店-经销'!D10+线下渠道!D10+淘系达播!D10+抖音达播!D10 -> 41319765 | E10: =淘系!E10+抖音!E10+PDD!E10+得物!E10+京东自营财经口径!E10+京东POP财经口径!E10+'视频号+官网+小程序'!E10+快手!E10+唯品会!E10+'线下门店-直营'!E10++'线下门店-经销'!E10+线下渠道!E10+淘系达播!E10+抖音达播!E10 -> 34649173 | F10: =淘系!F10+抖音!F10+PDD!F10+得物!F10+京东自营财经口径!F10+京东POP财经口径!F10+'视频号+官网+小程序'!F10+快手!F10+唯品会!F10+'线下门店-直营'!F10++'线下门店-经销'!F10+线下渠道!F10+淘系达播!F10+抖音达播!F10 -> 30349389 | G10: =淘系!G10+抖音!G10+PDD!G10+得物!G10+京东自营财经口径!G10+京东POP财经口径!G10+'视频号+官网+小程序'!G10+快手!G10+唯品会!G10+'线下门店-直营'!G10++'线下门店-经销'!G10+线下渠道!G10+淘系达播!G10+抖音达播!G10 -> 62773132 | H10: =淘系!H10+抖音!H10+PDD!H10+得物!H10+京东自营财经口径!H10+京东POP财经口径!H10+'视频号+官网+小程序'!H10+快手!H10+唯品会!H10+'线下门店-直营'!H10++'线下门店-经销'!H10+线下渠道!H10+淘系达播!H10+抖音达播!H10 -> 57311536 | I10: =淘系!I10+抖音!I10+PDD!I10+得物!I10+京东自营财经口径!I10+京东POP财经口径!I10+'视频号+官网+小程序'!I10+快手!I10+唯品会!I10+'线下门店-直营'!I10++'线下门店-经销'!I10+线下渠道!I10+淘系达播!I10+抖音达播!I10 -> 40240744 | J10: =淘系!J10+抖音!J10+PDD!J10+得物!J10+京东自营财经口径!J10+京东POP财经口径!J10+'视频号+官网+小程序'!J10+快手!J10+唯品会!J10+'线下门店-直营'!J10++'线下门店-经销'!J10+线下渠道!J10+淘系达播!J10+抖音达播!J10 -> 55453830 | ... N10: =淘系!N10+抖音!N10+PDD!N10+得物!N10+京东自营财经口径!N10+京东POP财经口径!N10+'视频号+官网+小程序'!N10+快手!N10+唯品会!N10+'线下门店-直营'!N10++'线下门店-经销'!N10+线下渠道!N10+淘系达播!N10+抖音达播!N10 -> 55451705 | O10: =SUM(C10:N10) -> 5.9951799e+08 | Q10: 渠道第二次填写
B11: 合同折扣及返利 (线下） | C11: =淘系!C11+抖音!C11+PDD!C11+得物!C11+京东自营财经口径!C11+京东POP财经口径!C11+'视频号+官网+小程序'!C11+快手!C11+唯品会!C11+'线下门店-直营'!C11+'线下门店-经销'!C11+线下渠道!C11+淘系达播!C11+抖音达播!C11 -> 1195159.2 | D11: =淘系!D11+抖音!D11+PDD!D11+得物!D11+京东自营财经口径!D11+京东POP财经口径!D11+'视频号+官网+小程序'!D11+快手!D11+唯品会!D11+'线下门店-直营'!D11+'线下门店-经销'!D11+线下渠道!D11+淘系达播!D11+抖音达播!D11 -> 1300782.2 | E11: =淘系!E11+抖音!E11+PDD!E11+得物!E11+京东自营财经口径!E11+京东POP财经口径!E11+'视频号+官网+小程序'!E11+快手!E11+唯品会!E11+'线下门店-直营'!E11+'线下门店-经销'!E11+线下渠道!E11+淘系达播!E11+抖音达播!E11 -> 1017203.9 | F11: =淘系!F11+抖音!F11+PDD!F11+得物!F11+京东自营财经口径!F11+京东POP财经口径!F11+'视频号+官网+小程序'!F11+快手!F11+唯品会!F11+'线下门店-直营'!F11+'线下门店-经销'!F11+线下渠道!F11+淘系达播!F11+抖音达播!F11 -> 947622.99 | G11: =淘系!G11+抖音!G11+PDD!G11+得物!G11+京东自营财经口径!G11+京东POP财经口径!G11+'视频号+官网+小程序'!G11+快手!G11+唯品会!G11+'线下门店-直营'!G11+'线下门店-经销'!G11+线下渠道!G11+淘系达播!G11+抖音达播!G11 -> 1706368.4 | H11: =淘系!H11+抖音!H11+PDD!H11+得物!H11+京东自营财经口径!H11+京东POP财经口径!H11+'视频号+官网+小程序'!H11+快手!H11+唯品会!H11+'线下门店-直营'!H11+'线下门店-经销'!H11+线下渠道!H11+淘系达播!H11+抖音达播!H11 -> 1674116.6 | I11: =淘系!I11+抖音!I11+PDD!I11+得物!I11+京东自营财经口径!I11+京东POP财经口径!I11+'视频号+官网+小程序'!I11+快手!I11+唯品会!I11+'线下门店-直营'!I11+'线下门店-经销'!I11+线下渠道!I11+淘系达播!I11+抖音达播!I11 -> 1317289.2 | J11: =淘系!J11+抖音!J11+PDD!J11+得物!J11+京东自营财经口径!J11+京东POP财经口径!J11+'视频号+官网+小程序'!J11+快手!J11+唯品会!J11+'线下门店-直营'!J11+'线下门店-经销'!J11+线下渠道!J11+淘系达播!J11+抖音达播!J11 -> 1660136.2 | ... N11: =淘系!N11+抖音!N11+PDD!N11+得物!N11+京东自营财经口径!N11+京东POP财经口径!N11+'视频号+官网+小程序'!N11+快手!N11+唯品会!N11+'线下门店-直营'!N11+'线下门店-经销'!N11+线下渠道!N11+淘系达播!N11+抖音达播!N11 -> 2086010.3 | O11: =SUM(C11:N11) -> 18348907 | P11: =O11/O8 -> 0.047419368 | Q11: 线下渠道填写 | R11: =O11/$O$10 -> 0.030606099
B12: 国补自补 （线上） | C12: =淘系!C12+抖音!C12+PDD!C12+得物!C12+京东自营财经口径!C12+京东POP财经口径!C12+'视频号+官网+小程序'!C12+快手!C12+唯品会!C12+'线下门店-直营'!C12+'线下门店-经销'!C12+线下渠道!C12+淘系达播!C12+抖音达播!C12 -> 3374204.7 | D12: =淘系!D12+抖音!D12+PDD!D12+得物!D12+京东自营财经口径!D12+京东POP财经口径!D12+'视频号+官网+小程序'!D12+快手!D12+唯品会!D12+'线下门店-直营'!D12+'线下门店-经销'!D12+线下渠道!D12+淘系达播!D12+抖音达播!D12 -> 3225504 | E12: =淘系!E12+抖音!E12+PDD!E12+得物!E12+京东自营财经口径!E12+京东POP财经口径!E12+'视频号+官网+小程序'!E12+快手!E12+唯品会!E12+'线下门店-直营'!E12+'线下门店-经销'!E12+线下渠道!E12+淘系达播!E12+抖音达播!E12 -> 2793045.8 | F12: =淘系!F12+抖音!F12+PDD!F12+得物!F12+京东自营财经口径!F12+京东POP财经口径!F12+'视频号+官网+小程序'!F12+快手!F12+唯品会!F12+'线下门店-直营'!F12+'线下门店-经销'!F12+线下渠道!F12+淘系达播!F12+抖音达播!F12 -> 2421445.1 | G12: =淘系!G12+抖音!G12+PDD!G12+得物!G12+京东自营财经口径!G12+京东POP财经口径!G12+'视频号+官网+小程序'!G12+快手!G12+唯品会!G12+'线下门店-直营'!G12+'线下门店-经销'!G12+线下渠道!G12+淘系达播!G12+抖音达播!G12 -> 5483400.1 | H12: =淘系!H12+抖音!H12+PDD!H12+得物!H12+京东自营财经口径!H12+京东POP财经口径!H12+'视频号+官网+小程序'!H12+快手!H12+唯品会!H12+'线下门店-直营'!H12+'线下门店-经销'!H12+线下渠道!H12+淘系达播!H12+抖音达播!H12 -> 4885124.8 | I12: =淘系!I12+抖音!I12+PDD!I12+得物!I12+京东自营财经口径!I12+京东POP财经口径!I12+'视频号+官网+小程序'!I12+快手!I12+唯品会!I12+'线下门店-直营'!I12+'线下门店-经销'!I12+线下渠道!I12+淘系达播!I12+抖音达播!I12 -> 3103718.8 | J12: =淘系!J12+抖音!J12+PDD!J12+得物!J12+京东自营财经口径!J12+京东POP财经口径!J12+'视频号+官网+小程序'!J12+快手!J12+唯品会!J12+'线下门店-直营'!J12+'线下门店-经销'!J12+线下渠道!J12+淘系达播!J12+抖音达播!J12 -> 4576920.8 | ... N12: =淘系!N12+抖音!N12+PDD!N12+得物!N12+京东自营财经口径!N12+京东POP财经口径!N12+'视频号+官网+小程序'!N12+快手!N12+唯品会!N12+'线下门店-直营'!N12+'线下门店-经销'!N12+线下渠道!N12+淘系达播!N12+抖音达播!N12 -> 4234950.4 | O12: =SUM(C12:N12) -> 48800085 | P12: =O12/O8 -> 0.12611482 | Q12: 渠道填写 | R12: =O12/$O$10 -> 0.081398866
B13: 红包消费券等促销折扣 | C13: =淘系!C13+抖音!C13+PDD!C13+得物!C13+京东自营财经口径!C13+京东POP财经口径!C13+'视频号+官网+小程序'!C13+快手!C13+唯品会!C13+'线下门店-直营'!C13+'线下门店-经销'!C13+线下渠道!C13+淘系达播!C13+抖音达播!C13 -> 7394578.7 | D13: =淘系!D13+抖音!D13+PDD!D13+得物!D13+京东自营财经口径!D13+京东POP财经口径!D13+'视频号+官网+小程序'!D13+快手!D13+唯品会!D13+'线下门店-直营'!D13+'线下门店-经销'!D13+线下渠道!D13+淘系达播!D13+抖音达播!D13 -> 5584980.1 | E13: =淘系!E13+抖音!E13+PDD!E13+得物!E13+京东自营财经口径!E13+京东POP财经口径!E13+'视频号+官网+小程序'!E13+快手!E13+唯品会!E13+'线下门店-直营'!E13+'线下门店-经销'!E13+线下渠道!E13+淘系达播!E13+抖音达播!E13 -> 4178396.9 | F13: =淘系!F13+抖音!F13+PDD!F13+得物!F13+京东自营财经口径!F13+京东POP财经口径!F13+'视频号+官网+小程序'!F13+快手!F13+唯品会!F13+'线下门店-直营'!F13+'线下门店-经销'!F13+线下渠道!F13+淘系达播!F13+抖音达播!F13 -> 3877961.3 | G13: =淘系!G13+抖音!G13+PDD!G13+得物!G13+京东自营财经口径!G13+京东POP财经口径!G13+'视频号+官网+小程序'!G13+快手!G13+唯品会!G13+'线下门店-直营'!G13+'线下门店-经销'!G13+线下渠道!G13+淘系达播!G13+抖音达播!G13 -> 7290043.5 | H13: =淘系!H13+抖音!H13+PDD!H13+得物!H13+京东自营财经口径!H13+京东POP财经口径!H13+'视频号+官网+小程序'!H13+快手!H13+唯品会!H13+'线下门店-直营'!H13+'线下门店-经销'!H13+线下渠道!H13+淘系达播!H13+抖音达播!H13 -> 6829676.2 | I13: =淘系!I13+抖音!I13+PDD!I13+得物!I13+京东自营财经口径!I13+京东POP财经口径!I13+'视频号+官网+小程序'!I13+快手!I13+唯品会!I13+'线下门店-直营'!I13+'线下门店-经销'!I13+线下渠道!I13+淘系达播!I13+抖音达播!I13 -> 5145768 | J13: =淘系!J13+抖音!J13+PDD!J13+得物!J13+京东自营财经口径!J13+京东POP财经口径!J13+'视频号+官网+小程序'!J13+快手!J13+唯品会!J13+'线下门店-直营'!J13+'线下门店-经销'!J13+线下渠道!J13+淘系达播!J13+抖音达播!J13 -> 6751727.9 | ... N13: =淘系!N13+抖音!N13+PDD!N13+得物!N13+京东自营财经口径!N13+京东POP财经口径!N13+'视频号+官网+小程序'!N13+快手!N13+唯品会!N13+'线下门店-直营'!N13+'线下门店-经销'!N13+线下渠道!N13+淘系达播!N13+抖音达播!N13 -> 7015669.9 | O13: =SUM(C13:N13) -> 75821557 | P13: =O13/O8 -> 0.19594684 | Q13: 渠道填写 | R13: =O13/$O$10 -> 0.12647086
B14: TTL 折扣合计 | C14: =SUM(C11:C13) -> 11963943 | D14: =SUM(D11:D13) -> 10111266 | E14: =SUM(E11:E13) -> 7988646.6 | F14: =SUM(F11:F13) -> 7247029.4 | G14: =SUM(G11:G13) -> 14479812 | H14: =SUM(H11:H13) -> 13388918 | I14: =SUM(I11:I13) -> 9566775.9 | J14: =SUM(J11:J13) -> 12988785 | ... N14: =SUM(N11:N13) -> 13336631 | O14: =SUM(C14:N14) -> 1.4297055e+08 | P14: =O14/O8 -> 0.36948103 | R14: =O14/$O$10 -> 0.23847583
B15: GSV | C15: =C8 -> 26612866 | D15: =D8 -> 26668868 | E15: =E8 -> 22743367 | F15: =F8 -> 19454083 | G15: =G8 -> 42336463 | H15: =H8 -> 37755914 | I15: =I8 -> 25554441 | J15: =J8 -> 36254156 | ... N15: =N8 -> 34010769 | O15: =SUM(C15:N15) -> 3.8694963e+08
B16: 营业收入 | C16: =+C8/1.13 -> 23551209 | D16: =+D8/1.13 -> 23600768 | E16: =+E8/1.13 -> 20126874 | F16: =+F8/1.13 -> 17216003 | G16: =+G8/1.13 -> 37465896 | H16: =+H8/1.13 -> 33412313 | I16: =+I8/1.13 -> 22614549 | J16: =+J8/1.13 -> 32083324 | ... N16: =+N8/1.13 -> 30098026 | O16: =SUM(C16:N16) -> 3.424333e+08 | T16: =O16-淘系!O16-淘系达播!O16-抖音!O16-抖音达播!O16-快手!O16-京东POP财经口径!O16-京东自营财经口径!O16-PDD!O16-得物!O16-'视频号+官网+小程序'!O16-唯品会!O16-'线下门店-直营'!O16-'线下门店-经销'!O16-线下渠道!O16 -> -61590983
C17: =C14/C15 -> 0.44955484 | T17: =O17-淘系!O17-淘系达播!O17-抖音!O17-抖音达播!O17-快手!O17-京东POP财经口径!O17-京东自营财经口径!O17-PDD!O17-得物!O17-'视频号+官网+小程序'!O17-唯品会!O17-'线下门店-直营'!O17-'线下门店-经销'!O17-线下渠道!O17 -> 0
B18: 标准主品配件成本 | C18: =淘系!C18+抖音!C18+PDD!C18+得物!C18+京东自营财经口径!C18+京东POP财经口径!C18+'视频号+官网+小程序'!C18+快手!C18+唯品会!C18+'线下门店-直营'!C18+'线下门店-经销'!C18+线下渠道!C18+淘系达播!C18+抖音达播!C18 -> 13519375 | D18: =淘系!D18+抖音!D18+PDD!D18+得物!D18+京东自营财经口径!D18+京东POP财经口径!D18+'视频号+官网+小程序'!D18+快手!D18+唯品会!D18+'线下门店-直营'!D18+'线下门店-经销'!D18+线下渠道!D18+淘系达播!D18+抖音达播!D18 -> 13428662 | E18: =淘系!E18+抖音!E18+PDD!E18+得物!E18+京东自营财经口径!E18+京东POP财经口径!E18+'视频号+官网+小程序'!E18+快手!E18+唯品会!E18+'线下门店-直营'!E18+'线下门店-经销'!E18+线下渠道!E18+淘系达播!E18+抖音达播!E18 -> 11966213 | F18: =淘系!F18+抖音!F18+PDD!F18+得物!F18+京东自营财经口径!F18+京东POP财经口径!F18+'视频号+官网+小程序'!F18+快手!F18+唯品会!F18+'线下门店-直营'!F18+'线下门店-经销'!F18+线下渠道!F18+淘系达播!F18+抖音达播!F18 -> 10347617 | G18: =淘系!G18+抖音!G18+PDD!G18+得物!G18+京东自营财经口径!G18+京东POP财经口径!G18+'视频号+官网+小程序'!G18+快手!G18+唯品会!G18+'线下门店-直营'!G18+'线下门店-经销'!G18+线下渠道!G18+淘系达播!G18+抖音达播!G18 -> 19576713 | H18: =淘系!H18+抖音!H18+PDD!H18+得物!H18+京东自营财经口径!H18+京东POP财经口径!H18+'视频号+官网+小程序'!H18+快手!H18+唯品会!H18+'线下门店-直营'!H18+'线下门店-经销'!H18+线下渠道!H18+淘系达播!H18+抖音达播!H18 -> 17979627 | I18: =淘系!I18+抖音!I18+PDD!I18+得物!I18+京东自营财经口径!I18+京东POP财经口径!I18+'视频号+官网+小程序'!I18+快手!I18+唯品会!I18+'线下门店-直营'!I18+'线下门店-经销'!I18+线下渠道!I18+淘系达播!I18+抖音达播!I18 -> 11695231 | J18: =淘系!J18+抖音!J18+PDD!J18+得物!J18+京东自营财经口径!J18+京东POP财经口径!J18+'视频号+官网+小程序'!J18+快手!J18+唯品会!J18+'线下门店-直营'!J18+'线下门店-经销'!J18+线下渠道!J18+淘系达播!J18+抖音达播!J18 -> 16035701 | ... N18: =淘系!N18+抖音!N18+PDD!N18+得物!N18+京东自营财经口径!N18+京东POP财经口径!N18+'视频号+官网+小程序'!N18+快手!N18+唯品会!N18+'线下门店-直营'!N18+'线下门店-经销'!N18+线下渠道!N18+淘系达播!N18+抖音达播!N18 -> 14738372 | O18: =SUM(C18:N18) -> 1.7888455e+08 | P18: =O18/O16 -> 0.52239239 | R18: Y25 Bi 成本54% | T18: =O18-淘系!O18-淘系达播!O18-抖音!O18-抖音达播!O18-快手!O18-京东POP财经口径!O18-京东自营财经口径!O18-PDD!O18-得物!O18-'视频号+官网+小程序'!O18-唯品会!O18-'线下门店-直营'!O18-'线下门店-经销'!O18-线下渠道!O18 -> 0
B19: 产品毛利 | C19: =C16-C18 -> 10031834 | D19: =D16-D18 -> 10172106 | E19: =E16-E18 -> 8160660.7 | F19: =F16-F18 -> 6868385.9 | G19: =G16-G18 -> 17889183 | H19: =H16-H18 -> 15432686 | I19: =I16-I18 -> 10919319 | J19: =J16-J18 -> 16047622 | ... N19: =N16-N18 -> 15359654 | O19: =SUM(C19:N19) -> 1.6354875e+08 | P19: =O19/$O$16 -> 0.47760761 | R19: =O16*0.12 -> 41091997 | T19: =O19-淘系!O19-淘系达播!O19-抖音!O19-抖音达播!O19-快手!O19-京东POP财经口径!O19-京东自营财经口径!O19-PDD!O19-得物!O19-'视频号+官网+小程序'!O19-唯品会!O19-'线下门店-直营'!O19-'线下门店-经销'!O19-线下渠道!O19 -> -61590983
B20: 头程/尾程物流/仓储费用 | C20: =C16*2.5% -> 588780.21 | D20: =D16*2.5% -> 590019.2 | E20: =E16*2.5% -> 503171.84 | F20: =F16*2.5% -> 430400.07 | G20: =G16*2.5% -> 936647.41 | H20: =H16*2.5% -> 835307.83 | I20: =I16*2.5% -> 565363.74 | J20: =J16*2.5% -> 802083.09 | ... N20: =N16*2.5% -> 752450.64 | O20: =SUM(C20:N20) -> 8560832.6 | P20: 0.025 | T20: =O20-淘系!O20-淘系达播!O20-抖音!O20-抖音达播!O20-快手!O20-京东POP财经口径!O20-京东自营财经口径!O20-PDD!O20-得物!O20-'视频号+官网+小程序'!O20-唯品会!O20-'线下门店-直营'!O20-'线下门店-经销'!O20-线下渠道!O20 -> -1499619.9
B21: 成本合计（产品+物流） | C21: =SUM(C18,C20) -> 14108155 | D21: =SUM(D18,D20) -> 14018681 | E21: =SUM(E18,E20) -> 12469385 | F21: =SUM(F18,F20) -> 10778017 | G21: =SUM(G18,G20) -> 20513361 | H21: =SUM(H18,H20) -> 18814934 | I21: =SUM(I18,I20) -> 12260594 | J21: =SUM(J18,J20) -> 16837785 | ... N21: =SUM(N18,N20) -> 15490822 | O21: =SUM(C21:N21) -> 1.8744539e+08 | P21: =O21/$O$16 -> 0.54739239 | T21: =O21-淘系!O21-淘系达播!O21-抖音!O21-抖音达播!O21-快手!O21-京东POP财经口径!O21-京东自营财经口径!O21-PDD!O21-得物!O21-'视频号+官网+小程序'!O21-唯品会!O21-'线下门店-直营'!O21-'线下门店-经销'!O21-线下渠道!O21 -> -1499619.9
B22: 净毛利 | C22: =C16-C21 -> 9443053.3 | D22: =D16-D21 -> 9582087.1 | E22: =E16-E21 -> 7657488.9 | F22: =F16-F21 -> 6437985.8 | G22: =G16-G21 -> 16952536 | H22: =H16-H21 -> 14597379 | I22: =I16-I21 -> 10353955 | J22: =J16-J21 -> 15245539 | ... N22: =N16-N21 -> 14607203 | O22: =SUM(C22:N22) -> 1.5498792e+08 | P22: =O22/$O$16 -> 0.45260761 | T22: =O22-淘系!O22-淘系达播!O22-抖音!O22-抖音达播!O22-快手!O22-京东POP财经口径!O22-京东自营财经口径!O22-PDD!O22-得物!O22-'视频号+官网+小程序'!O22-唯品会!O22-'线下门店-直营'!O22-'线下门店-经销'!O22-线下渠道!O22 -> -60091363
B23: 实际产品毛利率 | C23: =C19/C16 -> 0.42595833 | D23: =D19/D16 -> 0.43100743 | E23: =E19/E16 -> 0.40546092 | F23: =F19/F16 -> 0.39895358 | G23: =G19/G16 -> 0.47747912 | H23: =H19/H16 -> 0.4618862 | I23: =I19/I16 -> 0.48284485 | J23: =J19/J16 -> 0.50018578 | ... O23: =O19/O16 -> 0.47760761 | R23: top down 毛利53% | T23: =O23-淘系!O23-淘系达播!O23-抖音!O23-抖音达播!O23-快手!O23-京东POP财经口径!O23-京东自营财经口径!O23-PDD!O23-得物!O23-'视频号+官网+小程序'!O23-唯品会!O23-'线下门店-直营'!O23-'线下门店-经销'!O23-线下渠道!O23 -> -7.3606976
B24: 合计毛利率 | C24: =IFERROR(1-C21/C16,0) -> 0.40095833 | D24: =IFERROR(1-D21/D16,0) -> 0.40600743 | E24: =IFERROR(1-E21/E16,0) -> 0.38046092 | F24: =IFERROR(1-F21/F16,0) -> 0.37395358 | G24: =IFERROR(1-G21/G16,0) -> 0.45247912 | H24: =IFERROR(1-H21/H16,0) -> 0.4368862 | I24: =IFERROR(1-I21/I16,0) -> 0.45784485 | J24: =IFERROR(1-J21/J16,0) -> 0.47518578 | ... O24: =IFERROR(1-O21/O16,0) -> 0.45260761 | T24: =O24-淘系!O24-淘系达播!O24-抖音!O24-抖音达播!O24-快手!O24-京东POP财经口径!O24-京东自营财经口径!O24-PDD!O24-得物!O24-'视频号+官网+小程序'!O24-唯品会!O24-'线下门店-直营'!O24-'线下门店-经销'!O24-线下渠道!O24 -> -7.0686976
T25: =O25-淘系!O25-淘系达播!O25-抖音!O25-抖音达播!O25-快手!O25-京东POP财经口径!O25-京东自营财经口径!O25-PDD!O25-得物!O25-'视频号+官网+小程序'!O25-唯品会!O25-'线下门店-直营'!O25-'线下门店-经销'!O25-线下渠道!O25 -> 0
B26: 品牌及内容费用 | C26: =SUM(C27:C31) -> 751638.84 | D26: =SUM(D27:D31) -> 2209499.7 | E26: =SUM(E27:E31) -> 3628334.4 | F26: =SUM(F27:F31) -> 2088171 | G26: =SUM(G27:G31) -> 8100807.4 | H26: =SUM(H27:H31) -> 4791643.2 | I26: =SUM(I27:I31) -> 1089143.2 | J26: =SUM(J27:J31) -> 1639717.7 | ... N26: =SUM(N27:N31) -> 1241819.8 | O26: =SUM(C26:N26) -> 32991134 | P26: =O26/$O$16 -> 0.096343239 | T26: =O26-淘系!O26-淘系达播!O26-抖音!O26-抖音达播!O26-快手!O26-京东POP财经口径!O26-京东自营财经口径!O26-PDD!O26-得物!O26-'视频号+官网+小程序'!O26-唯品会!O26-'线下门店-直营'!O26-'线下门店-经销'!O26-线下渠道!O26 -> 0
B27: 展会 | C27: =淘系!C27+抖音!C27+PDD!C27+得物!C27+京东自营财经口径!C27+京东POP财经口径!C27+'视频号+官网+小程序'!C27+快手!C27+唯品会!C27+'线下门店-直营'!C27+'线下门店-经销'!C27+线下渠道!C27+淘系达播!C27+抖音达播!C27 -> 0 | D27: =淘系!D27+抖音!D27+PDD!D27+得物!D27+京东自营财经口径!D27+京东POP财经口径!D27+'视频号+官网+小程序'!D27+快手!D27+唯品会!D27+'线下门店-直营'!D27+'线下门店-经销'!D27+线下渠道!D27+淘系达播!D27+抖音达播!D27 -> 0 | E27: =淘系!E27+抖音!E27+PDD!E27+得物!E27+京东自营财经口径!E27+京东POP财经口径!E27+'视频号+官网+小程序'!E27+快手!E27+唯品会!E27+'线下门店-直营'!E27+'线下门店-经销'!E27+线下渠道!E27+淘系达播!E27+抖音达播!E27 -> 64814.267 | F27: =淘系!F27+抖音!F27+PDD!F27+得物!F27+京东自营财经口径!F27+京东POP财经口径!F27+'视频号+官网+小程序'!F27+快手!F27+唯品会!F27+'线下门店-直营'!F27+'线下门店-经销'!F27+线下渠道!F27+淘系达播!F27+抖音达播!F27 -> 54155.074 | G27: =淘系!G27+抖音!G27+PDD!G27+得物!G27+京东自营财经口径!G27+京东POP财经口径!G27+'视频号+官网+小程序'!G27+快手!G27+唯品会!G27+'线下门店-直营'!G27+'线下门店-经销'!G27+线下渠道!G27+淘系达播!G27+抖音达播!G27 -> 115388.16 | H27: =淘系!H27+抖音!H27+PDD!H27+得物!H27+京东自营财经口径!H27+京东POP财经口径!H27+'视频号+官网+小程序'!H27+快手!H27+唯品会!H27+'线下门店-直营'!H27+'线下门店-经销'!H27+线下渠道!H27+淘系达播!H27+抖音达播!H27 -> 101584.8 | I27: =淘系!I27+抖音!I27+PDD!I27+得物!I27+京东自营财经口径!I27+京东POP财经口径!I27+'视频号+官网+小程序'!I27+快手!I27+唯品会!I27+'线下门店-直营'!I27+'线下门店-经销'!I27+线下渠道!I27+淘系达播!I27+抖音达播!I27 -> 65500.288 | J27: =淘系!J27+抖音!J27+PDD!J27+得物!J27+京东自营财经口径!J27+京东POP财经口径!J27+'视频号+官网+小程序'!J27+快手!J27+唯品会!J27+'线下门店-直营'!J27+'线下门店-经销'!J27+线下渠道!J27+淘系达播!J27+抖音达播!J27 -> 90329.934 | ... N27: =淘系!N27+抖音!N27+PDD!N27+得物!N27+京东自营财经口径!N27+京东POP财经口径!N27+'视频号+官网+小程序'!N27+快手!N27+唯品会!N27+'线下门店-直营'!N27+'线下门店-经销'!N27+线下渠道!N27+淘系达播!N27+抖音达播!N27 -> 0 | O27: =SUM(C27:N27) -> 777231.54 | P27: =O27/$O$16 -> 0.0022697312 | T27: =O27-淘系!O27-淘系达播!O27-抖音!O27-抖音达播!O27-快手!O27-京东POP财经口径!O27-京东自营财经口径!O27-PDD!O27-得物!O27-'视频号+官网+小程序'!O27-唯品会!O27-'线下门店-直营'!O27-'线下门店-经销'!O27-线下渠道!O27 -> -1.6007107e-10
B28: 品牌营销 | C28: =淘系!C28+抖音!C28+PDD!C28+得物!C28+京东自营财经口径!C28+京东POP财经口径!C28+'视频号+官网+小程序'!C28+快手!C28+唯品会!C28+'线下门店-直营'!C28+'线下门店-经销'!C28+线下渠道!C28+淘系达播!C28+抖音达播!C28 -> 209195 | D28: =淘系!D28+抖音!D28+PDD!D28+得物!D28+京东自营财经口径!D28+京东POP财经口径!D28+'视频号+官网+小程序'!D28+快手!D28+唯品会!D28+'线下门店-直营'!D28+'线下门店-经销'!D28+线下渠道!D28+淘系达播!D28+抖音达播!D28 -> 209195 | E28: =淘系!E28+抖音!E28+PDD!E28+得物!E28+京东自营财经口径!E28+京东POP财经口径!E28+'视频号+官网+小程序'!E28+快手!E28+唯品会!E28+'线下门店-直营'!E28+'线下门店-经销'!E28+线下渠道!E28+淘系达播!E28+抖音达播!E28 -> 209195 | F28: =淘系!F28+抖音!F28+PDD!F28+得物!F28+京东自营财经口径!F28+京东POP财经口径!F28+'视频号+官网+小程序'!F28+快手!F28+唯品会!F28+'线下门店-直营'!F28+'线下门店-经销'!F28+线下渠道!F28+淘系达播!F28+抖音达播!F28 -> 274181.09 | G28: =淘系!G28+抖音!G28+PDD!G28+得物!G28+京东自营财经口径!G28+京东POP财经口径!G28+'视频号+官网+小程序'!G28+快手!G28+唯品会!G28+'线下门店-直营'!G28+'线下门店-经销'!G28+线下渠道!G28+淘系达播!G28+抖音达播!G28 -> 901523.98 | H28: =淘系!H28+抖音!H28+PDD!H28+得物!H28+京东自营财经口径!H28+京东POP财经口径!H28+'视频号+官网+小程序'!H28+快手!H28+唯品会!H28+'线下门店-直营'!H28+'线下门店-经销'!H28+线下渠道!H28+淘系达播!H28+抖音达播!H28 -> 534266.37 | I28: =淘系!I28+抖音!I28+PDD!I28+得物!I28+京东自营财经口径!I28+京东POP财经口径!I28+'视频号+官网+小程序'!I28+快手!I28+唯品会!I28+'线下门店-直营'!I28+'线下门店-经销'!I28+线下渠道!I28+淘系达播!I28+抖音达播!I28 -> 209195 | J28: =淘系!J28+抖音!J28+PDD!J28+得物!J28+京东自营财经口径!J28+京东POP财经口径!J28+'视频号+官网+小程序'!J28+快手!J28+唯品会!J28+'线下门店-直营'!J28+'线下门店-经销'!J28+线下渠道!J28+淘系达播!J28+抖音达播!J28 -> 317590.92 | ... N28: =淘系!N28+抖音!N28+PDD!N28+得物!N28+京东自营财经口径!N28+京东POP财经口径!N28+'视频号+官网+小程序'!N28+快手!N28+唯品会!N28+'线下门店-直营'!N28+'线下门店-经销'!N28+线下渠道!N28+淘系达播!N28+抖音达播!N28 -> 209195 | O28: =SUM(C28:N28) -> 4187779.5 | P28: =O28/$O$16 -> 0.012229475 | T28: =O28-淘系!O28-淘系达播!O28-抖音!O28-抖音达播!O28-快手!O28-京东POP财经口径!O28-京东自营财经口径!O28-PDD!O28-得物!O28-'视频号+官网+小程序'!O28-唯品会!O28-'线下门店-直营'!O28-'线下门店-经销'!O28-线下渠道!O28 -> 5.5297278e-10
B29: 内容素材制作 | C29: =淘系!C29+抖音!C29+PDD!C29+得物!C29+京东自营财经口径!C29+京东POP财经口径!C29+'视频号+官网+小程序'!C29+快手!C29+唯品会!C29+'线下门店-直营'!C29+'线下门店-经销'!C29+线下渠道!C29+淘系达播!C29+抖音达播!C29 -> 31801.759 | D29: =淘系!D29+抖音!D29+PDD!D29+得物!D29+京东自营财经口径!D29+京东POP财经口径!D29+'视频号+官网+小程序'!D29+快手!D29+唯品会!D29+'线下门店-直营'!D29+'线下门店-经销'!D29+线下渠道!D29+淘系达播!D29+抖音达播!D29 -> 25890.069 | E29: =淘系!E29+抖音!E29+PDD!E29+得物!E29+京东自营财经口径!E29+京东POP财经口径!E29+'视频号+官网+小程序'!E29+快手!E29+唯品会!E29+'线下门店-直营'!E29+'线下门店-经销'!E29+线下渠道!E29+淘系达播!E29+抖音达播!E29 -> 25925.707 | F29: =淘系!F29+抖音!F29+PDD!F29+得物!F29+京东自营财经口径!F29+京东POP财经口径!F29+'视频号+官网+小程序'!F29+快手!F29+唯品会!F29+'线下门店-直营'!F29+'线下门店-经销'!F29+线下渠道!F29+淘系达播!F29+抖音达播!F29 -> 108310.15 | G29: =淘系!G29+抖音!G29+PDD!G29+得物!G29+京东自营财经口径!G29+京东POP财经口径!G29+'视频号+官网+小程序'!G29+快手!G29+唯品会!G29+'线下门店-直营'!G29+'线下门店-经销'!G29+线下渠道!G29+淘系达播!G29+抖音达播!G29 -> 692328.98 | H29: =淘系!H29+抖音!H29+PDD!H29+得物!H29+京东自营财经口径!H29+京东POP财经口径!H29+'视频号+官网+小程序'!H29+快手!H29+唯品会!H29+'线下门店-直营'!H29+'线下门店-经销'!H29+线下渠道!H29+淘系达播!H29+抖音达播!H29 -> 446973.13 | I29: =淘系!I29+抖音!I29+PDD!I29+得物!I29+京东自营财经口径!I29+京东POP财经口径!I29+'视频号+官网+小程序'!I29+快手!I29+唯品会!I29+'线下门店-直营'!I29+'线下门店-经销'!I29+线下渠道!I29+淘系达播!I29+抖音达播!I29 -> 0 | J29: =淘系!J29+抖音!J29+PDD!J29+得物!J29+京东自营财经口径!J29+京东POP财经口径!J29+'视频号+官网+小程序'!J29+快手!J29+唯品会!J29+'线下门店-直营'!J29+'线下门店-经销'!J29+线下渠道!J29+淘系达播!J29+抖音达播!J29 -> 108395.92 | ... N29: =淘系!N29+抖音!N29+PDD!N29+得物!N29+京东自营财经口径!N29+京东POP财经口径!N29+'视频号+官网+小程序'!N29+快手!N29+唯品会!N29+'线下门店-直营'!N29+'线下门店-经销'!N29+线下渠道!N29+淘系达播!N29+抖音达播!N29 -> 32181.962 | O29: =SUM(C29:N29) -> 2129189.5 | P29: =O29/$O$16 -> 0.0062178225 | T29: =O29-淘系!O29-淘系达播!O29-抖音!O29-抖音达播!O29-快手!O29-京东POP财经口径!O29-京东自营财经口径!O29-PDD!O29-得物!O29-'视频号+官网+小程序'!O29-唯品会!O29-'线下门店-直营'!O29-'线下门店-经销'!O29-线下渠道!O29 -> 0
B30: 公关费用 | C30: =淘系!C30+抖音!C30+PDD!C30+得物!C30+京东自营财经口径!C30+京东POP财经口径!C30+'视频号+官网+小程序'!C30+快手!C30+唯品会!C30+'线下门店-直营'!C30+'线下门店-经销'!C30+线下渠道!C30+淘系达播!C30+抖音达播!C30 -> 31801.759 | D30: =淘系!D30+抖音!D30+PDD!D30+得物!D30+京东自营财经口径!D30+京东POP财经口径!D30+'视频号+官网+小程序'!D30+快手!D30+唯品会!D30+'线下门店-直营'!D30+'线下门店-经销'!D30+线下渠道!D30+淘系达播!D30+抖音达播!D30 -> 25890.069 | E30: =淘系!E30+抖音!E30+PDD!E30+得物!E30+京东自营财经口径!E30+京东POP财经口径!E30+'视频号+官网+小程序'!E30+快手!E30+唯品会!E30+'线下门店-直营'!E30+'线下门店-经销'!E30+线下渠道!E30+淘系达播!E30+抖音达播!E30 -> 207405.66 | F30: =淘系!F30+抖音!F30+PDD!F30+得物!F30+京东自营财经口径!F30+京东POP财经口径!F30+'视频号+官网+小程序'!F30+快手!F30+唯品会!F30+'线下门店-直营'!F30+'线下门店-经销'!F30+线下渠道!F30+淘系达播!F30+抖音达播!F30 -> 21662.029 | G30: =淘系!G30+抖音!G30+PDD!G30+得物!G30+京东自营财经口径!G30+京东POP财经口径!G30+'视频号+官网+小程序'!G30+快手!G30+唯品会!G30+'线下门店-直营'!G30+'线下门店-经销'!G30+线下渠道!G30+淘系达播!G30+抖音达播!G30 -> 138465.8 | H30: =淘系!H30+抖音!H30+PDD!H30+得物!H30+京东自营财经口径!H30+京东POP财经口径!H30+'视频号+官网+小程序'!H30+快手!H30+唯品会!H30+'线下门店-直营'!H30+'线下门店-经销'!H30+线下渠道!H30+淘系达播!H30+抖音达播!H30 -> 40633.921 | I30: =淘系!I30+抖音!I30+PDD!I30+得物!I30+京东自营财经口径!I30+京东POP财经口径!I30+'视频号+官网+小程序'!I30+快手!I30+唯品会!I30+'线下门店-直营'!I30+'线下门店-经销'!I30+线下渠道!I30+淘系达播!I30+抖音达播!I30 -> 26200.115 | J30: =淘系!J30+抖音!J30+PDD!J30+得物!J30+京东自营财经口径!J30+京东POP财经口径!J30+'视频号+官网+小程序'!J30+快手!J30+唯品会!J30+'线下门店-直营'!J30+'线下门店-经销'!J30+线下渠道!J30+淘系达播!J30+抖音达播!J30 -> 36131.973 | ... N30: =淘系!N30+抖音!N30+PDD!N30+得物!N30+京东自营财经口径!N30+京东POP财经口径!N30+'视频号+官网+小程序'!N30+快手!N30+唯品会!N30+'线下门店-直营'!N30+'线下门店-经销'!N30+线下渠道!N30+淘系达播!N30+抖音达播!N30 -> 32181.962 | O30: =SUM(C30:N30) -> 759919.23 | P30: =O30/$O$16 -> 0.0022191744 | T30: =O30-淘系!O30-淘系达播!O30-抖音!O30-抖音达播!O30-快手!O30-京东POP财经口径!O30-京东自营财经口径!O30-PDD!O30-得物!O30-'视频号+官网+小程序'!O30-唯品会!O30-'线下门店-直营'!O30-'线下门店-经销'!O30-线下渠道!O30 -> 0
B31: 达人种草、样机及加热 | C31: =淘系!C31+抖音!C31+PDD!C31+得物!C31+京东自营财经口径!C31+京东POP财经口径!C31+'视频号+官网+小程序'!C31+快手!C31+唯品会!C31+'线下门店-直营'!C31+'线下门店-经销'!C31+线下渠道!C31+淘系达播!C31+抖音达播!C31 -> 478840.32 | D31: =淘系!D31+抖音!D31+PDD!D31+得物!D31+京东自营财经口径!D31+京东POP财经口径!D31+'视频号+官网+小程序'!D31+快手!D31+唯品会!D31+'线下门店-直营'!D31+'线下门店-经销'!D31+线下渠道!D31+淘系达播!D31+抖音达播!D31 -> 1948524.6 | E31: =淘系!E31+抖音!E31+PDD!E31+得物!E31+京东自营财经口径!E31+京东POP财经口径!E31+'视频号+官网+小程序'!E31+快手!E31+唯品会!E31+'线下门店-直营'!E31+'线下门店-经销'!E31+线下渠道!E31+淘系达播!E31+抖音达播!E31 -> 3120993.8 | F31: =淘系!F31+抖音!F31+PDD!F31+得物!F31+京东自营财经口径!F31+京东POP财经口径!F31+'视频号+官网+小程序'!F31+快手!F31+唯品会!F31+'线下门店-直营'!F31+'线下门店-经销'!F31+线下渠道!F31+淘系达播!F31+抖音达播!F31 -> 1629862.7 | G31: =淘系!G31+抖音!G31+PDD!G31+得物!G31+京东自营财经口径!G31+京东POP财经口径!G31+'视频号+官网+小程序'!G31+快手!G31+唯品会!G31+'线下门店-直营'!G31+'线下门店-经销'!G31+线下渠道!G31+淘系达播!G31+抖音达播!G31 -> 6253100.5 | H31: =淘系!H31+抖音!H31+PDD!H31+得物!H31+京东自营财经口径!H31+京东POP财经口径!H31+'视频号+官网+小程序'!H31+快手!H31+唯品会!H31+'线下门店-直营'!H31+'线下门店-经销'!H31+线下渠道!H31+淘系达播!H31+抖音达播!H31 -> 3668185 | I31: =淘系!I31+抖音!I31+PDD!I31+得物!I31+京东自营财经口径!I31+京东POP财经口径!I31+'视频号+官网+小程序'!I31+快手!I31+唯品会!I31+'线下门店-直营'!I31+'线下门店-经销'!I31+线下渠道!I31+淘系达播!I31+抖音达播!I31 -> 788247.76 | J31: =淘系!J31+抖音!J31+PDD!J31+得物!J31+京东自营财经口径!J31+京东POP财经口径!J31+'视频号+官网+小程序'!J31+快手!J31+唯品会!J31+'线下门店-直营'!J31+'线下门店-经销'!J31+线下渠道!J31+淘系达播!J31+抖音达播!J31 -> 1087268.9 | ... N31: =淘系!N31+抖音!N31+PDD!N31+得物!N31+京东自营财经口径!N31+京东POP财经口径!N31+'视频号+官网+小程序'!N31+快手!N31+唯品会!N31+'线下门店-直营'!N31+'线下门店-经销'!N31+线下渠道!N31+淘系达播!N31+抖音达播!N31 -> 968260.91 | O31: =SUM(C31:N31) -> 25137014 | P31: =O31/$O$16 -> 0.073407036 | T31: =O31-淘系!O31-淘系达播!O31-抖音!O31-抖音达播!O31-快手!O31-京东POP财经口径!O31-京东自营财经口径!O31-PDD!O31-得物!O31-'视频号+官网+小程序'!O31-唯品会!O31-'线下门店-直营'!O31-'线下门店-经销'!O31-线下渠道!O31 -> 0
B32: 展会(费率) | T32: =O32-淘系!O32-淘系达播!O32-抖音!O32-抖音达播!O32-快手!O32-京东POP财经口径!O32-京东自营财经口径!O32-PDD!O32-得物!O32-'视频号+官网+小程序'!O32-唯品会!O32-'线下门店-直营'!O32-'线下门店-经销'!O32-线下渠道!O32 -> 0
B33: 品牌营销（费率） | T33: =O33-淘系!O33-淘系达播!O33-抖音!O33-抖音达播!O33-快手!O33-京东POP财经口径!O33-京东自营财经口径!O33-PDD!O33-得物!O33-'视频号+官网+小程序'!O33-唯品会!O33-'线下门店-直营'!O33-'线下门店-经销'!O33-线下渠道!O33 -> 0
B34: 内容素材制作（费率） | T34: =O34-淘系!O34-淘系达播!O34-抖音!O34-抖音达播!O34-快手!O34-京东POP财经口径!O34-京东自营财经口径!O34-PDD!O34-得物!O34-'视频号+官网+小程序'!O34-唯品会!O34-'线下门店-直营'!O34-'线下门店-经销'!O34-线下渠道!O34 -> 0
B35: 公关费用（费率） | T35: =O35-淘系!O35-淘系达播!O35-抖音!O35-抖音达播!O35-快手!O35-京东POP财经口径!O35-京东自营财经口径!O35-PDD!O35-得物!O35-'视频号+官网+小程序'!O35-唯品会!O35-'线下门店-直营'!O35-'线下门店-经销'!O35-线下渠道!O35 -> 0
B36: 达人种草、样机及加热（费率） | T36: =O36-淘系!O36-淘系达播!O36-抖音!O36-抖音达播!O36-快手!O36-京东POP财经口径!O36-京东自营财经口径!O36-PDD!O36-得物!O36-'视频号+官网+小程序'!O36-唯品会!O36-'线下门店-直营'!O36-'线下门店-经销'!O36-线下渠道!O36 -> 0
B37: 效果广告 | C37: =SUM(C38:C40) -> 5289161.1 | D37: =SUM(D38:D40) -> 6011795.3 | E37: =SUM(E38:E40) -> 4469411.7 | F37: =SUM(F38:F40) -> 3799706.2 | G37: =SUM(G38:G40) -> 9797097.2 | H37: =SUM(H38:H40) -> 8746823 | I37: =SUM(I38:I40) -> 4912801.7 | J37: =SUM(J38:J40) -> 8629549.9 | ... N37: =SUM(N38:N40) -> 6666059 | O37: =SUM(C37:N37) -> 82824979 | P37: =O37/$O$16 -> 0.24187186 | R37: =O16*20.5% -> 70198828 | T37: =O37-淘系!O37-淘系达播!O37-抖音!O37-抖音达播!O37-快手!O37-京东POP财经口径!O37-京东自营财经口径!O37-PDD!O37-得物!O37-'视频号+官网+小程序'!O37-唯品会!O37-'线下门店-直营'!O37-'线下门店-经销'!O37-线下渠道!O37 -> -2.3283064e-10
B38: 站内投放 | C38: =淘系!C38+抖音!C38+PDD!C38+得物!C38+京东自营财经口径!C38+京东POP财经口径!C38+'视频号+官网+小程序'!C38+快手!C38+唯品会!C38+'线下门店-直营'!C38+'线下门店-经销'!C38+线下渠道!C38+淘系达播!C38+抖音达播!C38 -> 2292019.8 | D38: =淘系!D38+抖音!D38+PDD!D38+得物!D38+京东自营财经口径!D38+京东POP财经口径!D38+'视频号+官网+小程序'!D38+快手!D38+唯品会!D38+'线下门店-直营'!D38+'线下门店-经销'!D38+线下渠道!D38+淘系达播!D38+抖音达播!D38 -> 2749177.4 | E38: =淘系!E38+抖音!E38+PDD!E38+得物!E38+京东自营财经口径!E38+京东POP财经口径!E38+'视频号+官网+小程序'!E38+快手!E38+唯品会!E38+'线下门店-直营'!E38+'线下门店-经销'!E38+线下渠道!E38+淘系达播!E38+抖音达播!E38 -> 2219902.6 | F38: =淘系!F38+抖音!F38+PDD!F38+得物!F38+京东自营财经口径!F38+京东POP财经口径!F38+'视频号+官网+小程序'!F38+快手!F38+唯品会!F38+'线下门店-直营'!F38+'线下门店-经销'!F38+线下渠道!F38+淘系达播!F38+抖音达播!F38 -> 1900622 | G38: =淘系!G38+抖音!G38+PDD!G38+得物!G38+京东自营财经口径!G38+京东POP财经口径!G38+'视频号+官网+小程序'!G38+快手!G38+唯品会!G38+'线下门店-直营'!G38+'线下门店-经销'!G38+线下渠道!G38+淘系达播!G38+抖音达播!G38 -> 4748153.5 | H38: =淘系!H38+抖音!H38+PDD!H38+得物!H38+京东自营财经口径!H38+京东POP财经口径!H38+'视频号+官网+小程序'!H38+快手!H38+唯品会!H38+'线下门店-直营'!H38+'线下门店-经销'!H38+线下渠道!H38+淘系达播!H38+抖音达播!H38 -> 4563874.8 | I38: =淘系!I38+抖音!I38+PDD!I38+得物!I38+京东自营财经口径!I38+京东POP财经口径!I38+'视频号+官网+小程序'!I38+快手!I38+唯品会!I38+'线下门店-直营'!I38+'线下门店-经销'!I38+线下渠道!I38+淘系达播!I38+抖音达播!I38 -> 2576178.9 | J38: =淘系!J38+抖音!J38+PDD!J38+得物!J38+京东自营财经口径!J38+京东POP财经口径!J38+'视频号+官网+小程序'!J38+快手!J38+唯品会!J38+'线下门店-直营'!J38+'线下门店-经销'!J38+线下渠道!J38+淘系达播!J38+抖音达播!J38 -> 4648298.8 | ... N38: =淘系!N38+抖音!N38+PDD!N38+得物!N38+京东自营财经口径!N38+京东POP财经口径!N38+'视频号+官网+小程序'!N38+快手!N38+唯品会!N38+'线下门店-直营'!N38+'线下门店-经销'!N38+线下渠道!N38+淘系达播!N38+抖音达播!N38 -> 3186379.6 | O38: =SUM(C38:N38) -> 41931094 | P38: =O38/$O$16 -> 0.1224504 | Q38: 投放填写 | T38: =O38-淘系!O38-淘系达播!O38-抖音!O38-抖音达播!O38-快手!O38-京东POP财经口径!O38-京东自营财经口径!O38-PDD!O38-得物!O38-'视频号+官网+小程序'!O38-唯品会!O38-'线下门店-直营'!O38-'线下门店-经销'!O38-线下渠道!O38 -> -1.3271347e-08
B39: 千川投放 | C39: =淘系!C39+抖音!C39+PDD!C39+得物!C39+京东自营财经口径!C39+京东POP财经口径!C39+'视频号+官网+小程序'!C39+快手!C39+唯品会!C39+'线下门店-直营'!C39+'线下门店-经销'!C39+线下渠道!C39+淘系达播!C39+抖音达播!C39 -> 2298503 | D39: =淘系!D39+抖音!D39+PDD!D39+得物!D39+京东自营财经口径!D39+京东POP财经口径!D39+'视频号+官网+小程序'!D39+快手!D39+唯品会!D39+'线下门店-直营'!D39+'线下门店-经销'!D39+线下渠道!D39+淘系达播!D39+抖音达播!D39 -> 2468200.8 | E39: =淘系!E39+抖音!E39+PDD!E39+得物!E39+京东自营财经口径!E39+京东POP财经口径!E39+'视频号+官网+小程序'!E39+快手!E39+唯品会!E39+'线下门店-直营'!E39+'线下门店-经销'!E39+线下渠道!E39+淘系达播!E39+抖音达播!E39 -> 1582066.6 | F39: =淘系!F39+抖音!F39+PDD!F39+得物!F39+京东自营财经口径!F39+京东POP财经口径!F39+'视频号+官网+小程序'!F39+快手!F39+唯品会!F39+'线下门店-直营'!F39+'线下门店-经销'!F39+线下渠道!F39+淘系达播!F39+抖音达播!F39 -> 1336204.9 | G39: =淘系!G39+抖音!G39+PDD!G39+得物!G39+京东自营财经口径!G39+京东POP财经口径!G39+'视频号+官网+小程序'!G39+快手!G39+唯品会!G39+'线下门店-直营'!G39+'线下门店-经销'!G39+线下渠道!G39+淘系达播!G39+抖音达播!G39 -> 3070752.4 | H39: =淘系!H39+抖音!H39+PDD!H39+得物!H39+京东自营财经口径!H39+京东POP财经口径!H39+'视频号+官网+小程序'!H39+快手!H39+唯品会!H39+'线下门店-直营'!H39+'线下门店-经销'!H39+线下渠道!H39+淘系达播!H39+抖音达播!H39 -> 2791593.1 | I39: =淘系!I39+抖音!I39+PDD!I39+得物!I39+京东自营财经口径!I39+京东POP财经口径!I39+'视频号+官网+小程序'!I39+快手!I39+唯品会!I39+'线下门店-直营'!I39+'线下门店-经销'!I39+线下渠道!I39+淘系达播!I39+抖音达播!I39 -> 1603445.8 | J39: =淘系!J39+抖音!J39+PDD!J39+得物!J39+京东自营财经口径!J39+京东POP财经口径!J39+'视频号+官网+小程序'!J39+快手!J39+唯品会!J39+'线下门店-直营'!J39+'线下门店-经销'!J39+线下渠道!J39+淘系达播!J39+抖音达播!J39 -> 2583206.5 | ... N39: =淘系!N39+抖音!N39+PDD!N39+得物!N39+京东自营财经口径!N39+京东POP财经口径!N39+'视频号+官网+小程序'!N39+快手!N39+唯品会!N39+'线下门店-直营'!N39+'线下门店-经销'!N39+线下渠道!N39+淘系达播!N39+抖音达播!N39 -> 2571042.5 | O39: =SUM(C39:N39) -> 27750461 | P39: =O39/$O$16 -> 0.081039024 | Q39: 投放填写 | T39: =O39-淘系!O39-淘系达播!O39-抖音!O39-抖音达播!O39-快手!O39-京东POP财经口径!O39-京东自营财经口径!O39-PDD!O39-得物!O39-'视频号+官网+小程序'!O39-唯品会!O39-'线下门店-直营'!O39-'线下门店-经销'!O39-线下渠道!O39 -> 0
B40: 站外投放 | C40: =淘系!C40+抖音!C40+PDD!C40+得物!C40+京东自营财经口径!C40+京东POP财经口径!C40+'视频号+官网+小程序'!C40+快手!C40+唯品会!C40+'线下门店-直营'!C40+'线下门店-经销'!C40+线下渠道!C40+淘系达播!C40+抖音达播!C40 -> 698638.3 | D40: =淘系!D40+抖音!D40+PDD!D40+得物!D40+京东自营财经口径!D40+京东POP财经口径!D40+'视频号+官网+小程序'!D40+快手!D40+唯品会!D40+'线下门店-直营'!D40+'线下门店-经销'!D40+线下渠道!D40+淘系达播!D40+抖音达播!D40 -> 794417.05 | E40: =淘系!E40+抖音!E40+PDD!E40+得物!E40+京东自营财经口径!E40+京东POP财经口径!E40+'视频号+官网+小程序'!E40+快手!E40+唯品会!E40+'线下门店-直营'!E40+'线下门店-经销'!E40+线下渠道!E40+淘系达播!E40+抖音达播!E40 -> 667442.57 | F40: =淘系!F40+抖音!F40+PDD!F40+得物!F40+京东自营财经口径!F40+京东POP财经口径!F40+'视频号+官网+小程序'!F40+快手!F40+唯品会!F40+'线下门店-直营'!F40+'线下门店-经销'!F40+线下渠道!F40+淘系达播!F40+抖音达播!F40 -> 562879.37 | G40: =淘系!G40+抖音!G40+PDD!G40+得物!G40+京东自营财经口径!G40+京东POP财经口径!G40+'视频号+官网+小程序'!G40+快手!G40+唯品会!G40+'线下门店-直营'!G40+'线下门店-经销'!G40+线下渠道!G40+淘系达播!G40+抖音达播!G40 -> 1978191.3 | H40: =淘系!H40+抖音!H40+PDD!H40+得物!H40+京东自营财经口径!H40+京东POP财经口径!H40+'视频号+官网+小程序'!H40+快手!H40+唯品会!H40+'线下门店-直营'!H40+'线下门店-经销'!H40+线下渠道!H40+淘系达播!H40+抖音达播!H40 -> 1391355.1 | I40: =淘系!I40+抖音!I40+PDD!I40+得物!I40+京东自营财经口径!I40+京东POP财经口径!I40+'视频号+官网+小程序'!I40+快手!I40+唯品会!I40+'线下门店-直营'!I40+'线下门店-经销'!I40+线下渠道!I40+淘系达播!I40+抖音达播!I40 -> 733176.96 | J40: =淘系!J40+抖音!J40+PDD!J40+得物!J40+京东自营财经口径!J40+京东POP财经口径!J40+'视频号+官网+小程序'!J40+快手!J40+唯品会!J40+'线下门店-直营'!J40+'线下门店-经销'!J40+线下渠道!J40+淘系达播!J40+抖音达播!J40 -> 1398044.6 | ... N40: =淘系!N40+抖音!N40+PDD!N40+得物!N40+京东自营财经口径!N40+京东POP财经口径!N40+'视频号+官网+小程序'!N40+快手!N40+唯品会!N40+'线下门店-直营'!N40+'线下门店-经销'!N40+线下渠道!N40+淘系达播!N40+抖音达播!N40 -> 908636.98 | O40: =SUM(C40:N40) -> 13143425 | P40: =O40/$O$16 -> 0.038382436 | Q40: 投放填写 | T40: =O40-淘系!O40-淘系达播!O40-抖音!O40-抖音达播!O40-快手!O40-京东POP财经口径!O40-京东自营财经口径!O40-PDD!O40-得物!O40-'视频号+官网+小程序'!O40-唯品会!O40-'线下门店-直营'!O40-'线下门店-经销'!O40-线下渠道!O40 -> 0
B41: 站内投放（费率） | C41: =C38/C$16 -> 0.097320685 | D41: =D38/D$16 -> 0.11648678 | E41: =E38/E$16 -> 0.11029545 | F41: =F38/F$16 -> 0.11039856 | G41: =G38/G$16 -> 0.12673268 | H41: =H38/H$16 -> 0.1365926 | I41: =I38/I$16 -> 0.11391688 | J41: =J38/J$16 -> 0.14488208 | ... N41: =N38/N$16 -> 0.10586673 | O41: =O38/$O$16 -> 0.1224504 | Q41: 投放填写 | T41: =O41-淘系!O41-淘系达播!O41-抖音!O41-抖音达播!O41-快手!O41-京东POP财经口径!O41-京东自营财经口径!O41-PDD!O41-得物!O41-'视频号+官网+小程序'!O41-唯品会!O41-'线下门店-直营'!O41-'线下门店-经销'!O41-线下渠道!O41 -> -0.97604192
B42: 千川投放（费率） | C42: =C39/C$16 -> 0.097595969 | D42: =D39/D$16 -> 0.10458138 | E42: =E39/E$16 -> 0.078604686 | F42: =F39/F$16 -> 0.077614118 | G42: =G39/G$16 -> 0.081961268 | H42: =H39/H$16 -> 0.08354983 | I42: =I39/I$16 -> 0.070903285 | J42: =J39/J$16 -> 0.080515553 | ... N42: =N39/N$16 -> 0.085422297 | O42: =O39/$O$16 -> 0.081039024 | Q42: 投放填写 | T42: =O42-淘系!O42-淘系达播!O42-抖音!O42-抖音达播!O42-快手!O42-京东POP财经口径!O42-京东自营财经口径!O42-PDD!O42-得物!O42-'视频号+官网+小程序'!O42-唯品会!O42-'线下门店-直营'!O42-'线下门店-经销'!O42-线下渠道!O42 -> -0.28366686
B43: 站外投放（费率） | C43: =C40/C$16 -> 0.029664648 | D43: =D40/D$16 -> 0.033660644 | E43: =E40/E$16 -> 0.033161761 | F43: =F40/F$16 -> 0.032695126 | G43: =G40/G$16 -> 0.052799787 | H43: =H40/H$16 -> 0.041641986 | I43: =I40/I$16 -> 0.032420587 | J43: =J40/J$16 -> 0.043575428 | ... N43: =N40/N$16 -> 0.030189255 | O43: =O40/$O$16 -> 0.038382436 | Q43: 投放填写 | T43: =O43-淘系!O43-淘系达播!O43-抖音!O43-抖音达播!O43-快手!O43-京东POP财经口径!O43-京东自营财经口径!O43-PDD!O43-得物!O43-'视频号+官网+小程序'!O43-唯品会!O43-'线下门店-直营'!O43-'线下门店-经销'!O43-线下渠道!O43 -> -0.084651627
B44: 线上营销费用 | C44: =SUM(C45:C46) -> 873457.07 | D44: =SUM(D45:D46) -> 891315.7 | E44: =SUM(E45:E46) -> 784090.16 | F44: =SUM(F45:F46) -> 610146.64 | G44: =SUM(G45:G46) -> 1521937.3 | H44: =SUM(H45:H46) -> 1188479.9 | I44: =SUM(I45:I46) -> 779366.81 | J44: =SUM(J45:J46) -> 1264018.6 | ... N44: =SUM(N45:N46) -> 1089471.6 | O44: =SUM(C44:N44) -> 13187609 | P44: =O44/$O$16 -> 0.038511467 | T44: =O44-淘系!O44-淘系达播!O44-抖音!O44-抖音达播!O44-快手!O44-京东POP财经口径!O44-京东自营财经口径!O44-PDD!O44-得物!O44-'视频号+官网+小程序'!O44-唯品会!O44-'线下门店-直营'!O44-'线下门店-经销'!O44-线下渠道!O44 -> -1.2805685e-09
B45: 直播费用 | C45: =淘系!C45+抖音!C45+PDD!C45+得物!C45+京东自营财经口径!C45+京东POP财经口径!C45+'视频号+官网+小程序'!C45+快手!C45+唯品会!C45+'线下门店-直营'!C45+'线下门店-经销'!C45+线下渠道!C45+淘系达播!C45+抖音达播!C45 -> 162529.49 | D45: =淘系!D45+抖音!D45+PDD!D45+得物!D45+京东自营财经口径!D45+京东POP财经口径!D45+'视频号+官网+小程序'!D45+快手!D45+唯品会!D45+'线下门店-直营'!D45+'线下门店-经销'!D45+线下渠道!D45+淘系达播!D45+抖音达播!D45 -> 155166.99 | E45: =淘系!E45+抖音!E45+PDD!E45+得物!E45+京东自营财经口径!E45+京东POP财经口径!E45+'视频号+官网+小程序'!E45+快手!E45+唯品会!E45+'线下门店-直营'!E45+'线下门店-经销'!E45+线下渠道!E45+淘系达播!E45+抖音达播!E45 -> 194579.22 | F45: =淘系!F45+抖音!F45+PDD!F45+得物!F45+京东自营财经口径!F45+京东POP财经口径!F45+'视频号+官网+小程序'!F45+快手!F45+唯品会!F45+'线下门店-直营'!F45+'线下门店-经销'!F45+线下渠道!F45+淘系达播!F45+抖音达播!F45 -> 106561.31 | G45: =淘系!G45+抖音!G45+PDD!G45+得物!G45+京东自营财经口径!G45+京东POP财经口径!G45+'视频号+官网+小程序'!G45+快手!G45+唯品会!G45+'线下门店-直营'!G45+'线下门店-经销'!G45+线下渠道!G45+淘系达播!G45+抖音达播!G45 -> 442337.33 | H45: =淘系!H45+抖音!H45+PDD!H45+得物!H45+京东自营财经口径!H45+京东POP财经口径!H45+'视频号+官网+小程序'!H45+快手!H45+唯品会!H45+'线下门店-直营'!H45+'线下门店-经销'!H45+线下渠道!H45+淘系达播!H45+抖音达播!H45 -> 242039.41 | I45: =淘系!I45+抖音!I45+PDD!I45+得物!I45+京东自营财经口径!I45+京东POP财经口径!I45+'视频号+官网+小程序'!I45+快手!I45+唯品会!I45+'线下门店-直营'!I45+'线下门店-经销'!I45+线下渠道!I45+淘系达播!I45+抖音达播!I45 -> 126179.03 | J45: =淘系!J45+抖音!J45+PDD!J45+得物!J45+京东自营财经口径!J45+京东POP财经口径!J45+'视频号+官网+小程序'!J45+快手!J45+唯品会!J45+'线下门店-直营'!J45+'线下门店-经销'!J45+线下渠道!J45+淘系达播!J45+抖音达播!J45 -> 326056.34 | ... N45: =淘系!N45+抖音!N45+PDD!N45+得物!N45+京东自营财经口径!N45+京东POP财经口径!N45+'视频号+官网+小程序'!N45+快手!N45+唯品会!N45+'线下门店-直营'!N45+'线下门店-经销'!N45+线下渠道!N45+淘系达播!N45+抖音达播!N45 -> 174825.03 | O45: =SUM(C45:N45) -> 3171238.9 | P45: =O45/$O$16 -> 0.009260895 | Q45: 达人填写 | T45: =O45-淘系!O45-淘系达播!O45-抖音!O45-抖音达播!O45-快手!O45-京东POP财经口径!O45-京东自营财经口径!O45-PDD!O45-得物!O45-'视频号+官网+小程序'!O45-唯品会!O45-'线下门店-直营'!O45-'线下门店-经销'!O45-线下渠道!O45 -> -5.3842086e-10
B46: 赠品费用 | C46: =淘系!C46+抖音!C46+PDD!C46+得物!C46+京东自营财经口径!C46+京东POP财经口径!C46+'视频号+官网+小程序'!C46+快手!C46+唯品会!C46+'线下门店-直营'!C46+'线下门店-经销'!C46+线下渠道!C46+淘系达播!C46+抖音达播!C46 -> 710927.58 | D46: =淘系!D46+抖音!D46+PDD!D46+得物!D46+京东自营财经口径!D46+京东POP财经口径!D46+'视频号+官网+小程序'!D46+快手!D46+唯品会!D46+'线下门店-直营'!D46+'线下门店-经销'!D46+线下渠道!D46+淘系达播!D46+抖音达播!D46 -> 736148.72 | E46: =淘系!E46+抖音!E46+PDD!E46+得物!E46+京东自营财经口径!E46+京东POP财经口径!E46+'视频号+官网+小程序'!E46+快手!E46+唯品会!E46+'线下门店-直营'!E46+'线下门店-经销'!E46+线下渠道!E46+淘系达播!E46+抖音达播!E46 -> 589510.94 | F46: =淘系!F46+抖音!F46+PDD!F46+得物!F46+京东自营财经口径!F46+京东POP财经口径!F46+'视频号+官网+小程序'!F46+快手!F46+唯品会!F46+'线下门店-直营'!F46+'线下门店-经销'!F46+线下渠道!F46+淘系达播!F46+抖音达播!F46 -> 503585.33 | G46: =淘系!G46+抖音!G46+PDD!G46+得物!G46+京东自营财经口径!G46+京东POP财经口径!G46+'视频号+官网+小程序'!G46+快手!G46+唯品会!G46+'线下门店-直营'!G46+'线下门店-经销'!G46+线下渠道!G46+淘系达播!G46+抖音达播!G46 -> 1079600 | H46: =淘系!H46+抖音!H46+PDD!H46+得物!H46+京东自营财经口径!H46+京东POP财经口径!H46+'视频号+官网+小程序'!H46+快手!H46+唯品会!H46+'线下门店-直营'!H46+'线下门店-经销'!H46+线下渠道!H46+淘系达播!H46+抖音达播!H46 -> 946440.5 | I46: =淘系!I46+抖音!I46+PDD!I46+得物!I46+京东自营财经口径!I46+京东POP财经口径!I46+'视频号+官网+小程序'!I46+快手!I46+唯品会!I46+'线下门店-直营'!I46+'线下门店-经销'!I46+线下渠道!I46+淘系达播!I46+抖音达播!I46 -> 653187.78 | J46: =淘系!J46+抖音!J46+PDD!J46+得物!J46+京东自营财经口径!J46+京东POP财经口径!J46+'视频号+官网+小程序'!J46+快手!J46+唯品会!J46+'线下门店-直营'!J46+'线下门店-经销'!J46+线下渠道!J46+淘系达播!J46+抖音达播!J46 -> 937962.25 | ... N46: =淘系!N46+抖音!N46+PDD!N46+得物!N46+京东自营财经口径!N46+京东POP财经口径!N46+'视频号+官网+小程序'!N46+快手!N46+唯品会!N46+'线下门店-直营'!N46+'线下门店-经销'!N46+线下渠道!N46+淘系达播!N46+抖音达播!N46 -> 914646.58 | O46: =SUM(C46:N46) -> 10016370 | P46: =O46/$O$16 -> 0.029250572 | Q46: 渠道填写 | T46: =O46-淘系!O46-淘系达播!O46-抖音!O46-抖音达播!O46-快手!O46-京东POP财经口径!O46-京东自营财经口径!O46-PDD!O46-得物!O46-'视频号+官网+小程序'!O46-唯品会!O46-'线下门店-直营'!O46-'线下门店-经销'!O46-线下渠道!O46 -> -18223.07
B47: 线下市场费用 | C47: =SUM(C48:C51) -> 657080.28 | D47: =SUM(D48:D51) -> 636510.42 | E47: =SUM(E48:E51) -> 641266.51 | F47: =SUM(F48:F51) -> 662889.29 | G47: =SUM(G48:G51) -> 717270.27 | H47: =SUM(H48:H51) -> 966198.14 | I47: =SUM(I48:I51) -> 933219.49 | J47: =SUM(J48:J51) -> 963447.11 | ... N47: =SUM(N48:N51) -> 1542325.9 | O47: =SUM(C47:N47) -> 11366424 | P47: =O47/$O$16 -> 0.033193103 | T47: =O47-淘系!O47-淘系达播!O47-抖音!O47-抖音达播!O47-快手!O47-京东POP财经口径!O47-京东自营财经口径!O47-PDD!O47-得物!O47-'视频号+官网+小程序'!O47-唯品会!O47-'线下门店-直营'!O47-'线下门店-经销'!O47-线下渠道!O47 -> 0
B48: 线下渠道展陈、促销费用 | C48: =淘系!C48+抖音!C48+PDD!C48+得物!C48+京东自营财经口径!C48+京东POP财经口径!C48+'视频号+官网+小程序'!C48+快手!C48+唯品会!C48+'线下门店-直营'!C48+'线下门店-经销'!C48+线下渠道!C48+淘系达播!C48+抖音达播!C48 -> 273499.09 | D48: =淘系!D48+抖音!D48+PDD!D48+得物!D48+京东自营财经口径!D48+京东POP财经口径!D48+'视频号+官网+小程序'!D48+快手!D48+唯品会!D48+'线下门店-直营'!D48+'线下门店-经销'!D48+线下渠道!D48+淘系达播!D48+抖音达播!D48 -> 282312.63 | E48: =淘系!E48+抖音!E48+PDD!E48+得物!E48+京东自营财经口径!E48+京东POP财经口径!E48+'视频号+官网+小程序'!E48+快手!E48+唯品会!E48+'线下门店-直营'!E48+'线下门店-经销'!E48+线下渠道!E48+淘系达播!E48+抖音达播!E48 -> 248013.19 | F48: =淘系!F48+抖音!F48+PDD!F48+得物!F48+京东自营财经口径!F48+京东POP财经口径!F48+'视频号+官网+小程序'!F48+快手!F48+唯品会!F48+'线下门店-直营'!F48+'线下门店-经销'!F48+线下渠道!F48+淘系达播!F48+抖音达播!F48 -> 271172.87 | G48: =淘系!G48+抖音!G48+PDD!G48+得物!G48+京东自营财经口径!G48+京东POP财经口径!G48+'视频号+官网+小程序'!G48+快手!G48+唯品会!G48+'线下门店-直营'!G48+'线下门店-经销'!G48+线下渠道!G48+淘系达播!G48+抖音达播!G48 -> 411814.03 | H48: =淘系!H48+抖音!H48+PDD!H48+得物!H48+京东自营财经口径!H48+京东POP财经口径!H48+'视频号+官网+小程序'!H48+快手!H48+唯品会!H48+'线下门店-直营'!H48+'线下门店-经销'!H48+线下渠道!H48+淘系达播!H48+抖音达播!H48 -> 560242.14 | I48: =淘系!I48+抖音!I48+PDD!I48+得物!I48+京东自营财经口径!I48+京东POP财经口径!I48+'视频号+官网+小程序'!I48+快手!I48+唯品会!I48+'线下门店-直营'!I48+'线下门店-经销'!I48+线下渠道!I48+淘系达播!I48+抖音达播!I48 -> 548529.71 | J48: =淘系!J48+抖音!J48+PDD!J48+得物!J48+京东自营财经口径!J48+京东POP财经口径!J48+'视频号+官网+小程序'!J48+快手!J48+唯品会!J48+'线下门店-直营'!J48+'线下门店-经销'!J48+线下渠道!J48+淘系达播!J48+抖音达播!J48 -> 616741.81 | ... N48: =淘系!N48+抖音!N48+PDD!N48+得物!N48+京东自营财经口径!N48+京东POP财经口径!N48+'视频号+官网+小程序'!N48+快手!N48+唯品会!N48+'线下门店-直营'!N48+'线下门店-经销'!N48+线下渠道!N48+淘系达播!N48+抖音达播!N48 -> 1012182.7 | O48: =SUM(C48:N48) -> 6581385.2 | P48: =O48/$O$16 -> 0.019219466 | Q48: 线下门店 | T48: =O48-淘系!O48-淘系达播!O48-抖音!O48-抖音达播!O48-快手!O48-京东POP财经口径!O48-京东自营财经口径!O48-PDD!O48-得物!O48-'视频号+官网+小程序'!O48-唯品会!O48-'线下门店-直营'!O48-'线下门店-经销'!O48-线下渠道!O48 -> 0
B49: 租金+物业+水电 | C49: =淘系!C49+抖音!C49+PDD!C49+得物!C49+京东自营财经口径!C49+京东POP财经口径!C49+'视频号+官网+小程序'!C49+快手!C49+唯品会!C49+'线下门店-直营'!C49+'线下门店-经销'!C49+线下渠道!C49+淘系达播!C49+抖音达播!C49 -> 151958.47 | D49: =淘系!D49+抖音!D49+PDD!D49+得物!D49+京东自营财经口径!D49+京东POP财经口径!D49+'视频号+官网+小程序'!D49+快手!D49+唯品会!D49+'线下门店-直营'!D49+'线下门店-经销'!D49+线下渠道!D49+淘系达播!D49+抖音达播!D49 -> 132683.54 | E49: =淘系!E49+抖音!E49+PDD!E49+得物!E49+京东自营财经口径!E49+京东POP财经口径!E49+'视频号+官网+小程序'!E49+快手!E49+唯品会!E49+'线下门店-直营'!E49+'线下门店-经销'!E49+线下渠道!E49+淘系达播!E49+抖音达播!E49 -> 144087.64 | F49: =淘系!F49+抖音!F49+PDD!F49+得物!F49+京东自营财经口径!F49+京东POP财经口径!F49+'视频号+官网+小程序'!F49+快手!F49+唯品会!F49+'线下门店-直营'!F49+'线下门店-经销'!F49+线下渠道!F49+淘系达播!F49+抖音达播!F49 -> 135605.02 | G49: =淘系!G49+抖音!G49+PDD!G49+得物!G49+京东自营财经口径!G49+京东POP财经口径!G49+'视频号+官网+小程序'!G49+快手!G49+唯品会!G49+'线下门店-直营'!G49+'线下门店-经销'!G49+线下渠道!G49+淘系达播!G49+抖音达播!G49 -> 102872.77 | H49: =淘系!H49+抖音!H49+PDD!H49+得物!H49+京东自营财经口径!H49+京东POP财经口径!H49+'视频号+官网+小程序'!H49+快手!H49+唯品会!H49+'线下门店-直营'!H49+'线下门店-经销'!H49+线下渠道!H49+淘系达播!H49+抖音达播!H49 -> 143943.35 | I49: =淘系!I49+抖音!I49+PDD!I49+得物!I49+京东自营财经口径!I49+京东POP财经口径!I49+'视频号+官网+小程序'!I49+快手!I49+唯品会!I49+'线下门店-直营'!I49+'线下门店-经销'!I49+线下渠道!I49+淘系达播!I49+抖音达播!I49 -> 131789.64 | J49: =淘系!J49+抖音!J49+PDD!J49+得物!J49+京东自营财经口径!J49+京东POP财经口径!J49+'视频号+官网+小程序'!J49+快手!J49+唯品会!J49+'线下门店-直营'!J49+'线下门店-经销'!J49+线下渠道!J49+淘系达播!J49+抖音达播!J49 -> 112127.73 | ... N49: =淘系!N49+抖音!N49+PDD!N49+得物!N49+京东自营财经口径!N49+京东POP财经口径!N49+'视频号+官网+小程序'!N49+快手!N49+唯品会!N49+'线下门店-直营'!N49+'线下门店-经销'!N49+线下渠道!N49+淘系达播!N49+抖音达播!N49 -> 139684.73 | O49: =SUM(C49:N49) -> 1566703.2 | P49: =O49/$O$16 -> 0.0045752069 | Q49: 线下门店 | T49: =O49-淘系!O49-淘系达播!O49-抖音!O49-抖音达播!O49-快手!O49-京东POP财经口径!O49-京东自营财经口径!O49-PDD!O49-得物!O49-'视频号+官网+小程序'!O49-唯品会!O49-'线下门店-直营'!O49-'线下门店-经销'!O49-线下渠道!O49 -> 0
B50: 门店人工 | C50: =淘系!C50+抖音!C50+PDD!C50+得物!C50+京东自营财经口径!C50+京东POP财经口径!C50+'视频号+官网+小程序'!C50+快手!C50+唯品会!C50+'线下门店-直营'!C50+'线下门店-经销'!C50+线下渠道!C50+淘系达播!C50+抖音达播!C50 -> 112000 | D50: =淘系!D50+抖音!D50+PDD!D50+得物!D50+京东自营财经口径!D50+京东POP财经口径!D50+'视频号+官网+小程序'!D50+快手!D50+唯品会!D50+'线下门店-直营'!D50+'线下门店-经销'!D50+线下渠道!D50+淘系达播!D50+抖音达播!D50 -> 120000 | E50: =淘系!E50+抖音!E50+PDD!E50+得物!E50+京东自营财经口径!E50+京东POP财经口径!E50+'视频号+官网+小程序'!E50+快手!E50+唯品会!E50+'线下门店-直营'!E50+'线下门店-经销'!E50+线下渠道!E50+淘系达播!E50+抖音达播!E50 -> 132000 | F50: =淘系!F50+抖音!F50+PDD!F50+得物!F50+京东自营财经口径!F50+京东POP财经口径!F50+'视频号+官网+小程序'!F50+快手!F50+唯品会!F50+'线下门店-直营'!F50+'线下门店-经销'!F50+线下渠道!F50+淘系达播!F50+抖音达播!F50 -> 145000 | G50: =淘系!G50+抖音!G50+PDD!G50+得物!G50+京东自营财经口径!G50+京东POP财经口径!G50+'视频号+官网+小程序'!G50+快手!G50+唯品会!G50+'线下门店-直营'!G50+'线下门店-经销'!G50+线下渠道!G50+淘系达播!G50+抖音达播!G50 -> 110000 | H50: =淘系!H50+抖音!H50+PDD!H50+得物!H50+京东自营财经口径!H50+京东POP财经口径!H50+'视频号+官网+小程序'!H50+快手!H50+唯品会!H50+'线下门店-直营'!H50+'线下门店-经销'!H50+线下渠道!H50+淘系达播!H50+抖音达播!H50 -> 135000 | I50: =淘系!I50+抖音!I50+PDD!I50+得物!I50+京东自营财经口径!I50+京东POP财经口径!I50+'视频号+官网+小程序'!I50+快手!I50+唯品会!I50+'线下门店-直营'!I50+'线下门店-经销'!I50+线下渠道!I50+淘系达播!I50+抖音达播!I50 -> 120000 | J50: =淘系!J50+抖音!J50+PDD!J50+得物!J50+京东自营财经口径!J50+京东POP财经口径!J50+'视频号+官网+小程序'!J50+快手!J50+唯品会!J50+'线下门店-直营'!J50+'线下门店-经销'!J50+线下渠道!J50+淘系达播!J50+抖音达播!J50 -> 110000 | ... N50: =淘系!N50+抖音!N50+PDD!N50+得物!N50+京东自营财经口径!N50+京东POP财经口径!N50+'视频号+官网+小程序'!N50+快手!N50+唯品会!N50+'线下门店-直营'!N50+'线下门店-经销'!N50+线下渠道!N50+淘系达播!N50+抖音达播!N50 -> 145000 | O50: =SUM(C50:N50) -> 1509000 | P50: =O50/$O$16 -> 0.0044066975 | Q50: 线下门店 | T50: =O50-淘系!O50-淘系达播!O50-抖音!O50-抖音达播!O50-快手!O50-京东POP财经口径!O50-京东自营财经口径!O50-PDD!O50-得物!O50-'视频号+官网+小程序'!O50-唯品会!O50-'线下门店-直营'!O50-'线下门店-经销'!O50-线下渠道!O50 -> 0
